Workbook

Sheet How to use
B1: Monthly & Annual Budget Planner
B2: Rajput Lalit & Associates · www.rajputlalitassociates.in · WhatsApp +91 93549 53603
B4: Steps
A5: 1 | B5: In 'Setup' type the year you are planning for and your monthly budget for each category. Rename or add categories in the 'Categories' sheet — each one is marked Need, Want or Savings.
A6: 2 | B6: Every time money comes in or goes out, add one line in 'Transactions' (date, category, amount). That's the only regular work.
A7: 3 | B7: 'Month View' — pick a month at the top to see budget vs actual for every category, and what is left.
A8: 4 | B8: 'Year Summary' shows all 12 months side by side, your savings rate and a chart.
A9: 5 | B9: '50-30-20 Check' compares your spending with the popular 50% needs / 30% wants / 20% savings rule.
B11: Good to know
B12: • Works in Excel, Google Sheets and LibreOffice.
B13: • Amounts are in rupees but work in any currency.
B15: Cells shaded light yellow are for your entries. White cells contain formulas — please don't type over them.
B17: Licensed for use in your own business. Please do not resell or share publicly. This template is a working aid, not professional advice.

Sheet Month View
A1: Month View — budget vs actual
A2: Pick the month in B3
A3: Month (1–12) | B3: 4 | C3: =TEXT(DATE(Setup!B4,B3,1),"mmmm yyyy")
A5: Category | B5: Type | C5: Budget | D5: Actual | E5: Left / (over)
A6: =IF(Categories!A5="","",Categories!A5) | B6: =IF(Categories!A5="","",Categories!B5) | C6: =IF(A6="","",N(Categories!C5)) | D6: =IF(A6="","",SUMIFS(Transactions!$C$5:$C$2004,Transactions!$B$5:$B$2004,A6,Transactions!$A$5:$A$2004,">="&DATE(Setup!$B$4,$B$3,1),Transactions!$A$5:$A$2004,"<="&EOMONTH(DATE(Setup!$B$4,$B$3,1),0))) | E6: =IF(OR(A6="",B6="Income"),"",C6-D6)
A7: =IF(Categories!A6="","",Categories!A6) | B7: =IF(Categories!A6="","",Categories!B6) | C7: =IF(A7="","",N(Categories!C6)) | D7: =IF(A7="","",SUMIFS(Transactions!$C$5:$C$2004,Transactions!$B$5:$B$2004,A7,Transactions!$A$5:$A$2004,">="&DATE(Setup!$B$4,$B$3,1),Transactions!$A$5:$A$2004,"<="&EOMONTH(DATE(Setup!$B$4,$B$3,1),0))) | E7: =IF(OR(A7="",B7="Income"),"",C7-D7)
A8: =IF(Categories!A7="","",Categories!A7) | B8: =IF(Categories!A7="","",Categories!B7) | C8: =IF(A8="","",N(Categories!C7)) | D8: =IF(A8="","",SUMIFS(Transactions!$C$5:$C$2004,Transactions!$B$5:$B$2004,A8,Transactions!$A$5:$A$2004,">="&DATE(Setup!$B$4,$B$3,1),Transactions!$A$5:$A$2004,"<="&EOMONTH(DATE(Setup!$B$4,$B$3,1),0))) | E8: =IF(OR(A8="",B8="Income"),"",C8-D8)
A9: =IF(Categories!A8="","",Categories!A8) | B9: =IF(Categories!A8="","",Categories!B8) | C9: =IF(A9="","",N(Categories!C8)) | D9: =IF(A9="","",SUMIFS(Transactions!$C$5:$C$2004,Transactions!$B$5:$B$2004,A9,Transactions!$A$5:$A$2004,">="&DATE(Setup!$B$4,$B$3,1),Transactions!$A$5:$A$2004,"<="&EOMONTH(DATE(Setup!$B$4,$B$3,1),0))) | E9: =IF(OR(A9="",B9="Income"),"",C9-D9)
A10: =IF(Categories!A9="","",Categories!A9) | B10: =IF(Categories!A9="","",Categories!B9) | C10: =IF(A10="","",N(Categories!C9)) | D10: =IF(A10="","",SUMIFS(Transactions!$C$5:$C$2004,Transactions!$B$5:$B$2004,A10,Transactions!$A$5:$A$2004,">="&DATE(Setup!$B$4,$B$3,1),Transactions!$A$5:$A$2004,"<="&EOMONTH(DATE(Setup!$B$4,$B$3,1),0))) | E10: =IF(OR(A10="",B10="Income"),"",C10-D10)
A11: =IF(Categories!A10="","",Categories!A10) | B11: =IF(Categories!A10="","",Categories!B10) | C11: =IF(A11="","",N(Categories!C10)) | D11: =IF(A11="","",SUMIFS(Transactions!$C$5:$C$2004,Transactions!$B$5:$B$2004,A11,Transactions!$A$5:$A$2004,">="&DATE(Setup!$B$4,$B$3,1),Transactions!$A$5:$A$2004,"<="&EOMONTH(DATE(Setup!$B$4,$B$3,1),0))) | E11: =IF(OR(A11="",B11="Income"),"",C11-D11)
A12: =IF(Categories!A11="","",Categories!A11) | B12: =IF(Categories!A11="","",Categories!B11) | C12: =IF(A12="","",N(Categories!C11)) | D12: =IF(A12="","",SUMIFS(Transactions!$C$5:$C$2004,Transactions!$B$5:$B$2004,A12,Transactions!$A$5:$A$2004,">="&DATE(Setup!$B$4,$B$3,1),Transactions!$A$5:$A$2004,"<="&EOMONTH(DATE(Setup!$B$4,$B$3,1),0))) | E12: =IF(OR(A12="",B12="Income"),"",C12-D12)
A13: =IF(Categories!A12="","",Categories!A12) | B13: =IF(Categories!A12="","",Categories!B12) | C13: =IF(A13="","",N(Categories!C12)) | D13: =IF(A13="","",SUMIFS(Transactions!$C$5:$C$2004,Transactions!$B$5:$B$2004,A13,Transactions!$A$5:$A$2004,">="&DATE(Setup!$B$4,$B$3,1),Transactions!$A$5:$A$2004,"<="&EOMONTH(DATE(Setup!$B$4,$B$3,1),0))) | E13: =IF(OR(A13="",B13="Income"),"",C13-D13)
A14: =IF(Categories!A13="","",Categories!A13) | B14: =IF(Categories!A13="","",Categories!B13) | C14: =IF(A14="","",N(Categories!C13)) | D14: =IF(A14="","",SUMIFS(Transactions!$C$5:$C$2004,Transactions!$B$5:$B$2004,A14,Transactions!$A$5:$A$2004,">="&DATE(Setup!$B$4,$B$3,1),Transactions!$A$5:$A$2004,"<="&EOMONTH(DATE(Setup!$B$4,$B$3,1),0))) | E14: =IF(OR(A14="",B14="Income"),"",C14-D14)
A15: =IF(Categories!A14="","",Categories!A14) | B15: =IF(Categories!A14="","",Categories!B14) | C15: =IF(A15="","",N(Categories!C14)) | D15: =IF(A15="","",SUMIFS(Transactions!$C$5:$C$2004,Transactions!$B$5:$B$2004,A15,Transactions!$A$5:$A$2004,">="&DATE(Setup!$B$4,$B$3,1),Transactions!$A$5:$A$2004,"<="&EOMONTH(DATE(Setup!$B$4,$B$3,1),0))) | E15: =IF(OR(A15="",B15="Income"),"",C15-D15)
A16: =IF(Categories!A15="","",Categories!A15) | B16: =IF(Categories!A15="","",Categories!B15) | C16: =IF(A16="","",N(Categories!C15)) | D16: =IF(A16="","",SUMIFS(Transactions!$C$5:$C$2004,Transactions!$B$5:$B$2004,A16,Transactions!$A$5:$A$2004,">="&DATE(Setup!$B$4,$B$3,1),Transactions!$A$5:$A$2004,"<="&EOMONTH(DATE(Setup!$B$4,$B$3,1),0))) | E16: =IF(OR(A16="",B16="Income"),"",C16-D16)
A17: =IF(Categories!A16="","",Categories!A16) | B17: =IF(Categories!A16="","",Categories!B16) | C17: =IF(A17="","",N(Categories!C16)) | D17: =IF(A17="","",SUMIFS(Transactions!$C$5:$C$2004,Transactions!$B$5:$B$2004,A17,Transactions!$A$5:$A$2004,">="&DATE(Setup!$B$4,$B$3,1),Transactions!$A$5:$A$2004,"<="&EOMONTH(DATE(Setup!$B$4,$B$3,1),0))) | E17: =IF(OR(A17="",B17="Income"),"",C17-D17)
... A45: =IF(Categories!A44="","",Categories!A44) | B45: =IF(Categories!A44="","",Categories!B44) | C45: =IF(A45="","",N(Categories!C44)) | D45: =IF(A45="","",SUMIFS(Transactions!$C$5:$C$2004,Transactions!$B$5:$B$2004,A45,Transactions!$A$5:$A$2004,">="&DATE(Setup!$B$4,$B$3,1),Transactions!$A$5:$A$2004,"<="&EOMONTH(DATE(Setup!$B$4,$B$3,1),0))) | E45: =IF(OR(A45="",B45="Income"),"",C45-D45)
A47: Income this month | B47: =SUMIFS(D6:D45,B6:B45,"Income")
A48: Spent (needs + wants) | B48: =SUMIFS(D6:D45,B6:B45,"Need")+SUMIFS(D6:D45,B6:B45,"Want")
A49: Saved / invested | B49: =SUMIFS(D6:D45,B6:B45,"Savings")
A50: Money not yet allocated | B50: =B47-B48-B49 | C50: Positive = extra cash; negative = you spent more than you earned

Sheet Year Summary
A1: Year Summary
A2: Actuals by month from 'Transactions'
A4: Category | B4: Type | C4: Jan | D4: Feb | E4: Mar | F4: Apr | G4: May | H4: Jun | I4: Jul | J4: Aug | K4: Sep | L4: Oct | M4: Nov | N4: Dec | O4: Total
A5: =IF(Categories!A5="","",Categories!A5) | B5: =IF(Categories!A5="","",Categories!B5) | C5: =IF($A5="","",SUMIFS(Transactions!$C$5:$C$2004,Transactions!$B$5:$B$2004,$A5,Transactions!$A$5:$A$2004,">="&DATE(Setup!$B$4,1,1),Transactions!$A$5:$A$2004,"<="&EOMONTH(DATE(Setup!$B$4,1,1),0))) | D5: =IF($A5="","",SUMIFS(Transactions!$C$5:$C$2004,Transactions!$B$5:$B$2004,$A5,Transactions!$A$5:$A$2004,">="&DATE(Setup!$B$4,2,1),Transactions!$A$5:$A$2004,"<="&EOMONTH(DATE(Setup!$B$4,2,1),0))) | E5: =IF($A5="","",SUMIFS(Transactions!$C$5:$C$2004,Transactions!$B$5:$B$2004,$A5,Transactions!$A$5:$A$2004,">="&DATE(Setup!$B$4,3,1),Transactions!$A$5:$A$2004,"<="&EOMONTH(DATE(Setup!$B$4,3,1),0))) | F5: =IF($A5="","",SUMIFS(Transactions!$C$5:$C$2004,Transactions!$B$5:$B$2004,$A5,Transactions!$A$5:$A$2004,">="&DATE(Setup!$B$4,4,1),Transactions!$A$5:$A$2004,"<="&EOMONTH(DATE(Setup!$B$4,4,1),0))) | G5: =IF($A5="","",SUMIFS(Transactions!$C$5:$C$2004,Transactions!$B$5:$B$2004,$A5,Transactions!$A$5:$A$2004,">="&DATE(Setup!$B$4,5,1),Transactions!$A$5:$A$2004,"<="&EOMONTH(DATE(Setup!$B$4,5,1),0))) | H5: =IF($A5="","",SUMIFS(Transactions!$C$5:$C$2004,Transactions!$B$5:$B$2004,$A5,Transactions!$A$5:$A$2004,">="&DATE(Setup!$B$4,6,1),Transactions!$A$5:$A$2004,"<="&EOMONTH(DATE(Setup!$B$4,6,1),0))) | I5: =IF($A5="","",SUMIFS(Transactions!$C$5:$C$2004,Transactions!$B$5:$B$2004,$A5,Transactions!$A$5:$A$2004,">="&DATE(Setup!$B$4,7,1),Transactions!$A$5:$A$2004,"<="&EOMONTH(DATE(Setup!$B$4,7,1),0))) | J5: =IF($A5="","",SUMIFS(Transactions!$C$5:$C$2004,Transactions!$B$5:$B$2004,$A5,Transactions!$A$5:$A$2004,">="&DATE(Setup!$B$4,8,1),Transactions!$A$5:$A$2004,"<="&EOMONTH(DATE(Setup!$B$4,8,1),0))) | K5: =IF($A5="","",SUMIFS(Transactions!$C$5:$C$2004,Transactions!$B$5:$B$2004,$A5,Transactions!$A$5:$A$2004,">="&DATE(Setup!$B$4,9,1),Transactions!$A$5:$A$2004,"<="&EOMONTH(DATE(Setup!$B$4,9,1),0))) | L5: =IF($A5="","",SUMIFS(Transactions!$C$5:$C$2004,Transactions!$B$5:$B$2004,$A5,Transactions!$A$5:$A$2004,">="&DATE(Setup!$B$4,10,1),Transactions!$A$5:$A$2004,"<="&EOMONTH(DATE(Setup!$B$4,10,1),0))) | M5: =IF($A5="","",SUMIFS(Transactions!$C$5:$C$2004,Transactions!$B$5:$B$2004,$A5,Transactions!$A$5:$A$2004,">="&DATE(Setup!$B$4,11,1),Transactions!$A$5:$A$2004,"<="&EOMONTH(DATE(Setup!$B$4,11,1),0))) | N5: =IF($A5="","",SUMIFS(Transactions!$C$5:$C$2004,Transactions!$B$5:$B$2004,$A5,Transactions!$A$5:$A$2004,">="&DATE(Setup!$B$4,12,1),Transactions!$A$5:$A$2004,"<="&EOMONTH(DATE(Setup!$B$4,12,1),0))) | O5: =IF($A5="","",SUM(C5:N5))
A6: =IF(Categories!A6="","",Categories!A6) | B6: =IF(Categories!A6="","",Categories!B6) | C6: =IF($A6="","",SUMIFS(Transactions!$C$5:$C$2004,Transactions!$B$5:$B$2004,$A6,Transactions!$A$5:$A$2004,">="&DATE(Setup!$B$4,1,1),Transactions!$A$5:$A$2004,"<="&EOMONTH(DATE(Setup!$B$4,1,1),0))) | D6: =IF($A6="","",SUMIFS(Transactions!$C$5:$C$2004,Transactions!$B$5:$B$2004,$A6,Transactions!$A$5:$A$2004,">="&DATE(Setup!$B$4,2,1),Transactions!$A$5:$A$2004,"<="&EOMONTH(DATE(Setup!$B$4,2,1),0))) | E6: =IF($A6="","",SUMIFS(Transactions!$C$5:$C$2004,Transactions!$B$5:$B$2004,$A6,Transactions!$A$5:$A$2004,">="&DATE(Setup!$B$4,3,1),Transactions!$A$5:$A$2004,"<="&EOMONTH(DATE(Setup!$B$4,3,1),0))) | F6: =IF($A6="","",SUMIFS(Transactions!$C$5:$C$2004,Transactions!$B$5:$B$2004,$A6,Transactions!$A$5:$A$2004,">="&DATE(Setup!$B$4,4,1),Transactions!$A$5:$A$2004,"<="&EOMONTH(DATE(Setup!$B$4,4,1),0))) | G6: =IF($A6="","",SUMIFS(Transactions!$C$5:$C$2004,Transactions!$B$5:$B$2004,$A6,Transactions!$A$5:$A$2004,">="&DATE(Setup!$B$4,5,1),Transactions!$A$5:$A$2004,"<="&EOMONTH(DATE(Setup!$B$4,5,1),0))) | H6: =IF($A6="","",SUMIFS(Transactions!$C$5:$C$2004,Transactions!$B$5:$B$2004,$A6,Transactions!$A$5:$A$2004,">="&DATE(Setup!$B$4,6,1),Transactions!$A$5:$A$2004,"<="&EOMONTH(DATE(Setup!$B$4,6,1),0))) | I6: =IF($A6="","",SUMIFS(Transactions!$C$5:$C$2004,Transactions!$B$5:$B$2004,$A6,Transactions!$A$5:$A$2004,">="&DATE(Setup!$B$4,7,1),Transactions!$A$5:$A$2004,"<="&EOMONTH(DATE(Setup!$B$4,7,1),0))) | J6: =IF($A6="","",SUMIFS(Transactions!$C$5:$C$2004,Transactions!$B$5:$B$2004,$A6,Transactions!$A$5:$A$2004,">="&DATE(Setup!$B$4,8,1),Transactions!$A$5:$A$2004,"<="&EOMONTH(DATE(Setup!$B$4,8,1),0))) | K6: =IF($A6="","",SUMIFS(Transactions!$C$5:$C$2004,Transactions!$B$5:$B$2004,$A6,Transactions!$A$5:$A$2004,">="&DATE(Setup!$B$4,9,1),Transactions!$A$5:$A$2004,"<="&EOMONTH(DATE(Setup!$B$4,9,1),0))) | L6: =IF($A6="","",SUMIFS(Transactions!$C$5:$C$2004,Transactions!$B$5:$B$2004,$A6,Transactions!$A$5:$A$2004,">="&DATE(Setup!$B$4,10,1),Transactions!$A$5:$A$2004,"<="&EOMONTH(DATE(Setup!$B$4,10,1),0))) | M6: =IF($A6="","",SUMIFS(Transactions!$C$5:$C$2004,Transactions!$B$5:$B$2004,$A6,Transactions!$A$5:$A$2004,">="&DATE(Setup!$B$4,11,1),Transactions!$A$5:$A$2004,"<="&EOMONTH(DATE(Setup!$B$4,11,1),0))) | N6: =IF($A6="","",SUMIFS(Transactions!$C$5:$C$2004,Transactions!$B$5:$B$2004,$A6,Transactions!$A$5:$A$2004,">="&DATE(Setup!$B$4,12,1),Transactions!$A$5:$A$2004,"<="&EOMONTH(DATE(Setup!$B$4,12,1),0))) | O6: =IF($A6="","",SUM(C6:N6))
A7: =IF(Categories!A7="","",Categories!A7) | B7: =IF(Categories!A7="","",Categories!B7) | C7: =IF($A7="","",SUMIFS(Transactions!$C$5:$C$2004,Transactions!$B$5:$B$2004,$A7,Transactions!$A$5:$A$2004,">="&DATE(Setup!$B$4,1,1),Transactions!$A$5:$A$2004,"<="&EOMONTH(DATE(Setup!$B$4,1,1),0))) | D7: =IF($A7="","",SUMIFS(Transactions!$C$5:$C$2004,Transactions!$B$5:$B$2004,$A7,Transactions!$A$5:$A$2004,">="&DATE(Setup!$B$4,2,1),Transactions!$A$5:$A$2004,"<="&EOMONTH(DATE(Setup!$B$4,2,1),0))) | E7: =IF($A7="","",SUMIFS(Transactions!$C$5:$C$2004,Transactions!$B$5:$B$2004,$A7,Transactions!$A$5:$A$2004,">="&DATE(Setup!$B$4,3,1),Transactions!$A$5:$A$2004,"<="&EOMONTH(DATE(Setup!$B$4,3,1),0))) | F7: =IF($A7="","",SUMIFS(Transactions!$C$5:$C$2004,Transactions!$B$5:$B$2004,$A7,Transactions!$A$5:$A$2004,">="&DATE(Setup!$B$4,4,1),Transactions!$A$5:$A$2004,"<="&EOMONTH(DATE(Setup!$B$4,4,1),0))) | G7: =IF($A7="","",SUMIFS(Transactions!$C$5:$C$2004,Transactions!$B$5:$B$2004,$A7,Transactions!$A$5:$A$2004,">="&DATE(Setup!$B$4,5,1),Transactions!$A$5:$A$2004,"<="&EOMONTH(DATE(Setup!$B$4,5,1),0))) | H7: =IF($A7="","",SUMIFS(Transactions!$C$5:$C$2004,Transactions!$B$5:$B$2004,$A7,Transactions!$A$5:$A$2004,">="&DATE(Setup!$B$4,6,1),Transactions!$A$5:$A$2004,"<="&EOMONTH(DATE(Setup!$B$4,6,1),0))) | I7: =IF($A7="","",SUMIFS(Transactions!$C$5:$C$2004,Transactions!$B$5:$B$2004,$A7,Transactions!$A$5:$A$2004,">="&DATE(Setup!$B$4,7,1),Transactions!$A$5:$A$2004,"<="&EOMONTH(DATE(Setup!$B$4,7,1),0))) | J7: =IF($A7="","",SUMIFS(Transactions!$C$5:$C$2004,Transactions!$B$5:$B$2004,$A7,Transactions!$A$5:$A$2004,">="&DATE(Setup!$B$4,8,1),Transactions!$A$5:$A$2004,"<="&EOMONTH(DATE(Setup!$B$4,8,1),0))) | K7: =IF($A7="","",SUMIFS(Transactions!$C$5:$C$2004,Transactions!$B$5:$B$2004,$A7,Transactions!$A$5:$A$2004,">="&DATE(Setup!$B$4,9,1),Transactions!$A$5:$A$2004,"<="&EOMONTH(DATE(Setup!$B$4,9,1),0))) | L7: =IF($A7="","",SUMIFS(Transactions!$C$5:$C$2004,Transactions!$B$5:$B$2004,$A7,Transactions!$A$5:$A$2004,">="&DATE(Setup!$B$4,10,1),Transactions!$A$5:$A$2004,"<="&EOMONTH(DATE(Setup!$B$4,10,1),0))) | M7: =IF($A7="","",SUMIFS(Transactions!$C$5:$C$2004,Transactions!$B$5:$B$2004,$A7,Transactions!$A$5:$A$2004,">="&DATE(Setup!$B$4,11,1),Transactions!$A$5:$A$2004,"<="&EOMONTH(DATE(Setup!$B$4,11,1),0))) | N7: =IF($A7="","",SUMIFS(Transactions!$C$5:$C$2004,Transactions!$B$5:$B$2004,$A7,Transactions!$A$5:$A$2004,">="&DATE(Setup!$B$4,12,1),Transactions!$A$5:$A$2004,"<="&EOMONTH(DATE(Setup!$B$4,12,1),0))) | O7: =IF($A7="","",SUM(C7:N7))
A8: =IF(Categories!A8="","",Categories!A8) | B8: =IF(Categories!A8="","",Categories!B8) | C8: =IF($A8="","",SUMIFS(Transactions!$C$5:$C$2004,Transactions!$B$5:$B$2004,$A8,Transactions!$A$5:$A$2004,">="&DATE(Setup!$B$4,1,1),Transactions!$A$5:$A$2004,"<="&EOMONTH(DATE(Setup!$B$4,1,1),0))) | D8: =IF($A8="","",SUMIFS(Transactions!$C$5:$C$2004,Transactions!$B$5:$B$2004,$A8,Transactions!$A$5:$A$2004,">="&DATE(Setup!$B$4,2,1),Transactions!$A$5:$A$2004,"<="&EOMONTH(DATE(Setup!$B$4,2,1),0))) | E8: =IF($A8="","",SUMIFS(Transactions!$C$5:$C$2004,Transactions!$B$5:$B$2004,$A8,Transactions!$A$5:$A$2004,">="&DATE(Setup!$B$4,3,1),Transactions!$A$5:$A$2004,"<="&EOMONTH(DATE(Setup!$B$4,3,1),0))) | F8: =IF($A8="","",SUMIFS(Transactions!$C$5:$C$2004,Transactions!$B$5:$B$2004,$A8,Transactions!$A$5:$A$2004,">="&DATE(Setup!$B$4,4,1),Transactions!$A$5:$A$2004,"<="&EOMONTH(DATE(Setup!$B$4,4,1),0))) | G8: =IF($A8="","",SUMIFS(Transactions!$C$5:$C$2004,Transactions!$B$5:$B$2004,$A8,Transactions!$A$5:$A$2004,">="&DATE(Setup!$B$4,5,1),Transactions!$A$5:$A$2004,"<="&EOMONTH(DATE(Setup!$B$4,5,1),0))) | H8: =IF($A8="","",SUMIFS(Transactions!$C$5:$C$2004,Transactions!$B$5:$B$2004,$A8,Transactions!$A$5:$A$2004,">="&DATE(Setup!$B$4,6,1),Transactions!$A$5:$A$2004,"<="&EOMONTH(DATE(Setup!$B$4,6,1),0))) | I8: =IF($A8="","",SUMIFS(Transactions!$C$5:$C$2004,Transactions!$B$5:$B$2004,$A8,Transactions!$A$5:$A$2004,">="&DATE(Setup!$B$4,7,1),Transactions!$A$5:$A$2004,"<="&EOMONTH(DATE(Setup!$B$4,7,1),0))) | J8: =IF($A8="","",SUMIFS(Transactions!$C$5:$C$2004,Transactions!$B$5:$B$2004,$A8,Transactions!$A$5:$A$2004,">="&DATE(Setup!$B$4,8,1),Transactions!$A$5:$A$2004,"<="&EOMONTH(DATE(Setup!$B$4,8,1),0))) | K8: =IF($A8="","",SUMIFS(Transactions!$C$5:$C$2004,Transactions!$B$5:$B$2004,$A8,Transactions!$A$5:$A$2004,">="&DATE(Setup!$B$4,9,1),Transactions!$A$5:$A$2004,"<="&EOMONTH(DATE(Setup!$B$4,9,1),0))) | L8: =IF($A8="","",SUMIFS(Transactions!$C$5:$C$2004,Transactions!$B$5:$B$2004,$A8,Transactions!$A$5:$A$2004,">="&DATE(Setup!$B$4,10,1),Transactions!$A$5:$A$2004,"<="&EOMONTH(DATE(Setup!$B$4,10,1),0))) | M8: =IF($A8="","",SUMIFS(Transactions!$C$5:$C$2004,Transactions!$B$5:$B$2004,$A8,Transactions!$A$5:$A$2004,">="&DATE(Setup!$B$4,11,1),Transactions!$A$5:$A$2004,"<="&EOMONTH(DATE(Setup!$B$4,11,1),0))) | N8: =IF($A8="","",SUMIFS(Transactions!$C$5:$C$2004,Transactions!$B$5:$B$2004,$A8,Transactions!$A$5:$A$2004,">="&DATE(Setup!$B$4,12,1),Transactions!$A$5:$A$2004,"<="&EOMONTH(DATE(Setup!$B$4,12,1),0))) | O8: =IF($A8="","",SUM(C8:N8))
A9: =IF(Categories!A9="","",Categories!A9) | B9: =IF(Categories!A9="","",Categories!B9) | C9: =IF($A9="","",SUMIFS(Transactions!$C$5:$C$2004,Transactions!$B$5:$B$2004,$A9,Transactions!$A$5:$A$2004,">="&DATE(Setup!$B$4,1,1),Transactions!$A$5:$A$2004,"<="&EOMONTH(DATE(Setup!$B$4,1,1),0))) | D9: =IF($A9="","",SUMIFS(Transactions!$C$5:$C$2004,Transactions!$B$5:$B$2004,$A9,Transactions!$A$5:$A$2004,">="&DATE(Setup!$B$4,2,1),Transactions!$A$5:$A$2004,"<="&EOMONTH(DATE(Setup!$B$4,2,1),0))) | E9: =IF($A9="","",SUMIFS(Transactions!$C$5:$C$2004,Transactions!$B$5:$B$2004,$A9,Transactions!$A$5:$A$2004,">="&DATE(Setup!$B$4,3,1),Transactions!$A$5:$A$2004,"<="&EOMONTH(DATE(Setup!$B$4,3,1),0))) | F9: =IF($A9="","",SUMIFS(Transactions!$C$5:$C$2004,Transactions!$B$5:$B$2004,$A9,Transactions!$A$5:$A$2004,">="&DATE(Setup!$B$4,4,1),Transactions!$A$5:$A$2004,"<="&EOMONTH(DATE(Setup!$B$4,4,1),0))) | G9: =IF($A9="","",SUMIFS(Transactions!$C$5:$C$2004,Transactions!$B$5:$B$2004,$A9,Transactions!$A$5:$A$2004,">="&DATE(Setup!$B$4,5,1),Transactions!$A$5:$A$2004,"<="&EOMONTH(DATE(Setup!$B$4,5,1),0))) | H9: =IF($A9="","",SUMIFS(Transactions!$C$5:$C$2004,Transactions!$B$5:$B$2004,$A9,Transactions!$A$5:$A$2004,">="&DATE(Setup!$B$4,6,1),Transactions!$A$5:$A$2004,"<="&EOMONTH(DATE(Setup!$B$4,6,1),0))) | I9: =IF($A9="","",SUMIFS(Transactions!$C$5:$C$2004,Transactions!$B$5:$B$2004,$A9,Transactions!$A$5:$A$2004,">="&DATE(Setup!$B$4,7,1),Transactions!$A$5:$A$2004,"<="&EOMONTH(DATE(Setup!$B$4,7,1),0))) | J9: =IF($A9="","",SUMIFS(Transactions!$C$5:$C$2004,Transactions!$B$5:$B$2004,$A9,Transactions!$A$5:$A$2004,">="&DATE(Setup!$B$4,8,1),Transactions!$A$5:$A$2004,"<="&EOMONTH(DATE(Setup!$B$4,8,1),0))) | K9: =IF($A9="","",SUMIFS(Transactions!$C$5:$C$2004,Transactions!$B$5:$B$2004,$A9,Transactions!$A$5:$A$2004,">="&DATE(Setup!$B$4,9,1),Transactions!$A$5:$A$2004,"<="&EOMONTH(DATE(Setup!$B$4,9,1),0))) | L9: =IF($A9="","",SUMIFS(Transactions!$C$5:$C$2004,Transactions!$B$5:$B$2004,$A9,Transactions!$A$5:$A$2004,">="&DATE(Setup!$B$4,10,1),Transactions!$A$5:$A$2004,"<="&EOMONTH(DATE(Setup!$B$4,10,1),0))) | M9: =IF($A9="","",SUMIFS(Transactions!$C$5:$C$2004,Transactions!$B$5:$B$2004,$A9,Transactions!$A$5:$A$2004,">="&DATE(Setup!$B$4,11,1),Transactions!$A$5:$A$2004,"<="&EOMONTH(DATE(Setup!$B$4,11,1),0))) | N9: =IF($A9="","",SUMIFS(Transactions!$C$5:$C$2004,Transactions!$B$5:$B$2004,$A9,Transactions!$A$5:$A$2004,">="&DATE(Setup!$B$4,12,1),Transactions!$A$5:$A$2004,"<="&EOMONTH(DATE(Setup!$B$4,12,1),0))) | O9: =IF($A9="","",SUM(C9:N9))
A10: =IF(Categories!A10="","",Categories!A10) | B10: =IF(Categories!A10="","",Categories!B10) | C10: =IF($A10="","",SUMIFS(Transactions!$C$5:$C$2004,Transactions!$B$5:$B$2004,$A10,Transactions!$A$5:$A$2004,">="&DATE(Setup!$B$4,1,1),Transactions!$A$5:$A$2004,"<="&EOMONTH(DATE(Setup!$B$4,1,1),0))) | D10: =IF($A10="","",SUMIFS(Transactions!$C$5:$C$2004,Transactions!$B$5:$B$2004,$A10,Transactions!$A$5:$A$2004,">="&DATE(Setup!$B$4,2,1),Transactions!$A$5:$A$2004,"<="&EOMONTH(DATE(Setup!$B$4,2,1),0))) | E10: =IF($A10="","",SUMIFS(Transactions!$C$5:$C$2004,Transactions!$B$5:$B$2004,$A10,Transactions!$A$5:$A$2004,">="&DATE(Setup!$B$4,3,1),Transactions!$A$5:$A$2004,"<="&EOMONTH(DATE(Setup!$B$4,3,1),0))) | F10: =IF($A10="","",SUMIFS(Transactions!$C$5:$C$2004,Transactions!$B$5:$B$2004,$A10,Transactions!$A$5:$A$2004,">="&DATE(Setup!$B$4,4,1),Transactions!$A$5:$A$2004,"<="&EOMONTH(DATE(Setup!$B$4,4,1),0))) | G10: =IF($A10="","",SUMIFS(Transactions!$C$5:$C$2004,Transactions!$B$5:$B$2004,$A10,Transactions!$A$5:$A$2004,">="&DATE(Setup!$B$4,5,1),Transactions!$A$5:$A$2004,"<="&EOMONTH(DATE(Setup!$B$4,5,1),0))) | H10: =IF($A10="","",SUMIFS(Transactions!$C$5:$C$2004,Transactions!$B$5:$B$2004,$A10,Transactions!$A$5:$A$2004,">="&DATE(Setup!$B$4,6,1),Transactions!$A$5:$A$2004,"<="&EOMONTH(DATE(Setup!$B$4,6,1),0))) | I10: =IF($A10="","",SUMIFS(Transactions!$C$5:$C$2004,Transactions!$B$5:$B$2004,$A10,Transactions!$A$5:$A$2004,">="&DATE(Setup!$B$4,7,1),Transactions!$A$5:$A$2004,"<="&EOMONTH(DATE(Setup!$B$4,7,1),0))) | J10: =IF($A10="","",SUMIFS(Transactions!$C$5:$C$2004,Transactions!$B$5:$B$2004,$A10,Transactions!$A$5:$A$2004,">="&DATE(Setup!$B$4,8,1),Transactions!$A$5:$A$2004,"<="&EOMONTH(DATE(Setup!$B$4,8,1),0))) | K10: =IF($A10="","",SUMIFS(Transactions!$C$5:$C$2004,Transactions!$B$5:$B$2004,$A10,Transactions!$A$5:$A$2004,">="&DATE(Setup!$B$4,9,1),Transactions!$A$5:$A$2004,"<="&EOMONTH(DATE(Setup!$B$4,9,1),0))) | L10: =IF($A10="","",SUMIFS(Transactions!$C$5:$C$2004,Transactions!$B$5:$B$2004,$A10,Transactions!$A$5:$A$2004,">="&DATE(Setup!$B$4,10,1),Transactions!$A$5:$A$2004,"<="&EOMONTH(DATE(Setup!$B$4,10,1),0))) | M10: =IF($A10="","",SUMIFS(Transactions!$C$5:$C$2004,Transactions!$B$5:$B$2004,$A10,Transactions!$A$5:$A$2004,">="&DATE(Setup!$B$4,11,1),Transactions!$A$5:$A$2004,"<="&EOMONTH(DATE(Setup!$B$4,11,1),0))) | N10: =IF($A10="","",SUMIFS(Transactions!$C$5:$C$2004,Transactions!$B$5:$B$2004,$A10,Transactions!$A$5:$A$2004,">="&DATE(Setup!$B$4,12,1),Transactions!$A$5:$A$2004,"<="&EOMONTH(DATE(Setup!$B$4,12,1),0))) | O10: =IF($A10="","",SUM(C10:N10))
A11: =IF(Categories!A11="","",Categories!A11) | B11: =IF(Categories!A11="","",Categories!B11) | C11: =IF($A11="","",SUMIFS(Transactions!$C$5:$C$2004,Transactions!$B$5:$B$2004,$A11,Transactions!$A$5:$A$2004,">="&DATE(Setup!$B$4,1,1),Transactions!$A$5:$A$2004,"<="&EOMONTH(DATE(Setup!$B$4,1,1),0))) | D11: =IF($A11="","",SUMIFS(Transactions!$C$5:$C$2004,Transactions!$B$5:$B$2004,$A11,Transactions!$A$5:$A$2004,">="&DATE(Setup!$B$4,2,1),Transactions!$A$5:$A$2004,"<="&EOMONTH(DATE(Setup!$B$4,2,1),0))) | E11: =IF($A11="","",SUMIFS(Transactions!$C$5:$C$2004,Transactions!$B$5:$B$2004,$A11,Transactions!$A$5:$A$2004,">="&DATE(Setup!$B$4,3,1),Transactions!$A$5:$A$2004,"<="&EOMONTH(DATE(Setup!$B$4,3,1),0))) | F11: =IF($A11="","",SUMIFS(Transactions!$C$5:$C$2004,Transactions!$B$5:$B$2004,$A11,Transactions!$A$5:$A$2004,">="&DATE(Setup!$B$4,4,1),Transactions!$A$5:$A$2004,"<="&EOMONTH(DATE(Setup!$B$4,4,1),0))) | G11: =IF($A11="","",SUMIFS(Transactions!$C$5:$C$2004,Transactions!$B$5:$B$2004,$A11,Transactions!$A$5:$A$2004,">="&DATE(Setup!$B$4,5,1),Transactions!$A$5:$A$2004,"<="&EOMONTH(DATE(Setup!$B$4,5,1),0))) | H11: =IF($A11="","",SUMIFS(Transactions!$C$5:$C$2004,Transactions!$B$5:$B$2004,$A11,Transactions!$A$5:$A$2004,">="&DATE(Setup!$B$4,6,1),Transactions!$A$5:$A$2004,"<="&EOMONTH(DATE(Setup!$B$4,6,1),0))) | I11: =IF($A11="","",SUMIFS(Transactions!$C$5:$C$2004,Transactions!$B$5:$B$2004,$A11,Transactions!$A$5:$A$2004,">="&DATE(Setup!$B$4,7,1),Transactions!$A$5:$A$2004,"<="&EOMONTH(DATE(Setup!$B$4,7,1),0))) | J11: =IF($A11="","",SUMIFS(Transactions!$C$5:$C$2004,Transactions!$B$5:$B$2004,$A11,Transactions!$A$5:$A$2004,">="&DATE(Setup!$B$4,8,1),Transactions!$A$5:$A$2004,"<="&EOMONTH(DATE(Setup!$B$4,8,1),0))) | K11: =IF($A11="","",SUMIFS(Transactions!$C$5:$C$2004,Transactions!$B$5:$B$2004,$A11,Transactions!$A$5:$A$2004,">="&DATE(Setup!$B$4,9,1),Transactions!$A$5:$A$2004,"<="&EOMONTH(DATE(Setup!$B$4,9,1),0))) | L11: =IF($A11="","",SUMIFS(Transactions!$C$5:$C$2004,Transactions!$B$5:$B$2004,$A11,Transactions!$A$5:$A$2004,">="&DATE(Setup!$B$4,10,1),Transactions!$A$5:$A$2004,"<="&EOMONTH(DATE(Setup!$B$4,10,1),0))) | M11: =IF($A11="","",SUMIFS(Transactions!$C$5:$C$2004,Transactions!$B$5:$B$2004,$A11,Transactions!$A$5:$A$2004,">="&DATE(Setup!$B$4,11,1),Transactions!$A$5:$A$2004,"<="&EOMONTH(DATE(Setup!$B$4,11,1),0))) | N11: =IF($A11="","",SUMIFS(Transactions!$C$5:$C$2004,Transactions!$B$5:$B$2004,$A11,Transactions!$A$5:$A$2004,">="&DATE(Setup!$B$4,12,1),Transactions!$A$5:$A$2004,"<="&EOMONTH(DATE(Setup!$B$4,12,1),0))) | O11: =IF($A11="","",SUM(C11:N11))
A12: =IF(Categories!A12="","",Categories!A12) | B12: =IF(Categories!A12="","",Categories!B12) | C12: =IF($A12="","",SUMIFS(Transactions!$C$5:$C$2004,Transactions!$B$5:$B$2004,$A12,Transactions!$A$5:$A$2004,">="&DATE(Setup!$B$4,1,1),Transactions!$A$5:$A$2004,"<="&EOMONTH(DATE(Setup!$B$4,1,1),0))) | D12: =IF($A12="","",SUMIFS(Transactions!$C$5:$C$2004,Transactions!$B$5:$B$2004,$A12,Transactions!$A$5:$A$2004,">="&DATE(Setup!$B$4,2,1),Transactions!$A$5:$A$2004,"<="&EOMONTH(DATE(Setup!$B$4,2,1),0))) | E12: =IF($A12="","",SUMIFS(Transactions!$C$5:$C$2004,Transactions!$B$5:$B$2004,$A12,Transactions!$A$5:$A$2004,">="&DATE(Setup!$B$4,3,1),Transactions!$A$5:$A$2004,"<="&EOMONTH(DATE(Setup!$B$4,3,1),0))) | F12: =IF($A12="","",SUMIFS(Transactions!$C$5:$C$2004,Transactions!$B$5:$B$2004,$A12,Transactions!$A$5:$A$2004,">="&DATE(Setup!$B$4,4,1),Transactions!$A$5:$A$2004,"<="&EOMONTH(DATE(Setup!$B$4,4,1),0))) | G12: =IF($A12="","",SUMIFS(Transactions!$C$5:$C$2004,Transactions!$B$5:$B$2004,$A12,Transactions!$A$5:$A$2004,">="&DATE(Setup!$B$4,5,1),Transactions!$A$5:$A$2004,"<="&EOMONTH(DATE(Setup!$B$4,5,1),0))) | H12: =IF($A12="","",SUMIFS(Transactions!$C$5:$C$2004,Transactions!$B$5:$B$2004,$A12,Transactions!$A$5:$A$2004,">="&DATE(Setup!$B$4,6,1),Transactions!$A$5:$A$2004,"<="&EOMONTH(DATE(Setup!$B$4,6,1),0))) | I12: =IF($A12="","",SUMIFS(Transactions!$C$5:$C$2004,Transactions!$B$5:$B$2004,$A12,Transactions!$A$5:$A$2004,">="&DATE(Setup!$B$4,7,1),Transactions!$A$5:$A$2004,"<="&EOMONTH(DATE(Setup!$B$4,7,1),0))) | J12: =IF($A12="","",SUMIFS(Transactions!$C$5:$C$2004,Transactions!$B$5:$B$2004,$A12,Transactions!$A$5:$A$2004,">="&DATE(Setup!$B$4,8,1),Transactions!$A$5:$A$2004,"<="&EOMONTH(DATE(Setup!$B$4,8,1),0))) | K12: =IF($A12="","",SUMIFS(Transactions!$C$5:$C$2004,Transactions!$B$5:$B$2004,$A12,Transactions!$A$5:$A$2004,">="&DATE(Setup!$B$4,9,1),Transactions!$A$5:$A$2004,"<="&EOMONTH(DATE(Setup!$B$4,9,1),0))) | L12: =IF($A12="","",SUMIFS(Transactions!$C$5:$C$2004,Transactions!$B$5:$B$2004,$A12,Transactions!$A$5:$A$2004,">="&DATE(Setup!$B$4,10,1),Transactions!$A$5:$A$2004,"<="&EOMONTH(DATE(Setup!$B$4,10,1),0))) | M12: =IF($A12="","",SUMIFS(Transactions!$C$5:$C$2004,Transactions!$B$5:$B$2004,$A12,Transactions!$A$5:$A$2004,">="&DATE(Setup!$B$4,11,1),Transactions!$A$5:$A$2004,"<="&EOMONTH(DATE(Setup!$B$4,11,1),0))) | N12: =IF($A12="","",SUMIFS(Transactions!$C$5:$C$2004,Transactions!$B$5:$B$2004,$A12,Transactions!$A$5:$A$2004,">="&DATE(Setup!$B$4,12,1),Transactions!$A$5:$A$2004,"<="&EOMONTH(DATE(Setup!$B$4,12,1),0))) | O12: =IF($A12="","",SUM(C12:N12))
A13: =IF(Categories!A13="","",Categories!A13) | B13: =IF(Categories!A13="","",Categories!B13) | C13: =IF($A13="","",SUMIFS(Transactions!$C$5:$C$2004,Transactions!$B$5:$B$2004,$A13,Transactions!$A$5:$A$2004,">="&DATE(Setup!$B$4,1,1),Transactions!$A$5:$A$2004,"<="&EOMONTH(DATE(Setup!$B$4,1,1),0))) | D13: =IF($A13="","",SUMIFS(Transactions!$C$5:$C$2004,Transactions!$B$5:$B$2004,$A13,Transactions!$A$5:$A$2004,">="&DATE(Setup!$B$4,2,1),Transactions!$A$5:$A$2004,"<="&EOMONTH(DATE(Setup!$B$4,2,1),0))) | E13: =IF($A13="","",SUMIFS(Transactions!$C$5:$C$2004,Transactions!$B$5:$B$2004,$A13,Transactions!$A$5:$A$2004,">="&DATE(Setup!$B$4,3,1),Transactions!$A$5:$A$2004,"<="&EOMONTH(DATE(Setup!$B$4,3,1),0))) | F13: =IF($A13="","",SUMIFS(Transactions!$C$5:$C$2004,Transactions!$B$5:$B$2004,$A13,Transactions!$A$5:$A$2004,">="&DATE(Setup!$B$4,4,1),Transactions!$A$5:$A$2004,"<="&EOMONTH(DATE(Setup!$B$4,4,1),0))) | G13: =IF($A13="","",SUMIFS(Transactions!$C$5:$C$2004,Transactions!$B$5:$B$2004,$A13,Transactions!$A$5:$A$2004,">="&DATE(Setup!$B$4,5,1),Transactions!$A$5:$A$2004,"<="&EOMONTH(DATE(Setup!$B$4,5,1),0))) | H13: =IF($A13="","",SUMIFS(Transactions!$C$5:$C$2004,Transactions!$B$5:$B$2004,$A13,Transactions!$A$5:$A$2004,">="&DATE(Setup!$B$4,6,1),Transactions!$A$5:$A$2004,"<="&EOMONTH(DATE(Setup!$B$4,6,1),0))) | I13: =IF($A13="","",SUMIFS(Transactions!$C$5:$C$2004,Transactions!$B$5:$B$2004,$A13,Transactions!$A$5:$A$2004,">="&DATE(Setup!$B$4,7,1),Transactions!$A$5:$A$2004,"<="&EOMONTH(DATE(Setup!$B$4,7,1),0))) | J13: =IF($A13="","",SUMIFS(Transactions!$C$5:$C$2004,Transactions!$B$5:$B$2004,$A13,Transactions!$A$5:$A$2004,">="&DATE(Setup!$B$4,8,1),Transactions!$A$5:$A$2004,"<="&EOMONTH(DATE(Setup!$B$4,8,1),0))) | K13: =IF($A13="","",SUMIFS(Transactions!$C$5:$C$2004,Transactions!$B$5:$B$2004,$A13,Transactions!$A$5:$A$2004,">="&DATE(Setup!$B$4,9,1),Transactions!$A$5:$A$2004,"<="&EOMONTH(DATE(Setup!$B$4,9,1),0))) | L13: =IF($A13="","",SUMIFS(Transactions!$C$5:$C$2004,Transactions!$B$5:$B$2004,$A13,Transactions!$A$5:$A$2004,">="&DATE(Setup!$B$4,10,1),Transactions!$A$5:$A$2004,"<="&EOMONTH(DATE(Setup!$B$4,10,1),0))) | M13: =IF($A13="","",SUMIFS(Transactions!$C$5:$C$2004,Transactions!$B$5:$B$2004,$A13,Transactions!$A$5:$A$2004,">="&DATE(Setup!$B$4,11,1),Transactions!$A$5:$A$2004,"<="&EOMONTH(DATE(Setup!$B$4,11,1),0))) | N13: =IF($A13="","",SUMIFS(Transactions!$C$5:$C$2004,Transactions!$B$5:$B$2004,$A13,Transactions!$A$5:$A$2004,">="&DATE(Setup!$B$4,12,1),Transactions!$A$5:$A$2004,"<="&EOMONTH(DATE(Setup!$B$4,12,1),0))) | O13: =IF($A13="","",SUM(C13:N13))
A14: =IF(Categories!A14="","",Categories!A14) | B14: =IF(Categories!A14="","",Categories!B14) | C14: =IF($A14="","",SUMIFS(Transactions!$C$5:$C$2004,Transactions!$B$5:$B$2004,$A14,Transactions!$A$5:$A$2004,">="&DATE(Setup!$B$4,1,1),Transactions!$A$5:$A$2004,"<="&EOMONTH(DATE(Setup!$B$4,1,1),0))) | D14: =IF($A14="","",SUMIFS(Transactions!$C$5:$C$2004,Transactions!$B$5:$B$2004,$A14,Transactions!$A$5:$A$2004,">="&DATE(Setup!$B$4,2,1),Transactions!$A$5:$A$2004,"<="&EOMONTH(DATE(Setup!$B$4,2,1),0))) | E14: =IF($A14="","",SUMIFS(Transactions!$C$5:$C$2004,Transactions!$B$5:$B$2004,$A14,Transactions!$A$5:$A$2004,">="&DATE(Setup!$B$4,3,1),Transactions!$A$5:$A$2004,"<="&EOMONTH(DATE(Setup!$B$4,3,1),0))) | F14: =IF($A14="","",SUMIFS(Transactions!$C$5:$C$2004,Transactions!$B$5:$B$2004,$A14,Transactions!$A$5:$A$2004,">="&DATE(Setup!$B$4,4,1),Transactions!$A$5:$A$2004,"<="&EOMONTH(DATE(Setup!$B$4,4,1),0))) | G14: =IF($A14="","",SUMIFS(Transactions!$C$5:$C$2004,Transactions!$B$5:$B$2004,$A14,Transactions!$A$5:$A$2004,">="&DATE(Setup!$B$4,5,1),Transactions!$A$5:$A$2004,"<="&EOMONTH(DATE(Setup!$B$4,5,1),0))) | H14: =IF($A14="","",SUMIFS(Transactions!$C$5:$C$2004,Transactions!$B$5:$B$2004,$A14,Transactions!$A$5:$A$2004,">="&DATE(Setup!$B$4,6,1),Transactions!$A$5:$A$2004,"<="&EOMONTH(DATE(Setup!$B$4,6,1),0))) | I14: =IF($A14="","",SUMIFS(Transactions!$C$5:$C$2004,Transactions!$B$5:$B$2004,$A14,Transactions!$A$5:$A$2004,">="&DATE(Setup!$B$4,7,1),Transactions!$A$5:$A$2004,"<="&EOMONTH(DATE(Setup!$B$4,7,1),0))) | J14: =IF($A14="","",SUMIFS(Transactions!$C$5:$C$2004,Transactions!$B$5:$B$2004,$A14,Transactions!$A$5:$A$2004,">="&DATE(Setup!$B$4,8,1),Transactions!$A$5:$A$2004,"<="&EOMONTH(DATE(Setup!$B$4,8,1),0))) | K14: =IF($A14="","",SUMIFS(Transactions!$C$5:$C$2004,Transactions!$B$5:$B$2004,$A14,Transactions!$A$5:$A$2004,">="&DATE(Setup!$B$4,9,1),Transactions!$A$5:$A$2004,"<="&EOMONTH(DATE(Setup!$B$4,9,1),0))) | L14: =IF($A14="","",SUMIFS(Transactions!$C$5:$C$2004,Transactions!$B$5:$B$2004,$A14,Transactions!$A$5:$A$2004,">="&DATE(Setup!$B$4,10,1),Transactions!$A$5:$A$2004,"<="&EOMONTH(DATE(Setup!$B$4,10,1),0))) | M14: =IF($A14="","",SUMIFS(Transactions!$C$5:$C$2004,Transactions!$B$5:$B$2004,$A14,Transactions!$A$5:$A$2004,">="&DATE(Setup!$B$4,11,1),Transactions!$A$5:$A$2004,"<="&EOMONTH(DATE(Setup!$B$4,11,1),0))) | N14: =IF($A14="","",SUMIFS(Transactions!$C$5:$C$2004,Transactions!$B$5:$B$2004,$A14,Transactions!$A$5:$A$2004,">="&DATE(Setup!$B$4,12,1),Transactions!$A$5:$A$2004,"<="&EOMONTH(DATE(Setup!$B$4,12,1),0))) | O14: =IF($A14="","",SUM(C14:N14))
A15: =IF(Categories!A15="","",Categories!A15) | B15: =IF(Categories!A15="","",Categories!B15) | C15: =IF($A15="","",SUMIFS(Transactions!$C$5:$C$2004,Transactions!$B$5:$B$2004,$A15,Transactions!$A$5:$A$2004,">="&DATE(Setup!$B$4,1,1),Transactions!$A$5:$A$2004,"<="&EOMONTH(DATE(Setup!$B$4,1,1),0))) | D15: =IF($A15="","",SUMIFS(Transactions!$C$5:$C$2004,Transactions!$B$5:$B$2004,$A15,Transactions!$A$5:$A$2004,">="&DATE(Setup!$B$4,2,1),Transactions!$A$5:$A$2004,"<="&EOMONTH(DATE(Setup!$B$4,2,1),0))) | E15: =IF($A15="","",SUMIFS(Transactions!$C$5:$C$2004,Transactions!$B$5:$B$2004,$A15,Transactions!$A$5:$A$2004,">="&DATE(Setup!$B$4,3,1),Transactions!$A$5:$A$2004,"<="&EOMONTH(DATE(Setup!$B$4,3,1),0))) | F15: =IF($A15="","",SUMIFS(Transactions!$C$5:$C$2004,Transactions!$B$5:$B$2004,$A15,Transactions!$A$5:$A$2004,">="&DATE(Setup!$B$4,4,1),Transactions!$A$5:$A$2004,"<="&EOMONTH(DATE(Setup!$B$4,4,1),0))) | G15: =IF($A15="","",SUMIFS(Transactions!$C$5:$C$2004,Transactions!$B$5:$B$2004,$A15,Transactions!$A$5:$A$2004,">="&DATE(Setup!$B$4,5,1),Transactions!$A$5:$A$2004,"<="&EOMONTH(DATE(Setup!$B$4,5,1),0))) | H15: =IF($A15="","",SUMIFS(Transactions!$C$5:$C$2004,Transactions!$B$5:$B$2004,$A15,Transactions!$A$5:$A$2004,">="&DATE(Setup!$B$4,6,1),Transactions!$A$5:$A$2004,"<="&EOMONTH(DATE(Setup!$B$4,6,1),0))) | I15: =IF($A15="","",SUMIFS(Transactions!$C$5:$C$2004,Transactions!$B$5:$B$2004,$A15,Transactions!$A$5:$A$2004,">="&DATE(Setup!$B$4,7,1),Transactions!$A$5:$A$2004,"<="&EOMONTH(DATE(Setup!$B$4,7,1),0))) | J15: =IF($A15="","",SUMIFS(Transactions!$C$5:$C$2004,Transactions!$B$5:$B$2004,$A15,Transactions!$A$5:$A$2004,">="&DATE(Setup!$B$4,8,1),Transactions!$A$5:$A$2004,"<="&EOMONTH(DATE(Setup!$B$4,8,1),0))) | K15: =IF($A15="","",SUMIFS(Transactions!$C$5:$C$2004,Transactions!$B$5:$B$2004,$A15,Transactions!$A$5:$A$2004,">="&DATE(Setup!$B$4,9,1),Transactions!$A$5:$A$2004,"<="&EOMONTH(DATE(Setup!$B$4,9,1),0))) | L15: =IF($A15="","",SUMIFS(Transactions!$C$5:$C$2004,Transactions!$B$5:$B$2004,$A15,Transactions!$A$5:$A$2004,">="&DATE(Setup!$B$4,10,1),Transactions!$A$5:$A$2004,"<="&EOMONTH(DATE(Setup!$B$4,10,1),0))) | M15: =IF($A15="","",SUMIFS(Transactions!$C$5:$C$2004,Transactions!$B$5:$B$2004,$A15,Transactions!$A$5:$A$2004,">="&DATE(Setup!$B$4,11,1),Transactions!$A$5:$A$2004,"<="&EOMONTH(DATE(Setup!$B$4,11,1),0))) | N15: =IF($A15="","",SUMIFS(Transactions!$C$5:$C$2004,Transactions!$B$5:$B$2004,$A15,Transactions!$A$5:$A$2004,">="&DATE(Setup!$B$4,12,1),Transactions!$A$5:$A$2004,"<="&EOMONTH(DATE(Setup!$B$4,12,1),0))) | O15: =IF($A15="","",SUM(C15:N15))
A16: =IF(Categories!A16="","",Categories!A16) | B16: =IF(Categories!A16="","",Categories!B16) | C16: =IF($A16="","",SUMIFS(Transactions!$C$5:$C$2004,Transactions!$B$5:$B$2004,$A16,Transactions!$A$5:$A$2004,">="&DATE(Setup!$B$4,1,1),Transactions!$A$5:$A$2004,"<="&EOMONTH(DATE(Setup!$B$4,1,1),0))) | D16: =IF($A16="","",SUMIFS(Transactions!$C$5:$C$2004,Transactions!$B$5:$B$2004,$A16,Transactions!$A$5:$A$2004,">="&DATE(Setup!$B$4,2,1),Transactions!$A$5:$A$2004,"<="&EOMONTH(DATE(Setup!$B$4,2,1),0))) | E16: =IF($A16="","",SUMIFS(Transactions!$C$5:$C$2004,Transactions!$B$5:$B$2004,$A16,Transactions!$A$5:$A$2004,">="&DATE(Setup!$B$4,3,1),Transactions!$A$5:$A$2004,"<="&EOMONTH(DATE(Setup!$B$4,3,1),0))) | F16: =IF($A16="","",SUMIFS(Transactions!$C$5:$C$2004,Transactions!$B$5:$B$2004,$A16,Transactions!$A$5:$A$2004,">="&DATE(Setup!$B$4,4,1),Transactions!$A$5:$A$2004,"<="&EOMONTH(DATE(Setup!$B$4,4,1),0))) | G16: =IF($A16="","",SUMIFS(Transactions!$C$5:$C$2004,Transactions!$B$5:$B$2004,$A16,Transactions!$A$5:$A$2004,">="&DATE(Setup!$B$4,5,1),Transactions!$A$5:$A$2004,"<="&EOMONTH(DATE(Setup!$B$4,5,1),0))) | H16: =IF($A16="","",SUMIFS(Transactions!$C$5:$C$2004,Transactions!$B$5:$B$2004,$A16,Transactions!$A$5:$A$2004,">="&DATE(Setup!$B$4,6,1),Transactions!$A$5:$A$2004,"<="&EOMONTH(DATE(Setup!$B$4,6,1),0))) | I16: =IF($A16="","",SUMIFS(Transactions!$C$5:$C$2004,Transactions!$B$5:$B$2004,$A16,Transactions!$A$5:$A$2004,">="&DATE(Setup!$B$4,7,1),Transactions!$A$5:$A$2004,"<="&EOMONTH(DATE(Setup!$B$4,7,1),0))) | J16: =IF($A16="","",SUMIFS(Transactions!$C$5:$C$2004,Transactions!$B$5:$B$2004,$A16,Transactions!$A$5:$A$2004,">="&DATE(Setup!$B$4,8,1),Transactions!$A$5:$A$2004,"<="&EOMONTH(DATE(Setup!$B$4,8,1),0))) | K16: =IF($A16="","",SUMIFS(Transactions!$C$5:$C$2004,Transactions!$B$5:$B$2004,$A16,Transactions!$A$5:$A$2004,">="&DATE(Setup!$B$4,9,1),Transactions!$A$5:$A$2004,"<="&EOMONTH(DATE(Setup!$B$4,9,1),0))) | L16: =IF($A16="","",SUMIFS(Transactions!$C$5:$C$2004,Transactions!$B$5:$B$2004,$A16,Transactions!$A$5:$A$2004,">="&DATE(Setup!$B$4,10,1),Transactions!$A$5:$A$2004,"<="&EOMONTH(DATE(Setup!$B$4,10,1),0))) | M16: =IF($A16="","",SUMIFS(Transactions!$C$5:$C$2004,Transactions!$B$5:$B$2004,$A16,Transactions!$A$5:$A$2004,">="&DATE(Setup!$B$4,11,1),Transactions!$A$5:$A$2004,"<="&EOMONTH(DATE(Setup!$B$4,11,1),0))) | N16: =IF($A16="","",SUMIFS(Transactions!$C$5:$C$2004,Transactions!$B$5:$B$2004,$A16,Transactions!$A$5:$A$2004,">="&DATE(Setup!$B$4,12,1),Transactions!$A$5:$A$2004,"<="&EOMONTH(DATE(Setup!$B$4,12,1),0))) | O16: =IF($A16="","",SUM(C16:N16))
... A44: =IF(Categories!A44="","",Categories!A44) | B44: =IF(Categories!A44="","",Categories!B44) | C44: =IF($A44="","",SUMIFS(Transactions!$C$5:$C$2004,Transactions!$B$5:$B$2004,$A44,Transactions!$A$5:$A$2004,">="&DATE(Setup!$B$4,1,1),Transactions!$A$5:$A$2004,"<="&EOMONTH(DATE(Setup!$B$4,1,1),0))) | D44: =IF($A44="","",SUMIFS(Transactions!$C$5:$C$2004,Transactions!$B$5:$B$2004,$A44,Transactions!$A$5:$A$2004,">="&DATE(Setup!$B$4,2,1),Transactions!$A$5:$A$2004,"<="&EOMONTH(DATE(Setup!$B$4,2,1),0))) | E44: =IF($A44="","",SUMIFS(Transactions!$C$5:$C$2004,Transactions!$B$5:$B$2004,$A44,Transactions!$A$5:$A$2004,">="&DATE(Setup!$B$4,3,1),Transactions!$A$5:$A$2004,"<="&EOMONTH(DATE(Setup!$B$4,3,1),0))) | F44: =IF($A44="","",SUMIFS(Transactions!$C$5:$C$2004,Transactions!$B$5:$B$2004,$A44,Transactions!$A$5:$A$2004,">="&DATE(Setup!$B$4,4,1),Transactions!$A$5:$A$2004,"<="&EOMONTH(DATE(Setup!$B$4,4,1),0))) | G44: =IF($A44="","",SUMIFS(Transactions!$C$5:$C$2004,Transactions!$B$5:$B$2004,$A44,Transactions!$A$5:$A$2004,">="&DATE(Setup!$B$4,5,1),Transactions!$A$5:$A$2004,"<="&EOMONTH(DATE(Setup!$B$4,5,1),0))) | H44: =IF($A44="","",SUMIFS(Transactions!$C$5:$C$2004,Transactions!$B$5:$B$2004,$A44,Transactions!$A$5:$A$2004,">="&DATE(Setup!$B$4,6,1),Transactions!$A$5:$A$2004,"<="&EOMONTH(DATE(Setup!$B$4,6,1),0))) | I44: =IF($A44="","",SUMIFS(Transactions!$C$5:$C$2004,Transactions!$B$5:$B$2004,$A44,Transactions!$A$5:$A$2004,">="&DATE(Setup!$B$4,7,1),Transactions!$A$5:$A$2004,"<="&EOMONTH(DATE(Setup!$B$4,7,1),0))) | J44: =IF($A44="","",SUMIFS(Transactions!$C$5:$C$2004,Transactions!$B$5:$B$2004,$A44,Transactions!$A$5:$A$2004,">="&DATE(Setup!$B$4,8,1),Transactions!$A$5:$A$2004,"<="&EOMONTH(DATE(Setup!$B$4,8,1),0))) | K44: =IF($A44="","",SUMIFS(Transactions!$C$5:$C$2004,Transactions!$B$5:$B$2004,$A44,Transactions!$A$5:$A$2004,">="&DATE(Setup!$B$4,9,1),Transactions!$A$5:$A$2004,"<="&EOMONTH(DATE(Setup!$B$4,9,1),0))) | L44: =IF($A44="","",SUMIFS(Transactions!$C$5:$C$2004,Transactions!$B$5:$B$2004,$A44,Transactions!$A$5:$A$2004,">="&DATE(Setup!$B$4,10,1),Transactions!$A$5:$A$2004,"<="&EOMONTH(DATE(Setup!$B$4,10,1),0))) | M44: =IF($A44="","",SUMIFS(Transactions!$C$5:$C$2004,Transactions!$B$5:$B$2004,$A44,Transactions!$A$5:$A$2004,">="&DATE(Setup!$B$4,11,1),Transactions!$A$5:$A$2004,"<="&EOMONTH(DATE(Setup!$B$4,11,1),0))) | N44: =IF($A44="","",SUMIFS(Transactions!$C$5:$C$2004,Transactions!$B$5:$B$2004,$A44,Transactions!$A$5:$A$2004,">="&DATE(Setup!$B$4,12,1),Transactions!$A$5:$A$2004,"<="&EOMONTH(DATE(Setup!$B$4,12,1),0))) | O44: =IF($A44="","",SUM(C44:N44))
A46: TOTAL INCOME | C46: =SUMIFS(C5:C44,$B$5:$B$44,"Income") | D46: =SUMIFS(D5:D44,$B$5:$B$44,"Income") | E46: =SUMIFS(E5:E44,$B$5:$B$44,"Income") | F46: =SUMIFS(F5:F44,$B$5:$B$44,"Income") | G46: =SUMIFS(G5:G44,$B$5:$B$44,"Income") | H46: =SUMIFS(H5:H44,$B$5:$B$44,"Income") | I46: =SUMIFS(I5:I44,$B$5:$B$44,"Income") | J46: =SUMIFS(J5:J44,$B$5:$B$44,"Income") | ... O46: =SUMIFS(O5:O44,$B$5:$B$44,"Income")
A47: TOTAL NEEDS | C47: =SUMIFS(C5:C44,$B$5:$B$44,"Need") | D47: =SUMIFS(D5:D44,$B$5:$B$44,"Need") | E47: =SUMIFS(E5:E44,$B$5:$B$44,"Need") | F47: =SUMIFS(F5:F44,$B$5:$B$44,"Need") | G47: =SUMIFS(G5:G44,$B$5:$B$44,"Need") | H47: =SUMIFS(H5:H44,$B$5:$B$44,"Need") | I47: =SUMIFS(I5:I44,$B$5:$B$44,"Need") | J47: =SUMIFS(J5:J44,$B$5:$B$44,"Need") | ... O47: =SUMIFS(O5:O44,$B$5:$B$44,"Need")
A48: TOTAL WANTS | C48: =SUMIFS(C5:C44,$B$5:$B$44,"Want") | D48: =SUMIFS(D5:D44,$B$5:$B$44,"Want") | E48: =SUMIFS(E5:E44,$B$5:$B$44,"Want") | F48: =SUMIFS(F5:F44,$B$5:$B$44,"Want") | G48: =SUMIFS(G5:G44,$B$5:$B$44,"Want") | H48: =SUMIFS(H5:H44,$B$5:$B$44,"Want") | I48: =SUMIFS(I5:I44,$B$5:$B$44,"Want") | J48: =SUMIFS(J5:J44,$B$5:$B$44,"Want") | ... O48: =SUMIFS(O5:O44,$B$5:$B$44,"Want")
A49: TOTAL SAVINGS | C49: =SUMIFS(C5:C44,$B$5:$B$44,"Savings") | D49: =SUMIFS(D5:D44,$B$5:$B$44,"Savings") | E49: =SUMIFS(E5:E44,$B$5:$B$44,"Savings") | F49: =SUMIFS(F5:F44,$B$5:$B$44,"Savings") | G49: =SUMIFS(G5:G44,$B$5:$B$44,"Savings") | H49: =SUMIFS(H5:H44,$B$5:$B$44,"Savings") | I49: =SUMIFS(I5:I44,$B$5:$B$44,"Savings") | J49: =SUMIFS(J5:J44,$B$5:$B$44,"Savings") | ... O49: =SUMIFS(O5:O44,$B$5:$B$44,"Savings")
A50: LEFT OVER (income − all outflows) | C50: =C46-C47-C48-C49 | D50: =D46-D47-D48-D49 | E50: =E46-E47-E48-E49 | F50: =F46-F47-F48-F49 | G50: =G46-G47-G48-G49 | H50: =H46-H47-H48-H49 | I50: =I46-I47-I48-I49 | J50: =J46-J47-J48-J49 | ... O50: =O46-O47-O48-O49
A51: Savings rate | C51: =IF(C46=0,"",C49/C46) | D51: =IF(D46=0,"",D49/D46) | E51: =IF(E46=0,"",E49/E46) | F51: =IF(F46=0,"",F49/F46) | G51: =IF(G46=0,"",G49/G46) | H51: =IF(H46=0,"",H49/H46) | I51: =IF(I46=0,"",I49/I46) | J51: =IF(J46=0,"",J49/J46) | ... O51: =IF(O46=0,"",O49/O46)

Sheet 50-30-20 Check
A1: 50 / 30 / 20 Check — whole year
A2: A simple rule of thumb: 50% needs, 30% wants, 20% savings
A4: Bucket | B4: Your share of income | C4: Rule of thumb | D4: Comment
A5: Needs | B5: =IF('Year Summary'!O46=0,0,'Year Summary'!O47/'Year Summary'!O46) | C5: 0.5 | D5: =IF('Year Summary'!O46=0,"Add some transactions first",IF(B5<=C5,"On track ✔","Higher than the rule — look for cuts here"))
A6: Wants | B6: =IF('Year Summary'!O46=0,0,'Year Summary'!O48/'Year Summary'!O46) | C6: 0.3 | D6: =IF('Year Summary'!O46=0,"Add some transactions first",IF(B6<=C6,"On track ✔","Higher than the rule — look for cuts here"))
A7: Savings | B7: =IF('Year Summary'!O46=0,0,'Year Summary'!O49/'Year Summary'!O46) | C7: 0.2 | D7: =IF('Year Summary'!O46=0,"Add some transactions first",IF(B7>=C7,"On track ✔","Try to save a little more"))
A10: Tax, GST or accounts question? Rajput Lalit & Associates — WhatsApp +91 93549 53603 · www.rajputlalitassociates.in

Sheet Setup
A1: Setup
A3: Your name
A4: Year | B4: 2026
A5: Starting bank balance (optional) | B5: 0
A7: Monthly budgets are entered in the 'Categories' sheet, column C.

Sheet Transactions
A1: Transactions
A2: One line per income or expense. Type and month fill in by themselves.
A4: Date | B4: Category | C4: Amount (₹) | D4: Paid by (Cash/UPI/Card/Bank) | E4: Note | F4: Type | G4: Month
F5: =IF(B5="","",IFERROR(INDEX(Categories!$B$5:$B$44,MATCH(B5,Categories!$A$5:$A$44,0)),"?")) | G5: =IF(A5="","",MONTH(A5))
F6: =IF(B6="","",IFERROR(INDEX(Categories!$B$5:$B$44,MATCH(B6,Categories!$A$5:$A$44,0)),"?")) | G6: =IF(A6="","",MONTH(A6))
F7: =IF(B7="","",IFERROR(INDEX(Categories!$B$5:$B$44,MATCH(B7,Categories!$A$5:$A$44,0)),"?")) | G7: =IF(A7="","",MONTH(A7))
F8: =IF(B8="","",IFERROR(INDEX(Categories!$B$5:$B$44,MATCH(B8,Categories!$A$5:$A$44,0)),"?")) | G8: =IF(A8="","",MONTH(A8))
F9: =IF(B9="","",IFERROR(INDEX(Categories!$B$5:$B$44,MATCH(B9,Categories!$A$5:$A$44,0)),"?")) | G9: =IF(A9="","",MONTH(A9))
F10: =IF(B10="","",IFERROR(INDEX(Categories!$B$5:$B$44,MATCH(B10,Categories!$A$5:$A$44,0)),"?")) | G10: =IF(A10="","",MONTH(A10))
F11: =IF(B11="","",IFERROR(INDEX(Categories!$B$5:$B$44,MATCH(B11,Categories!$A$5:$A$44,0)),"?")) | G11: =IF(A11="","",MONTH(A11))
F12: =IF(B12="","",IFERROR(INDEX(Categories!$B$5:$B$44,MATCH(B12,Categories!$A$5:$A$44,0)),"?")) | G12: =IF(A12="","",MONTH(A12))
F13: =IF(B13="","",IFERROR(INDEX(Categories!$B$5:$B$44,MATCH(B13,Categories!$A$5:$A$44,0)),"?")) | G13: =IF(A13="","",MONTH(A13))
F14: =IF(B14="","",IFERROR(INDEX(Categories!$B$5:$B$44,MATCH(B14,Categories!$A$5:$A$44,0)),"?")) | G14: =IF(A14="","",MONTH(A14))
F15: =IF(B15="","",IFERROR(INDEX(Categories!$B$5:$B$44,MATCH(B15,Categories!$A$5:$A$44,0)),"?")) | G15: =IF(A15="","",MONTH(A15))
F16: =IF(B16="","",IFERROR(INDEX(Categories!$B$5:$B$44,MATCH(B16,Categories!$A$5:$A$44,0)),"?")) | G16: =IF(A16="","",MONTH(A16))
... F2004: =IF(B2004="","",IFERROR(INDEX(Categories!$B$5:$B$44,MATCH(B2004,Categories!$A$5:$A$44,0)),"?")) | G2004: =IF(A2004="","",MONTH(A2004))

Sheet Categories
A1: Categories
A2: Edit names freely. Type: Income, Need, Want or Savings.
A4: Category | B4: Type | C4: Monthly budget (₹)
A5: Salary | B5: Income
A6: Business / freelance income | B6: Income
A7: Rent received | B7: Income
A8: Interest & dividends | B8: Income
A9: Other income | B9: Income
A10: Rent / home loan EMI | B10: Need
A11: Groceries | B11: Need
A12: Electricity, gas & water | B12: Need
A13: Mobile & internet | B13: Need
A14: Fuel & transport | B14: Need
A15: School / college fees | B15: Need
A16: Medical & insurance | B16: Need
... A29: Miscellaneous | B29: Want
