Workbook

Sheet How to use
B1: Debt & EMI Payoff Tracker — Snowball / Avalanche
B2: Rajput Lalit & Associates · www.rajputlalitassociates.in · WhatsApp +91 93549 53603
B4: Steps
A5: 1 | B5: In 'My Loans' list every loan and card: amount outstanding today, yearly interest rate and the EMI / minimum payment.
A6: 2 | B6: Choose a method: Snowball pays off the smallest balance first (quick wins); Avalanche pays the highest interest first (saves the most money).
A7: 3 | B7: Enter the extra amount you can pay every month on top of all EMIs — even ₹1,000 makes a difference.
A8: 4 | B8: 'Dashboard' shows your debt-free date, total interest, and the month each loan closes. 'Schedule' shows every month and the chart shows your total debt going down.
A9: 5 | B9: When a loan closes, its EMI automatically moves to the next loan in the order — that is what makes the method powerful.
B11: Good to know
B12: • Before prepaying a home or other loan, check prepayment charges with your bank.
B13: • Interest is worked out monthly on the reducing balance — the usual method for EMIs and cards.
B14: • If the minimum payment is less than the monthly interest, that loan never closes — the sheet warns you.
B16: Cells shaded light yellow are for your entries. White cells contain formulas — please don't type over them.
B18: Licensed for use in your own business. Please do not resell or share publicly. This template is a working aid, not professional advice.

Sheet Dashboard
A1: Dashboard
A2: Updates as you change 'My Loans'
A4: Total debt today | B4: =SUM('My Loans'!C6:C15)
A5: Paying every month (EMIs + extra) | B5: =(SUM('My Loans'!$E$6:$E$15)+'My Loans'!$D$3)
A6: Months to become debt-free | B6: =IF(Schedule!BB364>0.5,"More than 30 years — increase payments",COUNTIF(Schedule!BB5:BB364,">0.5")+1)
A7: Debt-free by | B7: =IF(ISNUMBER(B6),EOMONTH(TODAY(),B6-1),"—")
A8: Total interest you will pay | B8: =SUM(Schedule!N5:W364)-SUM(Schedule!D5:M364)
A10: Loan | B10: Order | C10: Closes in month # | D10: Closes by
A11: =IF(N('My Loans'!C6)<=0,"",'My Loans'!B6) | B11: =IF(A11="","",Schedule!D3) | C11: =IF(A11="","",IF(Schedule!AR364>0.5,"Never — EMI too low",COUNTIF(Schedule!AR5:AR364,">0.5")+1)) | D11: =IF(ISNUMBER(C11),EOMONTH(TODAY(),C11-1),"")
A12: =IF(N('My Loans'!C7)<=0,"",'My Loans'!B7) | B12: =IF(A12="","",Schedule!E3) | C12: =IF(A12="","",IF(Schedule!AS364>0.5,"Never — EMI too low",COUNTIF(Schedule!AS5:AS364,">0.5")+1)) | D12: =IF(ISNUMBER(C12),EOMONTH(TODAY(),C12-1),"")
A13: =IF(N('My Loans'!C8)<=0,"",'My Loans'!B8) | B13: =IF(A13="","",Schedule!F3) | C13: =IF(A13="","",IF(Schedule!AT364>0.5,"Never — EMI too low",COUNTIF(Schedule!AT5:AT364,">0.5")+1)) | D13: =IF(ISNUMBER(C13),EOMONTH(TODAY(),C13-1),"")
A14: =IF(N('My Loans'!C9)<=0,"",'My Loans'!B9) | B14: =IF(A14="","",Schedule!G3) | C14: =IF(A14="","",IF(Schedule!AU364>0.5,"Never — EMI too low",COUNTIF(Schedule!AU5:AU364,">0.5")+1)) | D14: =IF(ISNUMBER(C14),EOMONTH(TODAY(),C14-1),"")
A15: =IF(N('My Loans'!C10)<=0,"",'My Loans'!B10) | B15: =IF(A15="","",Schedule!H3) | C15: =IF(A15="","",IF(Schedule!AV364>0.5,"Never — EMI too low",COUNTIF(Schedule!AV5:AV364,">0.5")+1)) | D15: =IF(ISNUMBER(C15),EOMONTH(TODAY(),C15-1),"")
A16: =IF(N('My Loans'!C11)<=0,"",'My Loans'!B11) | B16: =IF(A16="","",Schedule!I3) | C16: =IF(A16="","",IF(Schedule!AW364>0.5,"Never — EMI too low",COUNTIF(Schedule!AW5:AW364,">0.5")+1)) | D16: =IF(ISNUMBER(C16),EOMONTH(TODAY(),C16-1),"")
A17: =IF(N('My Loans'!C12)<=0,"",'My Loans'!B12) | B17: =IF(A17="","",Schedule!J3) | C17: =IF(A17="","",IF(Schedule!AX364>0.5,"Never — EMI too low",COUNTIF(Schedule!AX5:AX364,">0.5")+1)) | D17: =IF(ISNUMBER(C17),EOMONTH(TODAY(),C17-1),"")
A18: =IF(N('My Loans'!C13)<=0,"",'My Loans'!B13) | B18: =IF(A18="","",Schedule!K3) | C18: =IF(A18="","",IF(Schedule!AY364>0.5,"Never — EMI too low",COUNTIF(Schedule!AY5:AY364,">0.5")+1)) | D18: =IF(ISNUMBER(C18),EOMONTH(TODAY(),C18-1),"")
A19: =IF(N('My Loans'!C14)<=0,"",'My Loans'!B14) | B19: =IF(A19="","",Schedule!L3) | C19: =IF(A19="","",IF(Schedule!AZ364>0.5,"Never — EMI too low",COUNTIF(Schedule!AZ5:AZ364,">0.5")+1)) | D19: =IF(ISNUMBER(C19),EOMONTH(TODAY(),C19-1),"")
A20: =IF(N('My Loans'!C15)<=0,"",'My Loans'!B15) | B20: =IF(A20="","",Schedule!M3) | C20: =IF(A20="","",IF(Schedule!BA364>0.5,"Never — EMI too low",COUNTIF(Schedule!BA5:BA364,">0.5")+1)) | D20: =IF(ISNUMBER(C20),EOMONTH(TODAY(),C20-1),"")
A23: Tax, GST or accounts question? Rajput Lalit & Associates — WhatsApp +91 93549 53603 · www.rajputlalitassociates.in

Sheet My Loans
A1: My Loans & Cards
A2: Up to 10. Yellow cells are yours to fill.
A3: Method | B3: Avalanche | C3: Extra per month (₹) | D3: 2000
A5: # | B5: Loan / card | C5: Outstanding today (₹) | D5: Interest % per year | E5: EMI / minimum (₹) | F5: Monthly interest now | G5: Sort key
A6: 1 | B6: Credit card | C6: 60000 | D6: 36 | E6: 3000 | F6: =IF(C6="","",C6*D6/1200) | G6: =IF(N(C6)<=0,1E+15,IF($B$3="Snowball",C6,-D6))+ROW()/1E+6
A7: 2 | B7: Personal loan | C7: 200000 | D7: 14 | E7: 7000 | F7: =IF(C7="","",C7*D7/1200) | G7: =IF(N(C7)<=0,1E+15,IF($B$3="Snowball",C7,-D7))+ROW()/1E+6
A8: 3 | B8: Car loan | C8: 350000 | D8: 9.5 | E8: 9000 | F8: =IF(C8="","",C8*D8/1200) | G8: =IF(N(C8)<=0,1E+15,IF($B$3="Snowball",C8,-D8))+ROW()/1E+6
A9: 4 | F9: =IF(C9="","",C9*D9/1200) | G9: =IF(N(C9)<=0,1E+15,IF($B$3="Snowball",C9,-D9))+ROW()/1E+6
A10: 5 | F10: =IF(C10="","",C10*D10/1200) | G10: =IF(N(C10)<=0,1E+15,IF($B$3="Snowball",C10,-D10))+ROW()/1E+6
A11: 6 | F11: =IF(C11="","",C11*D11/1200) | G11: =IF(N(C11)<=0,1E+15,IF($B$3="Snowball",C11,-D11))+ROW()/1E+6
A12: 7 | F12: =IF(C12="","",C12*D12/1200) | G12: =IF(N(C12)<=0,1E+15,IF($B$3="Snowball",C12,-D12))+ROW()/1E+6
A13: 8 | F13: =IF(C13="","",C13*D13/1200) | G13: =IF(N(C13)<=0,1E+15,IF($B$3="Snowball",C13,-D13))+ROW()/1E+6
A14: 9 | F14: =IF(C14="","",C14*D14/1200) | G14: =IF(N(C14)<=0,1E+15,IF($B$3="Snowball",C14,-D14))+ROW()/1E+6
A15: 10 | F15: =IF(C15="","",C15*D15/1200) | G15: =IF(N(C15)<=0,1E+15,IF($B$3="Snowball",C15,-D15))+ROW()/1E+6
B17: Red EMI = it doesn't even cover the monthly interest, so that loan will never close. Increase it.
B18: The sample rows are only an example — overwrite or clear them.

Sheet Schedule
A1: Month-by-month schedule
A2: Calculated — no entries needed here
A3: Order → | D3: =COUNTIF('My Loans'!$G$6:$G$15,"<"&'My Loans'!G6)+1 | E3: =COUNTIF('My Loans'!$G$6:$G$15,"<"&'My Loans'!G7)+1 | F3: =COUNTIF('My Loans'!$G$6:$G$15,"<"&'My Loans'!G8)+1 | G3: =COUNTIF('My Loans'!$G$6:$G$15,"<"&'My Loans'!G9)+1 | H3: =COUNTIF('My Loans'!$G$6:$G$15,"<"&'My Loans'!G10)+1 | I3: =COUNTIF('My Loans'!$G$6:$G$15,"<"&'My Loans'!G11)+1 | J3: =COUNTIF('My Loans'!$G$6:$G$15,"<"&'My Loans'!G12)+1 | K3: =COUNTIF('My Loans'!$G$6:$G$15,"<"&'My Loans'!G13)+1 | L3: =COUNTIF('My Loans'!$G$6:$G$15,"<"&'My Loans'!G14)+1 | M3: =COUNTIF('My Loans'!$G$6:$G$15,"<"&'My Loans'!G15)+1 | N3: =COUNTIF('My Loans'!$G$6:$G$15,"<"&'My Loans'!G6)+1 | O3: =COUNTIF('My Loans'!$G$6:$G$15,"<"&'My Loans'!G7)+1 | P3: =COUNTIF('My Loans'!$G$6:$G$15,"<"&'My Loans'!G8)+1 | Q3: =COUNTIF('My Loans'!$G$6:$G$15,"<"&'My Loans'!G9)+1 | R3: =COUNTIF('My Loans'!$G$6:$G$15,"<"&'My Loans'!G10)+1 | S3: =COUNTIF('My Loans'!$G$6:$G$15,"<"&'My Loans'!G11)+1 | T3: =COUNTIF('My Loans'!$G$6:$G$15,"<"&'My Loans'!G12)+1 | U3: =COUNTIF('My Loans'!$G$6:$G$15,"<"&'My Loans'!G13)+1 | V3: =COUNTIF('My Loans'!$G$6:$G$15,"<"&'My Loans'!G14)+1 | W3: =COUNTIF('My Loans'!$G$6:$G$15,"<"&'My Loans'!G15)+1 | X3: =COUNTIF('My Loans'!$G$6:$G$15,"<"&'My Loans'!G6)+1 | Y3: =COUNTIF('My Loans'!$G$6:$G$15,"<"&'My Loans'!G7)+1 | Z3: =COUNTIF('My Loans'!$G$6:$G$15,"<"&'My Loans'!G8)+1 | AA3: =COUNTIF('My Loans'!$G$6:$G$15,"<"&'My Loans'!G9)+1 | AB3: =COUNTIF('My Loans'!$G$6:$G$15,"<"&'My Loans'!G10)+1 | AC3: =COUNTIF('My Loans'!$G$6:$G$15,"<"&'My Loans'!G11)+1 | AD3: =COUNTIF('My Loans'!$G$6:$G$15,"<"&'My Loans'!G12)+1 | AE3: =COUNTIF('My Loans'!$G$6:$G$15,"<"&'My Loans'!G13)+1 | AF3: =COUNTIF('My Loans'!$G$6:$G$15,"<"&'My Loans'!G14)+1 | AG3: =COUNTIF('My Loans'!$G$6:$G$15,"<"&'My Loans'!G15)+1 | AH3: =COUNTIF('My Loans'!$G$6:$G$15,"<"&'My Loans'!G6)+1 | AI3: =COUNTIF('My Loans'!$G$6:$G$15,"<"&'My Loans'!G7)+1 | AJ3: =COUNTIF('My Loans'!$G$6:$G$15,"<"&'My Loans'!G8)+1 | AK3: =COUNTIF('My Loans'!$G$6:$G$15,"<"&'My Loans'!G9)+1 | AL3: =COUNTIF('My Loans'!$G$6:$G$15,"<"&'My Loans'!G10)+1 | AM3: =COUNTIF('My Loans'!$G$6:$G$15,"<"&'My Loans'!G11)+1 | AN3: =COUNTIF('My Loans'!$G$6:$G$15,"<"&'My Loans'!G12)+1 | AO3: =COUNTIF('My Loans'!$G$6:$G$15,"<"&'My Loans'!G13)+1 | AP3: =COUNTIF('My Loans'!$G$6:$G$15,"<"&'My Loans'!G14)+1 | AQ3: =COUNTIF('My Loans'!$G$6:$G$15,"<"&'My Loans'!G15)+1 | AR3: =COUNTIF('My Loans'!$G$6:$G$15,"<"&'My Loans'!G6)+1 | AS3: =COUNTIF('My Loans'!$G$6:$G$15,"<"&'My Loans'!G7)+1 | AT3: =COUNTIF('My Loans'!$G$6:$G$15,"<"&'My Loans'!G8)+1 | AU3: =COUNTIF('My Loans'!$G$6:$G$15,"<"&'My Loans'!G9)+1 | AV3: =COUNTIF('My Loans'!$G$6:$G$15,"<"&'My Loans'!G10)+1 | AW3: =COUNTIF('My Loans'!$G$6:$G$15,"<"&'My Loans'!G11)+1 | AX3: =COUNTIF('My Loans'!$G$6:$G$15,"<"&'My Loans'!G12)+1 | AY3: =COUNTIF('My Loans'!$G$6:$G$15,"<"&'My Loans'!G13)+1 | AZ3: =COUNTIF('My Loans'!$G$6:$G$15,"<"&'My Loans'!G14)+1 | BA3: =COUNTIF('My Loans'!$G$6:$G$15,"<"&'My Loans'!G15)+1
A4: Month | B4: Date | C4: Money for extra | D4: ='My Loans'!B6&" — Opening" | E4: ='My Loans'!B7&" — Opening" | F4: ='My Loans'!B8&" — Opening" | G4: ='My Loans'!B9&" — Opening" | H4: ='My Loans'!B10&" — Opening" | I4: ='My Loans'!B11&" — Opening" | J4: ='My Loans'!B12&" — Opening" | K4: ='My Loans'!B13&" — Opening" | L4: ='My Loans'!B14&" — Opening" | M4: ='My Loans'!B15&" — Opening" | N4: ='My Loans'!B6&" — With interest" | O4: ='My Loans'!B7&" — With interest" | P4: ='My Loans'!B8&" — With interest" | Q4: ='My Loans'!B9&" — With interest" | R4: ='My Loans'!B10&" — With interest" | S4: ='My Loans'!B11&" — With interest" | T4: ='My Loans'!B12&" — With interest" | U4: ='My Loans'!B13&" — With interest" | V4: ='My Loans'!B14&" — With interest" | W4: ='My Loans'!B15&" — With interest" | X4: ='My Loans'!B6&" — EMI paid" | Y4: ='My Loans'!B7&" — EMI paid" | Z4: ='My Loans'!B8&" — EMI paid" | AA4: ='My Loans'!B9&" — EMI paid" | AB4: ='My Loans'!B10&" — EMI paid" | AC4: ='My Loans'!B11&" — EMI paid" | AD4: ='My Loans'!B12&" — EMI paid" | AE4: ='My Loans'!B13&" — EMI paid" | AF4: ='My Loans'!B14&" — EMI paid" | AG4: ='My Loans'!B15&" — EMI paid" | AH4: ='My Loans'!B6&" — Extra paid" | AI4: ='My Loans'!B7&" — Extra paid" | AJ4: ='My Loans'!B8&" — Extra paid" | AK4: ='My Loans'!B9&" — Extra paid" | AL4: ='My Loans'!B10&" — Extra paid" | AM4: ='My Loans'!B11&" — Extra paid" | AN4: ='My Loans'!B12&" — Extra paid" | AO4: ='My Loans'!B13&" — Extra paid" | AP4: ='My Loans'!B14&" — Extra paid" | AQ4: ='My Loans'!B15&" — Extra paid" | AR4: ='My Loans'!B6&" — Closing" | AS4: ='My Loans'!B7&" — Closing" | AT4: ='My Loans'!B8&" — Closing" | AU4: ='My Loans'!B9&" — Closing" | AV4: ='My Loans'!B10&" — Closing" | AW4: ='My Loans'!B11&" — Closing" | AX4: ='My Loans'!B12&" — Closing" | AY4: ='My Loans'!B13&" — Closing" | AZ4: ='My Loans'!B14&" — Closing" | BA4: ='My Loans'!B15&" — Closing" | BB4: TOTAL DEBT
A5: 1 | B5: =EOMONTH(TODAY(),0) | C5: =MAX(0,(SUM('My Loans'!$E$6:$E$15)+'My Loans'!$D$3)-SUM($X5:$AG5)) | D5: =MAX(0,N('My Loans'!C6)) | E5: =MAX(0,N('My Loans'!C7)) | F5: =MAX(0,N('My Loans'!C8)) | G5: =MAX(0,N('My Loans'!C9)) | H5: =MAX(0,N('My Loans'!C10)) | I5: =MAX(0,N('My Loans'!C11)) | J5: =MAX(0,N('My Loans'!C12)) | K5: =MAX(0,N('My Loans'!C13)) | L5: =MAX(0,N('My Loans'!C14)) | M5: =MAX(0,N('My Loans'!C15)) | N5: =IF(D5<0.5,0,D5*(1+N('My Loans'!D6)/1200)) | O5: =IF(E5<0.5,0,E5*(1+N('My Loans'!D7)/1200)) | P5: =IF(F5<0.5,0,F5*(1+N('My Loans'!D8)/1200)) | Q5: =IF(G5<0.5,0,G5*(1+N('My Loans'!D9)/1200)) | R5: =IF(H5<0.5,0,H5*(1+N('My Loans'!D10)/1200)) | S5: =IF(I5<0.5,0,I5*(1+N('My Loans'!D11)/1200)) | T5: =IF(J5<0.5,0,J5*(1+N('My Loans'!D12)/1200)) | U5: =IF(K5<0.5,0,K5*(1+N('My Loans'!D13)/1200)) | V5: =IF(L5<0.5,0,L5*(1+N('My Loans'!D14)/1200)) | W5: =IF(M5<0.5,0,M5*(1+N('My Loans'!D15)/1200)) | X5: =MIN(N5,N('My Loans'!E6)) | Y5: =MIN(O5,N('My Loans'!E7)) | Z5: =MIN(P5,N('My Loans'!E8)) | AA5: =MIN(Q5,N('My Loans'!E9)) | AB5: =MIN(R5,N('My Loans'!E10)) | AC5: =MIN(S5,N('My Loans'!E11)) | AD5: =MIN(T5,N('My Loans'!E12)) | AE5: =MIN(U5,N('My Loans'!E13)) | AF5: =MIN(V5,N('My Loans'!E14)) | AG5: =MIN(W5,N('My Loans'!E15)) | AH5: =MIN(N5-X5,MAX(0,$C5-SUMPRODUCT(($D$3:$M$3<D$3)*($N5:$W5-$X5:$AG5)))) | AI5: =MIN(O5-Y5,MAX(0,$C5-SUMPRODUCT(($D$3:$M$3<E$3)*($N5:$W5-$X5:$AG5)))) | AJ5: =MIN(P5-Z5,MAX(0,$C5-SUMPRODUCT(($D$3:$M$3<F$3)*($N5:$W5-$X5:$AG5)))) | AK5: =MIN(Q5-AA5,MAX(0,$C5-SUMPRODUCT(($D$3:$M$3<G$3)*($N5:$W5-$X5:$AG5)))) | AL5: =MIN(R5-AB5,MAX(0,$C5-SUMPRODUCT(($D$3:$M$3<H$3)*($N5:$W5-$X5:$AG5)))) | AM5: =MIN(S5-AC5,MAX(0,$C5-SUMPRODUCT(($D$3:$M$3<I$3)*($N5:$W5-$X5:$AG5)))) | AN5: =MIN(T5-AD5,MAX(0,$C5-SUMPRODUCT(($D$3:$M$3<J$3)*($N5:$W5-$X5:$AG5)))) | AO5: =MIN(U5-AE5,MAX(0,$C5-SUMPRODUCT(($D$3:$M$3<K$3)*($N5:$W5-$X5:$AG5)))) | ... AQ5: =MIN(W5-AG5,MAX(0,$C5-SUMPRODUCT(($D$3:$M$3<M$3)*($N5:$W5-$X5:$AG5)))) | AR5: =ROUND(N5-X5-AH5,2) | AS5: =ROUND(O5-Y5-AI5,2) | AT5: =ROUND(P5-Z5-AJ5,2) | AU5: =ROUND(Q5-AA5-AK5,2) | AV5: =ROUND(R5-AB5-AL5,2) | AW5: =ROUND(S5-AC5-AM5,2) | AX5: =ROUND(T5-AD5-AN5,2) | AY5: =ROUND(U5-AE5-AO5,2) | ... BA5: =ROUND(W5-AG5-AQ5,2) | BB5: =SUM(AR5:BA5)
A6: 2 | B6: =EOMONTH(TODAY(),1) | C6: =MAX(0,(SUM('My Loans'!$E$6:$E$15)+'My Loans'!$D$3)-SUM($X6:$AG6)) | D6: =MAX(0,AR5) | E6: =MAX(0,AS5) | F6: =MAX(0,AT5) | G6: =MAX(0,AU5) | H6: =MAX(0,AV5) | I6: =MAX(0,AW5) | J6: =MAX(0,AX5) | K6: =MAX(0,AY5) | ... M6: =MAX(0,BA5) | N6: =IF(D6<0.5,0,D6*(1+N('My Loans'!D6)/1200)) | O6: =IF(E6<0.5,0,E6*(1+N('My Loans'!D7)/1200)) | P6: =IF(F6<0.5,0,F6*(1+N('My Loans'!D8)/1200)) | Q6: =IF(G6<0.5,0,G6*(1+N('My Loans'!D9)/1200)) | R6: =IF(H6<0.5,0,H6*(1+N('My Loans'!D10)/1200)) | S6: =IF(I6<0.5,0,I6*(1+N('My Loans'!D11)/1200)) | T6: =IF(J6<0.5,0,J6*(1+N('My Loans'!D12)/1200)) | U6: =IF(K6<0.5,0,K6*(1+N('My Loans'!D13)/1200)) | V6: =IF(L6<0.5,0,L6*(1+N('My Loans'!D14)/1200)) | W6: =IF(M6<0.5,0,M6*(1+N('My Loans'!D15)/1200)) | X6: =MIN(N6,N('My Loans'!E6)) | Y6: =MIN(O6,N('My Loans'!E7)) | Z6: =MIN(P6,N('My Loans'!E8)) | AA6: =MIN(Q6,N('My Loans'!E9)) | AB6: =MIN(R6,N('My Loans'!E10)) | AC6: =MIN(S6,N('My Loans'!E11)) | AD6: =MIN(T6,N('My Loans'!E12)) | AE6: =MIN(U6,N('My Loans'!E13)) | AF6: =MIN(V6,N('My Loans'!E14)) | AG6: =MIN(W6,N('My Loans'!E15)) | AH6: =MIN(N6-X6,MAX(0,$C6-SUMPRODUCT(($D$3:$M$3<D$3)*($N6:$W6-$X6:$AG6)))) | AI6: =MIN(O6-Y6,MAX(0,$C6-SUMPRODUCT(($D$3:$M$3<E$3)*($N6:$W6-$X6:$AG6)))) | AJ6: =MIN(P6-Z6,MAX(0,$C6-SUMPRODUCT(($D$3:$M$3<F$3)*($N6:$W6-$X6:$AG6)))) | AK6: =MIN(Q6-AA6,MAX(0,$C6-SUMPRODUCT(($D$3:$M$3<G$3)*($N6:$W6-$X6:$AG6)))) | AL6: =MIN(R6-AB6,MAX(0,$C6-SUMPRODUCT(($D$3:$M$3<H$3)*($N6:$W6-$X6:$AG6)))) | AM6: =MIN(S6-AC6,MAX(0,$C6-SUMPRODUCT(($D$3:$M$3<I$3)*($N6:$W6-$X6:$AG6)))) | AN6: =MIN(T6-AD6,MAX(0,$C6-SUMPRODUCT(($D$3:$M$3<J$3)*($N6:$W6-$X6:$AG6)))) | AO6: =MIN(U6-AE6,MAX(0,$C6-SUMPRODUCT(($D$3:$M$3<K$3)*($N6:$W6-$X6:$AG6)))) | ... AQ6: =MIN(W6-AG6,MAX(0,$C6-SUMPRODUCT(($D$3:$M$3<M$3)*($N6:$W6-$X6:$AG6)))) | AR6: =ROUND(N6-X6-AH6,2) | AS6: =ROUND(O6-Y6-AI6,2) | AT6: =ROUND(P6-Z6-AJ6,2) | AU6: =ROUND(Q6-AA6-AK6,2) | AV6: =ROUND(R6-AB6-AL6,2) | AW6: =ROUND(S6-AC6-AM6,2) | AX6: =ROUND(T6-AD6-AN6,2) | AY6: =ROUND(U6-AE6-AO6,2) | ... BA6: =ROUND(W6-AG6-AQ6,2) | BB6: =SUM(AR6:BA6)
A7: 3 | B7: =EOMONTH(TODAY(),2) | C7: =MAX(0,(SUM('My Loans'!$E$6:$E$15)+'My Loans'!$D$3)-SUM($X7:$AG7)) | D7: =MAX(0,AR6) | E7: =MAX(0,AS6) | F7: =MAX(0,AT6) | G7: =MAX(0,AU6) | H7: =MAX(0,AV6) | I7: =MAX(0,AW6) | J7: =MAX(0,AX6) | K7: =MAX(0,AY6) | ... M7: =MAX(0,BA6) | N7: =IF(D7<0.5,0,D7*(1+N('My Loans'!D6)/1200)) | O7: =IF(E7<0.5,0,E7*(1+N('My Loans'!D7)/1200)) | P7: =IF(F7<0.5,0,F7*(1+N('My Loans'!D8)/1200)) | Q7: =IF(G7<0.5,0,G7*(1+N('My Loans'!D9)/1200)) | R7: =IF(H7<0.5,0,H7*(1+N('My Loans'!D10)/1200)) | S7: =IF(I7<0.5,0,I7*(1+N('My Loans'!D11)/1200)) | T7: =IF(J7<0.5,0,J7*(1+N('My Loans'!D12)/1200)) | U7: =IF(K7<0.5,0,K7*(1+N('My Loans'!D13)/1200)) | V7: =IF(L7<0.5,0,L7*(1+N('My Loans'!D14)/1200)) | W7: =IF(M7<0.5,0,M7*(1+N('My Loans'!D15)/1200)) | X7: =MIN(N7,N('My Loans'!E6)) | Y7: =MIN(O7,N('My Loans'!E7)) | Z7: =MIN(P7,N('My Loans'!E8)) | AA7: =MIN(Q7,N('My Loans'!E9)) | AB7: =MIN(R7,N('My Loans'!E10)) | AC7: =MIN(S7,N('My Loans'!E11)) | AD7: =MIN(T7,N('My Loans'!E12)) | AE7: =MIN(U7,N('My Loans'!E13)) | AF7: =MIN(V7,N('My Loans'!E14)) | AG7: =MIN(W7,N('My Loans'!E15)) | AH7: =MIN(N7-X7,MAX(0,$C7-SUMPRODUCT(($D$3:$M$3<D$3)*($N7:$W7-$X7:$AG7)))) | AI7: =MIN(O7-Y7,MAX(0,$C7-SUMPRODUCT(($D$3:$M$3<E$3)*($N7:$W7-$X7:$AG7)))) | AJ7: =MIN(P7-Z7,MAX(0,$C7-SUMPRODUCT(($D$3:$M$3<F$3)*($N7:$W7-$X7:$AG7)))) | AK7: =MIN(Q7-AA7,MAX(0,$C7-SUMPRODUCT(($D$3:$M$3<G$3)*($N7:$W7-$X7:$AG7)))) | AL7: =MIN(R7-AB7,MAX(0,$C7-SUMPRODUCT(($D$3:$M$3<H$3)*($N7:$W7-$X7:$AG7)))) | AM7: =MIN(S7-AC7,MAX(0,$C7-SUMPRODUCT(($D$3:$M$3<I$3)*($N7:$W7-$X7:$AG7)))) | AN7: =MIN(T7-AD7,MAX(0,$C7-SUMPRODUCT(($D$3:$M$3<J$3)*($N7:$W7-$X7:$AG7)))) | AO7: =MIN(U7-AE7,MAX(0,$C7-SUMPRODUCT(($D$3:$M$3<K$3)*($N7:$W7-$X7:$AG7)))) | ... AQ7: =MIN(W7-AG7,MAX(0,$C7-SUMPRODUCT(($D$3:$M$3<M$3)*($N7:$W7-$X7:$AG7)))) | AR7: =ROUND(N7-X7-AH7,2) | AS7: =ROUND(O7-Y7-AI7,2) | AT7: =ROUND(P7-Z7-AJ7,2) | AU7: =ROUND(Q7-AA7-AK7,2) | AV7: =ROUND(R7-AB7-AL7,2) | AW7: =ROUND(S7-AC7-AM7,2) | AX7: =ROUND(T7-AD7-AN7,2) | AY7: =ROUND(U7-AE7-AO7,2) | ... BA7: =ROUND(W7-AG7-AQ7,2) | BB7: =SUM(AR7:BA7)
A8: 4 | B8: =EOMONTH(TODAY(),3) | C8: =MAX(0,(SUM('My Loans'!$E$6:$E$15)+'My Loans'!$D$3)-SUM($X8:$AG8)) | D8: =MAX(0,AR7) | E8: =MAX(0,AS7) | F8: =MAX(0,AT7) | G8: =MAX(0,AU7) | H8: =MAX(0,AV7) | I8: =MAX(0,AW7) | J8: =MAX(0,AX7) | K8: =MAX(0,AY7) | ... M8: =MAX(0,BA7) | N8: =IF(D8<0.5,0,D8*(1+N('My Loans'!D6)/1200)) | O8: =IF(E8<0.5,0,E8*(1+N('My Loans'!D7)/1200)) | P8: =IF(F8<0.5,0,F8*(1+N('My Loans'!D8)/1200)) | Q8: =IF(G8<0.5,0,G8*(1+N('My Loans'!D9)/1200)) | R8: =IF(H8<0.5,0,H8*(1+N('My Loans'!D10)/1200)) | S8: =IF(I8<0.5,0,I8*(1+N('My Loans'!D11)/1200)) | T8: =IF(J8<0.5,0,J8*(1+N('My Loans'!D12)/1200)) | U8: =IF(K8<0.5,0,K8*(1+N('My Loans'!D13)/1200)) | V8: =IF(L8<0.5,0,L8*(1+N('My Loans'!D14)/1200)) | W8: =IF(M8<0.5,0,M8*(1+N('My Loans'!D15)/1200)) | X8: =MIN(N8,N('My Loans'!E6)) | Y8: =MIN(O8,N('My Loans'!E7)) | Z8: =MIN(P8,N('My Loans'!E8)) | AA8: =MIN(Q8,N('My Loans'!E9)) | AB8: =MIN(R8,N('My Loans'!E10)) | AC8: =MIN(S8,N('My Loans'!E11)) | AD8: =MIN(T8,N('My Loans'!E12)) | AE8: =MIN(U8,N('My Loans'!E13)) | AF8: =MIN(V8,N('My Loans'!E14)) | AG8: =MIN(W8,N('My Loans'!E15)) | AH8: =MIN(N8-X8,MAX(0,$C8-SUMPRODUCT(($D$3:$M$3<D$3)*($N8:$W8-$X8:$AG8)))) | AI8: =MIN(O8-Y8,MAX(0,$C8-SUMPRODUCT(($D$3:$M$3<E$3)*($N8:$W8-$X8:$AG8)))) | AJ8: =MIN(P8-Z8,MAX(0,$C8-SUMPRODUCT(($D$3:$M$3<F$3)*($N8:$W8-$X8:$AG8)))) | AK8: =MIN(Q8-AA8,MAX(0,$C8-SUMPRODUCT(($D$3:$M$3<G$3)*($N8:$W8-$X8:$AG8)))) | AL8: =MIN(R8-AB8,MAX(0,$C8-SUMPRODUCT(($D$3:$M$3<H$3)*($N8:$W8-$X8:$AG8)))) | AM8: =MIN(S8-AC8,MAX(0,$C8-SUMPRODUCT(($D$3:$M$3<I$3)*($N8:$W8-$X8:$AG8)))) | AN8: =MIN(T8-AD8,MAX(0,$C8-SUMPRODUCT(($D$3:$M$3<J$3)*($N8:$W8-$X8:$AG8)))) | AO8: =MIN(U8-AE8,MAX(0,$C8-SUMPRODUCT(($D$3:$M$3<K$3)*($N8:$W8-$X8:$AG8)))) | ... AQ8: =MIN(W8-AG8,MAX(0,$C8-SUMPRODUCT(($D$3:$M$3<M$3)*($N8:$W8-$X8:$AG8)))) | AR8: =ROUND(N8-X8-AH8,2) | AS8: =ROUND(O8-Y8-AI8,2) | AT8: =ROUND(P8-Z8-AJ8,2) | AU8: =ROUND(Q8-AA8-AK8,2) | AV8: =ROUND(R8-AB8-AL8,2) | AW8: =ROUND(S8-AC8-AM8,2) | AX8: =ROUND(T8-AD8-AN8,2) | AY8: =ROUND(U8-AE8-AO8,2) | ... BA8: =ROUND(W8-AG8-AQ8,2) | BB8: =SUM(AR8:BA8)
A9: 5 | B9: =EOMONTH(TODAY(),4) | C9: =MAX(0,(SUM('My Loans'!$E$6:$E$15)+'My Loans'!$D$3)-SUM($X9:$AG9)) | D9: =MAX(0,AR8) | E9: =MAX(0,AS8) | F9: =MAX(0,AT8) | G9: =MAX(0,AU8) | H9: =MAX(0,AV8) | I9: =MAX(0,AW8) | J9: =MAX(0,AX8) | K9: =MAX(0,AY8) | ... M9: =MAX(0,BA8) | N9: =IF(D9<0.5,0,D9*(1+N('My Loans'!D6)/1200)) | O9: =IF(E9<0.5,0,E9*(1+N('My Loans'!D7)/1200)) | P9: =IF(F9<0.5,0,F9*(1+N('My Loans'!D8)/1200)) | Q9: =IF(G9<0.5,0,G9*(1+N('My Loans'!D9)/1200)) | R9: =IF(H9<0.5,0,H9*(1+N('My Loans'!D10)/1200)) | S9: =IF(I9<0.5,0,I9*(1+N('My Loans'!D11)/1200)) | T9: =IF(J9<0.5,0,J9*(1+N('My Loans'!D12)/1200)) | U9: =IF(K9<0.5,0,K9*(1+N('My Loans'!D13)/1200)) | V9: =IF(L9<0.5,0,L9*(1+N('My Loans'!D14)/1200)) | W9: =IF(M9<0.5,0,M9*(1+N('My Loans'!D15)/1200)) | X9: =MIN(N9,N('My Loans'!E6)) | Y9: =MIN(O9,N('My Loans'!E7)) | Z9: =MIN(P9,N('My Loans'!E8)) | AA9: =MIN(Q9,N('My Loans'!E9)) | AB9: =MIN(R9,N('My Loans'!E10)) | AC9: =MIN(S9,N('My Loans'!E11)) | AD9: =MIN(T9,N('My Loans'!E12)) | AE9: =MIN(U9,N('My Loans'!E13)) | AF9: =MIN(V9,N('My Loans'!E14)) | AG9: =MIN(W9,N('My Loans'!E15)) | AH9: =MIN(N9-X9,MAX(0,$C9-SUMPRODUCT(($D$3:$M$3<D$3)*($N9:$W9-$X9:$AG9)))) | AI9: =MIN(O9-Y9,MAX(0,$C9-SUMPRODUCT(($D$3:$M$3<E$3)*($N9:$W9-$X9:$AG9)))) | AJ9: =MIN(P9-Z9,MAX(0,$C9-SUMPRODUCT(($D$3:$M$3<F$3)*($N9:$W9-$X9:$AG9)))) | AK9: =MIN(Q9-AA9,MAX(0,$C9-SUMPRODUCT(($D$3:$M$3<G$3)*($N9:$W9-$X9:$AG9)))) | AL9: =MIN(R9-AB9,MAX(0,$C9-SUMPRODUCT(($D$3:$M$3<H$3)*($N9:$W9-$X9:$AG9)))) | AM9: =MIN(S9-AC9,MAX(0,$C9-SUMPRODUCT(($D$3:$M$3<I$3)*($N9:$W9-$X9:$AG9)))) | AN9: =MIN(T9-AD9,MAX(0,$C9-SUMPRODUCT(($D$3:$M$3<J$3)*($N9:$W9-$X9:$AG9)))) | AO9: =MIN(U9-AE9,MAX(0,$C9-SUMPRODUCT(($D$3:$M$3<K$3)*($N9:$W9-$X9:$AG9)))) | ... AQ9: =MIN(W9-AG9,MAX(0,$C9-SUMPRODUCT(($D$3:$M$3<M$3)*($N9:$W9-$X9:$AG9)))) | AR9: =ROUND(N9-X9-AH9,2) | AS9: =ROUND(O9-Y9-AI9,2) | AT9: =ROUND(P9-Z9-AJ9,2) | AU9: =ROUND(Q9-AA9-AK9,2) | AV9: =ROUND(R9-AB9-AL9,2) | AW9: =ROUND(S9-AC9-AM9,2) | AX9: =ROUND(T9-AD9-AN9,2) | AY9: =ROUND(U9-AE9-AO9,2) | ... BA9: =ROUND(W9-AG9-AQ9,2) | BB9: =SUM(AR9:BA9)
A10: 6 | B10: =EOMONTH(TODAY(),5) | C10: =MAX(0,(SUM('My Loans'!$E$6:$E$15)+'My Loans'!$D$3)-SUM($X10:$AG10)) | D10: =MAX(0,AR9) | E10: =MAX(0,AS9) | F10: =MAX(0,AT9) | G10: =MAX(0,AU9) | H10: =MAX(0,AV9) | I10: =MAX(0,AW9) | J10: =MAX(0,AX9) | K10: =MAX(0,AY9) | ... M10: =MAX(0,BA9) | N10: =IF(D10<0.5,0,D10*(1+N('My Loans'!D6)/1200)) | O10: =IF(E10<0.5,0,E10*(1+N('My Loans'!D7)/1200)) | P10: =IF(F10<0.5,0,F10*(1+N('My Loans'!D8)/1200)) | Q10: =IF(G10<0.5,0,G10*(1+N('My Loans'!D9)/1200)) | R10: =IF(H10<0.5,0,H10*(1+N('My Loans'!D10)/1200)) | S10: =IF(I10<0.5,0,I10*(1+N('My Loans'!D11)/1200)) | T10: =IF(J10<0.5,0,J10*(1+N('My Loans'!D12)/1200)) | U10: =IF(K10<0.5,0,K10*(1+N('My Loans'!D13)/1200)) | V10: =IF(L10<0.5,0,L10*(1+N('My Loans'!D14)/1200)) | W10: =IF(M10<0.5,0,M10*(1+N('My Loans'!D15)/1200)) | X10: =MIN(N10,N('My Loans'!E6)) | Y10: =MIN(O10,N('My Loans'!E7)) | Z10: =MIN(P10,N('My Loans'!E8)) | AA10: =MIN(Q10,N('My Loans'!E9)) | AB10: =MIN(R10,N('My Loans'!E10)) | AC10: =MIN(S10,N('My Loans'!E11)) | AD10: =MIN(T10,N('My Loans'!E12)) | AE10: =MIN(U10,N('My Loans'!E13)) | AF10: =MIN(V10,N('My Loans'!E14)) | AG10: =MIN(W10,N('My Loans'!E15)) | AH10: =MIN(N10-X10,MAX(0,$C10-SUMPRODUCT(($D$3:$M$3<D$3)*($N10:$W10-$X10:$AG10)))) | AI10: =MIN(O10-Y10,MAX(0,$C10-SUMPRODUCT(($D$3:$M$3<E$3)*($N10:$W10-$X10:$AG10)))) | AJ10: =MIN(P10-Z10,MAX(0,$C10-SUMPRODUCT(($D$3:$M$3<F$3)*($N10:$W10-$X10:$AG10)))) | AK10: =MIN(Q10-AA10,MAX(0,$C10-SUMPRODUCT(($D$3:$M$3<G$3)*($N10:$W10-$X10:$AG10)))) | AL10: =MIN(R10-AB10,MAX(0,$C10-SUMPRODUCT(($D$3:$M$3<H$3)*($N10:$W10-$X10:$AG10)))) | AM10: =MIN(S10-AC10,MAX(0,$C10-SUMPRODUCT(($D$3:$M$3<I$3)*($N10:$W10-$X10:$AG10)))) | AN10: =MIN(T10-AD10,MAX(0,$C10-SUMPRODUCT(($D$3:$M$3<J$3)*($N10:$W10-$X10:$AG10)))) | AO10: =MIN(U10-AE10,MAX(0,$C10-SUMPRODUCT(($D$3:$M$3<K$3)*($N10:$W10-$X10:$AG10)))) | ... AQ10: =MIN(W10-AG10,MAX(0,$C10-SUMPRODUCT(($D$3:$M$3<M$3)*($N10:$W10-$X10:$AG10)))) | AR10: =ROUND(N10-X10-AH10,2) | AS10: =ROUND(O10-Y10-AI10,2) | AT10: =ROUND(P10-Z10-AJ10,2) | AU10: =ROUND(Q10-AA10-AK10,2) | AV10: =ROUND(R10-AB10-AL10,2) | AW10: =ROUND(S10-AC10-AM10,2) | AX10: =ROUND(T10-AD10-AN10,2) | AY10: =ROUND(U10-AE10-AO10,2) | ... BA10: =ROUND(W10-AG10-AQ10,2) | BB10: =SUM(AR10:BA10)
A11: 7 | B11: =EOMONTH(TODAY(),6) | C11: =MAX(0,(SUM('My Loans'!$E$6:$E$15)+'My Loans'!$D$3)-SUM($X11:$AG11)) | D11: =MAX(0,AR10) | E11: =MAX(0,AS10) | F11: =MAX(0,AT10) | G11: =MAX(0,AU10) | H11: =MAX(0,AV10) | I11: =MAX(0,AW10) | J11: =MAX(0,AX10) | K11: =MAX(0,AY10) | ... M11: =MAX(0,BA10) | N11: =IF(D11<0.5,0,D11*(1+N('My Loans'!D6)/1200)) | O11: =IF(E11<0.5,0,E11*(1+N('My Loans'!D7)/1200)) | P11: =IF(F11<0.5,0,F11*(1+N('My Loans'!D8)/1200)) | Q11: =IF(G11<0.5,0,G11*(1+N('My Loans'!D9)/1200)) | R11: =IF(H11<0.5,0,H11*(1+N('My Loans'!D10)/1200)) | S11: =IF(I11<0.5,0,I11*(1+N('My Loans'!D11)/1200)) | T11: =IF(J11<0.5,0,J11*(1+N('My Loans'!D12)/1200)) | U11: =IF(K11<0.5,0,K11*(1+N('My Loans'!D13)/1200)) | V11: =IF(L11<0.5,0,L11*(1+N('My Loans'!D14)/1200)) | W11: =IF(M11<0.5,0,M11*(1+N('My Loans'!D15)/1200)) | X11: =MIN(N11,N('My Loans'!E6)) | Y11: =MIN(O11,N('My Loans'!E7)) | Z11: =MIN(P11,N('My Loans'!E8)) | AA11: =MIN(Q11,N('My Loans'!E9)) | AB11: =MIN(R11,N('My Loans'!E10)) | AC11: =MIN(S11,N('My Loans'!E11)) | AD11: =MIN(T11,N('My Loans'!E12)) | AE11: =MIN(U11,N('My Loans'!E13)) | AF11: =MIN(V11,N('My Loans'!E14)) | AG11: =MIN(W11,N('My Loans'!E15)) | AH11: =MIN(N11-X11,MAX(0,$C11-SUMPRODUCT(($D$3:$M$3<D$3)*($N11:$W11-$X11:$AG11)))) | AI11: =MIN(O11-Y11,MAX(0,$C11-SUMPRODUCT(($D$3:$M$3<E$3)*($N11:$W11-$X11:$AG11)))) | AJ11: =MIN(P11-Z11,MAX(0,$C11-SUMPRODUCT(($D$3:$M$3<F$3)*($N11:$W11-$X11:$AG11)))) | AK11: =MIN(Q11-AA11,MAX(0,$C11-SUMPRODUCT(($D$3:$M$3<G$3)*($N11:$W11-$X11:$AG11)))) | AL11: =MIN(R11-AB11,MAX(0,$C11-SUMPRODUCT(($D$3:$M$3<H$3)*($N11:$W11-$X11:$AG11)))) | AM11: =MIN(S11-AC11,MAX(0,$C11-SUMPRODUCT(($D$3:$M$3<I$3)*($N11:$W11-$X11:$AG11)))) | AN11: =MIN(T11-AD11,MAX(0,$C11-SUMPRODUCT(($D$3:$M$3<J$3)*($N11:$W11-$X11:$AG11)))) | AO11: =MIN(U11-AE11,MAX(0,$C11-SUMPRODUCT(($D$3:$M$3<K$3)*($N11:$W11-$X11:$AG11)))) | ... AQ11: =MIN(W11-AG11,MAX(0,$C11-SUMPRODUCT(($D$3:$M$3<M$3)*($N11:$W11-$X11:$AG11)))) | AR11: =ROUND(N11-X11-AH11,2) | AS11: =ROUND(O11-Y11-AI11,2) | AT11: =ROUND(P11-Z11-AJ11,2) | AU11: =ROUND(Q11-AA11-AK11,2) | AV11: =ROUND(R11-AB11-AL11,2) | AW11: =ROUND(S11-AC11-AM11,2) | AX11: =ROUND(T11-AD11-AN11,2) | AY11: =ROUND(U11-AE11-AO11,2) | ... BA11: =ROUND(W11-AG11-AQ11,2) | BB11: =SUM(AR11:BA11)
A12: 8 | B12: =EOMONTH(TODAY(),7) | C12: =MAX(0,(SUM('My Loans'!$E$6:$E$15)+'My Loans'!$D$3)-SUM($X12:$AG12)) | D12: =MAX(0,AR11) | E12: =MAX(0,AS11) | F12: =MAX(0,AT11) | G12: =MAX(0,AU11) | H12: =MAX(0,AV11) | I12: =MAX(0,AW11) | J12: =MAX(0,AX11) | K12: =MAX(0,AY11) | ... M12: =MAX(0,BA11) | N12: =IF(D12<0.5,0,D12*(1+N('My Loans'!D6)/1200)) | O12: =IF(E12<0.5,0,E12*(1+N('My Loans'!D7)/1200)) | P12: =IF(F12<0.5,0,F12*(1+N('My Loans'!D8)/1200)) | Q12: =IF(G12<0.5,0,G12*(1+N('My Loans'!D9)/1200)) | R12: =IF(H12<0.5,0,H12*(1+N('My Loans'!D10)/1200)) | S12: =IF(I12<0.5,0,I12*(1+N('My Loans'!D11)/1200)) | T12: =IF(J12<0.5,0,J12*(1+N('My Loans'!D12)/1200)) | U12: =IF(K12<0.5,0,K12*(1+N('My Loans'!D13)/1200)) | V12: =IF(L12<0.5,0,L12*(1+N('My Loans'!D14)/1200)) | W12: =IF(M12<0.5,0,M12*(1+N('My Loans'!D15)/1200)) | X12: =MIN(N12,N('My Loans'!E6)) | Y12: =MIN(O12,N('My Loans'!E7)) | Z12: =MIN(P12,N('My Loans'!E8)) | AA12: =MIN(Q12,N('My Loans'!E9)) | AB12: =MIN(R12,N('My Loans'!E10)) | AC12: =MIN(S12,N('My Loans'!E11)) | AD12: =MIN(T12,N('My Loans'!E12)) | AE12: =MIN(U12,N('My Loans'!E13)) | AF12: =MIN(V12,N('My Loans'!E14)) | AG12: =MIN(W12,N('My Loans'!E15)) | AH12: =MIN(N12-X12,MAX(0,$C12-SUMPRODUCT(($D$3:$M$3<D$3)*($N12:$W12-$X12:$AG12)))) | AI12: =MIN(O12-Y12,MAX(0,$C12-SUMPRODUCT(($D$3:$M$3<E$3)*($N12:$W12-$X12:$AG12)))) | AJ12: =MIN(P12-Z12,MAX(0,$C12-SUMPRODUCT(($D$3:$M$3<F$3)*($N12:$W12-$X12:$AG12)))) | AK12: =MIN(Q12-AA12,MAX(0,$C12-SUMPRODUCT(($D$3:$M$3<G$3)*($N12:$W12-$X12:$AG12)))) | AL12: =MIN(R12-AB12,MAX(0,$C12-SUMPRODUCT(($D$3:$M$3<H$3)*($N12:$W12-$X12:$AG12)))) | AM12: =MIN(S12-AC12,MAX(0,$C12-SUMPRODUCT(($D$3:$M$3<I$3)*($N12:$W12-$X12:$AG12)))) | AN12: =MIN(T12-AD12,MAX(0,$C12-SUMPRODUCT(($D$3:$M$3<J$3)*($N12:$W12-$X12:$AG12)))) | AO12: =MIN(U12-AE12,MAX(0,$C12-SUMPRODUCT(($D$3:$M$3<K$3)*($N12:$W12-$X12:$AG12)))) | ... AQ12: =MIN(W12-AG12,MAX(0,$C12-SUMPRODUCT(($D$3:$M$3<M$3)*($N12:$W12-$X12:$AG12)))) | AR12: =ROUND(N12-X12-AH12,2) | AS12: =ROUND(O12-Y12-AI12,2) | AT12: =ROUND(P12-Z12-AJ12,2) | AU12: =ROUND(Q12-AA12-AK12,2) | AV12: =ROUND(R12-AB12-AL12,2) | AW12: =ROUND(S12-AC12-AM12,2) | AX12: =ROUND(T12-AD12-AN12,2) | AY12: =ROUND(U12-AE12-AO12,2) | ... BA12: =ROUND(W12-AG12-AQ12,2) | BB12: =SUM(AR12:BA12)
A13: 9 | B13: =EOMONTH(TODAY(),8) | C13: =MAX(0,(SUM('My Loans'!$E$6:$E$15)+'My Loans'!$D$3)-SUM($X13:$AG13)) | D13: =MAX(0,AR12) | E13: =MAX(0,AS12) | F13: =MAX(0,AT12) | G13: =MAX(0,AU12) | H13: =MAX(0,AV12) | I13: =MAX(0,AW12) | J13: =MAX(0,AX12) | K13: =MAX(0,AY12) | ... M13: =MAX(0,BA12) | N13: =IF(D13<0.5,0,D13*(1+N('My Loans'!D6)/1200)) | O13: =IF(E13<0.5,0,E13*(1+N('My Loans'!D7)/1200)) | P13: =IF(F13<0.5,0,F13*(1+N('My Loans'!D8)/1200)) | Q13: =IF(G13<0.5,0,G13*(1+N('My Loans'!D9)/1200)) | R13: =IF(H13<0.5,0,H13*(1+N('My Loans'!D10)/1200)) | S13: =IF(I13<0.5,0,I13*(1+N('My Loans'!D11)/1200)) | T13: =IF(J13<0.5,0,J13*(1+N('My Loans'!D12)/1200)) | U13: =IF(K13<0.5,0,K13*(1+N('My Loans'!D13)/1200)) | V13: =IF(L13<0.5,0,L13*(1+N('My Loans'!D14)/1200)) | W13: =IF(M13<0.5,0,M13*(1+N('My Loans'!D15)/1200)) | X13: =MIN(N13,N('My Loans'!E6)) | Y13: =MIN(O13,N('My Loans'!E7)) | Z13: =MIN(P13,N('My Loans'!E8)) | AA13: =MIN(Q13,N('My Loans'!E9)) | AB13: =MIN(R13,N('My Loans'!E10)) | AC13: =MIN(S13,N('My Loans'!E11)) | AD13: =MIN(T13,N('My Loans'!E12)) | AE13: =MIN(U13,N('My Loans'!E13)) | AF13: =MIN(V13,N('My Loans'!E14)) | AG13: =MIN(W13,N('My Loans'!E15)) | AH13: =MIN(N13-X13,MAX(0,$C13-SUMPRODUCT(($D$3:$M$3<D$3)*($N13:$W13-$X13:$AG13)))) | AI13: =MIN(O13-Y13,MAX(0,$C13-SUMPRODUCT(($D$3:$M$3<E$3)*($N13:$W13-$X13:$AG13)))) | AJ13: =MIN(P13-Z13,MAX(0,$C13-SUMPRODUCT(($D$3:$M$3<F$3)*($N13:$W13-$X13:$AG13)))) | AK13: =MIN(Q13-AA13,MAX(0,$C13-SUMPRODUCT(($D$3:$M$3<G$3)*($N13:$W13-$X13:$AG13)))) | AL13: =MIN(R13-AB13,MAX(0,$C13-SUMPRODUCT(($D$3:$M$3<H$3)*($N13:$W13-$X13:$AG13)))) | AM13: =MIN(S13-AC13,MAX(0,$C13-SUMPRODUCT(($D$3:$M$3<I$3)*($N13:$W13-$X13:$AG13)))) | AN13: =MIN(T13-AD13,MAX(0,$C13-SUMPRODUCT(($D$3:$M$3<J$3)*($N13:$W13-$X13:$AG13)))) | AO13: =MIN(U13-AE13,MAX(0,$C13-SUMPRODUCT(($D$3:$M$3<K$3)*($N13:$W13-$X13:$AG13)))) | ... AQ13: =MIN(W13-AG13,MAX(0,$C13-SUMPRODUCT(($D$3:$M$3<M$3)*($N13:$W13-$X13:$AG13)))) | AR13: =ROUND(N13-X13-AH13,2) | AS13: =ROUND(O13-Y13-AI13,2) | AT13: =ROUND(P13-Z13-AJ13,2) | AU13: =ROUND(Q13-AA13-AK13,2) | AV13: =ROUND(R13-AB13-AL13,2) | AW13: =ROUND(S13-AC13-AM13,2) | AX13: =ROUND(T13-AD13-AN13,2) | AY13: =ROUND(U13-AE13-AO13,2) | ... BA13: =ROUND(W13-AG13-AQ13,2) | BB13: =SUM(AR13:BA13)
A14: 10 | B14: =EOMONTH(TODAY(),9) | C14: =MAX(0,(SUM('My Loans'!$E$6:$E$15)+'My Loans'!$D$3)-SUM($X14:$AG14)) | D14: =MAX(0,AR13) | E14: =MAX(0,AS13) | F14: =MAX(0,AT13) | G14: =MAX(0,AU13) | H14: =MAX(0,AV13) | I14: =MAX(0,AW13) | J14: =MAX(0,AX13) | K14: =MAX(0,AY13) | ... M14: =MAX(0,BA13) | N14: =IF(D14<0.5,0,D14*(1+N('My Loans'!D6)/1200)) | O14: =IF(E14<0.5,0,E14*(1+N('My Loans'!D7)/1200)) | P14: =IF(F14<0.5,0,F14*(1+N('My Loans'!D8)/1200)) | Q14: =IF(G14<0.5,0,G14*(1+N('My Loans'!D9)/1200)) | R14: =IF(H14<0.5,0,H14*(1+N('My Loans'!D10)/1200)) | S14: =IF(I14<0.5,0,I14*(1+N('My Loans'!D11)/1200)) | T14: =IF(J14<0.5,0,J14*(1+N('My Loans'!D12)/1200)) | U14: =IF(K14<0.5,0,K14*(1+N('My Loans'!D13)/1200)) | V14: =IF(L14<0.5,0,L14*(1+N('My Loans'!D14)/1200)) | W14: =IF(M14<0.5,0,M14*(1+N('My Loans'!D15)/1200)) | X14: =MIN(N14,N('My Loans'!E6)) | Y14: =MIN(O14,N('My Loans'!E7)) | Z14: =MIN(P14,N('My Loans'!E8)) | AA14: =MIN(Q14,N('My Loans'!E9)) | AB14: =MIN(R14,N('My Loans'!E10)) | AC14: =MIN(S14,N('My Loans'!E11)) | AD14: =MIN(T14,N('My Loans'!E12)) | AE14: =MIN(U14,N('My Loans'!E13)) | AF14: =MIN(V14,N('My Loans'!E14)) | AG14: =MIN(W14,N('My Loans'!E15)) | AH14: =MIN(N14-X14,MAX(0,$C14-SUMPRODUCT(($D$3:$M$3<D$3)*($N14:$W14-$X14:$AG14)))) | AI14: =MIN(O14-Y14,MAX(0,$C14-SUMPRODUCT(($D$3:$M$3<E$3)*($N14:$W14-$X14:$AG14)))) | AJ14: =MIN(P14-Z14,MAX(0,$C14-SUMPRODUCT(($D$3:$M$3<F$3)*($N14:$W14-$X14:$AG14)))) | AK14: =MIN(Q14-AA14,MAX(0,$C14-SUMPRODUCT(($D$3:$M$3<G$3)*($N14:$W14-$X14:$AG14)))) | AL14: =MIN(R14-AB14,MAX(0,$C14-SUMPRODUCT(($D$3:$M$3<H$3)*($N14:$W14-$X14:$AG14)))) | AM14: =MIN(S14-AC14,MAX(0,$C14-SUMPRODUCT(($D$3:$M$3<I$3)*($N14:$W14-$X14:$AG14)))) | AN14: =MIN(T14-AD14,MAX(0,$C14-SUMPRODUCT(($D$3:$M$3<J$3)*($N14:$W14-$X14:$AG14)))) | AO14: =MIN(U14-AE14,MAX(0,$C14-SUMPRODUCT(($D$3:$M$3<K$3)*($N14:$W14-$X14:$AG14)))) | ... AQ14: =MIN(W14-AG14,MAX(0,$C14-SUMPRODUCT(($D$3:$M$3<M$3)*($N14:$W14-$X14:$AG14)))) | AR14: =ROUND(N14-X14-AH14,2) | AS14: =ROUND(O14-Y14-AI14,2) | AT14: =ROUND(P14-Z14-AJ14,2) | AU14: =ROUND(Q14-AA14-AK14,2) | AV14: =ROUND(R14-AB14-AL14,2) | AW14: =ROUND(S14-AC14-AM14,2) | AX14: =ROUND(T14-AD14-AN14,2) | AY14: =ROUND(U14-AE14-AO14,2) | ... BA14: =ROUND(W14-AG14-AQ14,2) | BB14: =SUM(AR14:BA14)
A15: 11 | B15: =EOMONTH(TODAY(),10) | C15: =MAX(0,(SUM('My Loans'!$E$6:$E$15)+'My Loans'!$D$3)-SUM($X15:$AG15)) | D15: =MAX(0,AR14) | E15: =MAX(0,AS14) | F15: =MAX(0,AT14) | G15: =MAX(0,AU14) | H15: =MAX(0,AV14) | I15: =MAX(0,AW14) | J15: =MAX(0,AX14) | K15: =MAX(0,AY14) | ... M15: =MAX(0,BA14) | N15: =IF(D15<0.5,0,D15*(1+N('My Loans'!D6)/1200)) | O15: =IF(E15<0.5,0,E15*(1+N('My Loans'!D7)/1200)) | P15: =IF(F15<0.5,0,F15*(1+N('My Loans'!D8)/1200)) | Q15: =IF(G15<0.5,0,G15*(1+N('My Loans'!D9)/1200)) | R15: =IF(H15<0.5,0,H15*(1+N('My Loans'!D10)/1200)) | S15: =IF(I15<0.5,0,I15*(1+N('My Loans'!D11)/1200)) | T15: =IF(J15<0.5,0,J15*(1+N('My Loans'!D12)/1200)) | U15: =IF(K15<0.5,0,K15*(1+N('My Loans'!D13)/1200)) | V15: =IF(L15<0.5,0,L15*(1+N('My Loans'!D14)/1200)) | W15: =IF(M15<0.5,0,M15*(1+N('My Loans'!D15)/1200)) | X15: =MIN(N15,N('My Loans'!E6)) | Y15: =MIN(O15,N('My Loans'!E7)) | Z15: =MIN(P15,N('My Loans'!E8)) | AA15: =MIN(Q15,N('My Loans'!E9)) | AB15: =MIN(R15,N('My Loans'!E10)) | AC15: =MIN(S15,N('My Loans'!E11)) | AD15: =MIN(T15,N('My Loans'!E12)) | AE15: =MIN(U15,N('My Loans'!E13)) | AF15: =MIN(V15,N('My Loans'!E14)) | AG15: =MIN(W15,N('My Loans'!E15)) | AH15: =MIN(N15-X15,MAX(0,$C15-SUMPRODUCT(($D$3:$M$3<D$3)*($N15:$W15-$X15:$AG15)))) | AI15: =MIN(O15-Y15,MAX(0,$C15-SUMPRODUCT(($D$3:$M$3<E$3)*($N15:$W15-$X15:$AG15)))) | AJ15: =MIN(P15-Z15,MAX(0,$C15-SUMPRODUCT(($D$3:$M$3<F$3)*($N15:$W15-$X15:$AG15)))) | AK15: =MIN(Q15-AA15,MAX(0,$C15-SUMPRODUCT(($D$3:$M$3<G$3)*($N15:$W15-$X15:$AG15)))) | AL15: =MIN(R15-AB15,MAX(0,$C15-SUMPRODUCT(($D$3:$M$3<H$3)*($N15:$W15-$X15:$AG15)))) | AM15: =MIN(S15-AC15,MAX(0,$C15-SUMPRODUCT(($D$3:$M$3<I$3)*($N15:$W15-$X15:$AG15)))) | AN15: =MIN(T15-AD15,MAX(0,$C15-SUMPRODUCT(($D$3:$M$3<J$3)*($N15:$W15-$X15:$AG15)))) | AO15: =MIN(U15-AE15,MAX(0,$C15-SUMPRODUCT(($D$3:$M$3<K$3)*($N15:$W15-$X15:$AG15)))) | ... AQ15: =MIN(W15-AG15,MAX(0,$C15-SUMPRODUCT(($D$3:$M$3<M$3)*($N15:$W15-$X15:$AG15)))) | AR15: =ROUND(N15-X15-AH15,2) | AS15: =ROUND(O15-Y15-AI15,2) | AT15: =ROUND(P15-Z15-AJ15,2) | AU15: =ROUND(Q15-AA15-AK15,2) | AV15: =ROUND(R15-AB15-AL15,2) | AW15: =ROUND(S15-AC15-AM15,2) | AX15: =ROUND(T15-AD15-AN15,2) | AY15: =ROUND(U15-AE15-AO15,2) | ... BA15: =ROUND(W15-AG15-AQ15,2) | BB15: =SUM(AR15:BA15)
A16: 12 | B16: =EOMONTH(TODAY(),11) | C16: =MAX(0,(SUM('My Loans'!$E$6:$E$15)+'My Loans'!$D$3)-SUM($X16:$AG16)) | D16: =MAX(0,AR15) | E16: =MAX(0,AS15) | F16: =MAX(0,AT15) | G16: =MAX(0,AU15) | H16: =MAX(0,AV15) | I16: =MAX(0,AW15) | J16: =MAX(0,AX15) | K16: =MAX(0,AY15) | ... M16: =MAX(0,BA15) | N16: =IF(D16<0.5,0,D16*(1+N('My Loans'!D6)/1200)) | O16: =IF(E16<0.5,0,E16*(1+N('My Loans'!D7)/1200)) | P16: =IF(F16<0.5,0,F16*(1+N('My Loans'!D8)/1200)) | Q16: =IF(G16<0.5,0,G16*(1+N('My Loans'!D9)/1200)) | R16: =IF(H16<0.5,0,H16*(1+N('My Loans'!D10)/1200)) | S16: =IF(I16<0.5,0,I16*(1+N('My Loans'!D11)/1200)) | T16: =IF(J16<0.5,0,J16*(1+N('My Loans'!D12)/1200)) | U16: =IF(K16<0.5,0,K16*(1+N('My Loans'!D13)/1200)) | V16: =IF(L16<0.5,0,L16*(1+N('My Loans'!D14)/1200)) | W16: =IF(M16<0.5,0,M16*(1+N('My Loans'!D15)/1200)) | X16: =MIN(N16,N('My Loans'!E6)) | Y16: =MIN(O16,N('My Loans'!E7)) | Z16: =MIN(P16,N('My Loans'!E8)) | AA16: =MIN(Q16,N('My Loans'!E9)) | AB16: =MIN(R16,N('My Loans'!E10)) | AC16: =MIN(S16,N('My Loans'!E11)) | AD16: =MIN(T16,N('My Loans'!E12)) | AE16: =MIN(U16,N('My Loans'!E13)) | AF16: =MIN(V16,N('My Loans'!E14)) | AG16: =MIN(W16,N('My Loans'!E15)) | AH16: =MIN(N16-X16,MAX(0,$C16-SUMPRODUCT(($D$3:$M$3<D$3)*($N16:$W16-$X16:$AG16)))) | AI16: =MIN(O16-Y16,MAX(0,$C16-SUMPRODUCT(($D$3:$M$3<E$3)*($N16:$W16-$X16:$AG16)))) | AJ16: =MIN(P16-Z16,MAX(0,$C16-SUMPRODUCT(($D$3:$M$3<F$3)*($N16:$W16-$X16:$AG16)))) | AK16: =MIN(Q16-AA16,MAX(0,$C16-SUMPRODUCT(($D$3:$M$3<G$3)*($N16:$W16-$X16:$AG16)))) | AL16: =MIN(R16-AB16,MAX(0,$C16-SUMPRODUCT(($D$3:$M$3<H$3)*($N16:$W16-$X16:$AG16)))) | AM16: =MIN(S16-AC16,MAX(0,$C16-SUMPRODUCT(($D$3:$M$3<I$3)*($N16:$W16-$X16:$AG16)))) | AN16: =MIN(T16-AD16,MAX(0,$C16-SUMPRODUCT(($D$3:$M$3<J$3)*($N16:$W16-$X16:$AG16)))) | AO16: =MIN(U16-AE16,MAX(0,$C16-SUMPRODUCT(($D$3:$M$3<K$3)*($N16:$W16-$X16:$AG16)))) | ... AQ16: =MIN(W16-AG16,MAX(0,$C16-SUMPRODUCT(($D$3:$M$3<M$3)*($N16:$W16-$X16:$AG16)))) | AR16: =ROUND(N16-X16-AH16,2) | AS16: =ROUND(O16-Y16-AI16,2) | AT16: =ROUND(P16-Z16-AJ16,2) | AU16: =ROUND(Q16-AA16-AK16,2) | AV16: =ROUND(R16-AB16-AL16,2) | AW16: =ROUND(S16-AC16-AM16,2) | AX16: =ROUND(T16-AD16-AN16,2) | AY16: =ROUND(U16-AE16-AO16,2) | ... BA16: =ROUND(W16-AG16-AQ16,2) | BB16: =SUM(AR16:BA16)
A17: 13 | B17: =EOMONTH(TODAY(),12) | C17: =MAX(0,(SUM('My Loans'!$E$6:$E$15)+'My Loans'!$D$3)-SUM($X17:$AG17)) | D17: =MAX(0,AR16) | E17: =MAX(0,AS16) | F17: =MAX(0,AT16) | G17: =MAX(0,AU16) | H17: =MAX(0,AV16) | I17: =MAX(0,AW16) | J17: =MAX(0,AX16) | K17: =MAX(0,AY16) | ... M17: =MAX(0,BA16) | N17: =IF(D17<0.5,0,D17*(1+N('My Loans'!D6)/1200)) | O17: =IF(E17<0.5,0,E17*(1+N('My Loans'!D7)/1200)) | P17: =IF(F17<0.5,0,F17*(1+N('My Loans'!D8)/1200)) | Q17: =IF(G17<0.5,0,G17*(1+N('My Loans'!D9)/1200)) | R17: =IF(H17<0.5,0,H17*(1+N('My Loans'!D10)/1200)) | S17: =IF(I17<0.5,0,I17*(1+N('My Loans'!D11)/1200)) | T17: =IF(J17<0.5,0,J17*(1+N('My Loans'!D12)/1200)) | U17: =IF(K17<0.5,0,K17*(1+N('My Loans'!D13)/1200)) | V17: =IF(L17<0.5,0,L17*(1+N('My Loans'!D14)/1200)) | W17: =IF(M17<0.5,0,M17*(1+N('My Loans'!D15)/1200)) | X17: =MIN(N17,N('My Loans'!E6)) | Y17: =MIN(O17,N('My Loans'!E7)) | Z17: =MIN(P17,N('My Loans'!E8)) | AA17: =MIN(Q17,N('My Loans'!E9)) | AB17: =MIN(R17,N('My Loans'!E10)) | AC17: =MIN(S17,N('My Loans'!E11)) | AD17: =MIN(T17,N('My Loans'!E12)) | AE17: =MIN(U17,N('My Loans'!E13)) | AF17: =MIN(V17,N('My Loans'!E14)) | AG17: =MIN(W17,N('My Loans'!E15)) | AH17: =MIN(N17-X17,MAX(0,$C17-SUMPRODUCT(($D$3:$M$3<D$3)*($N17:$W17-$X17:$AG17)))) | AI17: =MIN(O17-Y17,MAX(0,$C17-SUMPRODUCT(($D$3:$M$3<E$3)*($N17:$W17-$X17:$AG17)))) | AJ17: =MIN(P17-Z17,MAX(0,$C17-SUMPRODUCT(($D$3:$M$3<F$3)*($N17:$W17-$X17:$AG17)))) | AK17: =MIN(Q17-AA17,MAX(0,$C17-SUMPRODUCT(($D$3:$M$3<G$3)*($N17:$W17-$X17:$AG17)))) | AL17: =MIN(R17-AB17,MAX(0,$C17-SUMPRODUCT(($D$3:$M$3<H$3)*($N17:$W17-$X17:$AG17)))) | AM17: =MIN(S17-AC17,MAX(0,$C17-SUMPRODUCT(($D$3:$M$3<I$3)*($N17:$W17-$X17:$AG17)))) | AN17: =MIN(T17-AD17,MAX(0,$C17-SUMPRODUCT(($D$3:$M$3<J$3)*($N17:$W17-$X17:$AG17)))) | AO17: =MIN(U17-AE17,MAX(0,$C17-SUMPRODUCT(($D$3:$M$3<K$3)*($N17:$W17-$X17:$AG17)))) | ... AQ17: =MIN(W17-AG17,MAX(0,$C17-SUMPRODUCT(($D$3:$M$3<M$3)*($N17:$W17-$X17:$AG17)))) | AR17: =ROUND(N17-X17-AH17,2) | AS17: =ROUND(O17-Y17-AI17,2) | AT17: =ROUND(P17-Z17-AJ17,2) | AU17: =ROUND(Q17-AA17-AK17,2) | AV17: =ROUND(R17-AB17-AL17,2) | AW17: =ROUND(S17-AC17-AM17,2) | AX17: =ROUND(T17-AD17-AN17,2) | AY17: =ROUND(U17-AE17-AO17,2) | ... BA17: =ROUND(W17-AG17-AQ17,2) | BB17: =SUM(AR17:BA17)
A18: 14 | B18: =EOMONTH(TODAY(),13) | C18: =MAX(0,(SUM('My Loans'!$E$6:$E$15)+'My Loans'!$D$3)-SUM($X18:$AG18)) | D18: =MAX(0,AR17) | E18: =MAX(0,AS17) | F18: =MAX(0,AT17) | G18: =MAX(0,AU17) | H18: =MAX(0,AV17) | I18: =MAX(0,AW17) | J18: =MAX(0,AX17) | K18: =MAX(0,AY17) | ... M18: =MAX(0,BA17) | N18: =IF(D18<0.5,0,D18*(1+N('My Loans'!D6)/1200)) | O18: =IF(E18<0.5,0,E18*(1+N('My Loans'!D7)/1200)) | P18: =IF(F18<0.5,0,F18*(1+N('My Loans'!D8)/1200)) | Q18: =IF(G18<0.5,0,G18*(1+N('My Loans'!D9)/1200)) | R18: =IF(H18<0.5,0,H18*(1+N('My Loans'!D10)/1200)) | S18: =IF(I18<0.5,0,I18*(1+N('My Loans'!D11)/1200)) | T18: =IF(J18<0.5,0,J18*(1+N('My Loans'!D12)/1200)) | U18: =IF(K18<0.5,0,K18*(1+N('My Loans'!D13)/1200)) | V18: =IF(L18<0.5,0,L18*(1+N('My Loans'!D14)/1200)) | W18: =IF(M18<0.5,0,M18*(1+N('My Loans'!D15)/1200)) | X18: =MIN(N18,N('My Loans'!E6)) | Y18: =MIN(O18,N('My Loans'!E7)) | Z18: =MIN(P18,N('My Loans'!E8)) | AA18: =MIN(Q18,N('My Loans'!E9)) | AB18: =MIN(R18,N('My Loans'!E10)) | AC18: =MIN(S18,N('My Loans'!E11)) | AD18: =MIN(T18,N('My Loans'!E12)) | AE18: =MIN(U18,N('My Loans'!E13)) | AF18: =MIN(V18,N('My Loans'!E14)) | AG18: =MIN(W18,N('My Loans'!E15)) | AH18: =MIN(N18-X18,MAX(0,$C18-SUMPRODUCT(($D$3:$M$3<D$3)*($N18:$W18-$X18:$AG18)))) | AI18: =MIN(O18-Y18,MAX(0,$C18-SUMPRODUCT(($D$3:$M$3<E$3)*($N18:$W18-$X18:$AG18)))) | AJ18: =MIN(P18-Z18,MAX(0,$C18-SUMPRODUCT(($D$3:$M$3<F$3)*($N18:$W18-$X18:$AG18)))) | AK18: =MIN(Q18-AA18,MAX(0,$C18-SUMPRODUCT(($D$3:$M$3<G$3)*($N18:$W18-$X18:$AG18)))) | AL18: =MIN(R18-AB18,MAX(0,$C18-SUMPRODUCT(($D$3:$M$3<H$3)*($N18:$W18-$X18:$AG18)))) | AM18: =MIN(S18-AC18,MAX(0,$C18-SUMPRODUCT(($D$3:$M$3<I$3)*($N18:$W18-$X18:$AG18)))) | AN18: =MIN(T18-AD18,MAX(0,$C18-SUMPRODUCT(($D$3:$M$3<J$3)*($N18:$W18-$X18:$AG18)))) | AO18: =MIN(U18-AE18,MAX(0,$C18-SUMPRODUCT(($D$3:$M$3<K$3)*($N18:$W18-$X18:$AG18)))) | ... AQ18: =MIN(W18-AG18,MAX(0,$C18-SUMPRODUCT(($D$3:$M$3<M$3)*($N18:$W18-$X18:$AG18)))) | AR18: =ROUND(N18-X18-AH18,2) | AS18: =ROUND(O18-Y18-AI18,2) | AT18: =ROUND(P18-Z18-AJ18,2) | AU18: =ROUND(Q18-AA18-AK18,2) | AV18: =ROUND(R18-AB18-AL18,2) | AW18: =ROUND(S18-AC18-AM18,2) | AX18: =ROUND(T18-AD18-AN18,2) | AY18: =ROUND(U18-AE18-AO18,2) | ... BA18: =ROUND(W18-AG18-AQ18,2) | BB18: =SUM(AR18:BA18)
A19: 15 | B19: =EOMONTH(TODAY(),14) | C19: =MAX(0,(SUM('My Loans'!$E$6:$E$15)+'My Loans'!$D$3)-SUM($X19:$AG19)) | D19: =MAX(0,AR18) | E19: =MAX(0,AS18) | F19: =MAX(0,AT18) | G19: =MAX(0,AU18) | H19: =MAX(0,AV18) | I19: =MAX(0,AW18) | J19: =MAX(0,AX18) | K19: =MAX(0,AY18) | ... M19: =MAX(0,BA18) | N19: =IF(D19<0.5,0,D19*(1+N('My Loans'!D6)/1200)) | O19: =IF(E19<0.5,0,E19*(1+N('My Loans'!D7)/1200)) | P19: =IF(F19<0.5,0,F19*(1+N('My Loans'!D8)/1200)) | Q19: =IF(G19<0.5,0,G19*(1+N('My Loans'!D9)/1200)) | R19: =IF(H19<0.5,0,H19*(1+N('My Loans'!D10)/1200)) | S19: =IF(I19<0.5,0,I19*(1+N('My Loans'!D11)/1200)) | T19: =IF(J19<0.5,0,J19*(1+N('My Loans'!D12)/1200)) | U19: =IF(K19<0.5,0,K19*(1+N('My Loans'!D13)/1200)) | V19: =IF(L19<0.5,0,L19*(1+N('My Loans'!D14)/1200)) | W19: =IF(M19<0.5,0,M19*(1+N('My Loans'!D15)/1200)) | X19: =MIN(N19,N('My Loans'!E6)) | Y19: =MIN(O19,N('My Loans'!E7)) | Z19: =MIN(P19,N('My Loans'!E8)) | AA19: =MIN(Q19,N('My Loans'!E9)) | AB19: =MIN(R19,N('My Loans'!E10)) | AC19: =MIN(S19,N('My Loans'!E11)) | AD19: =MIN(T19,N('My Loans'!E12)) | AE19: =MIN(U19,N('My Loans'!E13)) | AF19: =MIN(V19,N('My Loans'!E14)) | AG19: =MIN(W19,N('My Loans'!E15)) | AH19: =MIN(N19-X19,MAX(0,$C19-SUMPRODUCT(($D$3:$M$3<D$3)*($N19:$W19-$X19:$AG19)))) | AI19: =MIN(O19-Y19,MAX(0,$C19-SUMPRODUCT(($D$3:$M$3<E$3)*($N19:$W19-$X19:$AG19)))) | AJ19: =MIN(P19-Z19,MAX(0,$C19-SUMPRODUCT(($D$3:$M$3<F$3)*($N19:$W19-$X19:$AG19)))) | AK19: =MIN(Q19-AA19,MAX(0,$C19-SUMPRODUCT(($D$3:$M$3<G$3)*($N19:$W19-$X19:$AG19)))) | AL19: =MIN(R19-AB19,MAX(0,$C19-SUMPRODUCT(($D$3:$M$3<H$3)*($N19:$W19-$X19:$AG19)))) | AM19: =MIN(S19-AC19,MAX(0,$C19-SUMPRODUCT(($D$3:$M$3<I$3)*($N19:$W19-$X19:$AG19)))) | AN19: =MIN(T19-AD19,MAX(0,$C19-SUMPRODUCT(($D$3:$M$3<J$3)*($N19:$W19-$X19:$AG19)))) | AO19: =MIN(U19-AE19,MAX(0,$C19-SUMPRODUCT(($D$3:$M$3<K$3)*($N19:$W19-$X19:$AG19)))) | ... AQ19: =MIN(W19-AG19,MAX(0,$C19-SUMPRODUCT(($D$3:$M$3<M$3)*($N19:$W19-$X19:$AG19)))) | AR19: =ROUND(N19-X19-AH19,2) | AS19: =ROUND(O19-Y19-AI19,2) | AT19: =ROUND(P19-Z19-AJ19,2) | AU19: =ROUND(Q19-AA19-AK19,2) | AV19: =ROUND(R19-AB19-AL19,2) | AW19: =ROUND(S19-AC19-AM19,2) | AX19: =ROUND(T19-AD19-AN19,2) | AY19: =ROUND(U19-AE19-AO19,2) | ... BA19: =ROUND(W19-AG19-AQ19,2) | BB19: =SUM(AR19:BA19)
A20: 16 | B20: =EOMONTH(TODAY(),15) | C20: =MAX(0,(SUM('My Loans'!$E$6:$E$15)+'My Loans'!$D$3)-SUM($X20:$AG20)) | D20: =MAX(0,AR19) | E20: =MAX(0,AS19) | F20: =MAX(0,AT19) | G20: =MAX(0,AU19) | H20: =MAX(0,AV19) | I20: =MAX(0,AW19) | J20: =MAX(0,AX19) | K20: =MAX(0,AY19) | ... M20: =MAX(0,BA19) | N20: =IF(D20<0.5,0,D20*(1+N('My Loans'!D6)/1200)) | O20: =IF(E20<0.5,0,E20*(1+N('My Loans'!D7)/1200)) | P20: =IF(F20<0.5,0,F20*(1+N('My Loans'!D8)/1200)) | Q20: =IF(G20<0.5,0,G20*(1+N('My Loans'!D9)/1200)) | R20: =IF(H20<0.5,0,H20*(1+N('My Loans'!D10)/1200)) | S20: =IF(I20<0.5,0,I20*(1+N('My Loans'!D11)/1200)) | T20: =IF(J20<0.5,0,J20*(1+N('My Loans'!D12)/1200)) | U20: =IF(K20<0.5,0,K20*(1+N('My Loans'!D13)/1200)) | V20: =IF(L20<0.5,0,L20*(1+N('My Loans'!D14)/1200)) | W20: =IF(M20<0.5,0,M20*(1+N('My Loans'!D15)/1200)) | X20: =MIN(N20,N('My Loans'!E6)) | Y20: =MIN(O20,N('My Loans'!E7)) | Z20: =MIN(P20,N('My Loans'!E8)) | AA20: =MIN(Q20,N('My Loans'!E9)) | AB20: =MIN(R20,N('My Loans'!E10)) | AC20: =MIN(S20,N('My Loans'!E11)) | AD20: =MIN(T20,N('My Loans'!E12)) | AE20: =MIN(U20,N('My Loans'!E13)) | AF20: =MIN(V20,N('My Loans'!E14)) | AG20: =MIN(W20,N('My Loans'!E15)) | AH20: =MIN(N20-X20,MAX(0,$C20-SUMPRODUCT(($D$3:$M$3<D$3)*($N20:$W20-$X20:$AG20)))) | AI20: =MIN(O20-Y20,MAX(0,$C20-SUMPRODUCT(($D$3:$M$3<E$3)*($N20:$W20-$X20:$AG20)))) | AJ20: =MIN(P20-Z20,MAX(0,$C20-SUMPRODUCT(($D$3:$M$3<F$3)*($N20:$W20-$X20:$AG20)))) | AK20: =MIN(Q20-AA20,MAX(0,$C20-SUMPRODUCT(($D$3:$M$3<G$3)*($N20:$W20-$X20:$AG20)))) | AL20: =MIN(R20-AB20,MAX(0,$C20-SUMPRODUCT(($D$3:$M$3<H$3)*($N20:$W20-$X20:$AG20)))) | AM20: =MIN(S20-AC20,MAX(0,$C20-SUMPRODUCT(($D$3:$M$3<I$3)*($N20:$W20-$X20:$AG20)))) | AN20: =MIN(T20-AD20,MAX(0,$C20-SUMPRODUCT(($D$3:$M$3<J$3)*($N20:$W20-$X20:$AG20)))) | AO20: =MIN(U20-AE20,MAX(0,$C20-SUMPRODUCT(($D$3:$M$3<K$3)*($N20:$W20-$X20:$AG20)))) | ... AQ20: =MIN(W20-AG20,MAX(0,$C20-SUMPRODUCT(($D$3:$M$3<M$3)*($N20:$W20-$X20:$AG20)))) | AR20: =ROUND(N20-X20-AH20,2) | AS20: =ROUND(O20-Y20-AI20,2) | AT20: =ROUND(P20-Z20-AJ20,2) | AU20: =ROUND(Q20-AA20-AK20,2) | AV20: =ROUND(R20-AB20-AL20,2) | AW20: =ROUND(S20-AC20-AM20,2) | AX20: =ROUND(T20-AD20-AN20,2) | AY20: =ROUND(U20-AE20-AO20,2) | ... BA20: =ROUND(W20-AG20-AQ20,2) | BB20: =SUM(AR20:BA20)
A21: 17 | B21: =EOMONTH(TODAY(),16) | C21: =MAX(0,(SUM('My Loans'!$E$6:$E$15)+'My Loans'!$D$3)-SUM($X21:$AG21)) | D21: =MAX(0,AR20) | E21: =MAX(0,AS20) | F21: =MAX(0,AT20) | G21: =MAX(0,AU20) | H21: =MAX(0,AV20) | I21: =MAX(0,AW20) | J21: =MAX(0,AX20) | K21: =MAX(0,AY20) | ... M21: =MAX(0,BA20) | N21: =IF(D21<0.5,0,D21*(1+N('My Loans'!D6)/1200)) | O21: =IF(E21<0.5,0,E21*(1+N('My Loans'!D7)/1200)) | P21: =IF(F21<0.5,0,F21*(1+N('My Loans'!D8)/1200)) | Q21: =IF(G21<0.5,0,G21*(1+N('My Loans'!D9)/1200)) | R21: =IF(H21<0.5,0,H21*(1+N('My Loans'!D10)/1200)) | S21: =IF(I21<0.5,0,I21*(1+N('My Loans'!D11)/1200)) | T21: =IF(J21<0.5,0,J21*(1+N('My Loans'!D12)/1200)) | U21: =IF(K21<0.5,0,K21*(1+N('My Loans'!D13)/1200)) | V21: =IF(L21<0.5,0,L21*(1+N('My Loans'!D14)/1200)) | W21: =IF(M21<0.5,0,M21*(1+N('My Loans'!D15)/1200)) | X21: =MIN(N21,N('My Loans'!E6)) | Y21: =MIN(O21,N('My Loans'!E7)) | Z21: =MIN(P21,N('My Loans'!E8)) | AA21: =MIN(Q21,N('My Loans'!E9)) | AB21: =MIN(R21,N('My Loans'!E10)) | AC21: =MIN(S21,N('My Loans'!E11)) | AD21: =MIN(T21,N('My Loans'!E12)) | AE21: =MIN(U21,N('My Loans'!E13)) | AF21: =MIN(V21,N('My Loans'!E14)) | AG21: =MIN(W21,N('My Loans'!E15)) | AH21: =MIN(N21-X21,MAX(0,$C21-SUMPRODUCT(($D$3:$M$3<D$3)*($N21:$W21-$X21:$AG21)))) | AI21: =MIN(O21-Y21,MAX(0,$C21-SUMPRODUCT(($D$3:$M$3<E$3)*($N21:$W21-$X21:$AG21)))) | AJ21: =MIN(P21-Z21,MAX(0,$C21-SUMPRODUCT(($D$3:$M$3<F$3)*($N21:$W21-$X21:$AG21)))) | AK21: =MIN(Q21-AA21,MAX(0,$C21-SUMPRODUCT(($D$3:$M$3<G$3)*($N21:$W21-$X21:$AG21)))) | AL21: =MIN(R21-AB21,MAX(0,$C21-SUMPRODUCT(($D$3:$M$3<H$3)*($N21:$W21-$X21:$AG21)))) | AM21: =MIN(S21-AC21,MAX(0,$C21-SUMPRODUCT(($D$3:$M$3<I$3)*($N21:$W21-$X21:$AG21)))) | AN21: =MIN(T21-AD21,MAX(0,$C21-SUMPRODUCT(($D$3:$M$3<J$3)*($N21:$W21-$X21:$AG21)))) | AO21: =MIN(U21-AE21,MAX(0,$C21-SUMPRODUCT(($D$3:$M$3<K$3)*($N21:$W21-$X21:$AG21)))) | ... AQ21: =MIN(W21-AG21,MAX(0,$C21-SUMPRODUCT(($D$3:$M$3<M$3)*($N21:$W21-$X21:$AG21)))) | AR21: =ROUND(N21-X21-AH21,2) | AS21: =ROUND(O21-Y21-AI21,2) | AT21: =ROUND(P21-Z21-AJ21,2) | AU21: =ROUND(Q21-AA21-AK21,2) | AV21: =ROUND(R21-AB21-AL21,2) | AW21: =ROUND(S21-AC21-AM21,2) | AX21: =ROUND(T21-AD21-AN21,2) | AY21: =ROUND(U21-AE21-AO21,2) | ... BA21: =ROUND(W21-AG21-AQ21,2) | BB21: =SUM(AR21:BA21)
A22: 18 | B22: =EOMONTH(TODAY(),17) | C22: =MAX(0,(SUM('My Loans'!$E$6:$E$15)+'My Loans'!$D$3)-SUM($X22:$AG22)) | D22: =MAX(0,AR21) | E22: =MAX(0,AS21) | F22: =MAX(0,AT21) | G22: =MAX(0,AU21) | H22: =MAX(0,AV21) | I22: =MAX(0,AW21) | J22: =MAX(0,AX21) | K22: =MAX(0,AY21) | ... M22: =MAX(0,BA21) | N22: =IF(D22<0.5,0,D22*(1+N('My Loans'!D6)/1200)) | O22: =IF(E22<0.5,0,E22*(1+N('My Loans'!D7)/1200)) | P22: =IF(F22<0.5,0,F22*(1+N('My Loans'!D8)/1200)) | Q22: =IF(G22<0.5,0,G22*(1+N('My Loans'!D9)/1200)) | R22: =IF(H22<0.5,0,H22*(1+N('My Loans'!D10)/1200)) | S22: =IF(I22<0.5,0,I22*(1+N('My Loans'!D11)/1200)) | T22: =IF(J22<0.5,0,J22*(1+N('My Loans'!D12)/1200)) | U22: =IF(K22<0.5,0,K22*(1+N('My Loans'!D13)/1200)) | V22: =IF(L22<0.5,0,L22*(1+N('My Loans'!D14)/1200)) | W22: =IF(M22<0.5,0,M22*(1+N('My Loans'!D15)/1200)) | X22: =MIN(N22,N('My Loans'!E6)) | Y22: =MIN(O22,N('My Loans'!E7)) | Z22: =MIN(P22,N('My Loans'!E8)) | AA22: =MIN(Q22,N('My Loans'!E9)) | AB22: =MIN(R22,N('My Loans'!E10)) | AC22: =MIN(S22,N('My Loans'!E11)) | AD22: =MIN(T22,N('My Loans'!E12)) | AE22: =MIN(U22,N('My Loans'!E13)) | AF22: =MIN(V22,N('My Loans'!E14)) | AG22: =MIN(W22,N('My Loans'!E15)) | AH22: =MIN(N22-X22,MAX(0,$C22-SUMPRODUCT(($D$3:$M$3<D$3)*($N22:$W22-$X22:$AG22)))) | AI22: =MIN(O22-Y22,MAX(0,$C22-SUMPRODUCT(($D$3:$M$3<E$3)*($N22:$W22-$X22:$AG22)))) | AJ22: =MIN(P22-Z22,MAX(0,$C22-SUMPRODUCT(($D$3:$M$3<F$3)*($N22:$W22-$X22:$AG22)))) | AK22: =MIN(Q22-AA22,MAX(0,$C22-SUMPRODUCT(($D$3:$M$3<G$3)*($N22:$W22-$X22:$AG22)))) | AL22: =MIN(R22-AB22,MAX(0,$C22-SUMPRODUCT(($D$3:$M$3<H$3)*($N22:$W22-$X22:$AG22)))) | AM22: =MIN(S22-AC22,MAX(0,$C22-SUMPRODUCT(($D$3:$M$3<I$3)*($N22:$W22-$X22:$AG22)))) | AN22: =MIN(T22-AD22,MAX(0,$C22-SUMPRODUCT(($D$3:$M$3<J$3)*($N22:$W22-$X22:$AG22)))) | AO22: =MIN(U22-AE22,MAX(0,$C22-SUMPRODUCT(($D$3:$M$3<K$3)*($N22:$W22-$X22:$AG22)))) | ... AQ22: =MIN(W22-AG22,MAX(0,$C22-SUMPRODUCT(($D$3:$M$3<M$3)*($N22:$W22-$X22:$AG22)))) | AR22: =ROUND(N22-X22-AH22,2) | AS22: =ROUND(O22-Y22-AI22,2) | AT22: =ROUND(P22-Z22-AJ22,2) | AU22: =ROUND(Q22-AA22-AK22,2) | AV22: =ROUND(R22-AB22-AL22,2) | AW22: =ROUND(S22-AC22-AM22,2) | AX22: =ROUND(T22-AD22-AN22,2) | AY22: =ROUND(U22-AE22-AO22,2) | ... BA22: =ROUND(W22-AG22-AQ22,2) | BB22: =SUM(AR22:BA22)
A23: 19 | B23: =EOMONTH(TODAY(),18) | C23: =MAX(0,(SUM('My Loans'!$E$6:$E$15)+'My Loans'!$D$3)-SUM($X23:$AG23)) | D23: =MAX(0,AR22) | E23: =MAX(0,AS22) | F23: =MAX(0,AT22) | G23: =MAX(0,AU22) | H23: =MAX(0,AV22) | I23: =MAX(0,AW22) | J23: =MAX(0,AX22) | K23: =MAX(0,AY22) | ... M23: =MAX(0,BA22) | N23: =IF(D23<0.5,0,D23*(1+N('My Loans'!D6)/1200)) | O23: =IF(E23<0.5,0,E23*(1+N('My Loans'!D7)/1200)) | P23: =IF(F23<0.5,0,F23*(1+N('My Loans'!D8)/1200)) | Q23: =IF(G23<0.5,0,G23*(1+N('My Loans'!D9)/1200)) | R23: =IF(H23<0.5,0,H23*(1+N('My Loans'!D10)/1200)) | S23: =IF(I23<0.5,0,I23*(1+N('My Loans'!D11)/1200)) | T23: =IF(J23<0.5,0,J23*(1+N('My Loans'!D12)/1200)) | U23: =IF(K23<0.5,0,K23*(1+N('My Loans'!D13)/1200)) | V23: =IF(L23<0.5,0,L23*(1+N('My Loans'!D14)/1200)) | W23: =IF(M23<0.5,0,M23*(1+N('My Loans'!D15)/1200)) | X23: =MIN(N23,N('My Loans'!E6)) | Y23: =MIN(O23,N('My Loans'!E7)) | Z23: =MIN(P23,N('My Loans'!E8)) | AA23: =MIN(Q23,N('My Loans'!E9)) | AB23: =MIN(R23,N('My Loans'!E10)) | AC23: =MIN(S23,N('My Loans'!E11)) | AD23: =MIN(T23,N('My Loans'!E12)) | AE23: =MIN(U23,N('My Loans'!E13)) | AF23: =MIN(V23,N('My Loans'!E14)) | AG23: =MIN(W23,N('My Loans'!E15)) | AH23: =MIN(N23-X23,MAX(0,$C23-SUMPRODUCT(($D$3:$M$3<D$3)*($N23:$W23-$X23:$AG23)))) | AI23: =MIN(O23-Y23,MAX(0,$C23-SUMPRODUCT(($D$3:$M$3<E$3)*($N23:$W23-$X23:$AG23)))) | AJ23: =MIN(P23-Z23,MAX(0,$C23-SUMPRODUCT(($D$3:$M$3<F$3)*($N23:$W23-$X23:$AG23)))) | AK23: =MIN(Q23-AA23,MAX(0,$C23-SUMPRODUCT(($D$3:$M$3<G$3)*($N23:$W23-$X23:$AG23)))) | AL23: =MIN(R23-AB23,MAX(0,$C23-SUMPRODUCT(($D$3:$M$3<H$3)*($N23:$W23-$X23:$AG23)))) | AM23: =MIN(S23-AC23,MAX(0,$C23-SUMPRODUCT(($D$3:$M$3<I$3)*($N23:$W23-$X23:$AG23)))) | AN23: =MIN(T23-AD23,MAX(0,$C23-SUMPRODUCT(($D$3:$M$3<J$3)*($N23:$W23-$X23:$AG23)))) | AO23: =MIN(U23-AE23,MAX(0,$C23-SUMPRODUCT(($D$3:$M$3<K$3)*($N23:$W23-$X23:$AG23)))) | ... AQ23: =MIN(W23-AG23,MAX(0,$C23-SUMPRODUCT(($D$3:$M$3<M$3)*($N23:$W23-$X23:$AG23)))) | AR23: =ROUND(N23-X23-AH23,2) | AS23: =ROUND(O23-Y23-AI23,2) | AT23: =ROUND(P23-Z23-AJ23,2) | AU23: =ROUND(Q23-AA23-AK23,2) | AV23: =ROUND(R23-AB23-AL23,2) | AW23: =ROUND(S23-AC23-AM23,2) | AX23: =ROUND(T23-AD23-AN23,2) | AY23: =ROUND(U23-AE23-AO23,2) | ... BA23: =ROUND(W23-AG23-AQ23,2) | BB23: =SUM(AR23:BA23)
A24: 20 | B24: =EOMONTH(TODAY(),19) | C24: =MAX(0,(SUM('My Loans'!$E$6:$E$15)+'My Loans'!$D$3)-SUM($X24:$AG24)) | D24: =MAX(0,AR23) | E24: =MAX(0,AS23) | F24: =MAX(0,AT23) | G24: =MAX(0,AU23) | H24: =MAX(0,AV23) | I24: =MAX(0,AW23) | J24: =MAX(0,AX23) | K24: =MAX(0,AY23) | ... M24: =MAX(0,BA23) | N24: =IF(D24<0.5,0,D24*(1+N('My Loans'!D6)/1200)) | O24: =IF(E24<0.5,0,E24*(1+N('My Loans'!D7)/1200)) | P24: =IF(F24<0.5,0,F24*(1+N('My Loans'!D8)/1200)) | Q24: =IF(G24<0.5,0,G24*(1+N('My Loans'!D9)/1200)) | R24: =IF(H24<0.5,0,H24*(1+N('My Loans'!D10)/1200)) | S24: =IF(I24<0.5,0,I24*(1+N('My Loans'!D11)/1200)) | T24: =IF(J24<0.5,0,J24*(1+N('My Loans'!D12)/1200)) | U24: =IF(K24<0.5,0,K24*(1+N('My Loans'!D13)/1200)) | V24: =IF(L24<0.5,0,L24*(1+N('My Loans'!D14)/1200)) | W24: =IF(M24<0.5,0,M24*(1+N('My Loans'!D15)/1200)) | X24: =MIN(N24,N('My Loans'!E6)) | Y24: =MIN(O24,N('My Loans'!E7)) | Z24: =MIN(P24,N('My Loans'!E8)) | AA24: =MIN(Q24,N('My Loans'!E9)) | AB24: =MIN(R24,N('My Loans'!E10)) | AC24: =MIN(S24,N('My Loans'!E11)) | AD24: =MIN(T24,N('My Loans'!E12)) | AE24: =MIN(U24,N('My Loans'!E13)) | AF24: =MIN(V24,N('My Loans'!E14)) | AG24: =MIN(W24,N('My Loans'!E15)) | AH24: =MIN(N24-X24,MAX(0,$C24-SUMPRODUCT(($D$3:$M$3<D$3)*($N24:$W24-$X24:$AG24)))) | AI24: =MIN(O24-Y24,MAX(0,$C24-SUMPRODUCT(($D$3:$M$3<E$3)*($N24:$W24-$X24:$AG24)))) | AJ24: =MIN(P24-Z24,MAX(0,$C24-SUMPRODUCT(($D$3:$M$3<F$3)*($N24:$W24-$X24:$AG24)))) | AK24: =MIN(Q24-AA24,MAX(0,$C24-SUMPRODUCT(($D$3:$M$3<G$3)*($N24:$W24-$X24:$AG24)))) | AL24: =MIN(R24-AB24,MAX(0,$C24-SUMPRODUCT(($D$3:$M$3<H$3)*($N24:$W24-$X24:$AG24)))) | AM24: =MIN(S24-AC24,MAX(0,$C24-SUMPRODUCT(($D$3:$M$3<I$3)*($N24:$W24-$X24:$AG24)))) | AN24: =MIN(T24-AD24,MAX(0,$C24-SUMPRODUCT(($D$3:$M$3<J$3)*($N24:$W24-$X24:$AG24)))) | AO24: =MIN(U24-AE24,MAX(0,$C24-SUMPRODUCT(($D$3:$M$3<K$3)*($N24:$W24-$X24:$AG24)))) | ... AQ24: =MIN(W24-AG24,MAX(0,$C24-SUMPRODUCT(($D$3:$M$3<M$3)*($N24:$W24-$X24:$AG24)))) | AR24: =ROUND(N24-X24-AH24,2) | AS24: =ROUND(O24-Y24-AI24,2) | AT24: =ROUND(P24-Z24-AJ24,2) | AU24: =ROUND(Q24-AA24-AK24,2) | AV24: =ROUND(R24-AB24-AL24,2) | AW24: =ROUND(S24-AC24-AM24,2) | AX24: =ROUND(T24-AD24-AN24,2) | AY24: =ROUND(U24-AE24-AO24,2) | ... BA24: =ROUND(W24-AG24-AQ24,2) | BB24: =SUM(AR24:BA24)
A25: 21 | B25: =EOMONTH(TODAY(),20) | C25: =MAX(0,(SUM('My Loans'!$E$6:$E$15)+'My Loans'!$D$3)-SUM($X25:$AG25)) | D25: =MAX(0,AR24) | E25: =MAX(0,AS24) | F25: =MAX(0,AT24) | G25: =MAX(0,AU24) | H25: =MAX(0,AV24) | I25: =MAX(0,AW24) | J25: =MAX(0,AX24) | K25: =MAX(0,AY24) | ... M25: =MAX(0,BA24) | N25: =IF(D25<0.5,0,D25*(1+N('My Loans'!D6)/1200)) | O25: =IF(E25<0.5,0,E25*(1+N('My Loans'!D7)/1200)) | P25: =IF(F25<0.5,0,F25*(1+N('My Loans'!D8)/1200)) | Q25: =IF(G25<0.5,0,G25*(1+N('My Loans'!D9)/1200)) | R25: =IF(H25<0.5,0,H25*(1+N('My Loans'!D10)/1200)) | S25: =IF(I25<0.5,0,I25*(1+N('My Loans'!D11)/1200)) | T25: =IF(J25<0.5,0,J25*(1+N('My Loans'!D12)/1200)) | U25: =IF(K25<0.5,0,K25*(1+N('My Loans'!D13)/1200)) | V25: =IF(L25<0.5,0,L25*(1+N('My Loans'!D14)/1200)) | W25: =IF(M25<0.5,0,M25*(1+N('My Loans'!D15)/1200)) | X25: =MIN(N25,N('My Loans'!E6)) | Y25: =MIN(O25,N('My Loans'!E7)) | Z25: =MIN(P25,N('My Loans'!E8)) | AA25: =MIN(Q25,N('My Loans'!E9)) | AB25: =MIN(R25,N('My Loans'!E10)) | AC25: =MIN(S25,N('My Loans'!E11)) | AD25: =MIN(T25,N('My Loans'!E12)) | AE25: =MIN(U25,N('My Loans'!E13)) | AF25: =MIN(V25,N('My Loans'!E14)) | AG25: =MIN(W25,N('My Loans'!E15)) | AH25: =MIN(N25-X25,MAX(0,$C25-SUMPRODUCT(($D$3:$M$3<D$3)*($N25:$W25-$X25:$AG25)))) | AI25: =MIN(O25-Y25,MAX(0,$C25-SUMPRODUCT(($D$3:$M$3<E$3)*($N25:$W25-$X25:$AG25)))) | AJ25: =MIN(P25-Z25,MAX(0,$C25-SUMPRODUCT(($D$3:$M$3<F$3)*($N25:$W25-$X25:$AG25)))) | AK25: =MIN(Q25-AA25,MAX(0,$C25-SUMPRODUCT(($D$3:$M$3<G$3)*($N25:$W25-$X25:$AG25)))) | AL25: =MIN(R25-AB25,MAX(0,$C25-SUMPRODUCT(($D$3:$M$3<H$3)*($N25:$W25-$X25:$AG25)))) | AM25: =MIN(S25-AC25,MAX(0,$C25-SUMPRODUCT(($D$3:$M$3<I$3)*($N25:$W25-$X25:$AG25)))) | AN25: =MIN(T25-AD25,MAX(0,$C25-SUMPRODUCT(($D$3:$M$3<J$3)*($N25:$W25-$X25:$AG25)))) | AO25: =MIN(U25-AE25,MAX(0,$C25-SUMPRODUCT(($D$3:$M$3<K$3)*($N25:$W25-$X25:$AG25)))) | ... AQ25: =MIN(W25-AG25,MAX(0,$C25-SUMPRODUCT(($D$3:$M$3<M$3)*($N25:$W25-$X25:$AG25)))) | AR25: =ROUND(N25-X25-AH25,2) | AS25: =ROUND(O25-Y25-AI25,2) | AT25: =ROUND(P25-Z25-AJ25,2) | AU25: =ROUND(Q25-AA25-AK25,2) | AV25: =ROUND(R25-AB25-AL25,2) | AW25: =ROUND(S25-AC25-AM25,2) | AX25: =ROUND(T25-AD25-AN25,2) | AY25: =ROUND(U25-AE25-AO25,2) | ... BA25: =ROUND(W25-AG25-AQ25,2) | BB25: =SUM(AR25:BA25)
A26: 22 | B26: =EOMONTH(TODAY(),21) | C26: =MAX(0,(SUM('My Loans'!$E$6:$E$15)+'My Loans'!$D$3)-SUM($X26:$AG26)) | D26: =MAX(0,AR25) | E26: =MAX(0,AS25) | F26: =MAX(0,AT25) | G26: =MAX(0,AU25) | H26: =MAX(0,AV25) | I26: =MAX(0,AW25) | J26: =MAX(0,AX25) | K26: =MAX(0,AY25) | ... M26: =MAX(0,BA25) | N26: =IF(D26<0.5,0,D26*(1+N('My Loans'!D6)/1200)) | O26: =IF(E26<0.5,0,E26*(1+N('My Loans'!D7)/1200)) | P26: =IF(F26<0.5,0,F26*(1+N('My Loans'!D8)/1200)) | Q26: =IF(G26<0.5,0,G26*(1+N('My Loans'!D9)/1200)) | R26: =IF(H26<0.5,0,H26*(1+N('My Loans'!D10)/1200)) | S26: =IF(I26<0.5,0,I26*(1+N('My Loans'!D11)/1200)) | T26: =IF(J26<0.5,0,J26*(1+N('My Loans'!D12)/1200)) | U26: =IF(K26<0.5,0,K26*(1+N('My Loans'!D13)/1200)) | V26: =IF(L26<0.5,0,L26*(1+N('My Loans'!D14)/1200)) | W26: =IF(M26<0.5,0,M26*(1+N('My Loans'!D15)/1200)) | X26: =MIN(N26,N('My Loans'!E6)) | Y26: =MIN(O26,N('My Loans'!E7)) | Z26: =MIN(P26,N('My Loans'!E8)) | AA26: =MIN(Q26,N('My Loans'!E9)) | AB26: =MIN(R26,N('My Loans'!E10)) | AC26: =MIN(S26,N('My Loans'!E11)) | AD26: =MIN(T26,N('My Loans'!E12)) | AE26: =MIN(U26,N('My Loans'!E13)) | AF26: =MIN(V26,N('My Loans'!E14)) | AG26: =MIN(W26,N('My Loans'!E15)) | AH26: =MIN(N26-X26,MAX(0,$C26-SUMPRODUCT(($D$3:$M$3<D$3)*($N26:$W26-$X26:$AG26)))) | AI26: =MIN(O26-Y26,MAX(0,$C26-SUMPRODUCT(($D$3:$M$3<E$3)*($N26:$W26-$X26:$AG26)))) | AJ26: =MIN(P26-Z26,MAX(0,$C26-SUMPRODUCT(($D$3:$M$3<F$3)*($N26:$W26-$X26:$AG26)))) | AK26: =MIN(Q26-AA26,MAX(0,$C26-SUMPRODUCT(($D$3:$M$3<G$3)*($N26:$W26-$X26:$AG26)))) | AL26: =MIN(R26-AB26,MAX(0,$C26-SUMPRODUCT(($D$3:$M$3<H$3)*($N26:$W26-$X26:$AG26)))) | AM26: =MIN(S26-AC26,MAX(0,$C26-SUMPRODUCT(($D$3:$M$3<I$3)*($N26:$W26-$X26:$AG26)))) | AN26: =MIN(T26-AD26,MAX(0,$C26-SUMPRODUCT(($D$3:$M$3<J$3)*($N26:$W26-$X26:$AG26)))) | AO26: =MIN(U26-AE26,MAX(0,$C26-SUMPRODUCT(($D$3:$M$3<K$3)*($N26:$W26-$X26:$AG26)))) | ... AQ26: =MIN(W26-AG26,MAX(0,$C26-SUMPRODUCT(($D$3:$M$3<M$3)*($N26:$W26-$X26:$AG26)))) | AR26: =ROUND(N26-X26-AH26,2) | AS26: =ROUND(O26-Y26-AI26,2) | AT26: =ROUND(P26-Z26-AJ26,2) | AU26: =ROUND(Q26-AA26-AK26,2) | AV26: =ROUND(R26-AB26-AL26,2) | AW26: =ROUND(S26-AC26-AM26,2) | AX26: =ROUND(T26-AD26-AN26,2) | AY26: =ROUND(U26-AE26-AO26,2) | ... BA26: =ROUND(W26-AG26-AQ26,2) | BB26: =SUM(AR26:BA26)
A27: 23 | B27: =EOMONTH(TODAY(),22) | C27: =MAX(0,(SUM('My Loans'!$E$6:$E$15)+'My Loans'!$D$3)-SUM($X27:$AG27)) | D27: =MAX(0,AR26) | E27: =MAX(0,AS26) | F27: =MAX(0,AT26) | G27: =MAX(0,AU26) | H27: =MAX(0,AV26) | I27: =MAX(0,AW26) | J27: =MAX(0,AX26) | K27: =MAX(0,AY26) | ... M27: =MAX(0,BA26) | N27: =IF(D27<0.5,0,D27*(1+N('My Loans'!D6)/1200)) | O27: =IF(E27<0.5,0,E27*(1+N('My Loans'!D7)/1200)) | P27: =IF(F27<0.5,0,F27*(1+N('My Loans'!D8)/1200)) | Q27: =IF(G27<0.5,0,G27*(1+N('My Loans'!D9)/1200)) | R27: =IF(H27<0.5,0,H27*(1+N('My Loans'!D10)/1200)) | S27: =IF(I27<0.5,0,I27*(1+N('My Loans'!D11)/1200)) | T27: =IF(J27<0.5,0,J27*(1+N('My Loans'!D12)/1200)) | U27: =IF(K27<0.5,0,K27*(1+N('My Loans'!D13)/1200)) | V27: =IF(L27<0.5,0,L27*(1+N('My Loans'!D14)/1200)) | W27: =IF(M27<0.5,0,M27*(1+N('My Loans'!D15)/1200)) | X27: =MIN(N27,N('My Loans'!E6)) | Y27: =MIN(O27,N('My Loans'!E7)) | Z27: =MIN(P27,N('My Loans'!E8)) | AA27: =MIN(Q27,N('My Loans'!E9)) | AB27: =MIN(R27,N('My Loans'!E10)) | AC27: =MIN(S27,N('My Loans'!E11)) | AD27: =MIN(T27,N('My Loans'!E12)) | AE27: =MIN(U27,N('My Loans'!E13)) | AF27: =MIN(V27,N('My Loans'!E14)) | AG27: =MIN(W27,N('My Loans'!E15)) | AH27: =MIN(N27-X27,MAX(0,$C27-SUMPRODUCT(($D$3:$M$3<D$3)*($N27:$W27-$X27:$AG27)))) | AI27: =MIN(O27-Y27,MAX(0,$C27-SUMPRODUCT(($D$3:$M$3<E$3)*($N27:$W27-$X27:$AG27)))) | AJ27: =MIN(P27-Z27,MAX(0,$C27-SUMPRODUCT(($D$3:$M$3<F$3)*($N27:$W27-$X27:$AG27)))) | AK27: =MIN(Q27-AA27,MAX(0,$C27-SUMPRODUCT(($D$3:$M$3<G$3)*($N27:$W27-$X27:$AG27)))) | AL27: =MIN(R27-AB27,MAX(0,$C27-SUMPRODUCT(($D$3:$M$3<H$3)*($N27:$W27-$X27:$AG27)))) | AM27: =MIN(S27-AC27,MAX(0,$C27-SUMPRODUCT(($D$3:$M$3<I$3)*($N27:$W27-$X27:$AG27)))) | AN27: =MIN(T27-AD27,MAX(0,$C27-SUMPRODUCT(($D$3:$M$3<J$3)*($N27:$W27-$X27:$AG27)))) | AO27: =MIN(U27-AE27,MAX(0,$C27-SUMPRODUCT(($D$3:$M$3<K$3)*($N27:$W27-$X27:$AG27)))) | ... AQ27: =MIN(W27-AG27,MAX(0,$C27-SUMPRODUCT(($D$3:$M$3<M$3)*($N27:$W27-$X27:$AG27)))) | AR27: =ROUND(N27-X27-AH27,2) | AS27: =ROUND(O27-Y27-AI27,2) | AT27: =ROUND(P27-Z27-AJ27,2) | AU27: =ROUND(Q27-AA27-AK27,2) | AV27: =ROUND(R27-AB27-AL27,2) | AW27: =ROUND(S27-AC27-AM27,2) | AX27: =ROUND(T27-AD27-AN27,2) | AY27: =ROUND(U27-AE27-AO27,2) | ... BA27: =ROUND(W27-AG27-AQ27,2) | BB27: =SUM(AR27:BA27)
A28: 24 | B28: =EOMONTH(TODAY(),23) | C28: =MAX(0,(SUM('My Loans'!$E$6:$E$15)+'My Loans'!$D$3)-SUM($X28:$AG28)) | D28: =MAX(0,AR27) | E28: =MAX(0,AS27) | F28: =MAX(0,AT27) | G28: =MAX(0,AU27) | H28: =MAX(0,AV27) | I28: =MAX(0,AW27) | J28: =MAX(0,AX27) | K28: =MAX(0,AY27) | ... M28: =MAX(0,BA27) | N28: =IF(D28<0.5,0,D28*(1+N('My Loans'!D6)/1200)) | O28: =IF(E28<0.5,0,E28*(1+N('My Loans'!D7)/1200)) | P28: =IF(F28<0.5,0,F28*(1+N('My Loans'!D8)/1200)) | Q28: =IF(G28<0.5,0,G28*(1+N('My Loans'!D9)/1200)) | R28: =IF(H28<0.5,0,H28*(1+N('My Loans'!D10)/1200)) | S28: =IF(I28<0.5,0,I28*(1+N('My Loans'!D11)/1200)) | T28: =IF(J28<0.5,0,J28*(1+N('My Loans'!D12)/1200)) | U28: =IF(K28<0.5,0,K28*(1+N('My Loans'!D13)/1200)) | V28: =IF(L28<0.5,0,L28*(1+N('My Loans'!D14)/1200)) | W28: =IF(M28<0.5,0,M28*(1+N('My Loans'!D15)/1200)) | X28: =MIN(N28,N('My Loans'!E6)) | Y28: =MIN(O28,N('My Loans'!E7)) | Z28: =MIN(P28,N('My Loans'!E8)) | AA28: =MIN(Q28,N('My Loans'!E9)) | AB28: =MIN(R28,N('My Loans'!E10)) | AC28: =MIN(S28,N('My Loans'!E11)) | AD28: =MIN(T28,N('My Loans'!E12)) | AE28: =MIN(U28,N('My Loans'!E13)) | AF28: =MIN(V28,N('My Loans'!E14)) | AG28: =MIN(W28,N('My Loans'!E15)) | AH28: =MIN(N28-X28,MAX(0,$C28-SUMPRODUCT(($D$3:$M$3<D$3)*($N28:$W28-$X28:$AG28)))) | AI28: =MIN(O28-Y28,MAX(0,$C28-SUMPRODUCT(($D$3:$M$3<E$3)*($N28:$W28-$X28:$AG28)))) | AJ28: =MIN(P28-Z28,MAX(0,$C28-SUMPRODUCT(($D$3:$M$3<F$3)*($N28:$W28-$X28:$AG28)))) | AK28: =MIN(Q28-AA28,MAX(0,$C28-SUMPRODUCT(($D$3:$M$3<G$3)*($N28:$W28-$X28:$AG28)))) | AL28: =MIN(R28-AB28,MAX(0,$C28-SUMPRODUCT(($D$3:$M$3<H$3)*($N28:$W28-$X28:$AG28)))) | AM28: =MIN(S28-AC28,MAX(0,$C28-SUMPRODUCT(($D$3:$M$3<I$3)*($N28:$W28-$X28:$AG28)))) | AN28: =MIN(T28-AD28,MAX(0,$C28-SUMPRODUCT(($D$3:$M$3<J$3)*($N28:$W28-$X28:$AG28)))) | AO28: =MIN(U28-AE28,MAX(0,$C28-SUMPRODUCT(($D$3:$M$3<K$3)*($N28:$W28-$X28:$AG28)))) | ... AQ28: =MIN(W28-AG28,MAX(0,$C28-SUMPRODUCT(($D$3:$M$3<M$3)*($N28:$W28-$X28:$AG28)))) | AR28: =ROUND(N28-X28-AH28,2) | AS28: =ROUND(O28-Y28-AI28,2) | AT28: =ROUND(P28-Z28-AJ28,2) | AU28: =ROUND(Q28-AA28-AK28,2) | AV28: =ROUND(R28-AB28-AL28,2) | AW28: =ROUND(S28-AC28-AM28,2) | AX28: =ROUND(T28-AD28-AN28,2) | AY28: =ROUND(U28-AE28-AO28,2) | ... BA28: =ROUND(W28-AG28-AQ28,2) | BB28: =SUM(AR28:BA28)
A29: 25 | B29: =EOMONTH(TODAY(),24) | C29: =MAX(0,(SUM('My Loans'!$E$6:$E$15)+'My Loans'!$D$3)-SUM($X29:$AG29)) | D29: =MAX(0,AR28) | E29: =MAX(0,AS28) | F29: =MAX(0,AT28) | G29: =MAX(0,AU28) | H29: =MAX(0,AV28) | I29: =MAX(0,AW28) | J29: =MAX(0,AX28) | K29: =MAX(0,AY28) | ... M29: =MAX(0,BA28) | N29: =IF(D29<0.5,0,D29*(1+N('My Loans'!D6)/1200)) | O29: =IF(E29<0.5,0,E29*(1+N('My Loans'!D7)/1200)) | P29: =IF(F29<0.5,0,F29*(1+N('My Loans'!D8)/1200)) | Q29: =IF(G29<0.5,0,G29*(1+N('My Loans'!D9)/1200)) | R29: =IF(H29<0.5,0,H29*(1+N('My Loans'!D10)/1200)) | S29: =IF(I29<0.5,0,I29*(1+N('My Loans'!D11)/1200)) | T29: =IF(J29<0.5,0,J29*(1+N('My Loans'!D12)/1200)) | U29: =IF(K29<0.5,0,K29*(1+N('My Loans'!D13)/1200)) | V29: =IF(L29<0.5,0,L29*(1+N('My Loans'!D14)/1200)) | W29: =IF(M29<0.5,0,M29*(1+N('My Loans'!D15)/1200)) | X29: =MIN(N29,N('My Loans'!E6)) | Y29: =MIN(O29,N('My Loans'!E7)) | Z29: =MIN(P29,N('My Loans'!E8)) | AA29: =MIN(Q29,N('My Loans'!E9)) | AB29: =MIN(R29,N('My Loans'!E10)) | AC29: =MIN(S29,N('My Loans'!E11)) | AD29: =MIN(T29,N('My Loans'!E12)) | AE29: =MIN(U29,N('My Loans'!E13)) | AF29: =MIN(V29,N('My Loans'!E14)) | AG29: =MIN(W29,N('My Loans'!E15)) | AH29: =MIN(N29-X29,MAX(0,$C29-SUMPRODUCT(($D$3:$M$3<D$3)*($N29:$W29-$X29:$AG29)))) | AI29: =MIN(O29-Y29,MAX(0,$C29-SUMPRODUCT(($D$3:$M$3<E$3)*($N29:$W29-$X29:$AG29)))) | AJ29: =MIN(P29-Z29,MAX(0,$C29-SUMPRODUCT(($D$3:$M$3<F$3)*($N29:$W29-$X29:$AG29)))) | AK29: =MIN(Q29-AA29,MAX(0,$C29-SUMPRODUCT(($D$3:$M$3<G$3)*($N29:$W29-$X29:$AG29)))) | AL29: =MIN(R29-AB29,MAX(0,$C29-SUMPRODUCT(($D$3:$M$3<H$3)*($N29:$W29-$X29:$AG29)))) | AM29: =MIN(S29-AC29,MAX(0,$C29-SUMPRODUCT(($D$3:$M$3<I$3)*($N29:$W29-$X29:$AG29)))) | AN29: =MIN(T29-AD29,MAX(0,$C29-SUMPRODUCT(($D$3:$M$3<J$3)*($N29:$W29-$X29:$AG29)))) | AO29: =MIN(U29-AE29,MAX(0,$C29-SUMPRODUCT(($D$3:$M$3<K$3)*($N29:$W29-$X29:$AG29)))) | ... AQ29: =MIN(W29-AG29,MAX(0,$C29-SUMPRODUCT(($D$3:$M$3<M$3)*($N29:$W29-$X29:$AG29)))) | AR29: =ROUND(N29-X29-AH29,2) | AS29: =ROUND(O29-Y29-AI29,2) | AT29: =ROUND(P29-Z29-AJ29,2) | AU29: =ROUND(Q29-AA29-AK29,2) | AV29: =ROUND(R29-AB29-AL29,2) | AW29: =ROUND(S29-AC29-AM29,2) | AX29: =ROUND(T29-AD29-AN29,2) | AY29: =ROUND(U29-AE29-AO29,2) | ... BA29: =ROUND(W29-AG29-AQ29,2) | BB29: =SUM(AR29:BA29)
A30: 26 | B30: =EOMONTH(TODAY(),25) | C30: =MAX(0,(SUM('My Loans'!$E$6:$E$15)+'My Loans'!$D$3)-SUM($X30:$AG30)) | D30: =MAX(0,AR29) | E30: =MAX(0,AS29) | F30: =MAX(0,AT29) | G30: =MAX(0,AU29) | H30: =MAX(0,AV29) | I30: =MAX(0,AW29) | J30: =MAX(0,AX29) | K30: =MAX(0,AY29) | ... M30: =MAX(0,BA29) | N30: =IF(D30<0.5,0,D30*(1+N('My Loans'!D6)/1200)) | O30: =IF(E30<0.5,0,E30*(1+N('My Loans'!D7)/1200)) | P30: =IF(F30<0.5,0,F30*(1+N('My Loans'!D8)/1200)) | Q30: =IF(G30<0.5,0,G30*(1+N('My Loans'!D9)/1200)) | R30: =IF(H30<0.5,0,H30*(1+N('My Loans'!D10)/1200)) | S30: =IF(I30<0.5,0,I30*(1+N('My Loans'!D11)/1200)) | T30: =IF(J30<0.5,0,J30*(1+N('My Loans'!D12)/1200)) | U30: =IF(K30<0.5,0,K30*(1+N('My Loans'!D13)/1200)) | V30: =IF(L30<0.5,0,L30*(1+N('My Loans'!D14)/1200)) | W30: =IF(M30<0.5,0,M30*(1+N('My Loans'!D15)/1200)) | X30: =MIN(N30,N('My Loans'!E6)) | Y30: =MIN(O30,N('My Loans'!E7)) | Z30: =MIN(P30,N('My Loans'!E8)) | AA30: =MIN(Q30,N('My Loans'!E9)) | AB30: =MIN(R30,N('My Loans'!E10)) | AC30: =MIN(S30,N('My Loans'!E11)) | AD30: =MIN(T30,N('My Loans'!E12)) | AE30: =MIN(U30,N('My Loans'!E13)) | AF30: =MIN(V30,N('My Loans'!E14)) | AG30: =MIN(W30,N('My Loans'!E15)) | AH30: =MIN(N30-X30,MAX(0,$C30-SUMPRODUCT(($D$3:$M$3<D$3)*($N30:$W30-$X30:$AG30)))) | AI30: =MIN(O30-Y30,MAX(0,$C30-SUMPRODUCT(($D$3:$M$3<E$3)*($N30:$W30-$X30:$AG30)))) | AJ30: =MIN(P30-Z30,MAX(0,$C30-SUMPRODUCT(($D$3:$M$3<F$3)*($N30:$W30-$X30:$AG30)))) | AK30: =MIN(Q30-AA30,MAX(0,$C30-SUMPRODUCT(($D$3:$M$3<G$3)*($N30:$W30-$X30:$AG30)))) | AL30: =MIN(R30-AB30,MAX(0,$C30-SUMPRODUCT(($D$3:$M$3<H$3)*($N30:$W30-$X30:$AG30)))) | AM30: =MIN(S30-AC30,MAX(0,$C30-SUMPRODUCT(($D$3:$M$3<I$3)*($N30:$W30-$X30:$AG30)))) | AN30: =MIN(T30-AD30,MAX(0,$C30-SUMPRODUCT(($D$3:$M$3<J$3)*($N30:$W30-$X30:$AG30)))) | AO30: =MIN(U30-AE30,MAX(0,$C30-SUMPRODUCT(($D$3:$M$3<K$3)*($N30:$W30-$X30:$AG30)))) | ... AQ30: =MIN(W30-AG30,MAX(0,$C30-SUMPRODUCT(($D$3:$M$3<M$3)*($N30:$W30-$X30:$AG30)))) | AR30: =ROUND(N30-X30-AH30,2) | AS30: =ROUND(O30-Y30-AI30,2) | AT30: =ROUND(P30-Z30-AJ30,2) | AU30: =ROUND(Q30-AA30-AK30,2) | AV30: =ROUND(R30-AB30-AL30,2) | AW30: =ROUND(S30-AC30-AM30,2) | AX30: =ROUND(T30-AD30-AN30,2) | AY30: =ROUND(U30-AE30-AO30,2) | ... BA30: =ROUND(W30-AG30-AQ30,2) | BB30: =SUM(AR30:BA30)
A31: 27 | B31: =EOMONTH(TODAY(),26) | C31: =MAX(0,(SUM('My Loans'!$E$6:$E$15)+'My Loans'!$D$3)-SUM($X31:$AG31)) | D31: =MAX(0,AR30) | E31: =MAX(0,AS30) | F31: =MAX(0,AT30) | G31: =MAX(0,AU30) | H31: =MAX(0,AV30) | I31: =MAX(0,AW30) | J31: =MAX(0,AX30) | K31: =MAX(0,AY30) | ... M31: =MAX(0,BA30) | N31: =IF(D31<0.5,0,D31*(1+N('My Loans'!D6)/1200)) | O31: =IF(E31<0.5,0,E31*(1+N('My Loans'!D7)/1200)) | P31: =IF(F31<0.5,0,F31*(1+N('My Loans'!D8)/1200)) | Q31: =IF(G31<0.5,0,G31*(1+N('My Loans'!D9)/1200)) | R31: =IF(H31<0.5,0,H31*(1+N('My Loans'!D10)/1200)) | S31: =IF(I31<0.5,0,I31*(1+N('My Loans'!D11)/1200)) | T31: =IF(J31<0.5,0,J31*(1+N('My Loans'!D12)/1200)) | U31: =IF(K31<0.5,0,K31*(1+N('My Loans'!D13)/1200)) | V31: =IF(L31<0.5,0,L31*(1+N('My Loans'!D14)/1200)) | W31: =IF(M31<0.5,0,M31*(1+N('My Loans'!D15)/1200)) | X31: =MIN(N31,N('My Loans'!E6)) | Y31: =MIN(O31,N('My Loans'!E7)) | Z31: =MIN(P31,N('My Loans'!E8)) | AA31: =MIN(Q31,N('My Loans'!E9)) | AB31: =MIN(R31,N('My Loans'!E10)) | AC31: =MIN(S31,N('My Loans'!E11)) | AD31: =MIN(T31,N('My Loans'!E12)) | AE31: =MIN(U31,N('My Loans'!E13)) | AF31: =MIN(V31,N('My Loans'!E14)) | AG31: =MIN(W31,N('My Loans'!E15)) | AH31: =MIN(N31-X31,MAX(0,$C31-SUMPRODUCT(($D$3:$M$3<D$3)*($N31:$W31-$X31:$AG31)))) | AI31: =MIN(O31-Y31,MAX(0,$C31-SUMPRODUCT(($D$3:$M$3<E$3)*($N31:$W31-$X31:$AG31)))) | AJ31: =MIN(P31-Z31,MAX(0,$C31-SUMPRODUCT(($D$3:$M$3<F$3)*($N31:$W31-$X31:$AG31)))) | AK31: =MIN(Q31-AA31,MAX(0,$C31-SUMPRODUCT(($D$3:$M$3<G$3)*($N31:$W31-$X31:$AG31)))) | AL31: =MIN(R31-AB31,MAX(0,$C31-SUMPRODUCT(($D$3:$M$3<H$3)*($N31:$W31-$X31:$AG31)))) | AM31: =MIN(S31-AC31,MAX(0,$C31-SUMPRODUCT(($D$3:$M$3<I$3)*($N31:$W31-$X31:$AG31)))) | AN31: =MIN(T31-AD31,MAX(0,$C31-SUMPRODUCT(($D$3:$M$3<J$3)*($N31:$W31-$X31:$AG31)))) | AO31: =MIN(U31-AE31,MAX(0,$C31-SUMPRODUCT(($D$3:$M$3<K$3)*($N31:$W31-$X31:$AG31)))) | ... AQ31: =MIN(W31-AG31,MAX(0,$C31-SUMPRODUCT(($D$3:$M$3<M$3)*($N31:$W31-$X31:$AG31)))) | AR31: =ROUND(N31-X31-AH31,2) | AS31: =ROUND(O31-Y31-AI31,2) | AT31: =ROUND(P31-Z31-AJ31,2) | AU31: =ROUND(Q31-AA31-AK31,2) | AV31: =ROUND(R31-AB31-AL31,2) | AW31: =ROUND(S31-AC31-AM31,2) | AX31: =ROUND(T31-AD31-AN31,2) | AY31: =ROUND(U31-AE31-AO31,2) | ... BA31: =ROUND(W31-AG31-AQ31,2) | BB31: =SUM(AR31:BA31)
A32: 28 | B32: =EOMONTH(TODAY(),27) | C32: =MAX(0,(SUM('My Loans'!$E$6:$E$15)+'My Loans'!$D$3)-SUM($X32:$AG32)) | D32: =MAX(0,AR31) | E32: =MAX(0,AS31) | F32: =MAX(0,AT31) | G32: =MAX(0,AU31) | H32: =MAX(0,AV31) | I32: =MAX(0,AW31) | J32: =MAX(0,AX31) | K32: =MAX(0,AY31) | ... M32: =MAX(0,BA31) | N32: =IF(D32<0.5,0,D32*(1+N('My Loans'!D6)/1200)) | O32: =IF(E32<0.5,0,E32*(1+N('My Loans'!D7)/1200)) | P32: =IF(F32<0.5,0,F32*(1+N('My Loans'!D8)/1200)) | Q32: =IF(G32<0.5,0,G32*(1+N('My Loans'!D9)/1200)) | R32: =IF(H32<0.5,0,H32*(1+N('My Loans'!D10)/1200)) | S32: =IF(I32<0.5,0,I32*(1+N('My Loans'!D11)/1200)) | T32: =IF(J32<0.5,0,J32*(1+N('My Loans'!D12)/1200)) | U32: =IF(K32<0.5,0,K32*(1+N('My Loans'!D13)/1200)) | V32: =IF(L32<0.5,0,L32*(1+N('My Loans'!D14)/1200)) | W32: =IF(M32<0.5,0,M32*(1+N('My Loans'!D15)/1200)) | X32: =MIN(N32,N('My Loans'!E6)) | Y32: =MIN(O32,N('My Loans'!E7)) | Z32: =MIN(P32,N('My Loans'!E8)) | AA32: =MIN(Q32,N('My Loans'!E9)) | AB32: =MIN(R32,N('My Loans'!E10)) | AC32: =MIN(S32,N('My Loans'!E11)) | AD32: =MIN(T32,N('My Loans'!E12)) | AE32: =MIN(U32,N('My Loans'!E13)) | AF32: =MIN(V32,N('My Loans'!E14)) | AG32: =MIN(W32,N('My Loans'!E15)) | AH32: =MIN(N32-X32,MAX(0,$C32-SUMPRODUCT(($D$3:$M$3<D$3)*($N32:$W32-$X32:$AG32)))) | AI32: =MIN(O32-Y32,MAX(0,$C32-SUMPRODUCT(($D$3:$M$3<E$3)*($N32:$W32-$X32:$AG32)))) | AJ32: =MIN(P32-Z32,MAX(0,$C32-SUMPRODUCT(($D$3:$M$3<F$3)*($N32:$W32-$X32:$AG32)))) | AK32: =MIN(Q32-AA32,MAX(0,$C32-SUMPRODUCT(($D$3:$M$3<G$3)*($N32:$W32-$X32:$AG32)))) | AL32: =MIN(R32-AB32,MAX(0,$C32-SUMPRODUCT(($D$3:$M$3<H$3)*($N32:$W32-$X32:$AG32)))) | AM32: =MIN(S32-AC32,MAX(0,$C32-SUMPRODUCT(($D$3:$M$3<I$3)*($N32:$W32-$X32:$AG32)))) | AN32: =MIN(T32-AD32,MAX(0,$C32-SUMPRODUCT(($D$3:$M$3<J$3)*($N32:$W32-$X32:$AG32)))) | AO32: =MIN(U32-AE32,MAX(0,$C32-SUMPRODUCT(($D$3:$M$3<K$3)*($N32:$W32-$X32:$AG32)))) | ... AQ32: =MIN(W32-AG32,MAX(0,$C32-SUMPRODUCT(($D$3:$M$3<M$3)*($N32:$W32-$X32:$AG32)))) | AR32: =ROUND(N32-X32-AH32,2) | AS32: =ROUND(O32-Y32-AI32,2) | AT32: =ROUND(P32-Z32-AJ32,2) | AU32: =ROUND(Q32-AA32-AK32,2) | AV32: =ROUND(R32-AB32-AL32,2) | AW32: =ROUND(S32-AC32-AM32,2) | AX32: =ROUND(T32-AD32-AN32,2) | AY32: =ROUND(U32-AE32-AO32,2) | ... BA32: =ROUND(W32-AG32-AQ32,2) | BB32: =SUM(AR32:BA32)
A33: 29 | B33: =EOMONTH(TODAY(),28) | C33: =MAX(0,(SUM('My Loans'!$E$6:$E$15)+'My Loans'!$D$3)-SUM($X33:$AG33)) | D33: =MAX(0,AR32) | E33: =MAX(0,AS32) | F33: =MAX(0,AT32) | G33: =MAX(0,AU32) | H33: =MAX(0,AV32) | I33: =MAX(0,AW32) | J33: =MAX(0,AX32) | K33: =MAX(0,AY32) | ... M33: =MAX(0,BA32) | N33: =IF(D33<0.5,0,D33*(1+N('My Loans'!D6)/1200)) | O33: =IF(E33<0.5,0,E33*(1+N('My Loans'!D7)/1200)) | P33: =IF(F33<0.5,0,F33*(1+N('My Loans'!D8)/1200)) | Q33: =IF(G33<0.5,0,G33*(1+N('My Loans'!D9)/1200)) | R33: =IF(H33<0.5,0,H33*(1+N('My Loans'!D10)/1200)) | S33: =IF(I33<0.5,0,I33*(1+N('My Loans'!D11)/1200)) | T33: =IF(J33<0.5,0,J33*(1+N('My Loans'!D12)/1200)) | U33: =IF(K33<0.5,0,K33*(1+N('My Loans'!D13)/1200)) | V33: =IF(L33<0.5,0,L33*(1+N('My Loans'!D14)/1200)) | W33: =IF(M33<0.5,0,M33*(1+N('My Loans'!D15)/1200)) | X33: =MIN(N33,N('My Loans'!E6)) | Y33: =MIN(O33,N('My Loans'!E7)) | Z33: =MIN(P33,N('My Loans'!E8)) | AA33: =MIN(Q33,N('My Loans'!E9)) | AB33: =MIN(R33,N('My Loans'!E10)) | AC33: =MIN(S33,N('My Loans'!E11)) | AD33: =MIN(T33,N('My Loans'!E12)) | AE33: =MIN(U33,N('My Loans'!E13)) | AF33: =MIN(V33,N('My Loans'!E14)) | AG33: =MIN(W33,N('My Loans'!E15)) | AH33: =MIN(N33-X33,MAX(0,$C33-SUMPRODUCT(($D$3:$M$3<D$3)*($N33:$W33-$X33:$AG33)))) | AI33: =MIN(O33-Y33,MAX(0,$C33-SUMPRODUCT(($D$3:$M$3<E$3)*($N33:$W33-$X33:$AG33)))) | AJ33: =MIN(P33-Z33,MAX(0,$C33-SUMPRODUCT(($D$3:$M$3<F$3)*($N33:$W33-$X33:$AG33)))) | AK33: =MIN(Q33-AA33,MAX(0,$C33-SUMPRODUCT(($D$3:$M$3<G$3)*($N33:$W33-$X33:$AG33)))) | AL33: =MIN(R33-AB33,MAX(0,$C33-SUMPRODUCT(($D$3:$M$3<H$3)*($N33:$W33-$X33:$AG33)))) | AM33: =MIN(S33-AC33,MAX(0,$C33-SUMPRODUCT(($D$3:$M$3<I$3)*($N33:$W33-$X33:$AG33)))) | AN33: =MIN(T33-AD33,MAX(0,$C33-SUMPRODUCT(($D$3:$M$3<J$3)*($N33:$W33-$X33:$AG33)))) | AO33: =MIN(U33-AE33,MAX(0,$C33-SUMPRODUCT(($D$3:$M$3<K$3)*($N33:$W33-$X33:$AG33)))) | ... AQ33: =MIN(W33-AG33,MAX(0,$C33-SUMPRODUCT(($D$3:$M$3<M$3)*($N33:$W33-$X33:$AG33)))) | AR33: =ROUND(N33-X33-AH33,2) | AS33: =ROUND(O33-Y33-AI33,2) | AT33: =ROUND(P33-Z33-AJ33,2) | AU33: =ROUND(Q33-AA33-AK33,2) | AV33: =ROUND(R33-AB33-AL33,2) | AW33: =ROUND(S33-AC33-AM33,2) | AX33: =ROUND(T33-AD33-AN33,2) | AY33: =ROUND(U33-AE33-AO33,2) | ... BA33: =ROUND(W33-AG33-AQ33,2) | BB33: =SUM(AR33:BA33)
A34: 30 | B34: =EOMONTH(TODAY(),29) | C34: =MAX(0,(SUM('My Loans'!$E$6:$E$15)+'My Loans'!$D$3)-SUM($X34:$AG34)) | D34: =MAX(0,AR33) | E34: =MAX(0,AS33) | F34: =MAX(0,AT33) | G34: =MAX(0,AU33) | H34: =MAX(0,AV33) | I34: =MAX(0,AW33) | J34: =MAX(0,AX33) | K34: =MAX(0,AY33) | ... M34: =MAX(0,BA33) | N34: =IF(D34<0.5,0,D34*(1+N('My Loans'!D6)/1200)) | O34: =IF(E34<0.5,0,E34*(1+N('My Loans'!D7)/1200)) | P34: =IF(F34<0.5,0,F34*(1+N('My Loans'!D8)/1200)) | Q34: =IF(G34<0.5,0,G34*(1+N('My Loans'!D9)/1200)) | R34: =IF(H34<0.5,0,H34*(1+N('My Loans'!D10)/1200)) | S34: =IF(I34<0.5,0,I34*(1+N('My Loans'!D11)/1200)) | T34: =IF(J34<0.5,0,J34*(1+N('My Loans'!D12)/1200)) | U34: =IF(K34<0.5,0,K34*(1+N('My Loans'!D13)/1200)) | V34: =IF(L34<0.5,0,L34*(1+N('My Loans'!D14)/1200)) | W34: =IF(M34<0.5,0,M34*(1+N('My Loans'!D15)/1200)) | X34: =MIN(N34,N('My Loans'!E6)) | Y34: =MIN(O34,N('My Loans'!E7)) | Z34: =MIN(P34,N('My Loans'!E8)) | AA34: =MIN(Q34,N('My Loans'!E9)) | AB34: =MIN(R34,N('My Loans'!E10)) | AC34: =MIN(S34,N('My Loans'!E11)) | AD34: =MIN(T34,N('My Loans'!E12)) | AE34: =MIN(U34,N('My Loans'!E13)) | AF34: =MIN(V34,N('My Loans'!E14)) | AG34: =MIN(W34,N('My Loans'!E15)) | AH34: =MIN(N34-X34,MAX(0,$C34-SUMPRODUCT(($D$3:$M$3<D$3)*($N34:$W34-$X34:$AG34)))) | AI34: =MIN(O34-Y34,MAX(0,$C34-SUMPRODUCT(($D$3:$M$3<E$3)*($N34:$W34-$X34:$AG34)))) | AJ34: =MIN(P34-Z34,MAX(0,$C34-SUMPRODUCT(($D$3:$M$3<F$3)*($N34:$W34-$X34:$AG34)))) | AK34: =MIN(Q34-AA34,MAX(0,$C34-SUMPRODUCT(($D$3:$M$3<G$3)*($N34:$W34-$X34:$AG34)))) | AL34: =MIN(R34-AB34,MAX(0,$C34-SUMPRODUCT(($D$3:$M$3<H$3)*($N34:$W34-$X34:$AG34)))) | AM34: =MIN(S34-AC34,MAX(0,$C34-SUMPRODUCT(($D$3:$M$3<I$3)*($N34:$W34-$X34:$AG34)))) | AN34: =MIN(T34-AD34,MAX(0,$C34-SUMPRODUCT(($D$3:$M$3<J$3)*($N34:$W34-$X34:$AG34)))) | AO34: =MIN(U34-AE34,MAX(0,$C34-SUMPRODUCT(($D$3:$M$3<K$3)*($N34:$W34-$X34:$AG34)))) | ... AQ34: =MIN(W34-AG34,MAX(0,$C34-SUMPRODUCT(($D$3:$M$3<M$3)*($N34:$W34-$X34:$AG34)))) | AR34: =ROUND(N34-X34-AH34,2) | AS34: =ROUND(O34-Y34-AI34,2) | AT34: =ROUND(P34-Z34-AJ34,2) | AU34: =ROUND(Q34-AA34-AK34,2) | AV34: =ROUND(R34-AB34-AL34,2) | AW34: =ROUND(S34-AC34-AM34,2) | AX34: =ROUND(T34-AD34-AN34,2) | AY34: =ROUND(U34-AE34-AO34,2) | ... BA34: =ROUND(W34-AG34-AQ34,2) | BB34: =SUM(AR34:BA34)
A35: 31 | B35: =EOMONTH(TODAY(),30) | C35: =MAX(0,(SUM('My Loans'!$E$6:$E$15)+'My Loans'!$D$3)-SUM($X35:$AG35)) | D35: =MAX(0,AR34) | E35: =MAX(0,AS34) | F35: =MAX(0,AT34) | G35: =MAX(0,AU34) | H35: =MAX(0,AV34) | I35: =MAX(0,AW34) | J35: =MAX(0,AX34) | K35: =MAX(0,AY34) | ... M35: =MAX(0,BA34) | N35: =IF(D35<0.5,0,D35*(1+N('My Loans'!D6)/1200)) | O35: =IF(E35<0.5,0,E35*(1+N('My Loans'!D7)/1200)) | P35: =IF(F35<0.5,0,F35*(1+N('My Loans'!D8)/1200)) | Q35: =IF(G35<0.5,0,G35*(1+N('My Loans'!D9)/1200)) | R35: =IF(H35<0.5,0,H35*(1+N('My Loans'!D10)/1200)) | S35: =IF(I35<0.5,0,I35*(1+N('My Loans'!D11)/1200)) | T35: =IF(J35<0.5,0,J35*(1+N('My Loans'!D12)/1200)) | U35: =IF(K35<0.5,0,K35*(1+N('My Loans'!D13)/1200)) | V35: =IF(L35<0.5,0,L35*(1+N('My Loans'!D14)/1200)) | W35: =IF(M35<0.5,0,M35*(1+N('My Loans'!D15)/1200)) | X35: =MIN(N35,N('My Loans'!E6)) | Y35: =MIN(O35,N('My Loans'!E7)) | Z35: =MIN(P35,N('My Loans'!E8)) | AA35: =MIN(Q35,N('My Loans'!E9)) | AB35: =MIN(R35,N('My Loans'!E10)) | AC35: =MIN(S35,N('My Loans'!E11)) | AD35: =MIN(T35,N('My Loans'!E12)) | AE35: =MIN(U35,N('My Loans'!E13)) | AF35: =MIN(V35,N('My Loans'!E14)) | AG35: =MIN(W35,N('My Loans'!E15)) | AH35: =MIN(N35-X35,MAX(0,$C35-SUMPRODUCT(($D$3:$M$3<D$3)*($N35:$W35-$X35:$AG35)))) | AI35: =MIN(O35-Y35,MAX(0,$C35-SUMPRODUCT(($D$3:$M$3<E$3)*($N35:$W35-$X35:$AG35)))) | AJ35: =MIN(P35-Z35,MAX(0,$C35-SUMPRODUCT(($D$3:$M$3<F$3)*($N35:$W35-$X35:$AG35)))) | AK35: =MIN(Q35-AA35,MAX(0,$C35-SUMPRODUCT(($D$3:$M$3<G$3)*($N35:$W35-$X35:$AG35)))) | AL35: =MIN(R35-AB35,MAX(0,$C35-SUMPRODUCT(($D$3:$M$3<H$3)*($N35:$W35-$X35:$AG35)))) | AM35: =MIN(S35-AC35,MAX(0,$C35-SUMPRODUCT(($D$3:$M$3<I$3)*($N35:$W35-$X35:$AG35)))) | AN35: =MIN(T35-AD35,MAX(0,$C35-SUMPRODUCT(($D$3:$M$3<J$3)*($N35:$W35-$X35:$AG35)))) | AO35: =MIN(U35-AE35,MAX(0,$C35-SUMPRODUCT(($D$3:$M$3<K$3)*($N35:$W35-$X35:$AG35)))) | ... AQ35: =MIN(W35-AG35,MAX(0,$C35-SUMPRODUCT(($D$3:$M$3<M$3)*($N35:$W35-$X35:$AG35)))) | AR35: =ROUND(N35-X35-AH35,2) | AS35: =ROUND(O35-Y35-AI35,2) | AT35: =ROUND(P35-Z35-AJ35,2) | AU35: =ROUND(Q35-AA35-AK35,2) | AV35: =ROUND(R35-AB35-AL35,2) | AW35: =ROUND(S35-AC35-AM35,2) | AX35: =ROUND(T35-AD35-AN35,2) | AY35: =ROUND(U35-AE35-AO35,2) | ... BA35: =ROUND(W35-AG35-AQ35,2) | BB35: =SUM(AR35:BA35)
A36: 32 | B36: =EOMONTH(TODAY(),31) | C36: =MAX(0,(SUM('My Loans'!$E$6:$E$15)+'My Loans'!$D$3)-SUM($X36:$AG36)) | D36: =MAX(0,AR35) | E36: =MAX(0,AS35) | F36: =MAX(0,AT35) | G36: =MAX(0,AU35) | H36: =MAX(0,AV35) | I36: =MAX(0,AW35) | J36: =MAX(0,AX35) | K36: =MAX(0,AY35) | ... M36: =MAX(0,BA35) | N36: =IF(D36<0.5,0,D36*(1+N('My Loans'!D6)/1200)) | O36: =IF(E36<0.5,0,E36*(1+N('My Loans'!D7)/1200)) | P36: =IF(F36<0.5,0,F36*(1+N('My Loans'!D8)/1200)) | Q36: =IF(G36<0.5,0,G36*(1+N('My Loans'!D9)/1200)) | R36: =IF(H36<0.5,0,H36*(1+N('My Loans'!D10)/1200)) | S36: =IF(I36<0.5,0,I36*(1+N('My Loans'!D11)/1200)) | T36: =IF(J36<0.5,0,J36*(1+N('My Loans'!D12)/1200)) | U36: =IF(K36<0.5,0,K36*(1+N('My Loans'!D13)/1200)) | V36: =IF(L36<0.5,0,L36*(1+N('My Loans'!D14)/1200)) | W36: =IF(M36<0.5,0,M36*(1+N('My Loans'!D15)/1200)) | X36: =MIN(N36,N('My Loans'!E6)) | Y36: =MIN(O36,N('My Loans'!E7)) | Z36: =MIN(P36,N('My Loans'!E8)) | AA36: =MIN(Q36,N('My Loans'!E9)) | AB36: =MIN(R36,N('My Loans'!E10)) | AC36: =MIN(S36,N('My Loans'!E11)) | AD36: =MIN(T36,N('My Loans'!E12)) | AE36: =MIN(U36,N('My Loans'!E13)) | AF36: =MIN(V36,N('My Loans'!E14)) | AG36: =MIN(W36,N('My Loans'!E15)) | AH36: =MIN(N36-X36,MAX(0,$C36-SUMPRODUCT(($D$3:$M$3<D$3)*($N36:$W36-$X36:$AG36)))) | AI36: =MIN(O36-Y36,MAX(0,$C36-SUMPRODUCT(($D$3:$M$3<E$3)*($N36:$W36-$X36:$AG36)))) | AJ36: =MIN(P36-Z36,MAX(0,$C36-SUMPRODUCT(($D$3:$M$3<F$3)*($N36:$W36-$X36:$AG36)))) | AK36: =MIN(Q36-AA36,MAX(0,$C36-SUMPRODUCT(($D$3:$M$3<G$3)*($N36:$W36-$X36:$AG36)))) | AL36: =MIN(R36-AB36,MAX(0,$C36-SUMPRODUCT(($D$3:$M$3<H$3)*($N36:$W36-$X36:$AG36)))) | AM36: =MIN(S36-AC36,MAX(0,$C36-SUMPRODUCT(($D$3:$M$3<I$3)*($N36:$W36-$X36:$AG36)))) | AN36: =MIN(T36-AD36,MAX(0,$C36-SUMPRODUCT(($D$3:$M$3<J$3)*($N36:$W36-$X36:$AG36)))) | AO36: =MIN(U36-AE36,MAX(0,$C36-SUMPRODUCT(($D$3:$M$3<K$3)*($N36:$W36-$X36:$AG36)))) | ... AQ36: =MIN(W36-AG36,MAX(0,$C36-SUMPRODUCT(($D$3:$M$3<M$3)*($N36:$W36-$X36:$AG36)))) | AR36: =ROUND(N36-X36-AH36,2) | AS36: =ROUND(O36-Y36-AI36,2) | AT36: =ROUND(P36-Z36-AJ36,2) | AU36: =ROUND(Q36-AA36-AK36,2) | AV36: =ROUND(R36-AB36-AL36,2) | AW36: =ROUND(S36-AC36-AM36,2) | AX36: =ROUND(T36-AD36-AN36,2) | AY36: =ROUND(U36-AE36-AO36,2) | ... BA36: =ROUND(W36-AG36-AQ36,2) | BB36: =SUM(AR36:BA36)
A37: 33 | B37: =EOMONTH(TODAY(),32) | C37: =MAX(0,(SUM('My Loans'!$E$6:$E$15)+'My Loans'!$D$3)-SUM($X37:$AG37)) | D37: =MAX(0,AR36) | E37: =MAX(0,AS36) | F37: =MAX(0,AT36) | G37: =MAX(0,AU36) | H37: =MAX(0,AV36) | I37: =MAX(0,AW36) | J37: =MAX(0,AX36) | K37: =MAX(0,AY36) | ... M37: =MAX(0,BA36) | N37: =IF(D37<0.5,0,D37*(1+N('My Loans'!D6)/1200)) | O37: =IF(E37<0.5,0,E37*(1+N('My Loans'!D7)/1200)) | P37: =IF(F37<0.5,0,F37*(1+N('My Loans'!D8)/1200)) | Q37: =IF(G37<0.5,0,G37*(1+N('My Loans'!D9)/1200)) | R37: =IF(H37<0.5,0,H37*(1+N('My Loans'!D10)/1200)) | S37: =IF(I37<0.5,0,I37*(1+N('My Loans'!D11)/1200)) | T37: =IF(J37<0.5,0,J37*(1+N('My Loans'!D12)/1200)) | U37: =IF(K37<0.5,0,K37*(1+N('My Loans'!D13)/1200)) | V37: =IF(L37<0.5,0,L37*(1+N('My Loans'!D14)/1200)) | W37: =IF(M37<0.5,0,M37*(1+N('My Loans'!D15)/1200)) | X37: =MIN(N37,N('My Loans'!E6)) | Y37: =MIN(O37,N('My Loans'!E7)) | Z37: =MIN(P37,N('My Loans'!E8)) | AA37: =MIN(Q37,N('My Loans'!E9)) | AB37: =MIN(R37,N('My Loans'!E10)) | AC37: =MIN(S37,N('My Loans'!E11)) | AD37: =MIN(T37,N('My Loans'!E12)) | AE37: =MIN(U37,N('My Loans'!E13)) | AF37: =MIN(V37,N('My Loans'!E14)) | AG37: =MIN(W37,N('My Loans'!E15)) | AH37: =MIN(N37-X37,MAX(0,$C37-SUMPRODUCT(($D$3:$M$3<D$3)*($N37:$W37-$X37:$AG37)))) | AI37: =MIN(O37-Y37,MAX(0,$C37-SUMPRODUCT(($D$3:$M$3<E$3)*($N37:$W37-$X37:$AG37)))) | AJ37: =MIN(P37-Z37,MAX(0,$C37-SUMPRODUCT(($D$3:$M$3<F$3)*($N37:$W37-$X37:$AG37)))) | AK37: =MIN(Q37-AA37,MAX(0,$C37-SUMPRODUCT(($D$3:$M$3<G$3)*($N37:$W37-$X37:$AG37)))) | AL37: =MIN(R37-AB37,MAX(0,$C37-SUMPRODUCT(($D$3:$M$3<H$3)*($N37:$W37-$X37:$AG37)))) | AM37: =MIN(S37-AC37,MAX(0,$C37-SUMPRODUCT(($D$3:$M$3<I$3)*($N37:$W37-$X37:$AG37)))) | AN37: =MIN(T37-AD37,MAX(0,$C37-SUMPRODUCT(($D$3:$M$3<J$3)*($N37:$W37-$X37:$AG37)))) | AO37: =MIN(U37-AE37,MAX(0,$C37-SUMPRODUCT(($D$3:$M$3<K$3)*($N37:$W37-$X37:$AG37)))) | ... AQ37: =MIN(W37-AG37,MAX(0,$C37-SUMPRODUCT(($D$3:$M$3<M$3)*($N37:$W37-$X37:$AG37)))) | AR37: =ROUND(N37-X37-AH37,2) | AS37: =ROUND(O37-Y37-AI37,2) | AT37: =ROUND(P37-Z37-AJ37,2) | AU37: =ROUND(Q37-AA37-AK37,2) | AV37: =ROUND(R37-AB37-AL37,2) | AW37: =ROUND(S37-AC37-AM37,2) | AX37: =ROUND(T37-AD37-AN37,2) | AY37: =ROUND(U37-AE37-AO37,2) | ... BA37: =ROUND(W37-AG37-AQ37,2) | BB37: =SUM(AR37:BA37)
A38: 34 | B38: =EOMONTH(TODAY(),33) | C38: =MAX(0,(SUM('My Loans'!$E$6:$E$15)+'My Loans'!$D$3)-SUM($X38:$AG38)) | D38: =MAX(0,AR37) | E38: =MAX(0,AS37) | F38: =MAX(0,AT37) | G38: =MAX(0,AU37) | H38: =MAX(0,AV37) | I38: =MAX(0,AW37) | J38: =MAX(0,AX37) | K38: =MAX(0,AY37) | ... M38: =MAX(0,BA37) | N38: =IF(D38<0.5,0,D38*(1+N('My Loans'!D6)/1200)) | O38: =IF(E38<0.5,0,E38*(1+N('My Loans'!D7)/1200)) | P38: =IF(F38<0.5,0,F38*(1+N('My Loans'!D8)/1200)) | Q38: =IF(G38<0.5,0,G38*(1+N('My Loans'!D9)/1200)) | R38: =IF(H38<0.5,0,H38*(1+N('My Loans'!D10)/1200)) | S38: =IF(I38<0.5,0,I38*(1+N('My Loans'!D11)/1200)) | T38: =IF(J38<0.5,0,J38*(1+N('My Loans'!D12)/1200)) | U38: =IF(K38<0.5,0,K38*(1+N('My Loans'!D13)/1200)) | V38: =IF(L38<0.5,0,L38*(1+N('My Loans'!D14)/1200)) | W38: =IF(M38<0.5,0,M38*(1+N('My Loans'!D15)/1200)) | X38: =MIN(N38,N('My Loans'!E6)) | Y38: =MIN(O38,N('My Loans'!E7)) | Z38: =MIN(P38,N('My Loans'!E8)) | AA38: =MIN(Q38,N('My Loans'!E9)) | AB38: =MIN(R38,N('My Loans'!E10)) | AC38: =MIN(S38,N('My Loans'!E11)) | AD38: =MIN(T38,N('My Loans'!E12)) | AE38: =MIN(U38,N('My Loans'!E13)) | AF38: =MIN(V38,N('My Loans'!E14)) | AG38: =MIN(W38,N('My Loans'!E15)) | AH38: =MIN(N38-X38,MAX(0,$C38-SUMPRODUCT(($D$3:$M$3<D$3)*($N38:$W38-$X38:$AG38)))) | AI38: =MIN(O38-Y38,MAX(0,$C38-SUMPRODUCT(($D$3:$M$3<E$3)*($N38:$W38-$X38:$AG38)))) | AJ38: =MIN(P38-Z38,MAX(0,$C38-SUMPRODUCT(($D$3:$M$3<F$3)*($N38:$W38-$X38:$AG38)))) | AK38: =MIN(Q38-AA38,MAX(0,$C38-SUMPRODUCT(($D$3:$M$3<G$3)*($N38:$W38-$X38:$AG38)))) | AL38: =MIN(R38-AB38,MAX(0,$C38-SUMPRODUCT(($D$3:$M$3<H$3)*($N38:$W38-$X38:$AG38)))) | AM38: =MIN(S38-AC38,MAX(0,$C38-SUMPRODUCT(($D$3:$M$3<I$3)*($N38:$W38-$X38:$AG38)))) | AN38: =MIN(T38-AD38,MAX(0,$C38-SUMPRODUCT(($D$3:$M$3<J$3)*($N38:$W38-$X38:$AG38)))) | AO38: =MIN(U38-AE38,MAX(0,$C38-SUMPRODUCT(($D$3:$M$3<K$3)*($N38:$W38-$X38:$AG38)))) | ... AQ38: =MIN(W38-AG38,MAX(0,$C38-SUMPRODUCT(($D$3:$M$3<M$3)*($N38:$W38-$X38:$AG38)))) | AR38: =ROUND(N38-X38-AH38,2) | AS38: =ROUND(O38-Y38-AI38,2) | AT38: =ROUND(P38-Z38-AJ38,2) | AU38: =ROUND(Q38-AA38-AK38,2) | AV38: =ROUND(R38-AB38-AL38,2) | AW38: =ROUND(S38-AC38-AM38,2) | AX38: =ROUND(T38-AD38-AN38,2) | AY38: =ROUND(U38-AE38-AO38,2) | ... BA38: =ROUND(W38-AG38-AQ38,2) | BB38: =SUM(AR38:BA38)
A39: 35 | B39: =EOMONTH(TODAY(),34) | C39: =MAX(0,(SUM('My Loans'!$E$6:$E$15)+'My Loans'!$D$3)-SUM($X39:$AG39)) | D39: =MAX(0,AR38) | E39: =MAX(0,AS38) | F39: =MAX(0,AT38) | G39: =MAX(0,AU38) | H39: =MAX(0,AV38) | I39: =MAX(0,AW38) | J39: =MAX(0,AX38) | K39: =MAX(0,AY38) | ... M39: =MAX(0,BA38) | N39: =IF(D39<0.5,0,D39*(1+N('My Loans'!D6)/1200)) | O39: =IF(E39<0.5,0,E39*(1+N('My Loans'!D7)/1200)) | P39: =IF(F39<0.5,0,F39*(1+N('My Loans'!D8)/1200)) | Q39: =IF(G39<0.5,0,G39*(1+N('My Loans'!D9)/1200)) | R39: =IF(H39<0.5,0,H39*(1+N('My Loans'!D10)/1200)) | S39: =IF(I39<0.5,0,I39*(1+N('My Loans'!D11)/1200)) | T39: =IF(J39<0.5,0,J39*(1+N('My Loans'!D12)/1200)) | U39: =IF(K39<0.5,0,K39*(1+N('My Loans'!D13)/1200)) | V39: =IF(L39<0.5,0,L39*(1+N('My Loans'!D14)/1200)) | W39: =IF(M39<0.5,0,M39*(1+N('My Loans'!D15)/1200)) | X39: =MIN(N39,N('My Loans'!E6)) | Y39: =MIN(O39,N('My Loans'!E7)) | Z39: =MIN(P39,N('My Loans'!E8)) | AA39: =MIN(Q39,N('My Loans'!E9)) | AB39: =MIN(R39,N('My Loans'!E10)) | AC39: =MIN(S39,N('My Loans'!E11)) | AD39: =MIN(T39,N('My Loans'!E12)) | AE39: =MIN(U39,N('My Loans'!E13)) | AF39: =MIN(V39,N('My Loans'!E14)) | AG39: =MIN(W39,N('My Loans'!E15)) | AH39: =MIN(N39-X39,MAX(0,$C39-SUMPRODUCT(($D$3:$M$3<D$3)*($N39:$W39-$X39:$AG39)))) | AI39: =MIN(O39-Y39,MAX(0,$C39-SUMPRODUCT(($D$3:$M$3<E$3)*($N39:$W39-$X39:$AG39)))) | AJ39: =MIN(P39-Z39,MAX(0,$C39-SUMPRODUCT(($D$3:$M$3<F$3)*($N39:$W39-$X39:$AG39)))) | AK39: =MIN(Q39-AA39,MAX(0,$C39-SUMPRODUCT(($D$3:$M$3<G$3)*($N39:$W39-$X39:$AG39)))) | AL39: =MIN(R39-AB39,MAX(0,$C39-SUMPRODUCT(($D$3:$M$3<H$3)*($N39:$W39-$X39:$AG39)))) | AM39: =MIN(S39-AC39,MAX(0,$C39-SUMPRODUCT(($D$3:$M$3<I$3)*($N39:$W39-$X39:$AG39)))) | AN39: =MIN(T39-AD39,MAX(0,$C39-SUMPRODUCT(($D$3:$M$3<J$3)*($N39:$W39-$X39:$AG39)))) | AO39: =MIN(U39-AE39,MAX(0,$C39-SUMPRODUCT(($D$3:$M$3<K$3)*($N39:$W39-$X39:$AG39)))) | ... AQ39: =MIN(W39-AG39,MAX(0,$C39-SUMPRODUCT(($D$3:$M$3<M$3)*($N39:$W39-$X39:$AG39)))) | AR39: =ROUND(N39-X39-AH39,2) | AS39: =ROUND(O39-Y39-AI39,2) | AT39: =ROUND(P39-Z39-AJ39,2) | AU39: =ROUND(Q39-AA39-AK39,2) | AV39: =ROUND(R39-AB39-AL39,2) | AW39: =ROUND(S39-AC39-AM39,2) | AX39: =ROUND(T39-AD39-AN39,2) | AY39: =ROUND(U39-AE39-AO39,2) | ... BA39: =ROUND(W39-AG39-AQ39,2) | BB39: =SUM(AR39:BA39)
A40: 36 | B40: =EOMONTH(TODAY(),35) | C40: =MAX(0,(SUM('My Loans'!$E$6:$E$15)+'My Loans'!$D$3)-SUM($X40:$AG40)) | D40: =MAX(0,AR39) | E40: =MAX(0,AS39) | F40: =MAX(0,AT39) | G40: =MAX(0,AU39) | H40: =MAX(0,AV39) | I40: =MAX(0,AW39) | J40: =MAX(0,AX39) | K40: =MAX(0,AY39) | ... M40: =MAX(0,BA39) | N40: =IF(D40<0.5,0,D40*(1+N('My Loans'!D6)/1200)) | O40: =IF(E40<0.5,0,E40*(1+N('My Loans'!D7)/1200)) | P40: =IF(F40<0.5,0,F40*(1+N('My Loans'!D8)/1200)) | Q40: =IF(G40<0.5,0,G40*(1+N('My Loans'!D9)/1200)) | R40: =IF(H40<0.5,0,H40*(1+N('My Loans'!D10)/1200)) | S40: =IF(I40<0.5,0,I40*(1+N('My Loans'!D11)/1200)) | T40: =IF(J40<0.5,0,J40*(1+N('My Loans'!D12)/1200)) | U40: =IF(K40<0.5,0,K40*(1+N('My Loans'!D13)/1200)) | V40: =IF(L40<0.5,0,L40*(1+N('My Loans'!D14)/1200)) | W40: =IF(M40<0.5,0,M40*(1+N('My Loans'!D15)/1200)) | X40: =MIN(N40,N('My Loans'!E6)) | Y40: =MIN(O40,N('My Loans'!E7)) | Z40: =MIN(P40,N('My Loans'!E8)) | AA40: =MIN(Q40,N('My Loans'!E9)) | AB40: =MIN(R40,N('My Loans'!E10)) | AC40: =MIN(S40,N('My Loans'!E11)) | AD40: =MIN(T40,N('My Loans'!E12)) | AE40: =MIN(U40,N('My Loans'!E13)) | AF40: =MIN(V40,N('My Loans'!E14)) | AG40: =MIN(W40,N('My Loans'!E15)) | AH40: =MIN(N40-X40,MAX(0,$C40-SUMPRODUCT(($D$3:$M$3<D$3)*($N40:$W40-$X40:$AG40)))) | AI40: =MIN(O40-Y40,MAX(0,$C40-SUMPRODUCT(($D$3:$M$3<E$3)*($N40:$W40-$X40:$AG40)))) | AJ40: =MIN(P40-Z40,MAX(0,$C40-SUMPRODUCT(($D$3:$M$3<F$3)*($N40:$W40-$X40:$AG40)))) | AK40: =MIN(Q40-AA40,MAX(0,$C40-SUMPRODUCT(($D$3:$M$3<G$3)*($N40:$W40-$X40:$AG40)))) | AL40: =MIN(R40-AB40,MAX(0,$C40-SUMPRODUCT(($D$3:$M$3<H$3)*($N40:$W40-$X40:$AG40)))) | AM40: =MIN(S40-AC40,MAX(0,$C40-SUMPRODUCT(($D$3:$M$3<I$3)*($N40:$W40-$X40:$AG40)))) | AN40: =MIN(T40-AD40,MAX(0,$C40-SUMPRODUCT(($D$3:$M$3<J$3)*($N40:$W40-$X40:$AG40)))) | AO40: =MIN(U40-AE40,MAX(0,$C40-SUMPRODUCT(($D$3:$M$3<K$3)*($N40:$W40-$X40:$AG40)))) | ... AQ40: =MIN(W40-AG40,MAX(0,$C40-SUMPRODUCT(($D$3:$M$3<M$3)*($N40:$W40-$X40:$AG40)))) | AR40: =ROUND(N40-X40-AH40,2) | AS40: =ROUND(O40-Y40-AI40,2) | AT40: =ROUND(P40-Z40-AJ40,2) | AU40: =ROUND(Q40-AA40-AK40,2) | AV40: =ROUND(R40-AB40-AL40,2) | AW40: =ROUND(S40-AC40-AM40,2) | AX40: =ROUND(T40-AD40-AN40,2) | AY40: =ROUND(U40-AE40-AO40,2) | ... BA40: =ROUND(W40-AG40-AQ40,2) | BB40: =SUM(AR40:BA40)
A41: 37 | B41: =EOMONTH(TODAY(),36) | C41: =MAX(0,(SUM('My Loans'!$E$6:$E$15)+'My Loans'!$D$3)-SUM($X41:$AG41)) | D41: =MAX(0,AR40) | E41: =MAX(0,AS40) | F41: =MAX(0,AT40) | G41: =MAX(0,AU40) | H41: =MAX(0,AV40) | I41: =MAX(0,AW40) | J41: =MAX(0,AX40) | K41: =MAX(0,AY40) | ... M41: =MAX(0,BA40) | N41: =IF(D41<0.5,0,D41*(1+N('My Loans'!D6)/1200)) | O41: =IF(E41<0.5,0,E41*(1+N('My Loans'!D7)/1200)) | P41: =IF(F41<0.5,0,F41*(1+N('My Loans'!D8)/1200)) | Q41: =IF(G41<0.5,0,G41*(1+N('My Loans'!D9)/1200)) | R41: =IF(H41<0.5,0,H41*(1+N('My Loans'!D10)/1200)) | S41: =IF(I41<0.5,0,I41*(1+N('My Loans'!D11)/1200)) | T41: =IF(J41<0.5,0,J41*(1+N('My Loans'!D12)/1200)) | U41: =IF(K41<0.5,0,K41*(1+N('My Loans'!D13)/1200)) | V41: =IF(L41<0.5,0,L41*(1+N('My Loans'!D14)/1200)) | W41: =IF(M41<0.5,0,M41*(1+N('My Loans'!D15)/1200)) | X41: =MIN(N41,N('My Loans'!E6)) | Y41: =MIN(O41,N('My Loans'!E7)) | Z41: =MIN(P41,N('My Loans'!E8)) | AA41: =MIN(Q41,N('My Loans'!E9)) | AB41: =MIN(R41,N('My Loans'!E10)) | AC41: =MIN(S41,N('My Loans'!E11)) | AD41: =MIN(T41,N('My Loans'!E12)) | AE41: =MIN(U41,N('My Loans'!E13)) | AF41: =MIN(V41,N('My Loans'!E14)) | AG41: =MIN(W41,N('My Loans'!E15)) | AH41: =MIN(N41-X41,MAX(0,$C41-SUMPRODUCT(($D$3:$M$3<D$3)*($N41:$W41-$X41:$AG41)))) | AI41: =MIN(O41-Y41,MAX(0,$C41-SUMPRODUCT(($D$3:$M$3<E$3)*($N41:$W41-$X41:$AG41)))) | AJ41: =MIN(P41-Z41,MAX(0,$C41-SUMPRODUCT(($D$3:$M$3<F$3)*($N41:$W41-$X41:$AG41)))) | AK41: =MIN(Q41-AA41,MAX(0,$C41-SUMPRODUCT(($D$3:$M$3<G$3)*($N41:$W41-$X41:$AG41)))) | AL41: =MIN(R41-AB41,MAX(0,$C41-SUMPRODUCT(($D$3:$M$3<H$3)*($N41:$W41-$X41:$AG41)))) | AM41: =MIN(S41-AC41,MAX(0,$C41-SUMPRODUCT(($D$3:$M$3<I$3)*($N41:$W41-$X41:$AG41)))) | AN41: =MIN(T41-AD41,MAX(0,$C41-SUMPRODUCT(($D$3:$M$3<J$3)*($N41:$W41-$X41:$AG41)))) | AO41: =MIN(U41-AE41,MAX(0,$C41-SUMPRODUCT(($D$3:$M$3<K$3)*($N41:$W41-$X41:$AG41)))) | ... AQ41: =MIN(W41-AG41,MAX(0,$C41-SUMPRODUCT(($D$3:$M$3<M$3)*($N41:$W41-$X41:$AG41)))) | AR41: =ROUND(N41-X41-AH41,2) | AS41: =ROUND(O41-Y41-AI41,2) | AT41: =ROUND(P41-Z41-AJ41,2) | AU41: =ROUND(Q41-AA41-AK41,2) | AV41: =ROUND(R41-AB41-AL41,2) | AW41: =ROUND(S41-AC41-AM41,2) | AX41: =ROUND(T41-AD41-AN41,2) | AY41: =ROUND(U41-AE41-AO41,2) | ... BA41: =ROUND(W41-AG41-AQ41,2) | BB41: =SUM(AR41:BA41)
A42: 38 | B42: =EOMONTH(TODAY(),37) | C42: =MAX(0,(SUM('My Loans'!$E$6:$E$15)+'My Loans'!$D$3)-SUM($X42:$AG42)) | D42: =MAX(0,AR41) | E42: =MAX(0,AS41) | F42: =MAX(0,AT41) | G42: =MAX(0,AU41) | H42: =MAX(0,AV41) | I42: =MAX(0,AW41) | J42: =MAX(0,AX41) | K42: =MAX(0,AY41) | ... M42: =MAX(0,BA41) | N42: =IF(D42<0.5,0,D42*(1+N('My Loans'!D6)/1200)) | O42: =IF(E42<0.5,0,E42*(1+N('My Loans'!D7)/1200)) | P42: =IF(F42<0.5,0,F42*(1+N('My Loans'!D8)/1200)) | Q42: =IF(G42<0.5,0,G42*(1+N('My Loans'!D9)/1200)) | R42: =IF(H42<0.5,0,H42*(1+N('My Loans'!D10)/1200)) | S42: =IF(I42<0.5,0,I42*(1+N('My Loans'!D11)/1200)) | T42: =IF(J42<0.5,0,J42*(1+N('My Loans'!D12)/1200)) | U42: =IF(K42<0.5,0,K42*(1+N('My Loans'!D13)/1200)) | V42: =IF(L42<0.5,0,L42*(1+N('My Loans'!D14)/1200)) | W42: =IF(M42<0.5,0,M42*(1+N('My Loans'!D15)/1200)) | X42: =MIN(N42,N('My Loans'!E6)) | Y42: =MIN(O42,N('My Loans'!E7)) | Z42: =MIN(P42,N('My Loans'!E8)) | AA42: =MIN(Q42,N('My Loans'!E9)) | AB42: =MIN(R42,N('My Loans'!E10)) | AC42: =MIN(S42,N('My Loans'!E11)) | AD42: =MIN(T42,N('My Loans'!E12)) | AE42: =MIN(U42,N('My Loans'!E13)) | AF42: =MIN(V42,N('My Loans'!E14)) | AG42: =MIN(W42,N('My Loans'!E15)) | AH42: =MIN(N42-X42,MAX(0,$C42-SUMPRODUCT(($D$3:$M$3<D$3)*($N42:$W42-$X42:$AG42)))) | AI42: =MIN(O42-Y42,MAX(0,$C42-SUMPRODUCT(($D$3:$M$3<E$3)*($N42:$W42-$X42:$AG42)))) | AJ42: =MIN(P42-Z42,MAX(0,$C42-SUMPRODUCT(($D$3:$M$3<F$3)*($N42:$W42-$X42:$AG42)))) | AK42: =MIN(Q42-AA42,MAX(0,$C42-SUMPRODUCT(($D$3:$M$3<G$3)*($N42:$W42-$X42:$AG42)))) | AL42: =MIN(R42-AB42,MAX(0,$C42-SUMPRODUCT(($D$3:$M$3<H$3)*($N42:$W42-$X42:$AG42)))) | AM42: =MIN(S42-AC42,MAX(0,$C42-SUMPRODUCT(($D$3:$M$3<I$3)*($N42:$W42-$X42:$AG42)))) | AN42: =MIN(T42-AD42,MAX(0,$C42-SUMPRODUCT(($D$3:$M$3<J$3)*($N42:$W42-$X42:$AG42)))) | AO42: =MIN(U42-AE42,MAX(0,$C42-SUMPRODUCT(($D$3:$M$3<K$3)*($N42:$W42-$X42:$AG42)))) | ... AQ42: =MIN(W42-AG42,MAX(0,$C42-SUMPRODUCT(($D$3:$M$3<M$3)*($N42:$W42-$X42:$AG42)))) | AR42: =ROUND(N42-X42-AH42,2) | AS42: =ROUND(O42-Y42-AI42,2) | AT42: =ROUND(P42-Z42-AJ42,2) | AU42: =ROUND(Q42-AA42-AK42,2) | AV42: =ROUND(R42-AB42-AL42,2) | AW42: =ROUND(S42-AC42-AM42,2) | AX42: =ROUND(T42-AD42-AN42,2) | AY42: =ROUND(U42-AE42-AO42,2) | ... BA42: =ROUND(W42-AG42-AQ42,2) | BB42: =SUM(AR42:BA42)
A43: 39 | B43: =EOMONTH(TODAY(),38) | C43: =MAX(0,(SUM('My Loans'!$E$6:$E$15)+'My Loans'!$D$3)-SUM($X43:$AG43)) | D43: =MAX(0,AR42) | E43: =MAX(0,AS42) | F43: =MAX(0,AT42) | G43: =MAX(0,AU42) | H43: =MAX(0,AV42) | I43: =MAX(0,AW42) | J43: =MAX(0,AX42) | K43: =MAX(0,AY42) | ... M43: =MAX(0,BA42) | N43: =IF(D43<0.5,0,D43*(1+N('My Loans'!D6)/1200)) | O43: =IF(E43<0.5,0,E43*(1+N('My Loans'!D7)/1200)) | P43: =IF(F43<0.5,0,F43*(1+N('My Loans'!D8)/1200)) | Q43: =IF(G43<0.5,0,G43*(1+N('My Loans'!D9)/1200)) | R43: =IF(H43<0.5,0,H43*(1+N('My Loans'!D10)/1200)) | S43: =IF(I43<0.5,0,I43*(1+N('My Loans'!D11)/1200)) | T43: =IF(J43<0.5,0,J43*(1+N('My Loans'!D12)/1200)) | U43: =IF(K43<0.5,0,K43*(1+N('My Loans'!D13)/1200)) | V43: =IF(L43<0.5,0,L43*(1+N('My Loans'!D14)/1200)) | W43: =IF(M43<0.5,0,M43*(1+N('My Loans'!D15)/1200)) | X43: =MIN(N43,N('My Loans'!E6)) | Y43: =MIN(O43,N('My Loans'!E7)) | Z43: =MIN(P43,N('My Loans'!E8)) | AA43: =MIN(Q43,N('My Loans'!E9)) | AB43: =MIN(R43,N('My Loans'!E10)) | AC43: =MIN(S43,N('My Loans'!E11)) | AD43: =MIN(T43,N('My Loans'!E12)) | AE43: =MIN(U43,N('My Loans'!E13)) | AF43: =MIN(V43,N('My Loans'!E14)) | AG43: =MIN(W43,N('My Loans'!E15)) | AH43: =MIN(N43-X43,MAX(0,$C43-SUMPRODUCT(($D$3:$M$3<D$3)*($N43:$W43-$X43:$AG43)))) | AI43: =MIN(O43-Y43,MAX(0,$C43-SUMPRODUCT(($D$3:$M$3<E$3)*($N43:$W43-$X43:$AG43)))) | AJ43: =MIN(P43-Z43,MAX(0,$C43-SUMPRODUCT(($D$3:$M$3<F$3)*($N43:$W43-$X43:$AG43)))) | AK43: =MIN(Q43-AA43,MAX(0,$C43-SUMPRODUCT(($D$3:$M$3<G$3)*($N43:$W43-$X43:$AG43)))) | AL43: =MIN(R43-AB43,MAX(0,$C43-SUMPRODUCT(($D$3:$M$3<H$3)*($N43:$W43-$X43:$AG43)))) | AM43: =MIN(S43-AC43,MAX(0,$C43-SUMPRODUCT(($D$3:$M$3<I$3)*($N43:$W43-$X43:$AG43)))) | AN43: =MIN(T43-AD43,MAX(0,$C43-SUMPRODUCT(($D$3:$M$3<J$3)*($N43:$W43-$X43:$AG43)))) | AO43: =MIN(U43-AE43,MAX(0,$C43-SUMPRODUCT(($D$3:$M$3<K$3)*($N43:$W43-$X43:$AG43)))) | ... AQ43: =MIN(W43-AG43,MAX(0,$C43-SUMPRODUCT(($D$3:$M$3<M$3)*($N43:$W43-$X43:$AG43)))) | AR43: =ROUND(N43-X43-AH43,2) | AS43: =ROUND(O43-Y43-AI43,2) | AT43: =ROUND(P43-Z43-AJ43,2) | AU43: =ROUND(Q43-AA43-AK43,2) | AV43: =ROUND(R43-AB43-AL43,2) | AW43: =ROUND(S43-AC43-AM43,2) | AX43: =ROUND(T43-AD43-AN43,2) | AY43: =ROUND(U43-AE43-AO43,2) | ... BA43: =ROUND(W43-AG43-AQ43,2) | BB43: =SUM(AR43:BA43)
A44: 40 | B44: =EOMONTH(TODAY(),39) | C44: =MAX(0,(SUM('My Loans'!$E$6:$E$15)+'My Loans'!$D$3)-SUM($X44:$AG44)) | D44: =MAX(0,AR43) | E44: =MAX(0,AS43) | F44: =MAX(0,AT43) | G44: =MAX(0,AU43) | H44: =MAX(0,AV43) | I44: =MAX(0,AW43) | J44: =MAX(0,AX43) | K44: =MAX(0,AY43) | ... M44: =MAX(0,BA43) | N44: =IF(D44<0.5,0,D44*(1+N('My Loans'!D6)/1200)) | O44: =IF(E44<0.5,0,E44*(1+N('My Loans'!D7)/1200)) | P44: =IF(F44<0.5,0,F44*(1+N('My Loans'!D8)/1200)) | Q44: =IF(G44<0.5,0,G44*(1+N('My Loans'!D9)/1200)) | R44: =IF(H44<0.5,0,H44*(1+N('My Loans'!D10)/1200)) | S44: =IF(I44<0.5,0,I44*(1+N('My Loans'!D11)/1200)) | T44: =IF(J44<0.5,0,J44*(1+N('My Loans'!D12)/1200)) | U44: =IF(K44<0.5,0,K44*(1+N('My Loans'!D13)/1200)) | V44: =IF(L44<0.5,0,L44*(1+N('My Loans'!D14)/1200)) | W44: =IF(M44<0.5,0,M44*(1+N('My Loans'!D15)/1200)) | X44: =MIN(N44,N('My Loans'!E6)) | Y44: =MIN(O44,N('My Loans'!E7)) | Z44: =MIN(P44,N('My Loans'!E8)) | AA44: =MIN(Q44,N('My Loans'!E9)) | AB44: =MIN(R44,N('My Loans'!E10)) | AC44: =MIN(S44,N('My Loans'!E11)) | AD44: =MIN(T44,N('My Loans'!E12)) | AE44: =MIN(U44,N('My Loans'!E13)) | AF44: =MIN(V44,N('My Loans'!E14)) | AG44: =MIN(W44,N('My Loans'!E15)) | AH44: =MIN(N44-X44,MAX(0,$C44-SUMPRODUCT(($D$3:$M$3<D$3)*($N44:$W44-$X44:$AG44)))) | AI44: =MIN(O44-Y44,MAX(0,$C44-SUMPRODUCT(($D$3:$M$3<E$3)*($N44:$W44-$X44:$AG44)))) | AJ44: =MIN(P44-Z44,MAX(0,$C44-SUMPRODUCT(($D$3:$M$3<F$3)*($N44:$W44-$X44:$AG44)))) | AK44: =MIN(Q44-AA44,MAX(0,$C44-SUMPRODUCT(($D$3:$M$3<G$3)*($N44:$W44-$X44:$AG44)))) | AL44: =MIN(R44-AB44,MAX(0,$C44-SUMPRODUCT(($D$3:$M$3<H$3)*($N44:$W44-$X44:$AG44)))) | AM44: =MIN(S44-AC44,MAX(0,$C44-SUMPRODUCT(($D$3:$M$3<I$3)*($N44:$W44-$X44:$AG44)))) | AN44: =MIN(T44-AD44,MAX(0,$C44-SUMPRODUCT(($D$3:$M$3<J$3)*($N44:$W44-$X44:$AG44)))) | AO44: =MIN(U44-AE44,MAX(0,$C44-SUMPRODUCT(($D$3:$M$3<K$3)*($N44:$W44-$X44:$AG44)))) | ... AQ44: =MIN(W44-AG44,MAX(0,$C44-SUMPRODUCT(($D$3:$M$3<M$3)*($N44:$W44-$X44:$AG44)))) | AR44: =ROUND(N44-X44-AH44,2) | AS44: =ROUND(O44-Y44-AI44,2) | AT44: =ROUND(P44-Z44-AJ44,2) | AU44: =ROUND(Q44-AA44-AK44,2) | AV44: =ROUND(R44-AB44-AL44,2) | AW44: =ROUND(S44-AC44-AM44,2) | AX44: =ROUND(T44-AD44-AN44,2) | AY44: =ROUND(U44-AE44-AO44,2) | ... BA44: =ROUND(W44-AG44-AQ44,2) | BB44: =SUM(AR44:BA44)
A45: 41 | B45: =EOMONTH(TODAY(),40) | C45: =MAX(0,(SUM('My Loans'!$E$6:$E$15)+'My Loans'!$D$3)-SUM($X45:$AG45)) | D45: =MAX(0,AR44) | E45: =MAX(0,AS44) | F45: =MAX(0,AT44) | G45: =MAX(0,AU44) | H45: =MAX(0,AV44) | I45: =MAX(0,AW44) | J45: =MAX(0,AX44) | K45: =MAX(0,AY44) | ... M45: =MAX(0,BA44) | N45: =IF(D45<0.5,0,D45*(1+N('My Loans'!D6)/1200)) | O45: =IF(E45<0.5,0,E45*(1+N('My Loans'!D7)/1200)) | P45: =IF(F45<0.5,0,F45*(1+N('My Loans'!D8)/1200)) | Q45: =IF(G45<0.5,0,G45*(1+N('My Loans'!D9)/1200)) | R45: =IF(H45<0.5,0,H45*(1+N('My Loans'!D10)/1200)) | S45: =IF(I45<0.5,0,I45*(1+N('My Loans'!D11)/1200)) | T45: =IF(J45<0.5,0,J45*(1+N('My Loans'!D12)/1200)) | U45: =IF(K45<0.5,0,K45*(1+N('My Loans'!D13)/1200)) | V45: =IF(L45<0.5,0,L45*(1+N('My Loans'!D14)/1200)) | W45: =IF(M45<0.5,0,M45*(1+N('My Loans'!D15)/1200)) | X45: =MIN(N45,N('My Loans'!E6)) | Y45: =MIN(O45,N('My Loans'!E7)) | Z45: =MIN(P45,N('My Loans'!E8)) | AA45: =MIN(Q45,N('My Loans'!E9)) | AB45: =MIN(R45,N('My Loans'!E10)) | AC45: =MIN(S45,N('My Loans'!E11)) | AD45: =MIN(T45,N('My Loans'!E12)) | AE45: =MIN(U45,N('My Loans'!E13)) | AF45: =MIN(V45,N('My Loans'!E14)) | AG45: =MIN(W45,N('My Loans'!E15)) | AH45: =MIN(N45-X45,MAX(0,$C45-SUMPRODUCT(($D$3:$M$3<D$3)*($N45:$W45-$X45:$AG45)))) | AI45: =MIN(O45-Y45,MAX(0,$C45-SUMPRODUCT(($D$3:$M$3<E$3)*($N45:$W45-$X45:$AG45)))) | AJ45: =MIN(P45-Z45,MAX(0,$C45-SUMPRODUCT(($D$3:$M$3<F$3)*($N45:$W45-$X45:$AG45)))) | AK45: =MIN(Q45-AA45,MAX(0,$C45-SUMPRODUCT(($D$3:$M$3<G$3)*($N45:$W45-$X45:$AG45)))) | AL45: =MIN(R45-AB45,MAX(0,$C45-SUMPRODUCT(($D$3:$M$3<H$3)*($N45:$W45-$X45:$AG45)))) | AM45: =MIN(S45-AC45,MAX(0,$C45-SUMPRODUCT(($D$3:$M$3<I$3)*($N45:$W45-$X45:$AG45)))) | AN45: =MIN(T45-AD45,MAX(0,$C45-SUMPRODUCT(($D$3:$M$3<J$3)*($N45:$W45-$X45:$AG45)))) | AO45: =MIN(U45-AE45,MAX(0,$C45-SUMPRODUCT(($D$3:$M$3<K$3)*($N45:$W45-$X45:$AG45)))) | ... AQ45: =MIN(W45-AG45,MAX(0,$C45-SUMPRODUCT(($D$3:$M$3<M$3)*($N45:$W45-$X45:$AG45)))) | AR45: =ROUND(N45-X45-AH45,2) | AS45: =ROUND(O45-Y45-AI45,2) | AT45: =ROUND(P45-Z45-AJ45,2) | AU45: =ROUND(Q45-AA45-AK45,2) | AV45: =ROUND(R45-AB45-AL45,2) | AW45: =ROUND(S45-AC45-AM45,2) | AX45: =ROUND(T45-AD45-AN45,2) | AY45: =ROUND(U45-AE45-AO45,2) | ... BA45: =ROUND(W45-AG45-AQ45,2) | BB45: =SUM(AR45:BA45)
A46: 42 | B46: =EOMONTH(TODAY(),41) | C46: =MAX(0,(SUM('My Loans'!$E$6:$E$15)+'My Loans'!$D$3)-SUM($X46:$AG46)) | D46: =MAX(0,AR45) | E46: =MAX(0,AS45) | F46: =MAX(0,AT45) | G46: =MAX(0,AU45) | H46: =MAX(0,AV45) | I46: =MAX(0,AW45) | J46: =MAX(0,AX45) | K46: =MAX(0,AY45) | ... M46: =MAX(0,BA45) | N46: =IF(D46<0.5,0,D46*(1+N('My Loans'!D6)/1200)) | O46: =IF(E46<0.5,0,E46*(1+N('My Loans'!D7)/1200)) | P46: =IF(F46<0.5,0,F46*(1+N('My Loans'!D8)/1200)) | Q46: =IF(G46<0.5,0,G46*(1+N('My Loans'!D9)/1200)) | R46: =IF(H46<0.5,0,H46*(1+N('My Loans'!D10)/1200)) | S46: =IF(I46<0.5,0,I46*(1+N('My Loans'!D11)/1200)) | T46: =IF(J46<0.5,0,J46*(1+N('My Loans'!D12)/1200)) | U46: =IF(K46<0.5,0,K46*(1+N('My Loans'!D13)/1200)) | V46: =IF(L46<0.5,0,L46*(1+N('My Loans'!D14)/1200)) | W46: =IF(M46<0.5,0,M46*(1+N('My Loans'!D15)/1200)) | X46: =MIN(N46,N('My Loans'!E6)) | Y46: =MIN(O46,N('My Loans'!E7)) | Z46: =MIN(P46,N('My Loans'!E8)) | AA46: =MIN(Q46,N('My Loans'!E9)) | AB46: =MIN(R46,N('My Loans'!E10)) | AC46: =MIN(S46,N('My Loans'!E11)) | AD46: =MIN(T46,N('My Loans'!E12)) | AE46: =MIN(U46,N('My Loans'!E13)) | AF46: =MIN(V46,N('My Loans'!E14)) | AG46: =MIN(W46,N('My Loans'!E15)) | AH46: =MIN(N46-X46,MAX(0,$C46-SUMPRODUCT(($D$3:$M$3<D$3)*($N46:$W46-$X46:$AG46)))) | AI46: =MIN(O46-Y46,MAX(0,$C46-SUMPRODUCT(($D$3:$M$3<E$3)*($N46:$W46-$X46:$AG46)))) | AJ46: =MIN(P46-Z46,MAX(0,$C46-SUMPRODUCT(($D$3:$M$3<F$3)*($N46:$W46-$X46:$AG46)))) | AK46: =MIN(Q46-AA46,MAX(0,$C46-SUMPRODUCT(($D$3:$M$3<G$3)*($N46:$W46-$X46:$AG46)))) | AL46: =MIN(R46-AB46,MAX(0,$C46-SUMPRODUCT(($D$3:$M$3<H$3)*($N46:$W46-$X46:$AG46)))) | AM46: =MIN(S46-AC46,MAX(0,$C46-SUMPRODUCT(($D$3:$M$3<I$3)*($N46:$W46-$X46:$AG46)))) | AN46: =MIN(T46-AD46,MAX(0,$C46-SUMPRODUCT(($D$3:$M$3<J$3)*($N46:$W46-$X46:$AG46)))) | AO46: =MIN(U46-AE46,MAX(0,$C46-SUMPRODUCT(($D$3:$M$3<K$3)*($N46:$W46-$X46:$AG46)))) | ... AQ46: =MIN(W46-AG46,MAX(0,$C46-SUMPRODUCT(($D$3:$M$3<M$3)*($N46:$W46-$X46:$AG46)))) | AR46: =ROUND(N46-X46-AH46,2) | AS46: =ROUND(O46-Y46-AI46,2) | AT46: =ROUND(P46-Z46-AJ46,2) | AU46: =ROUND(Q46-AA46-AK46,2) | AV46: =ROUND(R46-AB46-AL46,2) | AW46: =ROUND(S46-AC46-AM46,2) | AX46: =ROUND(T46-AD46-AN46,2) | AY46: =ROUND(U46-AE46-AO46,2) | ... BA46: =ROUND(W46-AG46-AQ46,2) | BB46: =SUM(AR46:BA46)
A47: 43 | B47: =EOMONTH(TODAY(),42) | C47: =MAX(0,(SUM('My Loans'!$E$6:$E$15)+'My Loans'!$D$3)-SUM($X47:$AG47)) | D47: =MAX(0,AR46) | E47: =MAX(0,AS46) | F47: =MAX(0,AT46) | G47: =MAX(0,AU46) | H47: =MAX(0,AV46) | I47: =MAX(0,AW46) | J47: =MAX(0,AX46) | K47: =MAX(0,AY46) | ... M47: =MAX(0,BA46) | N47: =IF(D47<0.5,0,D47*(1+N('My Loans'!D6)/1200)) | O47: =IF(E47<0.5,0,E47*(1+N('My Loans'!D7)/1200)) | P47: =IF(F47<0.5,0,F47*(1+N('My Loans'!D8)/1200)) | Q47: =IF(G47<0.5,0,G47*(1+N('My Loans'!D9)/1200)) | R47: =IF(H47<0.5,0,H47*(1+N('My Loans'!D10)/1200)) | S47: =IF(I47<0.5,0,I47*(1+N('My Loans'!D11)/1200)) | T47: =IF(J47<0.5,0,J47*(1+N('My Loans'!D12)/1200)) | U47: =IF(K47<0.5,0,K47*(1+N('My Loans'!D13)/1200)) | V47: =IF(L47<0.5,0,L47*(1+N('My Loans'!D14)/1200)) | W47: =IF(M47<0.5,0,M47*(1+N('My Loans'!D15)/1200)) | X47: =MIN(N47,N('My Loans'!E6)) | Y47: =MIN(O47,N('My Loans'!E7)) | Z47: =MIN(P47,N('My Loans'!E8)) | AA47: =MIN(Q47,N('My Loans'!E9)) | AB47: =MIN(R47,N('My Loans'!E10)) | AC47: =MIN(S47,N('My Loans'!E11)) | AD47: =MIN(T47,N('My Loans'!E12)) | AE47: =MIN(U47,N('My Loans'!E13)) | AF47: =MIN(V47,N('My Loans'!E14)) | AG47: =MIN(W47,N('My Loans'!E15)) | AH47: =MIN(N47-X47,MAX(0,$C47-SUMPRODUCT(($D$3:$M$3<D$3)*($N47:$W47-$X47:$AG47)))) | AI47: =MIN(O47-Y47,MAX(0,$C47-SUMPRODUCT(($D$3:$M$3<E$3)*($N47:$W47-$X47:$AG47)))) | AJ47: =MIN(P47-Z47,MAX(0,$C47-SUMPRODUCT(($D$3:$M$3<F$3)*($N47:$W47-$X47:$AG47)))) | AK47: =MIN(Q47-AA47,MAX(0,$C47-SUMPRODUCT(($D$3:$M$3<G$3)*($N47:$W47-$X47:$AG47)))) | AL47: =MIN(R47-AB47,MAX(0,$C47-SUMPRODUCT(($D$3:$M$3<H$3)*($N47:$W47-$X47:$AG47)))) | AM47: =MIN(S47-AC47,MAX(0,$C47-SUMPRODUCT(($D$3:$M$3<I$3)*($N47:$W47-$X47:$AG47)))) | AN47: =MIN(T47-AD47,MAX(0,$C47-SUMPRODUCT(($D$3:$M$3<J$3)*($N47:$W47-$X47:$AG47)))) | AO47: =MIN(U47-AE47,MAX(0,$C47-SUMPRODUCT(($D$3:$M$3<K$3)*($N47:$W47-$X47:$AG47)))) | ... AQ47: =MIN(W47-AG47,MAX(0,$C47-SUMPRODUCT(($D$3:$M$3<M$3)*($N47:$W47-$X47:$AG47)))) | AR47: =ROUND(N47-X47-AH47,2) | AS47: =ROUND(O47-Y47-AI47,2) | AT47: =ROUND(P47-Z47-AJ47,2) | AU47: =ROUND(Q47-AA47-AK47,2) | AV47: =ROUND(R47-AB47-AL47,2) | AW47: =ROUND(S47-AC47-AM47,2) | AX47: =ROUND(T47-AD47-AN47,2) | AY47: =ROUND(U47-AE47-AO47,2) | ... BA47: =ROUND(W47-AG47-AQ47,2) | BB47: =SUM(AR47:BA47)
A48: 44 | B48: =EOMONTH(TODAY(),43) | C48: =MAX(0,(SUM('My Loans'!$E$6:$E$15)+'My Loans'!$D$3)-SUM($X48:$AG48)) | D48: =MAX(0,AR47) | E48: =MAX(0,AS47) | F48: =MAX(0,AT47) | G48: =MAX(0,AU47) | H48: =MAX(0,AV47) | I48: =MAX(0,AW47) | J48: =MAX(0,AX47) | K48: =MAX(0,AY47) | ... M48: =MAX(0,BA47) | N48: =IF(D48<0.5,0,D48*(1+N('My Loans'!D6)/1200)) | O48: =IF(E48<0.5,0,E48*(1+N('My Loans'!D7)/1200)) | P48: =IF(F48<0.5,0,F48*(1+N('My Loans'!D8)/1200)) | Q48: =IF(G48<0.5,0,G48*(1+N('My Loans'!D9)/1200)) | R48: =IF(H48<0.5,0,H48*(1+N('My Loans'!D10)/1200)) | S48: =IF(I48<0.5,0,I48*(1+N('My Loans'!D11)/1200)) | T48: =IF(J48<0.5,0,J48*(1+N('My Loans'!D12)/1200)) | U48: =IF(K48<0.5,0,K48*(1+N('My Loans'!D13)/1200)) | V48: =IF(L48<0.5,0,L48*(1+N('My Loans'!D14)/1200)) | W48: =IF(M48<0.5,0,M48*(1+N('My Loans'!D15)/1200)) | X48: =MIN(N48,N('My Loans'!E6)) | Y48: =MIN(O48,N('My Loans'!E7)) | Z48: =MIN(P48,N('My Loans'!E8)) | AA48: =MIN(Q48,N('My Loans'!E9)) | AB48: =MIN(R48,N('My Loans'!E10)) | AC48: =MIN(S48,N('My Loans'!E11)) | AD48: =MIN(T48,N('My Loans'!E12)) | AE48: =MIN(U48,N('My Loans'!E13)) | AF48: =MIN(V48,N('My Loans'!E14)) | AG48: =MIN(W48,N('My Loans'!E15)) | AH48: =MIN(N48-X48,MAX(0,$C48-SUMPRODUCT(($D$3:$M$3<D$3)*($N48:$W48-$X48:$AG48)))) | AI48: =MIN(O48-Y48,MAX(0,$C48-SUMPRODUCT(($D$3:$M$3<E$3)*($N48:$W48-$X48:$AG48)))) | AJ48: =MIN(P48-Z48,MAX(0,$C48-SUMPRODUCT(($D$3:$M$3<F$3)*($N48:$W48-$X48:$AG48)))) | AK48: =MIN(Q48-AA48,MAX(0,$C48-SUMPRODUCT(($D$3:$M$3<G$3)*($N48:$W48-$X48:$AG48)))) | AL48: =MIN(R48-AB48,MAX(0,$C48-SUMPRODUCT(($D$3:$M$3<H$3)*($N48:$W48-$X48:$AG48)))) | AM48: =MIN(S48-AC48,MAX(0,$C48-SUMPRODUCT(($D$3:$M$3<I$3)*($N48:$W48-$X48:$AG48)))) | AN48: =MIN(T48-AD48,MAX(0,$C48-SUMPRODUCT(($D$3:$M$3<J$3)*($N48:$W48-$X48:$AG48)))) | AO48: =MIN(U48-AE48,MAX(0,$C48-SUMPRODUCT(($D$3:$M$3<K$3)*($N48:$W48-$X48:$AG48)))) | ... AQ48: =MIN(W48-AG48,MAX(0,$C48-SUMPRODUCT(($D$3:$M$3<M$3)*($N48:$W48-$X48:$AG48)))) | AR48: =ROUND(N48-X48-AH48,2) | AS48: =ROUND(O48-Y48-AI48,2) | AT48: =ROUND(P48-Z48-AJ48,2) | AU48: =ROUND(Q48-AA48-AK48,2) | AV48: =ROUND(R48-AB48-AL48,2) | AW48: =ROUND(S48-AC48-AM48,2) | AX48: =ROUND(T48-AD48-AN48,2) | AY48: =ROUND(U48-AE48-AO48,2) | ... BA48: =ROUND(W48-AG48-AQ48,2) | BB48: =SUM(AR48:BA48)
A49: 45 | B49: =EOMONTH(TODAY(),44) | C49: =MAX(0,(SUM('My Loans'!$E$6:$E$15)+'My Loans'!$D$3)-SUM($X49:$AG49)) | D49: =MAX(0,AR48) | E49: =MAX(0,AS48) | F49: =MAX(0,AT48) | G49: =MAX(0,AU48) | H49: =MAX(0,AV48) | I49: =MAX(0,AW48) | J49: =MAX(0,AX48) | K49: =MAX(0,AY48) | ... M49: =MAX(0,BA48) | N49: =IF(D49<0.5,0,D49*(1+N('My Loans'!D6)/1200)) | O49: =IF(E49<0.5,0,E49*(1+N('My Loans'!D7)/1200)) | P49: =IF(F49<0.5,0,F49*(1+N('My Loans'!D8)/1200)) | Q49: =IF(G49<0.5,0,G49*(1+N('My Loans'!D9)/1200)) | R49: =IF(H49<0.5,0,H49*(1+N('My Loans'!D10)/1200)) | S49: =IF(I49<0.5,0,I49*(1+N('My Loans'!D11)/1200)) | T49: =IF(J49<0.5,0,J49*(1+N('My Loans'!D12)/1200)) | U49: =IF(K49<0.5,0,K49*(1+N('My Loans'!D13)/1200)) | V49: =IF(L49<0.5,0,L49*(1+N('My Loans'!D14)/1200)) | W49: =IF(M49<0.5,0,M49*(1+N('My Loans'!D15)/1200)) | X49: =MIN(N49,N('My Loans'!E6)) | Y49: =MIN(O49,N('My Loans'!E7)) | Z49: =MIN(P49,N('My Loans'!E8)) | AA49: =MIN(Q49,N('My Loans'!E9)) | AB49: =MIN(R49,N('My Loans'!E10)) | AC49: =MIN(S49,N('My Loans'!E11)) | AD49: =MIN(T49,N('My Loans'!E12)) | AE49: =MIN(U49,N('My Loans'!E13)) | AF49: =MIN(V49,N('My Loans'!E14)) | AG49: =MIN(W49,N('My Loans'!E15)) | AH49: =MIN(N49-X49,MAX(0,$C49-SUMPRODUCT(($D$3:$M$3<D$3)*($N49:$W49-$X49:$AG49)))) | AI49: =MIN(O49-Y49,MAX(0,$C49-SUMPRODUCT(($D$3:$M$3<E$3)*($N49:$W49-$X49:$AG49)))) | AJ49: =MIN(P49-Z49,MAX(0,$C49-SUMPRODUCT(($D$3:$M$3<F$3)*($N49:$W49-$X49:$AG49)))) | AK49: =MIN(Q49-AA49,MAX(0,$C49-SUMPRODUCT(($D$3:$M$3<G$3)*($N49:$W49-$X49:$AG49)))) | AL49: =MIN(R49-AB49,MAX(0,$C49-SUMPRODUCT(($D$3:$M$3<H$3)*($N49:$W49-$X49:$AG49)))) | AM49: =MIN(S49-AC49,MAX(0,$C49-SUMPRODUCT(($D$3:$M$3<I$3)*($N49:$W49-$X49:$AG49)))) | AN49: =MIN(T49-AD49,MAX(0,$C49-SUMPRODUCT(($D$3:$M$3<J$3)*($N49:$W49-$X49:$AG49)))) | AO49: =MIN(U49-AE49,MAX(0,$C49-SUMPRODUCT(($D$3:$M$3<K$3)*($N49:$W49-$X49:$AG49)))) | ... AQ49: =MIN(W49-AG49,MAX(0,$C49-SUMPRODUCT(($D$3:$M$3<M$3)*($N49:$W49-$X49:$AG49)))) | AR49: =ROUND(N49-X49-AH49,2) | AS49: =ROUND(O49-Y49-AI49,2) | AT49: =ROUND(P49-Z49-AJ49,2) | AU49: =ROUND(Q49-AA49-AK49,2) | AV49: =ROUND(R49-AB49-AL49,2) | AW49: =ROUND(S49-AC49-AM49,2) | AX49: =ROUND(T49-AD49-AN49,2) | AY49: =ROUND(U49-AE49-AO49,2) | ... BA49: =ROUND(W49-AG49-AQ49,2) | BB49: =SUM(AR49:BA49)
A50: 46 | B50: =EOMONTH(TODAY(),45) | C50: =MAX(0,(SUM('My Loans'!$E$6:$E$15)+'My Loans'!$D$3)-SUM($X50:$AG50)) | D50: =MAX(0,AR49) | E50: =MAX(0,AS49) | F50: =MAX(0,AT49) | G50: =MAX(0,AU49) | H50: =MAX(0,AV49) | I50: =MAX(0,AW49) | J50: =MAX(0,AX49) | K50: =MAX(0,AY49) | ... M50: =MAX(0,BA49) | N50: =IF(D50<0.5,0,D50*(1+N('My Loans'!D6)/1200)) | O50: =IF(E50<0.5,0,E50*(1+N('My Loans'!D7)/1200)) | P50: =IF(F50<0.5,0,F50*(1+N('My Loans'!D8)/1200)) | Q50: =IF(G50<0.5,0,G50*(1+N('My Loans'!D9)/1200)) | R50: =IF(H50<0.5,0,H50*(1+N('My Loans'!D10)/1200)) | S50: =IF(I50<0.5,0,I50*(1+N('My Loans'!D11)/1200)) | T50: =IF(J50<0.5,0,J50*(1+N('My Loans'!D12)/1200)) | U50: =IF(K50<0.5,0,K50*(1+N('My Loans'!D13)/1200)) | V50: =IF(L50<0.5,0,L50*(1+N('My Loans'!D14)/1200)) | W50: =IF(M50<0.5,0,M50*(1+N('My Loans'!D15)/1200)) | X50: =MIN(N50,N('My Loans'!E6)) | Y50: =MIN(O50,N('My Loans'!E7)) | Z50: =MIN(P50,N('My Loans'!E8)) | AA50: =MIN(Q50,N('My Loans'!E9)) | AB50: =MIN(R50,N('My Loans'!E10)) | AC50: =MIN(S50,N('My Loans'!E11)) | AD50: =MIN(T50,N('My Loans'!E12)) | AE50: =MIN(U50,N('My Loans'!E13)) | AF50: =MIN(V50,N('My Loans'!E14)) | AG50: =MIN(W50,N('My Loans'!E15)) | AH50: =MIN(N50-X50,MAX(0,$C50-SUMPRODUCT(($D$3:$M$3<D$3)*($N50:$W50-$X50:$AG50)))) | AI50: =MIN(O50-Y50,MAX(0,$C50-SUMPRODUCT(($D$3:$M$3<E$3)*($N50:$W50-$X50:$AG50)))) | AJ50: =MIN(P50-Z50,MAX(0,$C50-SUMPRODUCT(($D$3:$M$3<F$3)*($N50:$W50-$X50:$AG50)))) | AK50: =MIN(Q50-AA50,MAX(0,$C50-SUMPRODUCT(($D$3:$M$3<G$3)*($N50:$W50-$X50:$AG50)))) | AL50: =MIN(R50-AB50,MAX(0,$C50-SUMPRODUCT(($D$3:$M$3<H$3)*($N50:$W50-$X50:$AG50)))) | AM50: =MIN(S50-AC50,MAX(0,$C50-SUMPRODUCT(($D$3:$M$3<I$3)*($N50:$W50-$X50:$AG50)))) | AN50: =MIN(T50-AD50,MAX(0,$C50-SUMPRODUCT(($D$3:$M$3<J$3)*($N50:$W50-$X50:$AG50)))) | AO50: =MIN(U50-AE50,MAX(0,$C50-SUMPRODUCT(($D$3:$M$3<K$3)*($N50:$W50-$X50:$AG50)))) | ... AQ50: =MIN(W50-AG50,MAX(0,$C50-SUMPRODUCT(($D$3:$M$3<M$3)*($N50:$W50-$X50:$AG50)))) | AR50: =ROUND(N50-X50-AH50,2) | AS50: =ROUND(O50-Y50-AI50,2) | AT50: =ROUND(P50-Z50-AJ50,2) | AU50: =ROUND(Q50-AA50-AK50,2) | AV50: =ROUND(R50-AB50-AL50,2) | AW50: =ROUND(S50-AC50-AM50,2) | AX50: =ROUND(T50-AD50-AN50,2) | AY50: =ROUND(U50-AE50-AO50,2) | ... BA50: =ROUND(W50-AG50-AQ50,2) | BB50: =SUM(AR50:BA50)
A51: 47 | B51: =EOMONTH(TODAY(),46) | C51: =MAX(0,(SUM('My Loans'!$E$6:$E$15)+'My Loans'!$D$3)-SUM($X51:$AG51)) | D51: =MAX(0,AR50) | E51: =MAX(0,AS50) | F51: =MAX(0,AT50) | G51: =MAX(0,AU50) | H51: =MAX(0,AV50) | I51: =MAX(0,AW50) | J51: =MAX(0,AX50) | K51: =MAX(0,AY50) | ... M51: =MAX(0,BA50) | N51: =IF(D51<0.5,0,D51*(1+N('My Loans'!D6)/1200)) | O51: =IF(E51<0.5,0,E51*(1+N('My Loans'!D7)/1200)) | P51: =IF(F51<0.5,0,F51*(1+N('My Loans'!D8)/1200)) | Q51: =IF(G51<0.5,0,G51*(1+N('My Loans'!D9)/1200)) | R51: =IF(H51<0.5,0,H51*(1+N('My Loans'!D10)/1200)) | S51: =IF(I51<0.5,0,I51*(1+N('My Loans'!D11)/1200)) | T51: =IF(J51<0.5,0,J51*(1+N('My Loans'!D12)/1200)) | U51: =IF(K51<0.5,0,K51*(1+N('My Loans'!D13)/1200)) | V51: =IF(L51<0.5,0,L51*(1+N('My Loans'!D14)/1200)) | W51: =IF(M51<0.5,0,M51*(1+N('My Loans'!D15)/1200)) | X51: =MIN(N51,N('My Loans'!E6)) | Y51: =MIN(O51,N('My Loans'!E7)) | Z51: =MIN(P51,N('My Loans'!E8)) | AA51: =MIN(Q51,N('My Loans'!E9)) | AB51: =MIN(R51,N('My Loans'!E10)) | AC51: =MIN(S51,N('My Loans'!E11)) | AD51: =MIN(T51,N('My Loans'!E12)) | AE51: =MIN(U51,N('My Loans'!E13)) | AF51: =MIN(V51,N('My Loans'!E14)) | AG51: =MIN(W51,N('My Loans'!E15)) | AH51: =MIN(N51-X51,MAX(0,$C51-SUMPRODUCT(($D$3:$M$3<D$3)*($N51:$W51-$X51:$AG51)))) | AI51: =MIN(O51-Y51,MAX(0,$C51-SUMPRODUCT(($D$3:$M$3<E$3)*($N51:$W51-$X51:$AG51)))) | AJ51: =MIN(P51-Z51,MAX(0,$C51-SUMPRODUCT(($D$3:$M$3<F$3)*($N51:$W51-$X51:$AG51)))) | AK51: =MIN(Q51-AA51,MAX(0,$C51-SUMPRODUCT(($D$3:$M$3<G$3)*($N51:$W51-$X51:$AG51)))) | AL51: =MIN(R51-AB51,MAX(0,$C51-SUMPRODUCT(($D$3:$M$3<H$3)*($N51:$W51-$X51:$AG51)))) | AM51: =MIN(S51-AC51,MAX(0,$C51-SUMPRODUCT(($D$3:$M$3<I$3)*($N51:$W51-$X51:$AG51)))) | AN51: =MIN(T51-AD51,MAX(0,$C51-SUMPRODUCT(($D$3:$M$3<J$3)*($N51:$W51-$X51:$AG51)))) | AO51: =MIN(U51-AE51,MAX(0,$C51-SUMPRODUCT(($D$3:$M$3<K$3)*($N51:$W51-$X51:$AG51)))) | ... AQ51: =MIN(W51-AG51,MAX(0,$C51-SUMPRODUCT(($D$3:$M$3<M$3)*($N51:$W51-$X51:$AG51)))) | AR51: =ROUND(N51-X51-AH51,2) | AS51: =ROUND(O51-Y51-AI51,2) | AT51: =ROUND(P51-Z51-AJ51,2) | AU51: =ROUND(Q51-AA51-AK51,2) | AV51: =ROUND(R51-AB51-AL51,2) | AW51: =ROUND(S51-AC51-AM51,2) | AX51: =ROUND(T51-AD51-AN51,2) | AY51: =ROUND(U51-AE51-AO51,2) | ... BA51: =ROUND(W51-AG51-AQ51,2) | BB51: =SUM(AR51:BA51)
A52: 48 | B52: =EOMONTH(TODAY(),47) | C52: =MAX(0,(SUM('My Loans'!$E$6:$E$15)+'My Loans'!$D$3)-SUM($X52:$AG52)) | D52: =MAX(0,AR51) | E52: =MAX(0,AS51) | F52: =MAX(0,AT51) | G52: =MAX(0,AU51) | H52: =MAX(0,AV51) | I52: =MAX(0,AW51) | J52: =MAX(0,AX51) | K52: =MAX(0,AY51) | ... M52: =MAX(0,BA51) | N52: =IF(D52<0.5,0,D52*(1+N('My Loans'!D6)/1200)) | O52: =IF(E52<0.5,0,E52*(1+N('My Loans'!D7)/1200)) | P52: =IF(F52<0.5,0,F52*(1+N('My Loans'!D8)/1200)) | Q52: =IF(G52<0.5,0,G52*(1+N('My Loans'!D9)/1200)) | R52: =IF(H52<0.5,0,H52*(1+N('My Loans'!D10)/1200)) | S52: =IF(I52<0.5,0,I52*(1+N('My Loans'!D11)/1200)) | T52: =IF(J52<0.5,0,J52*(1+N('My Loans'!D12)/1200)) | U52: =IF(K52<0.5,0,K52*(1+N('My Loans'!D13)/1200)) | V52: =IF(L52<0.5,0,L52*(1+N('My Loans'!D14)/1200)) | W52: =IF(M52<0.5,0,M52*(1+N('My Loans'!D15)/1200)) | X52: =MIN(N52,N('My Loans'!E6)) | Y52: =MIN(O52,N('My Loans'!E7)) | Z52: =MIN(P52,N('My Loans'!E8)) | AA52: =MIN(Q52,N('My Loans'!E9)) | AB52: =MIN(R52,N('My Loans'!E10)) | AC52: =MIN(S52,N('My Loans'!E11)) | AD52: =MIN(T52,N('My Loans'!E12)) | AE52: =MIN(U52,N('My Loans'!E13)) | AF52: =MIN(V52,N('My Loans'!E14)) | AG52: =MIN(W52,N('My Loans'!E15)) | AH52: =MIN(N52-X52,MAX(0,$C52-SUMPRODUCT(($D$3:$M$3<D$3)*($N52:$W52-$X52:$AG52)))) | AI52: =MIN(O52-Y52,MAX(0,$C52-SUMPRODUCT(($D$3:$M$3<E$3)*($N52:$W52-$X52:$AG52)))) | AJ52: =MIN(P52-Z52,MAX(0,$C52-SUMPRODUCT(($D$3:$M$3<F$3)*($N52:$W52-$X52:$AG52)))) | AK52: =MIN(Q52-AA52,MAX(0,$C52-SUMPRODUCT(($D$3:$M$3<G$3)*($N52:$W52-$X52:$AG52)))) | AL52: =MIN(R52-AB52,MAX(0,$C52-SUMPRODUCT(($D$3:$M$3<H$3)*($N52:$W52-$X52:$AG52)))) | AM52: =MIN(S52-AC52,MAX(0,$C52-SUMPRODUCT(($D$3:$M$3<I$3)*($N52:$W52-$X52:$AG52)))) | AN52: =MIN(T52-AD52,MAX(0,$C52-SUMPRODUCT(($D$3:$M$3<J$3)*($N52:$W52-$X52:$AG52)))) | AO52: =MIN(U52-AE52,MAX(0,$C52-SUMPRODUCT(($D$3:$M$3<K$3)*($N52:$W52-$X52:$AG52)))) | ... AQ52: =MIN(W52-AG52,MAX(0,$C52-SUMPRODUCT(($D$3:$M$3<M$3)*($N52:$W52-$X52:$AG52)))) | AR52: =ROUND(N52-X52-AH52,2) | AS52: =ROUND(O52-Y52-AI52,2) | AT52: =ROUND(P52-Z52-AJ52,2) | AU52: =ROUND(Q52-AA52-AK52,2) | AV52: =ROUND(R52-AB52-AL52,2) | AW52: =ROUND(S52-AC52-AM52,2) | AX52: =ROUND(T52-AD52-AN52,2) | AY52: =ROUND(U52-AE52-AO52,2) | ... BA52: =ROUND(W52-AG52-AQ52,2) | BB52: =SUM(AR52:BA52)
A53: 49 | B53: =EOMONTH(TODAY(),48) | C53: =MAX(0,(SUM('My Loans'!$E$6:$E$15)+'My Loans'!$D$3)-SUM($X53:$AG53)) | D53: =MAX(0,AR52) | E53: =MAX(0,AS52) | F53: =MAX(0,AT52) | G53: =MAX(0,AU52) | H53: =MAX(0,AV52) | I53: =MAX(0,AW52) | J53: =MAX(0,AX52) | K53: =MAX(0,AY52) | ... M53: =MAX(0,BA52) | N53: =IF(D53<0.5,0,D53*(1+N('My Loans'!D6)/1200)) | O53: =IF(E53<0.5,0,E53*(1+N('My Loans'!D7)/1200)) | P53: =IF(F53<0.5,0,F53*(1+N('My Loans'!D8)/1200)) | Q53: =IF(G53<0.5,0,G53*(1+N('My Loans'!D9)/1200)) | R53: =IF(H53<0.5,0,H53*(1+N('My Loans'!D10)/1200)) | S53: =IF(I53<0.5,0,I53*(1+N('My Loans'!D11)/1200)) | T53: =IF(J53<0.5,0,J53*(1+N('My Loans'!D12)/1200)) | U53: =IF(K53<0.5,0,K53*(1+N('My Loans'!D13)/1200)) | V53: =IF(L53<0.5,0,L53*(1+N('My Loans'!D14)/1200)) | W53: =IF(M53<0.5,0,M53*(1+N('My Loans'!D15)/1200)) | X53: =MIN(N53,N('My Loans'!E6)) | Y53: =MIN(O53,N('My Loans'!E7)) | Z53: =MIN(P53,N('My Loans'!E8)) | AA53: =MIN(Q53,N('My Loans'!E9)) | AB53: =MIN(R53,N('My Loans'!E10)) | AC53: =MIN(S53,N('My Loans'!E11)) | AD53: =MIN(T53,N('My Loans'!E12)) | AE53: =MIN(U53,N('My Loans'!E13)) | AF53: =MIN(V53,N('My Loans'!E14)) | AG53: =MIN(W53,N('My Loans'!E15)) | AH53: =MIN(N53-X53,MAX(0,$C53-SUMPRODUCT(($D$3:$M$3<D$3)*($N53:$W53-$X53:$AG53)))) | AI53: =MIN(O53-Y53,MAX(0,$C53-SUMPRODUCT(($D$3:$M$3<E$3)*($N53:$W53-$X53:$AG53)))) | AJ53: =MIN(P53-Z53,MAX(0,$C53-SUMPRODUCT(($D$3:$M$3<F$3)*($N53:$W53-$X53:$AG53)))) | AK53: =MIN(Q53-AA53,MAX(0,$C53-SUMPRODUCT(($D$3:$M$3<G$3)*($N53:$W53-$X53:$AG53)))) | AL53: =MIN(R53-AB53,MAX(0,$C53-SUMPRODUCT(($D$3:$M$3<H$3)*($N53:$W53-$X53:$AG53)))) | AM53: =MIN(S53-AC53,MAX(0,$C53-SUMPRODUCT(($D$3:$M$3<I$3)*($N53:$W53-$X53:$AG53)))) | AN53: =MIN(T53-AD53,MAX(0,$C53-SUMPRODUCT(($D$3:$M$3<J$3)*($N53:$W53-$X53:$AG53)))) | AO53: =MIN(U53-AE53,MAX(0,$C53-SUMPRODUCT(($D$3:$M$3<K$3)*($N53:$W53-$X53:$AG53)))) | ... AQ53: =MIN(W53-AG53,MAX(0,$C53-SUMPRODUCT(($D$3:$M$3<M$3)*($N53:$W53-$X53:$AG53)))) | AR53: =ROUND(N53-X53-AH53,2) | AS53: =ROUND(O53-Y53-AI53,2) | AT53: =ROUND(P53-Z53-AJ53,2) | AU53: =ROUND(Q53-AA53-AK53,2) | AV53: =ROUND(R53-AB53-AL53,2) | AW53: =ROUND(S53-AC53-AM53,2) | AX53: =ROUND(T53-AD53-AN53,2) | AY53: =ROUND(U53-AE53-AO53,2) | ... BA53: =ROUND(W53-AG53-AQ53,2) | BB53: =SUM(AR53:BA53)
A54: 50 | B54: =EOMONTH(TODAY(),49) | C54: =MAX(0,(SUM('My Loans'!$E$6:$E$15)+'My Loans'!$D$3)-SUM($X54:$AG54)) | D54: =MAX(0,AR53) | E54: =MAX(0,AS53) | F54: =MAX(0,AT53) | G54: =MAX(0,AU53) | H54: =MAX(0,AV53) | I54: =MAX(0,AW53) | J54: =MAX(0,AX53) | K54: =MAX(0,AY53) | ... M54: =MAX(0,BA53) | N54: =IF(D54<0.5,0,D54*(1+N('My Loans'!D6)/1200)) | O54: =IF(E54<0.5,0,E54*(1+N('My Loans'!D7)/1200)) | P54: =IF(F54<0.5,0,F54*(1+N('My Loans'!D8)/1200)) | Q54: =IF(G54<0.5,0,G54*(1+N('My Loans'!D9)/1200)) | R54: =IF(H54<0.5,0,H54*(1+N('My Loans'!D10)/1200)) | S54: =IF(I54<0.5,0,I54*(1+N('My Loans'!D11)/1200)) | T54: =IF(J54<0.5,0,J54*(1+N('My Loans'!D12)/1200)) | U54: =IF(K54<0.5,0,K54*(1+N('My Loans'!D13)/1200)) | V54: =IF(L54<0.5,0,L54*(1+N('My Loans'!D14)/1200)) | W54: =IF(M54<0.5,0,M54*(1+N('My Loans'!D15)/1200)) | X54: =MIN(N54,N('My Loans'!E6)) | Y54: =MIN(O54,N('My Loans'!E7)) | Z54: =MIN(P54,N('My Loans'!E8)) | AA54: =MIN(Q54,N('My Loans'!E9)) | AB54: =MIN(R54,N('My Loans'!E10)) | AC54: =MIN(S54,N('My Loans'!E11)) | AD54: =MIN(T54,N('My Loans'!E12)) | AE54: =MIN(U54,N('My Loans'!E13)) | AF54: =MIN(V54,N('My Loans'!E14)) | AG54: =MIN(W54,N('My Loans'!E15)) | AH54: =MIN(N54-X54,MAX(0,$C54-SUMPRODUCT(($D$3:$M$3<D$3)*($N54:$W54-$X54:$AG54)))) | AI54: =MIN(O54-Y54,MAX(0,$C54-SUMPRODUCT(($D$3:$M$3<E$3)*($N54:$W54-$X54:$AG54)))) | AJ54: =MIN(P54-Z54,MAX(0,$C54-SUMPRODUCT(($D$3:$M$3<F$3)*($N54:$W54-$X54:$AG54)))) | AK54: =MIN(Q54-AA54,MAX(0,$C54-SUMPRODUCT(($D$3:$M$3<G$3)*($N54:$W54-$X54:$AG54)))) | AL54: =MIN(R54-AB54,MAX(0,$C54-SUMPRODUCT(($D$3:$M$3<H$3)*($N54:$W54-$X54:$AG54)))) | AM54: =MIN(S54-AC54,MAX(0,$C54-SUMPRODUCT(($D$3:$M$3<I$3)*($N54:$W54-$X54:$AG54)))) | AN54: =MIN(T54-AD54,MAX(0,$C54-SUMPRODUCT(($D$3:$M$3<J$3)*($N54:$W54-$X54:$AG54)))) | AO54: =MIN(U54-AE54,MAX(0,$C54-SUMPRODUCT(($D$3:$M$3<K$3)*($N54:$W54-$X54:$AG54)))) | ... AQ54: =MIN(W54-AG54,MAX(0,$C54-SUMPRODUCT(($D$3:$M$3<M$3)*($N54:$W54-$X54:$AG54)))) | AR54: =ROUND(N54-X54-AH54,2) | AS54: =ROUND(O54-Y54-AI54,2) | AT54: =ROUND(P54-Z54-AJ54,2) | AU54: =ROUND(Q54-AA54-AK54,2) | AV54: =ROUND(R54-AB54-AL54,2) | AW54: =ROUND(S54-AC54-AM54,2) | AX54: =ROUND(T54-AD54-AN54,2) | AY54: =ROUND(U54-AE54-AO54,2) | ... BA54: =ROUND(W54-AG54-AQ54,2) | BB54: =SUM(AR54:BA54)
A55: 51 | B55: =EOMONTH(TODAY(),50) | C55: =MAX(0,(SUM('My Loans'!$E$6:$E$15)+'My Loans'!$D$3)-SUM($X55:$AG55)) | D55: =MAX(0,AR54) | E55: =MAX(0,AS54) | F55: =MAX(0,AT54) | G55: =MAX(0,AU54) | H55: =MAX(0,AV54) | I55: =MAX(0,AW54) | J55: =MAX(0,AX54) | K55: =MAX(0,AY54) | ... M55: =MAX(0,BA54) | N55: =IF(D55<0.5,0,D55*(1+N('My Loans'!D6)/1200)) | O55: =IF(E55<0.5,0,E55*(1+N('My Loans'!D7)/1200)) | P55: =IF(F55<0.5,0,F55*(1+N('My Loans'!D8)/1200)) | Q55: =IF(G55<0.5,0,G55*(1+N('My Loans'!D9)/1200)) | R55: =IF(H55<0.5,0,H55*(1+N('My Loans'!D10)/1200)) | S55: =IF(I55<0.5,0,I55*(1+N('My Loans'!D11)/1200)) | T55: =IF(J55<0.5,0,J55*(1+N('My Loans'!D12)/1200)) | U55: =IF(K55<0.5,0,K55*(1+N('My Loans'!D13)/1200)) | V55: =IF(L55<0.5,0,L55*(1+N('My Loans'!D14)/1200)) | W55: =IF(M55<0.5,0,M55*(1+N('My Loans'!D15)/1200)) | X55: =MIN(N55,N('My Loans'!E6)) | Y55: =MIN(O55,N('My Loans'!E7)) | Z55: =MIN(P55,N('My Loans'!E8)) | AA55: =MIN(Q55,N('My Loans'!E9)) | AB55: =MIN(R55,N('My Loans'!E10)) | AC55: =MIN(S55,N('My Loans'!E11)) | AD55: =MIN(T55,N('My Loans'!E12)) | AE55: =MIN(U55,N('My Loans'!E13)) | AF55: =MIN(V55,N('My Loans'!E14)) | AG55: =MIN(W55,N('My Loans'!E15)) | AH55: =MIN(N55-X55,MAX(0,$C55-SUMPRODUCT(($D$3:$M$3<D$3)*($N55:$W55-$X55:$AG55)))) | AI55: =MIN(O55-Y55,MAX(0,$C55-SUMPRODUCT(($D$3:$M$3<E$3)*($N55:$W55-$X55:$AG55)))) | AJ55: =MIN(P55-Z55,MAX(0,$C55-SUMPRODUCT(($D$3:$M$3<F$3)*($N55:$W55-$X55:$AG55)))) | AK55: =MIN(Q55-AA55,MAX(0,$C55-SUMPRODUCT(($D$3:$M$3<G$3)*($N55:$W55-$X55:$AG55)))) | AL55: =MIN(R55-AB55,MAX(0,$C55-SUMPRODUCT(($D$3:$M$3<H$3)*($N55:$W55-$X55:$AG55)))) | AM55: =MIN(S55-AC55,MAX(0,$C55-SUMPRODUCT(($D$3:$M$3<I$3)*($N55:$W55-$X55:$AG55)))) | AN55: =MIN(T55-AD55,MAX(0,$C55-SUMPRODUCT(($D$3:$M$3<J$3)*($N55:$W55-$X55:$AG55)))) | AO55: =MIN(U55-AE55,MAX(0,$C55-SUMPRODUCT(($D$3:$M$3<K$3)*($N55:$W55-$X55:$AG55)))) | ... AQ55: =MIN(W55-AG55,MAX(0,$C55-SUMPRODUCT(($D$3:$M$3<M$3)*($N55:$W55-$X55:$AG55)))) | AR55: =ROUND(N55-X55-AH55,2) | AS55: =ROUND(O55-Y55-AI55,2) | AT55: =ROUND(P55-Z55-AJ55,2) | AU55: =ROUND(Q55-AA55-AK55,2) | AV55: =ROUND(R55-AB55-AL55,2) | AW55: =ROUND(S55-AC55-AM55,2) | AX55: =ROUND(T55-AD55-AN55,2) | AY55: =ROUND(U55-AE55-AO55,2) | ... BA55: =ROUND(W55-AG55-AQ55,2) | BB55: =SUM(AR55:BA55)
A56: 52 | B56: =EOMONTH(TODAY(),51) | C56: =MAX(0,(SUM('My Loans'!$E$6:$E$15)+'My Loans'!$D$3)-SUM($X56:$AG56)) | D56: =MAX(0,AR55) | E56: =MAX(0,AS55) | F56: =MAX(0,AT55) | G56: =MAX(0,AU55) | H56: =MAX(0,AV55) | I56: =MAX(0,AW55) | J56: =MAX(0,AX55) | K56: =MAX(0,AY55) | ... M56: =MAX(0,BA55) | N56: =IF(D56<0.5,0,D56*(1+N('My Loans'!D6)/1200)) | O56: =IF(E56<0.5,0,E56*(1+N('My Loans'!D7)/1200)) | P56: =IF(F56<0.5,0,F56*(1+N('My Loans'!D8)/1200)) | Q56: =IF(G56<0.5,0,G56*(1+N('My Loans'!D9)/1200)) | R56: =IF(H56<0.5,0,H56*(1+N('My Loans'!D10)/1200)) | S56: =IF(I56<0.5,0,I56*(1+N('My Loans'!D11)/1200)) | T56: =IF(J56<0.5,0,J56*(1+N('My Loans'!D12)/1200)) | U56: =IF(K56<0.5,0,K56*(1+N('My Loans'!D13)/1200)) | V56: =IF(L56<0.5,0,L56*(1+N('My Loans'!D14)/1200)) | W56: =IF(M56<0.5,0,M56*(1+N('My Loans'!D15)/1200)) | X56: =MIN(N56,N('My Loans'!E6)) | Y56: =MIN(O56,N('My Loans'!E7)) | Z56: =MIN(P56,N('My Loans'!E8)) | AA56: =MIN(Q56,N('My Loans'!E9)) | AB56: =MIN(R56,N('My Loans'!E10)) | AC56: =MIN(S56,N('My Loans'!E11)) | AD56: =MIN(T56,N('My Loans'!E12)) | AE56: =MIN(U56,N('My Loans'!E13)) | AF56: =MIN(V56,N('My Loans'!E14)) | AG56: =MIN(W56,N('My Loans'!E15)) | AH56: =MIN(N56-X56,MAX(0,$C56-SUMPRODUCT(($D$3:$M$3<D$3)*($N56:$W56-$X56:$AG56)))) | AI56: =MIN(O56-Y56,MAX(0,$C56-SUMPRODUCT(($D$3:$M$3<E$3)*($N56:$W56-$X56:$AG56)))) | AJ56: =MIN(P56-Z56,MAX(0,$C56-SUMPRODUCT(($D$3:$M$3<F$3)*($N56:$W56-$X56:$AG56)))) | AK56: =MIN(Q56-AA56,MAX(0,$C56-SUMPRODUCT(($D$3:$M$3<G$3)*($N56:$W56-$X56:$AG56)))) | AL56: =MIN(R56-AB56,MAX(0,$C56-SUMPRODUCT(($D$3:$M$3<H$3)*($N56:$W56-$X56:$AG56)))) | AM56: =MIN(S56-AC56,MAX(0,$C56-SUMPRODUCT(($D$3:$M$3<I$3)*($N56:$W56-$X56:$AG56)))) | AN56: =MIN(T56-AD56,MAX(0,$C56-SUMPRODUCT(($D$3:$M$3<J$3)*($N56:$W56-$X56:$AG56)))) | AO56: =MIN(U56-AE56,MAX(0,$C56-SUMPRODUCT(($D$3:$M$3<K$3)*($N56:$W56-$X56:$AG56)))) | ... AQ56: =MIN(W56-AG56,MAX(0,$C56-SUMPRODUCT(($D$3:$M$3<M$3)*($N56:$W56-$X56:$AG56)))) | AR56: =ROUND(N56-X56-AH56,2) | AS56: =ROUND(O56-Y56-AI56,2) | AT56: =ROUND(P56-Z56-AJ56,2) | AU56: =ROUND(Q56-AA56-AK56,2) | AV56: =ROUND(R56-AB56-AL56,2) | AW56: =ROUND(S56-AC56-AM56,2) | AX56: =ROUND(T56-AD56-AN56,2) | AY56: =ROUND(U56-AE56-AO56,2) | ... BA56: =ROUND(W56-AG56-AQ56,2) | BB56: =SUM(AR56:BA56)
A57: 53 | B57: =EOMONTH(TODAY(),52) | C57: =MAX(0,(SUM('My Loans'!$E$6:$E$15)+'My Loans'!$D$3)-SUM($X57:$AG57)) | D57: =MAX(0,AR56) | E57: =MAX(0,AS56) | F57: =MAX(0,AT56) | G57: =MAX(0,AU56) | H57: =MAX(0,AV56) | I57: =MAX(0,AW56) | J57: =MAX(0,AX56) | K57: =MAX(0,AY56) | ... M57: =MAX(0,BA56) | N57: =IF(D57<0.5,0,D57*(1+N('My Loans'!D6)/1200)) | O57: =IF(E57<0.5,0,E57*(1+N('My Loans'!D7)/1200)) | P57: =IF(F57<0.5,0,F57*(1+N('My Loans'!D8)/1200)) | Q57: =IF(G57<0.5,0,G57*(1+N('My Loans'!D9)/1200)) | R57: =IF(H57<0.5,0,H57*(1+N('My Loans'!D10)/1200)) | S57: =IF(I57<0.5,0,I57*(1+N('My Loans'!D11)/1200)) | T57: =IF(J57<0.5,0,J57*(1+N('My Loans'!D12)/1200)) | U57: =IF(K57<0.5,0,K57*(1+N('My Loans'!D13)/1200)) | V57: =IF(L57<0.5,0,L57*(1+N('My Loans'!D14)/1200)) | W57: =IF(M57<0.5,0,M57*(1+N('My Loans'!D15)/1200)) | X57: =MIN(N57,N('My Loans'!E6)) | Y57: =MIN(O57,N('My Loans'!E7)) | Z57: =MIN(P57,N('My Loans'!E8)) | AA57: =MIN(Q57,N('My Loans'!E9)) | AB57: =MIN(R57,N('My Loans'!E10)) | AC57: =MIN(S57,N('My Loans'!E11)) | AD57: =MIN(T57,N('My Loans'!E12)) | AE57: =MIN(U57,N('My Loans'!E13)) | AF57: =MIN(V57,N('My Loans'!E14)) | AG57: =MIN(W57,N('My Loans'!E15)) | AH57: =MIN(N57-X57,MAX(0,$C57-SUMPRODUCT(($D$3:$M$3<D$3)*($N57:$W57-$X57:$AG57)))) | AI57: =MIN(O57-Y57,MAX(0,$C57-SUMPRODUCT(($D$3:$M$3<E$3)*($N57:$W57-$X57:$AG57)))) | AJ57: =MIN(P57-Z57,MAX(0,$C57-SUMPRODUCT(($D$3:$M$3<F$3)*($N57:$W57-$X57:$AG57)))) | AK57: =MIN(Q57-AA57,MAX(0,$C57-SUMPRODUCT(($D$3:$M$3<G$3)*($N57:$W57-$X57:$AG57)))) | AL57: =MIN(R57-AB57,MAX(0,$C57-SUMPRODUCT(($D$3:$M$3<H$3)*($N57:$W57-$X57:$AG57)))) | AM57: =MIN(S57-AC57,MAX(0,$C57-SUMPRODUCT(($D$3:$M$3<I$3)*($N57:$W57-$X57:$AG57)))) | AN57: =MIN(T57-AD57,MAX(0,$C57-SUMPRODUCT(($D$3:$M$3<J$3)*($N57:$W57-$X57:$AG57)))) | AO57: =MIN(U57-AE57,MAX(0,$C57-SUMPRODUCT(($D$3:$M$3<K$3)*($N57:$W57-$X57:$AG57)))) | ... AQ57: =MIN(W57-AG57,MAX(0,$C57-SUMPRODUCT(($D$3:$M$3<M$3)*($N57:$W57-$X57:$AG57)))) | AR57: =ROUND(N57-X57-AH57,2) | AS57: =ROUND(O57-Y57-AI57,2) | AT57: =ROUND(P57-Z57-AJ57,2) | AU57: =ROUND(Q57-AA57-AK57,2) | AV57: =ROUND(R57-AB57-AL57,2) | AW57: =ROUND(S57-AC57-AM57,2) | AX57: =ROUND(T57-AD57-AN57,2) | AY57: =ROUND(U57-AE57-AO57,2) | ... BA57: =ROUND(W57-AG57-AQ57,2) | BB57: =SUM(AR57:BA57)
A58: 54 | B58: =EOMONTH(TODAY(),53) | C58: =MAX(0,(SUM('My Loans'!$E$6:$E$15)+'My Loans'!$D$3)-SUM($X58:$AG58)) | D58: =MAX(0,AR57) | E58: =MAX(0,AS57) | F58: =MAX(0,AT57) | G58: =MAX(0,AU57) | H58: =MAX(0,AV57) | I58: =MAX(0,AW57) | J58: =MAX(0,AX57) | K58: =MAX(0,AY57) | ... M58: =MAX(0,BA57) | N58: =IF(D58<0.5,0,D58*(1+N('My Loans'!D6)/1200)) | O58: =IF(E58<0.5,0,E58*(1+N('My Loans'!D7)/1200)) | P58: =IF(F58<0.5,0,F58*(1+N('My Loans'!D8)/1200)) | Q58: =IF(G58<0.5,0,G58*(1+N('My Loans'!D9)/1200)) | R58: =IF(H58<0.5,0,H58*(1+N('My Loans'!D10)/1200)) | S58: =IF(I58<0.5,0,I58*(1+N('My Loans'!D11)/1200)) | T58: =IF(J58<0.5,0,J58*(1+N('My Loans'!D12)/1200)) | U58: =IF(K58<0.5,0,K58*(1+N('My Loans'!D13)/1200)) | V58: =IF(L58<0.5,0,L58*(1+N('My Loans'!D14)/1200)) | W58: =IF(M58<0.5,0,M58*(1+N('My Loans'!D15)/1200)) | X58: =MIN(N58,N('My Loans'!E6)) | Y58: =MIN(O58,N('My Loans'!E7)) | Z58: =MIN(P58,N('My Loans'!E8)) | AA58: =MIN(Q58,N('My Loans'!E9)) | AB58: =MIN(R58,N('My Loans'!E10)) | AC58: =MIN(S58,N('My Loans'!E11)) | AD58: =MIN(T58,N('My Loans'!E12)) | AE58: =MIN(U58,N('My Loans'!E13)) | AF58: =MIN(V58,N('My Loans'!E14)) | AG58: =MIN(W58,N('My Loans'!E15)) | AH58: =MIN(N58-X58,MAX(0,$C58-SUMPRODUCT(($D$3:$M$3<D$3)*($N58:$W58-$X58:$AG58)))) | AI58: =MIN(O58-Y58,MAX(0,$C58-SUMPRODUCT(($D$3:$M$3<E$3)*($N58:$W58-$X58:$AG58)))) | AJ58: =MIN(P58-Z58,MAX(0,$C58-SUMPRODUCT(($D$3:$M$3<F$3)*($N58:$W58-$X58:$AG58)))) | AK58: =MIN(Q58-AA58,MAX(0,$C58-SUMPRODUCT(($D$3:$M$3<G$3)*($N58:$W58-$X58:$AG58)))) | AL58: =MIN(R58-AB58,MAX(0,$C58-SUMPRODUCT(($D$3:$M$3<H$3)*($N58:$W58-$X58:$AG58)))) | AM58: =MIN(S58-AC58,MAX(0,$C58-SUMPRODUCT(($D$3:$M$3<I$3)*($N58:$W58-$X58:$AG58)))) | AN58: =MIN(T58-AD58,MAX(0,$C58-SUMPRODUCT(($D$3:$M$3<J$3)*($N58:$W58-$X58:$AG58)))) | AO58: =MIN(U58-AE58,MAX(0,$C58-SUMPRODUCT(($D$3:$M$3<K$3)*($N58:$W58-$X58:$AG58)))) | ... AQ58: =MIN(W58-AG58,MAX(0,$C58-SUMPRODUCT(($D$3:$M$3<M$3)*($N58:$W58-$X58:$AG58)))) | AR58: =ROUND(N58-X58-AH58,2) | AS58: =ROUND(O58-Y58-AI58,2) | AT58: =ROUND(P58-Z58-AJ58,2) | AU58: =ROUND(Q58-AA58-AK58,2) | AV58: =ROUND(R58-AB58-AL58,2) | AW58: =ROUND(S58-AC58-AM58,2) | AX58: =ROUND(T58-AD58-AN58,2) | AY58: =ROUND(U58-AE58-AO58,2) | ... BA58: =ROUND(W58-AG58-AQ58,2) | BB58: =SUM(AR58:BA58)
A59: 55 | B59: =EOMONTH(TODAY(),54) | C59: =MAX(0,(SUM('My Loans'!$E$6:$E$15)+'My Loans'!$D$3)-SUM($X59:$AG59)) | D59: =MAX(0,AR58) | E59: =MAX(0,AS58) | F59: =MAX(0,AT58) | G59: =MAX(0,AU58) | H59: =MAX(0,AV58) | I59: =MAX(0,AW58) | J59: =MAX(0,AX58) | K59: =MAX(0,AY58) | ... M59: =MAX(0,BA58) | N59: =IF(D59<0.5,0,D59*(1+N('My Loans'!D6)/1200)) | O59: =IF(E59<0.5,0,E59*(1+N('My Loans'!D7)/1200)) | P59: =IF(F59<0.5,0,F59*(1+N('My Loans'!D8)/1200)) | Q59: =IF(G59<0.5,0,G59*(1+N('My Loans'!D9)/1200)) | R59: =IF(H59<0.5,0,H59*(1+N('My Loans'!D10)/1200)) | S59: =IF(I59<0.5,0,I59*(1+N('My Loans'!D11)/1200)) | T59: =IF(J59<0.5,0,J59*(1+N('My Loans'!D12)/1200)) | U59: =IF(K59<0.5,0,K59*(1+N('My Loans'!D13)/1200)) | V59: =IF(L59<0.5,0,L59*(1+N('My Loans'!D14)/1200)) | W59: =IF(M59<0.5,0,M59*(1+N('My Loans'!D15)/1200)) | X59: =MIN(N59,N('My Loans'!E6)) | Y59: =MIN(O59,N('My Loans'!E7)) | Z59: =MIN(P59,N('My Loans'!E8)) | AA59: =MIN(Q59,N('My Loans'!E9)) | AB59: =MIN(R59,N('My Loans'!E10)) | AC59: =MIN(S59,N('My Loans'!E11)) | AD59: =MIN(T59,N('My Loans'!E12)) | AE59: =MIN(U59,N('My Loans'!E13)) | AF59: =MIN(V59,N('My Loans'!E14)) | AG59: =MIN(W59,N('My Loans'!E15)) | AH59: =MIN(N59-X59,MAX(0,$C59-SUMPRODUCT(($D$3:$M$3<D$3)*($N59:$W59-$X59:$AG59)))) | AI59: =MIN(O59-Y59,MAX(0,$C59-SUMPRODUCT(($D$3:$M$3<E$3)*($N59:$W59-$X59:$AG59)))) | AJ59: =MIN(P59-Z59,MAX(0,$C59-SUMPRODUCT(($D$3:$M$3<F$3)*($N59:$W59-$X59:$AG59)))) | AK59: =MIN(Q59-AA59,MAX(0,$C59-SUMPRODUCT(($D$3:$M$3<G$3)*($N59:$W59-$X59:$AG59)))) | AL59: =MIN(R59-AB59,MAX(0,$C59-SUMPRODUCT(($D$3:$M$3<H$3)*($N59:$W59-$X59:$AG59)))) | AM59: =MIN(S59-AC59,MAX(0,$C59-SUMPRODUCT(($D$3:$M$3<I$3)*($N59:$W59-$X59:$AG59)))) | AN59: =MIN(T59-AD59,MAX(0,$C59-SUMPRODUCT(($D$3:$M$3<J$3)*($N59:$W59-$X59:$AG59)))) | AO59: =MIN(U59-AE59,MAX(0,$C59-SUMPRODUCT(($D$3:$M$3<K$3)*($N59:$W59-$X59:$AG59)))) | ... AQ59: =MIN(W59-AG59,MAX(0,$C59-SUMPRODUCT(($D$3:$M$3<M$3)*($N59:$W59-$X59:$AG59)))) | AR59: =ROUND(N59-X59-AH59,2) | AS59: =ROUND(O59-Y59-AI59,2) | AT59: =ROUND(P59-Z59-AJ59,2) | AU59: =ROUND(Q59-AA59-AK59,2) | AV59: =ROUND(R59-AB59-AL59,2) | AW59: =ROUND(S59-AC59-AM59,2) | AX59: =ROUND(T59-AD59-AN59,2) | AY59: =ROUND(U59-AE59-AO59,2) | ... BA59: =ROUND(W59-AG59-AQ59,2) | BB59: =SUM(AR59:BA59)
A60: 56 | B60: =EOMONTH(TODAY(),55) | C60: =MAX(0,(SUM('My Loans'!$E$6:$E$15)+'My Loans'!$D$3)-SUM($X60:$AG60)) | D60: =MAX(0,AR59) | E60: =MAX(0,AS59) | F60: =MAX(0,AT59) | G60: =MAX(0,AU59) | H60: =MAX(0,AV59) | I60: =MAX(0,AW59) | J60: =MAX(0,AX59) | K60: =MAX(0,AY59) | ... M60: =MAX(0,BA59) | N60: =IF(D60<0.5,0,D60*(1+N('My Loans'!D6)/1200)) | O60: =IF(E60<0.5,0,E60*(1+N('My Loans'!D7)/1200)) | P60: =IF(F60<0.5,0,F60*(1+N('My Loans'!D8)/1200)) | Q60: =IF(G60<0.5,0,G60*(1+N('My Loans'!D9)/1200)) | R60: =IF(H60<0.5,0,H60*(1+N('My Loans'!D10)/1200)) | S60: =IF(I60<0.5,0,I60*(1+N('My Loans'!D11)/1200)) | T60: =IF(J60<0.5,0,J60*(1+N('My Loans'!D12)/1200)) | U60: =IF(K60<0.5,0,K60*(1+N('My Loans'!D13)/1200)) | V60: =IF(L60<0.5,0,L60*(1+N('My Loans'!D14)/1200)) | W60: =IF(M60<0.5,0,M60*(1+N('My Loans'!D15)/1200)) | X60: =MIN(N60,N('My Loans'!E6)) | Y60: =MIN(O60,N('My Loans'!E7)) | Z60: =MIN(P60,N('My Loans'!E8)) | AA60: =MIN(Q60,N('My Loans'!E9)) | AB60: =MIN(R60,N('My Loans'!E10)) | AC60: =MIN(S60,N('My Loans'!E11)) | AD60: =MIN(T60,N('My Loans'!E12)) | AE60: =MIN(U60,N('My Loans'!E13)) | AF60: =MIN(V60,N('My Loans'!E14)) | AG60: =MIN(W60,N('My Loans'!E15)) | AH60: =MIN(N60-X60,MAX(0,$C60-SUMPRODUCT(($D$3:$M$3<D$3)*($N60:$W60-$X60:$AG60)))) | AI60: =MIN(O60-Y60,MAX(0,$C60-SUMPRODUCT(($D$3:$M$3<E$3)*($N60:$W60-$X60:$AG60)))) | AJ60: =MIN(P60-Z60,MAX(0,$C60-SUMPRODUCT(($D$3:$M$3<F$3)*($N60:$W60-$X60:$AG60)))) | AK60: =MIN(Q60-AA60,MAX(0,$C60-SUMPRODUCT(($D$3:$M$3<G$3)*($N60:$W60-$X60:$AG60)))) | AL60: =MIN(R60-AB60,MAX(0,$C60-SUMPRODUCT(($D$3:$M$3<H$3)*($N60:$W60-$X60:$AG60)))) | AM60: =MIN(S60-AC60,MAX(0,$C60-SUMPRODUCT(($D$3:$M$3<I$3)*($N60:$W60-$X60:$AG60)))) | AN60: =MIN(T60-AD60,MAX(0,$C60-SUMPRODUCT(($D$3:$M$3<J$3)*($N60:$W60-$X60:$AG60)))) | AO60: =MIN(U60-AE60,MAX(0,$C60-SUMPRODUCT(($D$3:$M$3<K$3)*($N60:$W60-$X60:$AG60)))) | ... AQ60: =MIN(W60-AG60,MAX(0,$C60-SUMPRODUCT(($D$3:$M$3<M$3)*($N60:$W60-$X60:$AG60)))) | AR60: =ROUND(N60-X60-AH60,2) | AS60: =ROUND(O60-Y60-AI60,2) | AT60: =ROUND(P60-Z60-AJ60,2) | AU60: =ROUND(Q60-AA60-AK60,2) | AV60: =ROUND(R60-AB60-AL60,2) | AW60: =ROUND(S60-AC60-AM60,2) | AX60: =ROUND(T60-AD60-AN60,2) | AY60: =ROUND(U60-AE60-AO60,2) | ... BA60: =ROUND(W60-AG60-AQ60,2) | BB60: =SUM(AR60:BA60)
A61: 57 | B61: =EOMONTH(TODAY(),56) | C61: =MAX(0,(SUM('My Loans'!$E$6:$E$15)+'My Loans'!$D$3)-SUM($X61:$AG61)) | D61: =MAX(0,AR60) | E61: =MAX(0,AS60) | F61: =MAX(0,AT60) | G61: =MAX(0,AU60) | H61: =MAX(0,AV60) | I61: =MAX(0,AW60) | J61: =MAX(0,AX60) | K61: =MAX(0,AY60) | ... M61: =MAX(0,BA60) | N61: =IF(D61<0.5,0,D61*(1+N('My Loans'!D6)/1200)) | O61: =IF(E61<0.5,0,E61*(1+N('My Loans'!D7)/1200)) | P61: =IF(F61<0.5,0,F61*(1+N('My Loans'!D8)/1200)) | Q61: =IF(G61<0.5,0,G61*(1+N('My Loans'!D9)/1200)) | R61: =IF(H61<0.5,0,H61*(1+N('My Loans'!D10)/1200)) | S61: =IF(I61<0.5,0,I61*(1+N('My Loans'!D11)/1200)) | T61: =IF(J61<0.5,0,J61*(1+N('My Loans'!D12)/1200)) | U61: =IF(K61<0.5,0,K61*(1+N('My Loans'!D13)/1200)) | V61: =IF(L61<0.5,0,L61*(1+N('My Loans'!D14)/1200)) | W61: =IF(M61<0.5,0,M61*(1+N('My Loans'!D15)/1200)) | X61: =MIN(N61,N('My Loans'!E6)) | Y61: =MIN(O61,N('My Loans'!E7)) | Z61: =MIN(P61,N('My Loans'!E8)) | AA61: =MIN(Q61,N('My Loans'!E9)) | AB61: =MIN(R61,N('My Loans'!E10)) | AC61: =MIN(S61,N('My Loans'!E11)) | AD61: =MIN(T61,N('My Loans'!E12)) | AE61: =MIN(U61,N('My Loans'!E13)) | AF61: =MIN(V61,N('My Loans'!E14)) | AG61: =MIN(W61,N('My Loans'!E15)) | AH61: =MIN(N61-X61,MAX(0,$C61-SUMPRODUCT(($D$3:$M$3<D$3)*($N61:$W61-$X61:$AG61)))) | AI61: =MIN(O61-Y61,MAX(0,$C61-SUMPRODUCT(($D$3:$M$3<E$3)*($N61:$W61-$X61:$AG61)))) | AJ61: =MIN(P61-Z61,MAX(0,$C61-SUMPRODUCT(($D$3:$M$3<F$3)*($N61:$W61-$X61:$AG61)))) | AK61: =MIN(Q61-AA61,MAX(0,$C61-SUMPRODUCT(($D$3:$M$3<G$3)*($N61:$W61-$X61:$AG61)))) | AL61: =MIN(R61-AB61,MAX(0,$C61-SUMPRODUCT(($D$3:$M$3<H$3)*($N61:$W61-$X61:$AG61)))) | AM61: =MIN(S61-AC61,MAX(0,$C61-SUMPRODUCT(($D$3:$M$3<I$3)*($N61:$W61-$X61:$AG61)))) | AN61: =MIN(T61-AD61,MAX(0,$C61-SUMPRODUCT(($D$3:$M$3<J$3)*($N61:$W61-$X61:$AG61)))) | AO61: =MIN(U61-AE61,MAX(0,$C61-SUMPRODUCT(($D$3:$M$3<K$3)*($N61:$W61-$X61:$AG61)))) | ... AQ61: =MIN(W61-AG61,MAX(0,$C61-SUMPRODUCT(($D$3:$M$3<M$3)*($N61:$W61-$X61:$AG61)))) | AR61: =ROUND(N61-X61-AH61,2) | AS61: =ROUND(O61-Y61-AI61,2) | AT61: =ROUND(P61-Z61-AJ61,2) | AU61: =ROUND(Q61-AA61-AK61,2) | AV61: =ROUND(R61-AB61-AL61,2) | AW61: =ROUND(S61-AC61-AM61,2) | AX61: =ROUND(T61-AD61-AN61,2) | AY61: =ROUND(U61-AE61-AO61,2) | ... BA61: =ROUND(W61-AG61-AQ61,2) | BB61: =SUM(AR61:BA61)
A62: 58 | B62: =EOMONTH(TODAY(),57) | C62: =MAX(0,(SUM('My Loans'!$E$6:$E$15)+'My Loans'!$D$3)-SUM($X62:$AG62)) | D62: =MAX(0,AR61) | E62: =MAX(0,AS61) | F62: =MAX(0,AT61) | G62: =MAX(0,AU61) | H62: =MAX(0,AV61) | I62: =MAX(0,AW61) | J62: =MAX(0,AX61) | K62: =MAX(0,AY61) | ... M62: =MAX(0,BA61) | N62: =IF(D62<0.5,0,D62*(1+N('My Loans'!D6)/1200)) | O62: =IF(E62<0.5,0,E62*(1+N('My Loans'!D7)/1200)) | P62: =IF(F62<0.5,0,F62*(1+N('My Loans'!D8)/1200)) | Q62: =IF(G62<0.5,0,G62*(1+N('My Loans'!D9)/1200)) | R62: =IF(H62<0.5,0,H62*(1+N('My Loans'!D10)/1200)) | S62: =IF(I62<0.5,0,I62*(1+N('My Loans'!D11)/1200)) | T62: =IF(J62<0.5,0,J62*(1+N('My Loans'!D12)/1200)) | U62: =IF(K62<0.5,0,K62*(1+N('My Loans'!D13)/1200)) | V62: =IF(L62<0.5,0,L62*(1+N('My Loans'!D14)/1200)) | W62: =IF(M62<0.5,0,M62*(1+N('My Loans'!D15)/1200)) | X62: =MIN(N62,N('My Loans'!E6)) | Y62: =MIN(O62,N('My Loans'!E7)) | Z62: =MIN(P62,N('My Loans'!E8)) | AA62: =MIN(Q62,N('My Loans'!E9)) | AB62: =MIN(R62,N('My Loans'!E10)) | AC62: =MIN(S62,N('My Loans'!E11)) | AD62: =MIN(T62,N('My Loans'!E12)) | AE62: =MIN(U62,N('My Loans'!E13)) | AF62: =MIN(V62,N('My Loans'!E14)) | AG62: =MIN(W62,N('My Loans'!E15)) | AH62: =MIN(N62-X62,MAX(0,$C62-SUMPRODUCT(($D$3:$M$3<D$3)*($N62:$W62-$X62:$AG62)))) | AI62: =MIN(O62-Y62,MAX(0,$C62-SUMPRODUCT(($D$3:$M$3<E$3)*($N62:$W62-$X62:$AG62)))) | AJ62: =MIN(P62-Z62,MAX(0,$C62-SUMPRODUCT(($D$3:$M$3<F$3)*($N62:$W62-$X62:$AG62)))) | AK62: =MIN(Q62-AA62,MAX(0,$C62-SUMPRODUCT(($D$3:$M$3<G$3)*($N62:$W62-$X62:$AG62)))) | AL62: =MIN(R62-AB62,MAX(0,$C62-SUMPRODUCT(($D$3:$M$3<H$3)*($N62:$W62-$X62:$AG62)))) | AM62: =MIN(S62-AC62,MAX(0,$C62-SUMPRODUCT(($D$3:$M$3<I$3)*($N62:$W62-$X62:$AG62)))) | AN62: =MIN(T62-AD62,MAX(0,$C62-SUMPRODUCT(($D$3:$M$3<J$3)*($N62:$W62-$X62:$AG62)))) | AO62: =MIN(U62-AE62,MAX(0,$C62-SUMPRODUCT(($D$3:$M$3<K$3)*($N62:$W62-$X62:$AG62)))) | ... AQ62: =MIN(W62-AG62,MAX(0,$C62-SUMPRODUCT(($D$3:$M$3<M$3)*($N62:$W62-$X62:$AG62)))) | AR62: =ROUND(N62-X62-AH62,2) | AS62: =ROUND(O62-Y62-AI62,2) | AT62: =ROUND(P62-Z62-AJ62,2) | AU62: =ROUND(Q62-AA62-AK62,2) | AV62: =ROUND(R62-AB62-AL62,2) | AW62: =ROUND(S62-AC62-AM62,2) | AX62: =ROUND(T62-AD62-AN62,2) | AY62: =ROUND(U62-AE62-AO62,2) | ... BA62: =ROUND(W62-AG62-AQ62,2) | BB62: =SUM(AR62:BA62)
A63: 59 | B63: =EOMONTH(TODAY(),58) | C63: =MAX(0,(SUM('My Loans'!$E$6:$E$15)+'My Loans'!$D$3)-SUM($X63:$AG63)) | D63: =MAX(0,AR62) | E63: =MAX(0,AS62) | F63: =MAX(0,AT62) | G63: =MAX(0,AU62) | H63: =MAX(0,AV62) | I63: =MAX(0,AW62) | J63: =MAX(0,AX62) | K63: =MAX(0,AY62) | ... M63: =MAX(0,BA62) | N63: =IF(D63<0.5,0,D63*(1+N('My Loans'!D6)/1200)) | O63: =IF(E63<0.5,0,E63*(1+N('My Loans'!D7)/1200)) | P63: =IF(F63<0.5,0,F63*(1+N('My Loans'!D8)/1200)) | Q63: =IF(G63<0.5,0,G63*(1+N('My Loans'!D9)/1200)) | R63: =IF(H63<0.5,0,H63*(1+N('My Loans'!D10)/1200)) | S63: =IF(I63<0.5,0,I63*(1+N('My Loans'!D11)/1200)) | T63: =IF(J63<0.5,0,J63*(1+N('My Loans'!D12)/1200)) | U63: =IF(K63<0.5,0,K63*(1+N('My Loans'!D13)/1200)) | V63: =IF(L63<0.5,0,L63*(1+N('My Loans'!D14)/1200)) | W63: =IF(M63<0.5,0,M63*(1+N('My Loans'!D15)/1200)) | X63: =MIN(N63,N('My Loans'!E6)) | Y63: =MIN(O63,N('My Loans'!E7)) | Z63: =MIN(P63,N('My Loans'!E8)) | AA63: =MIN(Q63,N('My Loans'!E9)) | AB63: =MIN(R63,N('My Loans'!E10)) | AC63: =MIN(S63,N('My Loans'!E11)) | AD63: =MIN(T63,N('My Loans'!E12)) | AE63: =MIN(U63,N('My Loans'!E13)) | AF63: =MIN(V63,N('My Loans'!E14)) | AG63: =MIN(W63,N('My Loans'!E15)) | AH63: =MIN(N63-X63,MAX(0,$C63-SUMPRODUCT(($D$3:$M$3<D$3)*($N63:$W63-$X63:$AG63)))) | AI63: =MIN(O63-Y63,MAX(0,$C63-SUMPRODUCT(($D$3:$M$3<E$3)*($N63:$W63-$X63:$AG63)))) | AJ63: =MIN(P63-Z63,MAX(0,$C63-SUMPRODUCT(($D$3:$M$3<F$3)*($N63:$W63-$X63:$AG63)))) | AK63: =MIN(Q63-AA63,MAX(0,$C63-SUMPRODUCT(($D$3:$M$3<G$3)*($N63:$W63-$X63:$AG63)))) | AL63: =MIN(R63-AB63,MAX(0,$C63-SUMPRODUCT(($D$3:$M$3<H$3)*($N63:$W63-$X63:$AG63)))) | AM63: =MIN(S63-AC63,MAX(0,$C63-SUMPRODUCT(($D$3:$M$3<I$3)*($N63:$W63-$X63:$AG63)))) | AN63: =MIN(T63-AD63,MAX(0,$C63-SUMPRODUCT(($D$3:$M$3<J$3)*($N63:$W63-$X63:$AG63)))) | AO63: =MIN(U63-AE63,MAX(0,$C63-SUMPRODUCT(($D$3:$M$3<K$3)*($N63:$W63-$X63:$AG63)))) | ... AQ63: =MIN(W63-AG63,MAX(0,$C63-SUMPRODUCT(($D$3:$M$3<M$3)*($N63:$W63-$X63:$AG63)))) | AR63: =ROUND(N63-X63-AH63,2) | AS63: =ROUND(O63-Y63-AI63,2) | AT63: =ROUND(P63-Z63-AJ63,2) | AU63: =ROUND(Q63-AA63-AK63,2) | AV63: =ROUND(R63-AB63-AL63,2) | AW63: =ROUND(S63-AC63-AM63,2) | AX63: =ROUND(T63-AD63-AN63,2) | AY63: =ROUND(U63-AE63-AO63,2) | ... BA63: =ROUND(W63-AG63-AQ63,2) | BB63: =SUM(AR63:BA63)
A64: 60 | B64: =EOMONTH(TODAY(),59) | C64: =MAX(0,(SUM('My Loans'!$E$6:$E$15)+'My Loans'!$D$3)-SUM($X64:$AG64)) | D64: =MAX(0,AR63) | E64: =MAX(0,AS63) | F64: =MAX(0,AT63) | G64: =MAX(0,AU63) | H64: =MAX(0,AV63) | I64: =MAX(0,AW63) | J64: =MAX(0,AX63) | K64: =MAX(0,AY63) | ... M64: =MAX(0,BA63) | N64: =IF(D64<0.5,0,D64*(1+N('My Loans'!D6)/1200)) | O64: =IF(E64<0.5,0,E64*(1+N('My Loans'!D7)/1200)) | P64: =IF(F64<0.5,0,F64*(1+N('My Loans'!D8)/1200)) | Q64: =IF(G64<0.5,0,G64*(1+N('My Loans'!D9)/1200)) | R64: =IF(H64<0.5,0,H64*(1+N('My Loans'!D10)/1200)) | S64: =IF(I64<0.5,0,I64*(1+N('My Loans'!D11)/1200)) | T64: =IF(J64<0.5,0,J64*(1+N('My Loans'!D12)/1200)) | U64: =IF(K64<0.5,0,K64*(1+N('My Loans'!D13)/1200)) | V64: =IF(L64<0.5,0,L64*(1+N('My Loans'!D14)/1200)) | W64: =IF(M64<0.5,0,M64*(1+N('My Loans'!D15)/1200)) | X64: =MIN(N64,N('My Loans'!E6)) | Y64: =MIN(O64,N('My Loans'!E7)) | Z64: =MIN(P64,N('My Loans'!E8)) | AA64: =MIN(Q64,N('My Loans'!E9)) | AB64: =MIN(R64,N('My Loans'!E10)) | AC64: =MIN(S64,N('My Loans'!E11)) | AD64: =MIN(T64,N('My Loans'!E12)) | AE64: =MIN(U64,N('My Loans'!E13)) | AF64: =MIN(V64,N('My Loans'!E14)) | AG64: =MIN(W64,N('My Loans'!E15)) | AH64: =MIN(N64-X64,MAX(0,$C64-SUMPRODUCT(($D$3:$M$3<D$3)*($N64:$W64-$X64:$AG64)))) | AI64: =MIN(O64-Y64,MAX(0,$C64-SUMPRODUCT(($D$3:$M$3<E$3)*($N64:$W64-$X64:$AG64)))) | AJ64: =MIN(P64-Z64,MAX(0,$C64-SUMPRODUCT(($D$3:$M$3<F$3)*($N64:$W64-$X64:$AG64)))) | AK64: =MIN(Q64-AA64,MAX(0,$C64-SUMPRODUCT(($D$3:$M$3<G$3)*($N64:$W64-$X64:$AG64)))) | AL64: =MIN(R64-AB64,MAX(0,$C64-SUMPRODUCT(($D$3:$M$3<H$3)*($N64:$W64-$X64:$AG64)))) | AM64: =MIN(S64-AC64,MAX(0,$C64-SUMPRODUCT(($D$3:$M$3<I$3)*($N64:$W64-$X64:$AG64)))) | AN64: =MIN(T64-AD64,MAX(0,$C64-SUMPRODUCT(($D$3:$M$3<J$3)*($N64:$W64-$X64:$AG64)))) | AO64: =MIN(U64-AE64,MAX(0,$C64-SUMPRODUCT(($D$3:$M$3<K$3)*($N64:$W64-$X64:$AG64)))) | ... AQ64: =MIN(W64-AG64,MAX(0,$C64-SUMPRODUCT(($D$3:$M$3<M$3)*($N64:$W64-$X64:$AG64)))) | AR64: =ROUND(N64-X64-AH64,2) | AS64: =ROUND(O64-Y64-AI64,2) | AT64: =ROUND(P64-Z64-AJ64,2) | AU64: =ROUND(Q64-AA64-AK64,2) | AV64: =ROUND(R64-AB64-AL64,2) | AW64: =ROUND(S64-AC64-AM64,2) | AX64: =ROUND(T64-AD64-AN64,2) | AY64: =ROUND(U64-AE64-AO64,2) | ... BA64: =ROUND(W64-AG64-AQ64,2) | BB64: =SUM(AR64:BA64)
A65: 61 | B65: =EOMONTH(TODAY(),60) | C65: =MAX(0,(SUM('My Loans'!$E$6:$E$15)+'My Loans'!$D$3)-SUM($X65:$AG65)) | D65: =MAX(0,AR64) | E65: =MAX(0,AS64) | F65: =MAX(0,AT64) | G65: =MAX(0,AU64) | H65: =MAX(0,AV64) | I65: =MAX(0,AW64) | J65: =MAX(0,AX64) | K65: =MAX(0,AY64) | ... M65: =MAX(0,BA64) | N65: =IF(D65<0.5,0,D65*(1+N('My Loans'!D6)/1200)) | O65: =IF(E65<0.5,0,E65*(1+N('My Loans'!D7)/1200)) | P65: =IF(F65<0.5,0,F65*(1+N('My Loans'!D8)/1200)) | Q65: =IF(G65<0.5,0,G65*(1+N('My Loans'!D9)/1200)) | R65: =IF(H65<0.5,0,H65*(1+N('My Loans'!D10)/1200)) | S65: =IF(I65<0.5,0,I65*(1+N('My Loans'!D11)/1200)) | T65: =IF(J65<0.5,0,J65*(1+N('My Loans'!D12)/1200)) | U65: =IF(K65<0.5,0,K65*(1+N('My Loans'!D13)/1200)) | V65: =IF(L65<0.5,0,L65*(1+N('My Loans'!D14)/1200)) | W65: =IF(M65<0.5,0,M65*(1+N('My Loans'!D15)/1200)) | X65: =MIN(N65,N('My Loans'!E6)) | Y65: =MIN(O65,N('My Loans'!E7)) | Z65: =MIN(P65,N('My Loans'!E8)) | AA65: =MIN(Q65,N('My Loans'!E9)) | AB65: =MIN(R65,N('My Loans'!E10)) | AC65: =MIN(S65,N('My Loans'!E11)) | AD65: =MIN(T65,N('My Loans'!E12)) | AE65: =MIN(U65,N('My Loans'!E13)) | AF65: =MIN(V65,N('My Loans'!E14)) | AG65: =MIN(W65,N('My Loans'!E15)) | AH65: =MIN(N65-X65,MAX(0,$C65-SUMPRODUCT(($D$3:$M$3<D$3)*($N65:$W65-$X65:$AG65)))) | AI65: =MIN(O65-Y65,MAX(0,$C65-SUMPRODUCT(($D$3:$M$3<E$3)*($N65:$W65-$X65:$AG65)))) | AJ65: =MIN(P65-Z65,MAX(0,$C65-SUMPRODUCT(($D$3:$M$3<F$3)*($N65:$W65-$X65:$AG65)))) | AK65: =MIN(Q65-AA65,MAX(0,$C65-SUMPRODUCT(($D$3:$M$3<G$3)*($N65:$W65-$X65:$AG65)))) | AL65: =MIN(R65-AB65,MAX(0,$C65-SUMPRODUCT(($D$3:$M$3<H$3)*($N65:$W65-$X65:$AG65)))) | AM65: =MIN(S65-AC65,MAX(0,$C65-SUMPRODUCT(($D$3:$M$3<I$3)*($N65:$W65-$X65:$AG65)))) | AN65: =MIN(T65-AD65,MAX(0,$C65-SUMPRODUCT(($D$3:$M$3<J$3)*($N65:$W65-$X65:$AG65)))) | AO65: =MIN(U65-AE65,MAX(0,$C65-SUMPRODUCT(($D$3:$M$3<K$3)*($N65:$W65-$X65:$AG65)))) | ... AQ65: =MIN(W65-AG65,MAX(0,$C65-SUMPRODUCT(($D$3:$M$3<M$3)*($N65:$W65-$X65:$AG65)))) | AR65: =ROUND(N65-X65-AH65,2) | AS65: =ROUND(O65-Y65-AI65,2) | AT65: =ROUND(P65-Z65-AJ65,2) | AU65: =ROUND(Q65-AA65-AK65,2) | AV65: =ROUND(R65-AB65-AL65,2) | AW65: =ROUND(S65-AC65-AM65,2) | AX65: =ROUND(T65-AD65-AN65,2) | AY65: =ROUND(U65-AE65-AO65,2) | ... BA65: =ROUND(W65-AG65-AQ65,2) | BB65: =SUM(AR65:BA65)
A66: 62 | B66: =EOMONTH(TODAY(),61) | C66: =MAX(0,(SUM('My Loans'!$E$6:$E$15)+'My Loans'!$D$3)-SUM($X66:$AG66)) | D66: =MAX(0,AR65) | E66: =MAX(0,AS65) | F66: =MAX(0,AT65) | G66: =MAX(0,AU65) | H66: =MAX(0,AV65) | I66: =MAX(0,AW65) | J66: =MAX(0,AX65) | K66: =MAX(0,AY65) | ... M66: =MAX(0,BA65) | N66: =IF(D66<0.5,0,D66*(1+N('My Loans'!D6)/1200)) | O66: =IF(E66<0.5,0,E66*(1+N('My Loans'!D7)/1200)) | P66: =IF(F66<0.5,0,F66*(1+N('My Loans'!D8)/1200)) | Q66: =IF(G66<0.5,0,G66*(1+N('My Loans'!D9)/1200)) | R66: =IF(H66<0.5,0,H66*(1+N('My Loans'!D10)/1200)) | S66: =IF(I66<0.5,0,I66*(1+N('My Loans'!D11)/1200)) | T66: =IF(J66<0.5,0,J66*(1+N('My Loans'!D12)/1200)) | U66: =IF(K66<0.5,0,K66*(1+N('My Loans'!D13)/1200)) | V66: =IF(L66<0.5,0,L66*(1+N('My Loans'!D14)/1200)) | W66: =IF(M66<0.5,0,M66*(1+N('My Loans'!D15)/1200)) | X66: =MIN(N66,N('My Loans'!E6)) | Y66: =MIN(O66,N('My Loans'!E7)) | Z66: =MIN(P66,N('My Loans'!E8)) | AA66: =MIN(Q66,N('My Loans'!E9)) | AB66: =MIN(R66,N('My Loans'!E10)) | AC66: =MIN(S66,N('My Loans'!E11)) | AD66: =MIN(T66,N('My Loans'!E12)) | AE66: =MIN(U66,N('My Loans'!E13)) | AF66: =MIN(V66,N('My Loans'!E14)) | AG66: =MIN(W66,N('My Loans'!E15)) | AH66: =MIN(N66-X66,MAX(0,$C66-SUMPRODUCT(($D$3:$M$3<D$3)*($N66:$W66-$X66:$AG66)))) | AI66: =MIN(O66-Y66,MAX(0,$C66-SUMPRODUCT(($D$3:$M$3<E$3)*($N66:$W66-$X66:$AG66)))) | AJ66: =MIN(P66-Z66,MAX(0,$C66-SUMPRODUCT(($D$3:$M$3<F$3)*($N66:$W66-$X66:$AG66)))) | AK66: =MIN(Q66-AA66,MAX(0,$C66-SUMPRODUCT(($D$3:$M$3<G$3)*($N66:$W66-$X66:$AG66)))) | AL66: =MIN(R66-AB66,MAX(0,$C66-SUMPRODUCT(($D$3:$M$3<H$3)*($N66:$W66-$X66:$AG66)))) | AM66: =MIN(S66-AC66,MAX(0,$C66-SUMPRODUCT(($D$3:$M$3<I$3)*($N66:$W66-$X66:$AG66)))) | AN66: =MIN(T66-AD66,MAX(0,$C66-SUMPRODUCT(($D$3:$M$3<J$3)*($N66:$W66-$X66:$AG66)))) | AO66: =MIN(U66-AE66,MAX(0,$C66-SUMPRODUCT(($D$3:$M$3<K$3)*($N66:$W66-$X66:$AG66)))) | ... AQ66: =MIN(W66-AG66,MAX(0,$C66-SUMPRODUCT(($D$3:$M$3<M$3)*($N66:$W66-$X66:$AG66)))) | AR66: =ROUND(N66-X66-AH66,2) | AS66: =ROUND(O66-Y66-AI66,2) | AT66: =ROUND(P66-Z66-AJ66,2) | AU66: =ROUND(Q66-AA66-AK66,2) | AV66: =ROUND(R66-AB66-AL66,2) | AW66: =ROUND(S66-AC66-AM66,2) | AX66: =ROUND(T66-AD66-AN66,2) | AY66: =ROUND(U66-AE66-AO66,2) | ... BA66: =ROUND(W66-AG66-AQ66,2) | BB66: =SUM(AR66:BA66)
A67: 63 | B67: =EOMONTH(TODAY(),62) | C67: =MAX(0,(SUM('My Loans'!$E$6:$E$15)+'My Loans'!$D$3)-SUM($X67:$AG67)) | D67: =MAX(0,AR66) | E67: =MAX(0,AS66) | F67: =MAX(0,AT66) | G67: =MAX(0,AU66) | H67: =MAX(0,AV66) | I67: =MAX(0,AW66) | J67: =MAX(0,AX66) | K67: =MAX(0,AY66) | ... M67: =MAX(0,BA66) | N67: =IF(D67<0.5,0,D67*(1+N('My Loans'!D6)/1200)) | O67: =IF(E67<0.5,0,E67*(1+N('My Loans'!D7)/1200)) | P67: =IF(F67<0.5,0,F67*(1+N('My Loans'!D8)/1200)) | Q67: =IF(G67<0.5,0,G67*(1+N('My Loans'!D9)/1200)) | R67: =IF(H67<0.5,0,H67*(1+N('My Loans'!D10)/1200)) | S67: =IF(I67<0.5,0,I67*(1+N('My Loans'!D11)/1200)) | T67: =IF(J67<0.5,0,J67*(1+N('My Loans'!D12)/1200)) | U67: =IF(K67<0.5,0,K67*(1+N('My Loans'!D13)/1200)) | V67: =IF(L67<0.5,0,L67*(1+N('My Loans'!D14)/1200)) | W67: =IF(M67<0.5,0,M67*(1+N('My Loans'!D15)/1200)) | X67: =MIN(N67,N('My Loans'!E6)) | Y67: =MIN(O67,N('My Loans'!E7)) | Z67: =MIN(P67,N('My Loans'!E8)) | AA67: =MIN(Q67,N('My Loans'!E9)) | AB67: =MIN(R67,N('My Loans'!E10)) | AC67: =MIN(S67,N('My Loans'!E11)) | AD67: =MIN(T67,N('My Loans'!E12)) | AE67: =MIN(U67,N('My Loans'!E13)) | AF67: =MIN(V67,N('My Loans'!E14)) | AG67: =MIN(W67,N('My Loans'!E15)) | AH67: =MIN(N67-X67,MAX(0,$C67-SUMPRODUCT(($D$3:$M$3<D$3)*($N67:$W67-$X67:$AG67)))) | AI67: =MIN(O67-Y67,MAX(0,$C67-SUMPRODUCT(($D$3:$M$3<E$3)*($N67:$W67-$X67:$AG67)))) | AJ67: =MIN(P67-Z67,MAX(0,$C67-SUMPRODUCT(($D$3:$M$3<F$3)*($N67:$W67-$X67:$AG67)))) | AK67: =MIN(Q67-AA67,MAX(0,$C67-SUMPRODUCT(($D$3:$M$3<G$3)*($N67:$W67-$X67:$AG67)))) | AL67: =MIN(R67-AB67,MAX(0,$C67-SUMPRODUCT(($D$3:$M$3<H$3)*($N67:$W67-$X67:$AG67)))) | AM67: =MIN(S67-AC67,MAX(0,$C67-SUMPRODUCT(($D$3:$M$3<I$3)*($N67:$W67-$X67:$AG67)))) | AN67: =MIN(T67-AD67,MAX(0,$C67-SUMPRODUCT(($D$3:$M$3<J$3)*($N67:$W67-$X67:$AG67)))) | AO67: =MIN(U67-AE67,MAX(0,$C67-SUMPRODUCT(($D$3:$M$3<K$3)*($N67:$W67-$X67:$AG67)))) | ... AQ67: =MIN(W67-AG67,MAX(0,$C67-SUMPRODUCT(($D$3:$M$3<M$3)*($N67:$W67-$X67:$AG67)))) | AR67: =ROUND(N67-X67-AH67,2) | AS67: =ROUND(O67-Y67-AI67,2) | AT67: =ROUND(P67-Z67-AJ67,2) | AU67: =ROUND(Q67-AA67-AK67,2) | AV67: =ROUND(R67-AB67-AL67,2) | AW67: =ROUND(S67-AC67-AM67,2) | AX67: =ROUND(T67-AD67-AN67,2) | AY67: =ROUND(U67-AE67-AO67,2) | ... BA67: =ROUND(W67-AG67-AQ67,2) | BB67: =SUM(AR67:BA67)
A68: 64 | B68: =EOMONTH(TODAY(),63) | C68: =MAX(0,(SUM('My Loans'!$E$6:$E$15)+'My Loans'!$D$3)-SUM($X68:$AG68)) | D68: =MAX(0,AR67) | E68: =MAX(0,AS67) | F68: =MAX(0,AT67) | G68: =MAX(0,AU67) | H68: =MAX(0,AV67) | I68: =MAX(0,AW67) | J68: =MAX(0,AX67) | K68: =MAX(0,AY67) | ... M68: =MAX(0,BA67) | N68: =IF(D68<0.5,0,D68*(1+N('My Loans'!D6)/1200)) | O68: =IF(E68<0.5,0,E68*(1+N('My Loans'!D7)/1200)) | P68: =IF(F68<0.5,0,F68*(1+N('My Loans'!D8)/1200)) | Q68: =IF(G68<0.5,0,G68*(1+N('My Loans'!D9)/1200)) | R68: =IF(H68<0.5,0,H68*(1+N('My Loans'!D10)/1200)) | S68: =IF(I68<0.5,0,I68*(1+N('My Loans'!D11)/1200)) | T68: =IF(J68<0.5,0,J68*(1+N('My Loans'!D12)/1200)) | U68: =IF(K68<0.5,0,K68*(1+N('My Loans'!D13)/1200)) | V68: =IF(L68<0.5,0,L68*(1+N('My Loans'!D14)/1200)) | W68: =IF(M68<0.5,0,M68*(1+N('My Loans'!D15)/1200)) | X68: =MIN(N68,N('My Loans'!E6)) | Y68: =MIN(O68,N('My Loans'!E7)) | Z68: =MIN(P68,N('My Loans'!E8)) | AA68: =MIN(Q68,N('My Loans'!E9)) | AB68: =MIN(R68,N('My Loans'!E10)) | AC68: =MIN(S68,N('My Loans'!E11)) | AD68: =MIN(T68,N('My Loans'!E12)) | AE68: =MIN(U68,N('My Loans'!E13)) | AF68: =MIN(V68,N('My Loans'!E14)) | AG68: =MIN(W68,N('My Loans'!E15)) | AH68: =MIN(N68-X68,MAX(0,$C68-SUMPRODUCT(($D$3:$M$3<D$3)*($N68:$W68-$X68:$AG68)))) | AI68: =MIN(O68-Y68,MAX(0,$C68-SUMPRODUCT(($D$3:$M$3<E$3)*($N68:$W68-$X68:$AG68)))) | AJ68: =MIN(P68-Z68,MAX(0,$C68-SUMPRODUCT(($D$3:$M$3<F$3)*($N68:$W68-$X68:$AG68)))) | AK68: =MIN(Q68-AA68,MAX(0,$C68-SUMPRODUCT(($D$3:$M$3<G$3)*($N68:$W68-$X68:$AG68)))) | AL68: =MIN(R68-AB68,MAX(0,$C68-SUMPRODUCT(($D$3:$M$3<H$3)*($N68:$W68-$X68:$AG68)))) | AM68: =MIN(S68-AC68,MAX(0,$C68-SUMPRODUCT(($D$3:$M$3<I$3)*($N68:$W68-$X68:$AG68)))) | AN68: =MIN(T68-AD68,MAX(0,$C68-SUMPRODUCT(($D$3:$M$3<J$3)*($N68:$W68-$X68:$AG68)))) | AO68: =MIN(U68-AE68,MAX(0,$C68-SUMPRODUCT(($D$3:$M$3<K$3)*($N68:$W68-$X68:$AG68)))) | ... AQ68: =MIN(W68-AG68,MAX(0,$C68-SUMPRODUCT(($D$3:$M$3<M$3)*($N68:$W68-$X68:$AG68)))) | AR68: =ROUND(N68-X68-AH68,2) | AS68: =ROUND(O68-Y68-AI68,2) | AT68: =ROUND(P68-Z68-AJ68,2) | AU68: =ROUND(Q68-AA68-AK68,2) | AV68: =ROUND(R68-AB68-AL68,2) | AW68: =ROUND(S68-AC68-AM68,2) | AX68: =ROUND(T68-AD68-AN68,2) | AY68: =ROUND(U68-AE68-AO68,2) | ... BA68: =ROUND(W68-AG68-AQ68,2) | BB68: =SUM(AR68:BA68)
A69: 65 | B69: =EOMONTH(TODAY(),64) | C69: =MAX(0,(SUM('My Loans'!$E$6:$E$15)+'My Loans'!$D$3)-SUM($X69:$AG69)) | D69: =MAX(0,AR68) | E69: =MAX(0,AS68) | F69: =MAX(0,AT68) | G69: =MAX(0,AU68) | H69: =MAX(0,AV68) | I69: =MAX(0,AW68) | J69: =MAX(0,AX68) | K69: =MAX(0,AY68) | ... M69: =MAX(0,BA68) | N69: =IF(D69<0.5,0,D69*(1+N('My Loans'!D6)/1200)) | O69: =IF(E69<0.5,0,E69*(1+N('My Loans'!D7)/1200)) | P69: =IF(F69<0.5,0,F69*(1+N('My Loans'!D8)/1200)) | Q69: =IF(G69<0.5,0,G69*(1+N('My Loans'!D9)/1200)) | R69: =IF(H69<0.5,0,H69*(1+N('My Loans'!D10)/1200)) | S69: =IF(I69<0.5,0,I69*(1+N('My Loans'!D11)/1200)) | T69: =IF(J69<0.5,0,J69*(1+N('My Loans'!D12)/1200)) | U69: =IF(K69<0.5,0,K69*(1+N('My Loans'!D13)/1200)) | V69: =IF(L69<0.5,0,L69*(1+N('My Loans'!D14)/1200)) | W69: =IF(M69<0.5,0,M69*(1+N('My Loans'!D15)/1200)) | X69: =MIN(N69,N('My Loans'!E6)) | Y69: =MIN(O69,N('My Loans'!E7)) | Z69: =MIN(P69,N('My Loans'!E8)) | AA69: =MIN(Q69,N('My Loans'!E9)) | AB69: =MIN(R69,N('My Loans'!E10)) | AC69: =MIN(S69,N('My Loans'!E11)) | AD69: =MIN(T69,N('My Loans'!E12)) | AE69: =MIN(U69,N('My Loans'!E13)) | AF69: =MIN(V69,N('My Loans'!E14)) | AG69: =MIN(W69,N('My Loans'!E15)) | AH69: =MIN(N69-X69,MAX(0,$C69-SUMPRODUCT(($D$3:$M$3<D$3)*($N69:$W69-$X69:$AG69)))) | AI69: =MIN(O69-Y69,MAX(0,$C69-SUMPRODUCT(($D$3:$M$3<E$3)*($N69:$W69-$X69:$AG69)))) | AJ69: =MIN(P69-Z69,MAX(0,$C69-SUMPRODUCT(($D$3:$M$3<F$3)*($N69:$W69-$X69:$AG69)))) | AK69: =MIN(Q69-AA69,MAX(0,$C69-SUMPRODUCT(($D$3:$M$3<G$3)*($N69:$W69-$X69:$AG69)))) | AL69: =MIN(R69-AB69,MAX(0,$C69-SUMPRODUCT(($D$3:$M$3<H$3)*($N69:$W69-$X69:$AG69)))) | AM69: =MIN(S69-AC69,MAX(0,$C69-SUMPRODUCT(($D$3:$M$3<I$3)*($N69:$W69-$X69:$AG69)))) | AN69: =MIN(T69-AD69,MAX(0,$C69-SUMPRODUCT(($D$3:$M$3<J$3)*($N69:$W69-$X69:$AG69)))) | AO69: =MIN(U69-AE69,MAX(0,$C69-SUMPRODUCT(($D$3:$M$3<K$3)*($N69:$W69-$X69:$AG69)))) | ... AQ69: =MIN(W69-AG69,MAX(0,$C69-SUMPRODUCT(($D$3:$M$3<M$3)*($N69:$W69-$X69:$AG69)))) | AR69: =ROUND(N69-X69-AH69,2) | AS69: =ROUND(O69-Y69-AI69,2) | AT69: =ROUND(P69-Z69-AJ69,2) | AU69: =ROUND(Q69-AA69-AK69,2) | AV69: =ROUND(R69-AB69-AL69,2) | AW69: =ROUND(S69-AC69-AM69,2) | AX69: =ROUND(T69-AD69-AN69,2) | AY69: =ROUND(U69-AE69-AO69,2) | ... BA69: =ROUND(W69-AG69-AQ69,2) | BB69: =SUM(AR69:BA69)
A70: 66 | B70: =EOMONTH(TODAY(),65) | C70: =MAX(0,(SUM('My Loans'!$E$6:$E$15)+'My Loans'!$D$3)-SUM($X70:$AG70)) | D70: =MAX(0,AR69) | E70: =MAX(0,AS69) | F70: =MAX(0,AT69) | G70: =MAX(0,AU69) | H70: =MAX(0,AV69) | I70: =MAX(0,AW69) | J70: =MAX(0,AX69) | K70: =MAX(0,AY69) | ... M70: =MAX(0,BA69) | N70: =IF(D70<0.5,0,D70*(1+N('My Loans'!D6)/1200)) | O70: =IF(E70<0.5,0,E70*(1+N('My Loans'!D7)/1200)) | P70: =IF(F70<0.5,0,F70*(1+N('My Loans'!D8)/1200)) | Q70: =IF(G70<0.5,0,G70*(1+N('My Loans'!D9)/1200)) | R70: =IF(H70<0.5,0,H70*(1+N('My Loans'!D10)/1200)) | S70: =IF(I70<0.5,0,I70*(1+N('My Loans'!D11)/1200)) | T70: =IF(J70<0.5,0,J70*(1+N('My Loans'!D12)/1200)) | U70: =IF(K70<0.5,0,K70*(1+N('My Loans'!D13)/1200)) | V70: =IF(L70<0.5,0,L70*(1+N('My Loans'!D14)/1200)) | W70: =IF(M70<0.5,0,M70*(1+N('My Loans'!D15)/1200)) | X70: =MIN(N70,N('My Loans'!E6)) | Y70: =MIN(O70,N('My Loans'!E7)) | Z70: =MIN(P70,N('My Loans'!E8)) | AA70: =MIN(Q70,N('My Loans'!E9)) | AB70: =MIN(R70,N('My Loans'!E10)) | AC70: =MIN(S70,N('My Loans'!E11)) | AD70: =MIN(T70,N('My Loans'!E12)) | AE70: =MIN(U70,N('My Loans'!E13)) | AF70: =MIN(V70,N('My Loans'!E14)) | AG70: =MIN(W70,N('My Loans'!E15)) | AH70: =MIN(N70-X70,MAX(0,$C70-SUMPRODUCT(($D$3:$M$3<D$3)*($N70:$W70-$X70:$AG70)))) | AI70: =MIN(O70-Y70,MAX(0,$C70-SUMPRODUCT(($D$3:$M$3<E$3)*($N70:$W70-$X70:$AG70)))) | AJ70: =MIN(P70-Z70,MAX(0,$C70-SUMPRODUCT(($D$3:$M$3<F$3)*($N70:$W70-$X70:$AG70)))) | AK70: =MIN(Q70-AA70,MAX(0,$C70-SUMPRODUCT(($D$3:$M$3<G$3)*($N70:$W70-$X70:$AG70)))) | AL70: =MIN(R70-AB70,MAX(0,$C70-SUMPRODUCT(($D$3:$M$3<H$3)*($N70:$W70-$X70:$AG70)))) | AM70: =MIN(S70-AC70,MAX(0,$C70-SUMPRODUCT(($D$3:$M$3<I$3)*($N70:$W70-$X70:$AG70)))) | AN70: =MIN(T70-AD70,MAX(0,$C70-SUMPRODUCT(($D$3:$M$3<J$3)*($N70:$W70-$X70:$AG70)))) | AO70: =MIN(U70-AE70,MAX(0,$C70-SUMPRODUCT(($D$3:$M$3<K$3)*($N70:$W70-$X70:$AG70)))) | ... AQ70: =MIN(W70-AG70,MAX(0,$C70-SUMPRODUCT(($D$3:$M$3<M$3)*($N70:$W70-$X70:$AG70)))) | AR70: =ROUND(N70-X70-AH70,2) | AS70: =ROUND(O70-Y70-AI70,2) | AT70: =ROUND(P70-Z70-AJ70,2) | AU70: =ROUND(Q70-AA70-AK70,2) | AV70: =ROUND(R70-AB70-AL70,2) | AW70: =ROUND(S70-AC70-AM70,2) | AX70: =ROUND(T70-AD70-AN70,2) | AY70: =ROUND(U70-AE70-AO70,2) | ... BA70: =ROUND(W70-AG70-AQ70,2) | BB70: =SUM(AR70:BA70)
A71: 67 | B71: =EOMONTH(TODAY(),66) | C71: =MAX(0,(SUM('My Loans'!$E$6:$E$15)+'My Loans'!$D$3)-SUM($X71:$AG71)) | D71: =MAX(0,AR70) | E71: =MAX(0,AS70) | F71: =MAX(0,AT70) | G71: =MAX(0,AU70) | H71: =MAX(0,AV70) | I71: =MAX(0,AW70) | J71: =MAX(0,AX70) | K71: =MAX(0,AY70) | ... M71: =MAX(0,BA70) | N71: =IF(D71<0.5,0,D71*(1+N('My Loans'!D6)/1200)) | O71: =IF(E71<0.5,0,E71*(1+N('My Loans'!D7)/1200)) | P71: =IF(F71<0.5,0,F71*(1+N('My Loans'!D8)/1200)) | Q71: =IF(G71<0.5,0,G71*(1+N('My Loans'!D9)/1200)) | R71: =IF(H71<0.5,0,H71*(1+N('My Loans'!D10)/1200)) | S71: =IF(I71<0.5,0,I71*(1+N('My Loans'!D11)/1200)) | T71: =IF(J71<0.5,0,J71*(1+N('My Loans'!D12)/1200)) | U71: =IF(K71<0.5,0,K71*(1+N('My Loans'!D13)/1200)) | V71: =IF(L71<0.5,0,L71*(1+N('My Loans'!D14)/1200)) | W71: =IF(M71<0.5,0,M71*(1+N('My Loans'!D15)/1200)) | X71: =MIN(N71,N('My Loans'!E6)) | Y71: =MIN(O71,N('My Loans'!E7)) | Z71: =MIN(P71,N('My Loans'!E8)) | AA71: =MIN(Q71,N('My Loans'!E9)) | AB71: =MIN(R71,N('My Loans'!E10)) | AC71: =MIN(S71,N('My Loans'!E11)) | AD71: =MIN(T71,N('My Loans'!E12)) | AE71: =MIN(U71,N('My Loans'!E13)) | AF71: =MIN(V71,N('My Loans'!E14)) | AG71: =MIN(W71,N('My Loans'!E15)) | AH71: =MIN(N71-X71,MAX(0,$C71-SUMPRODUCT(($D$3:$M$3<D$3)*($N71:$W71-$X71:$AG71)))) | AI71: =MIN(O71-Y71,MAX(0,$C71-SUMPRODUCT(($D$3:$M$3<E$3)*($N71:$W71-$X71:$AG71)))) | AJ71: =MIN(P71-Z71,MAX(0,$C71-SUMPRODUCT(($D$3:$M$3<F$3)*($N71:$W71-$X71:$AG71)))) | AK71: =MIN(Q71-AA71,MAX(0,$C71-SUMPRODUCT(($D$3:$M$3<G$3)*($N71:$W71-$X71:$AG71)))) | AL71: =MIN(R71-AB71,MAX(0,$C71-SUMPRODUCT(($D$3:$M$3<H$3)*($N71:$W71-$X71:$AG71)))) | AM71: =MIN(S71-AC71,MAX(0,$C71-SUMPRODUCT(($D$3:$M$3<I$3)*($N71:$W71-$X71:$AG71)))) | AN71: =MIN(T71-AD71,MAX(0,$C71-SUMPRODUCT(($D$3:$M$3<J$3)*($N71:$W71-$X71:$AG71)))) | AO71: =MIN(U71-AE71,MAX(0,$C71-SUMPRODUCT(($D$3:$M$3<K$3)*($N71:$W71-$X71:$AG71)))) | ... AQ71: =MIN(W71-AG71,MAX(0,$C71-SUMPRODUCT(($D$3:$M$3<M$3)*($N71:$W71-$X71:$AG71)))) | AR71: =ROUND(N71-X71-AH71,2) | AS71: =ROUND(O71-Y71-AI71,2) | AT71: =ROUND(P71-Z71-AJ71,2) | AU71: =ROUND(Q71-AA71-AK71,2) | AV71: =ROUND(R71-AB71-AL71,2) | AW71: =ROUND(S71-AC71-AM71,2) | AX71: =ROUND(T71-AD71-AN71,2) | AY71: =ROUND(U71-AE71-AO71,2) | ... BA71: =ROUND(W71-AG71-AQ71,2) | BB71: =SUM(AR71:BA71)
A72: 68 | B72: =EOMONTH(TODAY(),67) | C72: =MAX(0,(SUM('My Loans'!$E$6:$E$15)+'My Loans'!$D$3)-SUM($X72:$AG72)) | D72: =MAX(0,AR71) | E72: =MAX(0,AS71) | F72: =MAX(0,AT71) | G72: =MAX(0,AU71) | H72: =MAX(0,AV71) | I72: =MAX(0,AW71) | J72: =MAX(0,AX71) | K72: =MAX(0,AY71) | ... M72: =MAX(0,BA71) | N72: =IF(D72<0.5,0,D72*(1+N('My Loans'!D6)/1200)) | O72: =IF(E72<0.5,0,E72*(1+N('My Loans'!D7)/1200)) | P72: =IF(F72<0.5,0,F72*(1+N('My Loans'!D8)/1200)) | Q72: =IF(G72<0.5,0,G72*(1+N('My Loans'!D9)/1200)) | R72: =IF(H72<0.5,0,H72*(1+N('My Loans'!D10)/1200)) | S72: =IF(I72<0.5,0,I72*(1+N('My Loans'!D11)/1200)) | T72: =IF(J72<0.5,0,J72*(1+N('My Loans'!D12)/1200)) | U72: =IF(K72<0.5,0,K72*(1+N('My Loans'!D13)/1200)) | V72: =IF(L72<0.5,0,L72*(1+N('My Loans'!D14)/1200)) | W72: =IF(M72<0.5,0,M72*(1+N('My Loans'!D15)/1200)) | X72: =MIN(N72,N('My Loans'!E6)) | Y72: =MIN(O72,N('My Loans'!E7)) | Z72: =MIN(P72,N('My Loans'!E8)) | AA72: =MIN(Q72,N('My Loans'!E9)) | AB72: =MIN(R72,N('My Loans'!E10)) | AC72: =MIN(S72,N('My Loans'!E11)) | AD72: =MIN(T72,N('My Loans'!E12)) | AE72: =MIN(U72,N('My Loans'!E13)) | AF72: =MIN(V72,N('My Loans'!E14)) | AG72: =MIN(W72,N('My Loans'!E15)) | AH72: =MIN(N72-X72,MAX(0,$C72-SUMPRODUCT(($D$3:$M$3<D$3)*($N72:$W72-$X72:$AG72)))) | AI72: =MIN(O72-Y72,MAX(0,$C72-SUMPRODUCT(($D$3:$M$3<E$3)*($N72:$W72-$X72:$AG72)))) | AJ72: =MIN(P72-Z72,MAX(0,$C72-SUMPRODUCT(($D$3:$M$3<F$3)*($N72:$W72-$X72:$AG72)))) | AK72: =MIN(Q72-AA72,MAX(0,$C72-SUMPRODUCT(($D$3:$M$3<G$3)*($N72:$W72-$X72:$AG72)))) | AL72: =MIN(R72-AB72,MAX(0,$C72-SUMPRODUCT(($D$3:$M$3<H$3)*($N72:$W72-$X72:$AG72)))) | AM72: =MIN(S72-AC72,MAX(0,$C72-SUMPRODUCT(($D$3:$M$3<I$3)*($N72:$W72-$X72:$AG72)))) | AN72: =MIN(T72-AD72,MAX(0,$C72-SUMPRODUCT(($D$3:$M$3<J$3)*($N72:$W72-$X72:$AG72)))) | AO72: =MIN(U72-AE72,MAX(0,$C72-SUMPRODUCT(($D$3:$M$3<K$3)*($N72:$W72-$X72:$AG72)))) | ... AQ72: =MIN(W72-AG72,MAX(0,$C72-SUMPRODUCT(($D$3:$M$3<M$3)*($N72:$W72-$X72:$AG72)))) | AR72: =ROUND(N72-X72-AH72,2) | AS72: =ROUND(O72-Y72-AI72,2) | AT72: =ROUND(P72-Z72-AJ72,2) | AU72: =ROUND(Q72-AA72-AK72,2) | AV72: =ROUND(R72-AB72-AL72,2) | AW72: =ROUND(S72-AC72-AM72,2) | AX72: =ROUND(T72-AD72-AN72,2) | AY72: =ROUND(U72-AE72-AO72,2) | ... BA72: =ROUND(W72-AG72-AQ72,2) | BB72: =SUM(AR72:BA72)
A73: 69 | B73: =EOMONTH(TODAY(),68) | C73: =MAX(0,(SUM('My Loans'!$E$6:$E$15)+'My Loans'!$D$3)-SUM($X73:$AG73)) | D73: =MAX(0,AR72) | E73: =MAX(0,AS72) | F73: =MAX(0,AT72) | G73: =MAX(0,AU72) | H73: =MAX(0,AV72) | I73: =MAX(0,AW72) | J73: =MAX(0,AX72) | K73: =MAX(0,AY72) | ... M73: =MAX(0,BA72) | N73: =IF(D73<0.5,0,D73*(1+N('My Loans'!D6)/1200)) | O73: =IF(E73<0.5,0,E73*(1+N('My Loans'!D7)/1200)) | P73: =IF(F73<0.5,0,F73*(1+N('My Loans'!D8)/1200)) | Q73: =IF(G73<0.5,0,G73*(1+N('My Loans'!D9)/1200)) | R73: =IF(H73<0.5,0,H73*(1+N('My Loans'!D10)/1200)) | S73: =IF(I73<0.5,0,I73*(1+N('My Loans'!D11)/1200)) | T73: =IF(J73<0.5,0,J73*(1+N('My Loans'!D12)/1200)) | U73: =IF(K73<0.5,0,K73*(1+N('My Loans'!D13)/1200)) | V73: =IF(L73<0.5,0,L73*(1+N('My Loans'!D14)/1200)) | W73: =IF(M73<0.5,0,M73*(1+N('My Loans'!D15)/1200)) | X73: =MIN(N73,N('My Loans'!E6)) | Y73: =MIN(O73,N('My Loans'!E7)) | Z73: =MIN(P73,N('My Loans'!E8)) | AA73: =MIN(Q73,N('My Loans'!E9)) | AB73: =MIN(R73,N('My Loans'!E10)) | AC73: =MIN(S73,N('My Loans'!E11)) | AD73: =MIN(T73,N('My Loans'!E12)) | AE73: =MIN(U73,N('My Loans'!E13)) | AF73: =MIN(V73,N('My Loans'!E14)) | AG73: =MIN(W73,N('My Loans'!E15)) | AH73: =MIN(N73-X73,MAX(0,$C73-SUMPRODUCT(($D$3:$M$3<D$3)*($N73:$W73-$X73:$AG73)))) | AI73: =MIN(O73-Y73,MAX(0,$C73-SUMPRODUCT(($D$3:$M$3<E$3)*($N73:$W73-$X73:$AG73)))) | AJ73: =MIN(P73-Z73,MAX(0,$C73-SUMPRODUCT(($D$3:$M$3<F$3)*($N73:$W73-$X73:$AG73)))) | AK73: =MIN(Q73-AA73,MAX(0,$C73-SUMPRODUCT(($D$3:$M$3<G$3)*($N73:$W73-$X73:$AG73)))) | AL73: =MIN(R73-AB73,MAX(0,$C73-SUMPRODUCT(($D$3:$M$3<H$3)*($N73:$W73-$X73:$AG73)))) | AM73: =MIN(S73-AC73,MAX(0,$C73-SUMPRODUCT(($D$3:$M$3<I$3)*($N73:$W73-$X73:$AG73)))) | AN73: =MIN(T73-AD73,MAX(0,$C73-SUMPRODUCT(($D$3:$M$3<J$3)*($N73:$W73-$X73:$AG73)))) | AO73: =MIN(U73-AE73,MAX(0,$C73-SUMPRODUCT(($D$3:$M$3<K$3)*($N73:$W73-$X73:$AG73)))) | ... AQ73: =MIN(W73-AG73,MAX(0,$C73-SUMPRODUCT(($D$3:$M$3<M$3)*($N73:$W73-$X73:$AG73)))) | AR73: =ROUND(N73-X73-AH73,2) | AS73: =ROUND(O73-Y73-AI73,2) | AT73: =ROUND(P73-Z73-AJ73,2) | AU73: =ROUND(Q73-AA73-AK73,2) | AV73: =ROUND(R73-AB73-AL73,2) | AW73: =ROUND(S73-AC73-AM73,2) | AX73: =ROUND(T73-AD73-AN73,2) | AY73: =ROUND(U73-AE73-AO73,2) | ... BA73: =ROUND(W73-AG73-AQ73,2) | BB73: =SUM(AR73:BA73)
A74: 70 | B74: =EOMONTH(TODAY(),69) | C74: =MAX(0,(SUM('My Loans'!$E$6:$E$15)+'My Loans'!$D$3)-SUM($X74:$AG74)) | D74: =MAX(0,AR73) | E74: =MAX(0,AS73) | F74: =MAX(0,AT73) | G74: =MAX(0,AU73) | H74: =MAX(0,AV73) | I74: =MAX(0,AW73) | J74: =MAX(0,AX73) | K74: =MAX(0,AY73) | ... M74: =MAX(0,BA73) | N74: =IF(D74<0.5,0,D74*(1+N('My Loans'!D6)/1200)) | O74: =IF(E74<0.5,0,E74*(1+N('My Loans'!D7)/1200)) | P74: =IF(F74<0.5,0,F74*(1+N('My Loans'!D8)/1200)) | Q74: =IF(G74<0.5,0,G74*(1+N('My Loans'!D9)/1200)) | R74: =IF(H74<0.5,0,H74*(1+N('My Loans'!D10)/1200)) | S74: =IF(I74<0.5,0,I74*(1+N('My Loans'!D11)/1200)) | T74: =IF(J74<0.5,0,J74*(1+N('My Loans'!D12)/1200)) | U74: =IF(K74<0.5,0,K74*(1+N('My Loans'!D13)/1200)) | V74: =IF(L74<0.5,0,L74*(1+N('My Loans'!D14)/1200)) | W74: =IF(M74<0.5,0,M74*(1+N('My Loans'!D15)/1200)) | X74: =MIN(N74,N('My Loans'!E6)) | Y74: =MIN(O74,N('My Loans'!E7)) | Z74: =MIN(P74,N('My Loans'!E8)) | AA74: =MIN(Q74,N('My Loans'!E9)) | AB74: =MIN(R74,N('My Loans'!E10)) | AC74: =MIN(S74,N('My Loans'!E11)) | AD74: =MIN(T74,N('My Loans'!E12)) | AE74: =MIN(U74,N('My Loans'!E13)) | AF74: =MIN(V74,N('My Loans'!E14)) | AG74: =MIN(W74,N('My Loans'!E15)) | AH74: =MIN(N74-X74,MAX(0,$C74-SUMPRODUCT(($D$3:$M$3<D$3)*($N74:$W74-$X74:$AG74)))) | AI74: =MIN(O74-Y74,MAX(0,$C74-SUMPRODUCT(($D$3:$M$3<E$3)*($N74:$W74-$X74:$AG74)))) | AJ74: =MIN(P74-Z74,MAX(0,$C74-SUMPRODUCT(($D$3:$M$3<F$3)*($N74:$W74-$X74:$AG74)))) | AK74: =MIN(Q74-AA74,MAX(0,$C74-SUMPRODUCT(($D$3:$M$3<G$3)*($N74:$W74-$X74:$AG74)))) | AL74: =MIN(R74-AB74,MAX(0,$C74-SUMPRODUCT(($D$3:$M$3<H$3)*($N74:$W74-$X74:$AG74)))) | AM74: =MIN(S74-AC74,MAX(0,$C74-SUMPRODUCT(($D$3:$M$3<I$3)*($N74:$W74-$X74:$AG74)))) | AN74: =MIN(T74-AD74,MAX(0,$C74-SUMPRODUCT(($D$3:$M$3<J$3)*($N74:$W74-$X74:$AG74)))) | AO74: =MIN(U74-AE74,MAX(0,$C74-SUMPRODUCT(($D$3:$M$3<K$3)*($N74:$W74-$X74:$AG74)))) | ... AQ74: =MIN(W74-AG74,MAX(0,$C74-SUMPRODUCT(($D$3:$M$3<M$3)*($N74:$W74-$X74:$AG74)))) | AR74: =ROUND(N74-X74-AH74,2) | AS74: =ROUND(O74-Y74-AI74,2) | AT74: =ROUND(P74-Z74-AJ74,2) | AU74: =ROUND(Q74-AA74-AK74,2) | AV74: =ROUND(R74-AB74-AL74,2) | AW74: =ROUND(S74-AC74-AM74,2) | AX74: =ROUND(T74-AD74-AN74,2) | AY74: =ROUND(U74-AE74-AO74,2) | ... BA74: =ROUND(W74-AG74-AQ74,2) | BB74: =SUM(AR74:BA74)
A75: 71 | B75: =EOMONTH(TODAY(),70) | C75: =MAX(0,(SUM('My Loans'!$E$6:$E$15)+'My Loans'!$D$3)-SUM($X75:$AG75)) | D75: =MAX(0,AR74) | E75: =MAX(0,AS74) | F75: =MAX(0,AT74) | G75: =MAX(0,AU74) | H75: =MAX(0,AV74) | I75: =MAX(0,AW74) | J75: =MAX(0,AX74) | K75: =MAX(0,AY74) | ... M75: =MAX(0,BA74) | N75: =IF(D75<0.5,0,D75*(1+N('My Loans'!D6)/1200)) | O75: =IF(E75<0.5,0,E75*(1+N('My Loans'!D7)/1200)) | P75: =IF(F75<0.5,0,F75*(1+N('My Loans'!D8)/1200)) | Q75: =IF(G75<0.5,0,G75*(1+N('My Loans'!D9)/1200)) | R75: =IF(H75<0.5,0,H75*(1+N('My Loans'!D10)/1200)) | S75: =IF(I75<0.5,0,I75*(1+N('My Loans'!D11)/1200)) | T75: =IF(J75<0.5,0,J75*(1+N('My Loans'!D12)/1200)) | U75: =IF(K75<0.5,0,K75*(1+N('My Loans'!D13)/1200)) | V75: =IF(L75<0.5,0,L75*(1+N('My Loans'!D14)/1200)) | W75: =IF(M75<0.5,0,M75*(1+N('My Loans'!D15)/1200)) | X75: =MIN(N75,N('My Loans'!E6)) | Y75: =MIN(O75,N('My Loans'!E7)) | Z75: =MIN(P75,N('My Loans'!E8)) | AA75: =MIN(Q75,N('My Loans'!E9)) | AB75: =MIN(R75,N('My Loans'!E10)) | AC75: =MIN(S75,N('My Loans'!E11)) | AD75: =MIN(T75,N('My Loans'!E12)) | AE75: =MIN(U75,N('My Loans'!E13)) | AF75: =MIN(V75,N('My Loans'!E14)) | AG75: =MIN(W75,N('My Loans'!E15)) | AH75: =MIN(N75-X75,MAX(0,$C75-SUMPRODUCT(($D$3:$M$3<D$3)*($N75:$W75-$X75:$AG75)))) | AI75: =MIN(O75-Y75,MAX(0,$C75-SUMPRODUCT(($D$3:$M$3<E$3)*($N75:$W75-$X75:$AG75)))) | AJ75: =MIN(P75-Z75,MAX(0,$C75-SUMPRODUCT(($D$3:$M$3<F$3)*($N75:$W75-$X75:$AG75)))) | AK75: =MIN(Q75-AA75,MAX(0,$C75-SUMPRODUCT(($D$3:$M$3<G$3)*($N75:$W75-$X75:$AG75)))) | AL75: =MIN(R75-AB75,MAX(0,$C75-SUMPRODUCT(($D$3:$M$3<H$3)*($N75:$W75-$X75:$AG75)))) | AM75: =MIN(S75-AC75,MAX(0,$C75-SUMPRODUCT(($D$3:$M$3<I$3)*($N75:$W75-$X75:$AG75)))) | AN75: =MIN(T75-AD75,MAX(0,$C75-SUMPRODUCT(($D$3:$M$3<J$3)*($N75:$W75-$X75:$AG75)))) | AO75: =MIN(U75-AE75,MAX(0,$C75-SUMPRODUCT(($D$3:$M$3<K$3)*($N75:$W75-$X75:$AG75)))) | ... AQ75: =MIN(W75-AG75,MAX(0,$C75-SUMPRODUCT(($D$3:$M$3<M$3)*($N75:$W75-$X75:$AG75)))) | AR75: =ROUND(N75-X75-AH75,2) | AS75: =ROUND(O75-Y75-AI75,2) | AT75: =ROUND(P75-Z75-AJ75,2) | AU75: =ROUND(Q75-AA75-AK75,2) | AV75: =ROUND(R75-AB75-AL75,2) | AW75: =ROUND(S75-AC75-AM75,2) | AX75: =ROUND(T75-AD75-AN75,2) | AY75: =ROUND(U75-AE75-AO75,2) | ... BA75: =ROUND(W75-AG75-AQ75,2) | BB75: =SUM(AR75:BA75)
A76: 72 | B76: =EOMONTH(TODAY(),71) | C76: =MAX(0,(SUM('My Loans'!$E$6:$E$15)+'My Loans'!$D$3)-SUM($X76:$AG76)) | D76: =MAX(0,AR75) | E76: =MAX(0,AS75) | F76: =MAX(0,AT75) | G76: =MAX(0,AU75) | H76: =MAX(0,AV75) | I76: =MAX(0,AW75) | J76: =MAX(0,AX75) | K76: =MAX(0,AY75) | ... M76: =MAX(0,BA75) | N76: =IF(D76<0.5,0,D76*(1+N('My Loans'!D6)/1200)) | O76: =IF(E76<0.5,0,E76*(1+N('My Loans'!D7)/1200)) | P76: =IF(F76<0.5,0,F76*(1+N('My Loans'!D8)/1200)) | Q76: =IF(G76<0.5,0,G76*(1+N('My Loans'!D9)/1200)) | R76: =IF(H76<0.5,0,H76*(1+N('My Loans'!D10)/1200)) | S76: =IF(I76<0.5,0,I76*(1+N('My Loans'!D11)/1200)) | T76: =IF(J76<0.5,0,J76*(1+N('My Loans'!D12)/1200)) | U76: =IF(K76<0.5,0,K76*(1+N('My Loans'!D13)/1200)) | V76: =IF(L76<0.5,0,L76*(1+N('My Loans'!D14)/1200)) | W76: =IF(M76<0.5,0,M76*(1+N('My Loans'!D15)/1200)) | X76: =MIN(N76,N('My Loans'!E6)) | Y76: =MIN(O76,N('My Loans'!E7)) | Z76: =MIN(P76,N('My Loans'!E8)) | AA76: =MIN(Q76,N('My Loans'!E9)) | AB76: =MIN(R76,N('My Loans'!E10)) | AC76: =MIN(S76,N('My Loans'!E11)) | AD76: =MIN(T76,N('My Loans'!E12)) | AE76: =MIN(U76,N('My Loans'!E13)) | AF76: =MIN(V76,N('My Loans'!E14)) | AG76: =MIN(W76,N('My Loans'!E15)) | AH76: =MIN(N76-X76,MAX(0,$C76-SUMPRODUCT(($D$3:$M$3<D$3)*($N76:$W76-$X76:$AG76)))) | AI76: =MIN(O76-Y76,MAX(0,$C76-SUMPRODUCT(($D$3:$M$3<E$3)*($N76:$W76-$X76:$AG76)))) | AJ76: =MIN(P76-Z76,MAX(0,$C76-SUMPRODUCT(($D$3:$M$3<F$3)*($N76:$W76-$X76:$AG76)))) | AK76: =MIN(Q76-AA76,MAX(0,$C76-SUMPRODUCT(($D$3:$M$3<G$3)*($N76:$W76-$X76:$AG76)))) | AL76: =MIN(R76-AB76,MAX(0,$C76-SUMPRODUCT(($D$3:$M$3<H$3)*($N76:$W76-$X76:$AG76)))) | AM76: =MIN(S76-AC76,MAX(0,$C76-SUMPRODUCT(($D$3:$M$3<I$3)*($N76:$W76-$X76:$AG76)))) | AN76: =MIN(T76-AD76,MAX(0,$C76-SUMPRODUCT(($D$3:$M$3<J$3)*($N76:$W76-$X76:$AG76)))) | AO76: =MIN(U76-AE76,MAX(0,$C76-SUMPRODUCT(($D$3:$M$3<K$3)*($N76:$W76-$X76:$AG76)))) | ... AQ76: =MIN(W76-AG76,MAX(0,$C76-SUMPRODUCT(($D$3:$M$3<M$3)*($N76:$W76-$X76:$AG76)))) | AR76: =ROUND(N76-X76-AH76,2) | AS76: =ROUND(O76-Y76-AI76,2) | AT76: =ROUND(P76-Z76-AJ76,2) | AU76: =ROUND(Q76-AA76-AK76,2) | AV76: =ROUND(R76-AB76-AL76,2) | AW76: =ROUND(S76-AC76-AM76,2) | AX76: =ROUND(T76-AD76-AN76,2) | AY76: =ROUND(U76-AE76-AO76,2) | ... BA76: =ROUND(W76-AG76-AQ76,2) | BB76: =SUM(AR76:BA76)
A77: 73 | B77: =EOMONTH(TODAY(),72) | C77: =MAX(0,(SUM('My Loans'!$E$6:$E$15)+'My Loans'!$D$3)-SUM($X77:$AG77)) | D77: =MAX(0,AR76) | E77: =MAX(0,AS76) | F77: =MAX(0,AT76) | G77: =MAX(0,AU76) | H77: =MAX(0,AV76) | I77: =MAX(0,AW76) | J77: =MAX(0,AX76) | K77: =MAX(0,AY76) | ... M77: =MAX(0,BA76) | N77: =IF(D77<0.5,0,D77*(1+N('My Loans'!D6)/1200)) | O77: =IF(E77<0.5,0,E77*(1+N('My Loans'!D7)/1200)) | P77: =IF(F77<0.5,0,F77*(1+N('My Loans'!D8)/1200)) | Q77: =IF(G77<0.5,0,G77*(1+N('My Loans'!D9)/1200)) | R77: =IF(H77<0.5,0,H77*(1+N('My Loans'!D10)/1200)) | S77: =IF(I77<0.5,0,I77*(1+N('My Loans'!D11)/1200)) | T77: =IF(J77<0.5,0,J77*(1+N('My Loans'!D12)/1200)) | U77: =IF(K77<0.5,0,K77*(1+N('My Loans'!D13)/1200)) | V77: =IF(L77<0.5,0,L77*(1+N('My Loans'!D14)/1200)) | W77: =IF(M77<0.5,0,M77*(1+N('My Loans'!D15)/1200)) | X77: =MIN(N77,N('My Loans'!E6)) | Y77: =MIN(O77,N('My Loans'!E7)) | Z77: =MIN(P77,N('My Loans'!E8)) | AA77: =MIN(Q77,N('My Loans'!E9)) | AB77: =MIN(R77,N('My Loans'!E10)) | AC77: =MIN(S77,N('My Loans'!E11)) | AD77: =MIN(T77,N('My Loans'!E12)) | AE77: =MIN(U77,N('My Loans'!E13)) | AF77: =MIN(V77,N('My Loans'!E14)) | AG77: =MIN(W77,N('My Loans'!E15)) | AH77: =MIN(N77-X77,MAX(0,$C77-SUMPRODUCT(($D$3:$M$3<D$3)*($N77:$W77-$X77:$AG77)))) | AI77: =MIN(O77-Y77,MAX(0,$C77-SUMPRODUCT(($D$3:$M$3<E$3)*($N77:$W77-$X77:$AG77)))) | AJ77: =MIN(P77-Z77,MAX(0,$C77-SUMPRODUCT(($D$3:$M$3<F$3)*($N77:$W77-$X77:$AG77)))) | AK77: =MIN(Q77-AA77,MAX(0,$C77-SUMPRODUCT(($D$3:$M$3<G$3)*($N77:$W77-$X77:$AG77)))) | AL77: =MIN(R77-AB77,MAX(0,$C77-SUMPRODUCT(($D$3:$M$3<H$3)*($N77:$W77-$X77:$AG77)))) | AM77: =MIN(S77-AC77,MAX(0,$C77-SUMPRODUCT(($D$3:$M$3<I$3)*($N77:$W77-$X77:$AG77)))) | AN77: =MIN(T77-AD77,MAX(0,$C77-SUMPRODUCT(($D$3:$M$3<J$3)*($N77:$W77-$X77:$AG77)))) | AO77: =MIN(U77-AE77,MAX(0,$C77-SUMPRODUCT(($D$3:$M$3<K$3)*($N77:$W77-$X77:$AG77)))) | ... AQ77: =MIN(W77-AG77,MAX(0,$C77-SUMPRODUCT(($D$3:$M$3<M$3)*($N77:$W77-$X77:$AG77)))) | AR77: =ROUND(N77-X77-AH77,2) | AS77: =ROUND(O77-Y77-AI77,2) | AT77: =ROUND(P77-Z77-AJ77,2) | AU77: =ROUND(Q77-AA77-AK77,2) | AV77: =ROUND(R77-AB77-AL77,2) | AW77: =ROUND(S77-AC77-AM77,2) | AX77: =ROUND(T77-AD77-AN77,2) | AY77: =ROUND(U77-AE77-AO77,2) | ... BA77: =ROUND(W77-AG77-AQ77,2) | BB77: =SUM(AR77:BA77)
A78: 74 | B78: =EOMONTH(TODAY(),73) | C78: =MAX(0,(SUM('My Loans'!$E$6:$E$15)+'My Loans'!$D$3)-SUM($X78:$AG78)) | D78: =MAX(0,AR77) | E78: =MAX(0,AS77) | F78: =MAX(0,AT77) | G78: =MAX(0,AU77) | H78: =MAX(0,AV77) | I78: =MAX(0,AW77) | J78: =MAX(0,AX77) | K78: =MAX(0,AY77) | ... M78: =MAX(0,BA77) | N78: =IF(D78<0.5,0,D78*(1+N('My Loans'!D6)/1200)) | O78: =IF(E78<0.5,0,E78*(1+N('My Loans'!D7)/1200)) | P78: =IF(F78<0.5,0,F78*(1+N('My Loans'!D8)/1200)) | Q78: =IF(G78<0.5,0,G78*(1+N('My Loans'!D9)/1200)) | R78: =IF(H78<0.5,0,H78*(1+N('My Loans'!D10)/1200)) | S78: =IF(I78<0.5,0,I78*(1+N('My Loans'!D11)/1200)) | T78: =IF(J78<0.5,0,J78*(1+N('My Loans'!D12)/1200)) | U78: =IF(K78<0.5,0,K78*(1+N('My Loans'!D13)/1200)) | V78: =IF(L78<0.5,0,L78*(1+N('My Loans'!D14)/1200)) | W78: =IF(M78<0.5,0,M78*(1+N('My Loans'!D15)/1200)) | X78: =MIN(N78,N('My Loans'!E6)) | Y78: =MIN(O78,N('My Loans'!E7)) | Z78: =MIN(P78,N('My Loans'!E8)) | AA78: =MIN(Q78,N('My Loans'!E9)) | AB78: =MIN(R78,N('My Loans'!E10)) | AC78: =MIN(S78,N('My Loans'!E11)) | AD78: =MIN(T78,N('My Loans'!E12)) | AE78: =MIN(U78,N('My Loans'!E13)) | AF78: =MIN(V78,N('My Loans'!E14)) | AG78: =MIN(W78,N('My Loans'!E15)) | AH78: =MIN(N78-X78,MAX(0,$C78-SUMPRODUCT(($D$3:$M$3<D$3)*($N78:$W78-$X78:$AG78)))) | AI78: =MIN(O78-Y78,MAX(0,$C78-SUMPRODUCT(($D$3:$M$3<E$3)*($N78:$W78-$X78:$AG78)))) | AJ78: =MIN(P78-Z78,MAX(0,$C78-SUMPRODUCT(($D$3:$M$3<F$3)*($N78:$W78-$X78:$AG78)))) | AK78: =MIN(Q78-AA78,MAX(0,$C78-SUMPRODUCT(($D$3:$M$3<G$3)*($N78:$W78-$X78:$AG78)))) | AL78: =MIN(R78-AB78,MAX(0,$C78-SUMPRODUCT(($D$3:$M$3<H$3)*($N78:$W78-$X78:$AG78)))) | AM78: =MIN(S78-AC78,MAX(0,$C78-SUMPRODUCT(($D$3:$M$3<I$3)*($N78:$W78-$X78:$AG78)))) | AN78: =MIN(T78-AD78,MAX(0,$C78-SUMPRODUCT(($D$3:$M$3<J$3)*($N78:$W78-$X78:$AG78)))) | AO78: =MIN(U78-AE78,MAX(0,$C78-SUMPRODUCT(($D$3:$M$3<K$3)*($N78:$W78-$X78:$AG78)))) | ... AQ78: =MIN(W78-AG78,MAX(0,$C78-SUMPRODUCT(($D$3:$M$3<M$3)*($N78:$W78-$X78:$AG78)))) | AR78: =ROUND(N78-X78-AH78,2) | AS78: =ROUND(O78-Y78-AI78,2) | AT78: =ROUND(P78-Z78-AJ78,2) | AU78: =ROUND(Q78-AA78-AK78,2) | AV78: =ROUND(R78-AB78-AL78,2) | AW78: =ROUND(S78-AC78-AM78,2) | AX78: =ROUND(T78-AD78-AN78,2) | AY78: =ROUND(U78-AE78-AO78,2) | ... BA78: =ROUND(W78-AG78-AQ78,2) | BB78: =SUM(AR78:BA78)
A79: 75 | B79: =EOMONTH(TODAY(),74) | C79: =MAX(0,(SUM('My Loans'!$E$6:$E$15)+'My Loans'!$D$3)-SUM($X79:$AG79)) | D79: =MAX(0,AR78) | E79: =MAX(0,AS78) | F79: =MAX(0,AT78) | G79: =MAX(0,AU78) | H79: =MAX(0,AV78) | I79: =MAX(0,AW78) | J79: =MAX(0,AX78) | K79: =MAX(0,AY78) | ... M79: =MAX(0,BA78) | N79: =IF(D79<0.5,0,D79*(1+N('My Loans'!D6)/1200)) | O79: =IF(E79<0.5,0,E79*(1+N('My Loans'!D7)/1200)) | P79: =IF(F79<0.5,0,F79*(1+N('My Loans'!D8)/1200)) | Q79: =IF(G79<0.5,0,G79*(1+N('My Loans'!D9)/1200)) | R79: =IF(H79<0.5,0,H79*(1+N('My Loans'!D10)/1200)) | S79: =IF(I79<0.5,0,I79*(1+N('My Loans'!D11)/1200)) | T79: =IF(J79<0.5,0,J79*(1+N('My Loans'!D12)/1200)) | U79: =IF(K79<0.5,0,K79*(1+N('My Loans'!D13)/1200)) | V79: =IF(L79<0.5,0,L79*(1+N('My Loans'!D14)/1200)) | W79: =IF(M79<0.5,0,M79*(1+N('My Loans'!D15)/1200)) | X79: =MIN(N79,N('My Loans'!E6)) | Y79: =MIN(O79,N('My Loans'!E7)) | Z79: =MIN(P79,N('My Loans'!E8)) | AA79: =MIN(Q79,N('My Loans'!E9)) | AB79: =MIN(R79,N('My Loans'!E10)) | AC79: =MIN(S79,N('My Loans'!E11)) | AD79: =MIN(T79,N('My Loans'!E12)) | AE79: =MIN(U79,N('My Loans'!E13)) | AF79: =MIN(V79,N('My Loans'!E14)) | AG79: =MIN(W79,N('My Loans'!E15)) | AH79: =MIN(N79-X79,MAX(0,$C79-SUMPRODUCT(($D$3:$M$3<D$3)*($N79:$W79-$X79:$AG79)))) | AI79: =MIN(O79-Y79,MAX(0,$C79-SUMPRODUCT(($D$3:$M$3<E$3)*($N79:$W79-$X79:$AG79)))) | AJ79: =MIN(P79-Z79,MAX(0,$C79-SUMPRODUCT(($D$3:$M$3<F$3)*($N79:$W79-$X79:$AG79)))) | AK79: =MIN(Q79-AA79,MAX(0,$C79-SUMPRODUCT(($D$3:$M$3<G$3)*($N79:$W79-$X79:$AG79)))) | AL79: =MIN(R79-AB79,MAX(0,$C79-SUMPRODUCT(($D$3:$M$3<H$3)*($N79:$W79-$X79:$AG79)))) | AM79: =MIN(S79-AC79,MAX(0,$C79-SUMPRODUCT(($D$3:$M$3<I$3)*($N79:$W79-$X79:$AG79)))) | AN79: =MIN(T79-AD79,MAX(0,$C79-SUMPRODUCT(($D$3:$M$3<J$3)*($N79:$W79-$X79:$AG79)))) | AO79: =MIN(U79-AE79,MAX(0,$C79-SUMPRODUCT(($D$3:$M$3<K$3)*($N79:$W79-$X79:$AG79)))) | ... AQ79: =MIN(W79-AG79,MAX(0,$C79-SUMPRODUCT(($D$3:$M$3<M$3)*($N79:$W79-$X79:$AG79)))) | AR79: =ROUND(N79-X79-AH79,2) | AS79: =ROUND(O79-Y79-AI79,2) | AT79: =ROUND(P79-Z79-AJ79,2) | AU79: =ROUND(Q79-AA79-AK79,2) | AV79: =ROUND(R79-AB79-AL79,2) | AW79: =ROUND(S79-AC79-AM79,2) | AX79: =ROUND(T79-AD79-AN79,2) | AY79: =ROUND(U79-AE79-AO79,2) | ... BA79: =ROUND(W79-AG79-AQ79,2) | BB79: =SUM(AR79:BA79)
A80: 76 | B80: =EOMONTH(TODAY(),75) | C80: =MAX(0,(SUM('My Loans'!$E$6:$E$15)+'My Loans'!$D$3)-SUM($X80:$AG80)) | D80: =MAX(0,AR79) | E80: =MAX(0,AS79) | F80: =MAX(0,AT79) | G80: =MAX(0,AU79) | H80: =MAX(0,AV79) | I80: =MAX(0,AW79) | J80: =MAX(0,AX79) | K80: =MAX(0,AY79) | ... M80: =MAX(0,BA79) | N80: =IF(D80<0.5,0,D80*(1+N('My Loans'!D6)/1200)) | O80: =IF(E80<0.5,0,E80*(1+N('My Loans'!D7)/1200)) | P80: =IF(F80<0.5,0,F80*(1+N('My Loans'!D8)/1200)) | Q80: =IF(G80<0.5,0,G80*(1+N('My Loans'!D9)/1200)) | R80: =IF(H80<0.5,0,H80*(1+N('My Loans'!D10)/1200)) | S80: =IF(I80<0.5,0,I80*(1+N('My Loans'!D11)/1200)) | T80: =IF(J80<0.5,0,J80*(1+N('My Loans'!D12)/1200)) | U80: =IF(K80<0.5,0,K80*(1+N('My Loans'!D13)/1200)) | V80: =IF(L80<0.5,0,L80*(1+N('My Loans'!D14)/1200)) | W80: =IF(M80<0.5,0,M80*(1+N('My Loans'!D15)/1200)) | X80: =MIN(N80,N('My Loans'!E6)) | Y80: =MIN(O80,N('My Loans'!E7)) | Z80: =MIN(P80,N('My Loans'!E8)) | AA80: =MIN(Q80,N('My Loans'!E9)) | AB80: =MIN(R80,N('My Loans'!E10)) | AC80: =MIN(S80,N('My Loans'!E11)) | AD80: =MIN(T80,N('My Loans'!E12)) | AE80: =MIN(U80,N('My Loans'!E13)) | AF80: =MIN(V80,N('My Loans'!E14)) | AG80: =MIN(W80,N('My Loans'!E15)) | AH80: =MIN(N80-X80,MAX(0,$C80-SUMPRODUCT(($D$3:$M$3<D$3)*($N80:$W80-$X80:$AG80)))) | AI80: =MIN(O80-Y80,MAX(0,$C80-SUMPRODUCT(($D$3:$M$3<E$3)*($N80:$W80-$X80:$AG80)))) | AJ80: =MIN(P80-Z80,MAX(0,$C80-SUMPRODUCT(($D$3:$M$3<F$3)*($N80:$W80-$X80:$AG80)))) | AK80: =MIN(Q80-AA80,MAX(0,$C80-SUMPRODUCT(($D$3:$M$3<G$3)*($N80:$W80-$X80:$AG80)))) | AL80: =MIN(R80-AB80,MAX(0,$C80-SUMPRODUCT(($D$3:$M$3<H$3)*($N80:$W80-$X80:$AG80)))) | AM80: =MIN(S80-AC80,MAX(0,$C80-SUMPRODUCT(($D$3:$M$3<I$3)*($N80:$W80-$X80:$AG80)))) | AN80: =MIN(T80-AD80,MAX(0,$C80-SUMPRODUCT(($D$3:$M$3<J$3)*($N80:$W80-$X80:$AG80)))) | AO80: =MIN(U80-AE80,MAX(0,$C80-SUMPRODUCT(($D$3:$M$3<K$3)*($N80:$W80-$X80:$AG80)))) | ... AQ80: =MIN(W80-AG80,MAX(0,$C80-SUMPRODUCT(($D$3:$M$3<M$3)*($N80:$W80-$X80:$AG80)))) | AR80: =ROUND(N80-X80-AH80,2) | AS80: =ROUND(O80-Y80-AI80,2) | AT80: =ROUND(P80-Z80-AJ80,2) | AU80: =ROUND(Q80-AA80-AK80,2) | AV80: =ROUND(R80-AB80-AL80,2) | AW80: =ROUND(S80-AC80-AM80,2) | AX80: =ROUND(T80-AD80-AN80,2) | AY80: =ROUND(U80-AE80-AO80,2) | ... BA80: =ROUND(W80-AG80-AQ80,2) | BB80: =SUM(AR80:BA80)
A81: 77 | B81: =EOMONTH(TODAY(),76) | C81: =MAX(0,(SUM('My Loans'!$E$6:$E$15)+'My Loans'!$D$3)-SUM($X81:$AG81)) | D81: =MAX(0,AR80) | E81: =MAX(0,AS80) | F81: =MAX(0,AT80) | G81: =MAX(0,AU80) | H81: =MAX(0,AV80) | I81: =MAX(0,AW80) | J81: =MAX(0,AX80) | K81: =MAX(0,AY80) | ... M81: =MAX(0,BA80) | N81: =IF(D81<0.5,0,D81*(1+N('My Loans'!D6)/1200)) | O81: =IF(E81<0.5,0,E81*(1+N('My Loans'!D7)/1200)) | P81: =IF(F81<0.5,0,F81*(1+N('My Loans'!D8)/1200)) | Q81: =IF(G81<0.5,0,G81*(1+N('My Loans'!D9)/1200)) | R81: =IF(H81<0.5,0,H81*(1+N('My Loans'!D10)/1200)) | S81: =IF(I81<0.5,0,I81*(1+N('My Loans'!D11)/1200)) | T81: =IF(J81<0.5,0,J81*(1+N('My Loans'!D12)/1200)) | U81: =IF(K81<0.5,0,K81*(1+N('My Loans'!D13)/1200)) | V81: =IF(L81<0.5,0,L81*(1+N('My Loans'!D14)/1200)) | W81: =IF(M81<0.5,0,M81*(1+N('My Loans'!D15)/1200)) | X81: =MIN(N81,N('My Loans'!E6)) | Y81: =MIN(O81,N('My Loans'!E7)) | Z81: =MIN(P81,N('My Loans'!E8)) | AA81: =MIN(Q81,N('My Loans'!E9)) | AB81: =MIN(R81,N('My Loans'!E10)) | AC81: =MIN(S81,N('My Loans'!E11)) | AD81: =MIN(T81,N('My Loans'!E12)) | AE81: =MIN(U81,N('My Loans'!E13)) | AF81: =MIN(V81,N('My Loans'!E14)) | AG81: =MIN(W81,N('My Loans'!E15)) | AH81: =MIN(N81-X81,MAX(0,$C81-SUMPRODUCT(($D$3:$M$3<D$3)*($N81:$W81-$X81:$AG81)))) | AI81: =MIN(O81-Y81,MAX(0,$C81-SUMPRODUCT(($D$3:$M$3<E$3)*($N81:$W81-$X81:$AG81)))) | AJ81: =MIN(P81-Z81,MAX(0,$C81-SUMPRODUCT(($D$3:$M$3<F$3)*($N81:$W81-$X81:$AG81)))) | AK81: =MIN(Q81-AA81,MAX(0,$C81-SUMPRODUCT(($D$3:$M$3<G$3)*($N81:$W81-$X81:$AG81)))) | AL81: =MIN(R81-AB81,MAX(0,$C81-SUMPRODUCT(($D$3:$M$3<H$3)*($N81:$W81-$X81:$AG81)))) | AM81: =MIN(S81-AC81,MAX(0,$C81-SUMPRODUCT(($D$3:$M$3<I$3)*($N81:$W81-$X81:$AG81)))) | AN81: =MIN(T81-AD81,MAX(0,$C81-SUMPRODUCT(($D$3:$M$3<J$3)*($N81:$W81-$X81:$AG81)))) | AO81: =MIN(U81-AE81,MAX(0,$C81-SUMPRODUCT(($D$3:$M$3<K$3)*($N81:$W81-$X81:$AG81)))) | ... AQ81: =MIN(W81-AG81,MAX(0,$C81-SUMPRODUCT(($D$3:$M$3<M$3)*($N81:$W81-$X81:$AG81)))) | AR81: =ROUND(N81-X81-AH81,2) | AS81: =ROUND(O81-Y81-AI81,2) | AT81: =ROUND(P81-Z81-AJ81,2) | AU81: =ROUND(Q81-AA81-AK81,2) | AV81: =ROUND(R81-AB81-AL81,2) | AW81: =ROUND(S81-AC81-AM81,2) | AX81: =ROUND(T81-AD81-AN81,2) | AY81: =ROUND(U81-AE81-AO81,2) | ... BA81: =ROUND(W81-AG81-AQ81,2) | BB81: =SUM(AR81:BA81)
A82: 78 | B82: =EOMONTH(TODAY(),77) | C82: =MAX(0,(SUM('My Loans'!$E$6:$E$15)+'My Loans'!$D$3)-SUM($X82:$AG82)) | D82: =MAX(0,AR81) | E82: =MAX(0,AS81) | F82: =MAX(0,AT81) | G82: =MAX(0,AU81) | H82: =MAX(0,AV81) | I82: =MAX(0,AW81) | J82: =MAX(0,AX81) | K82: =MAX(0,AY81) | ... M82: =MAX(0,BA81) | N82: =IF(D82<0.5,0,D82*(1+N('My Loans'!D6)/1200)) | O82: =IF(E82<0.5,0,E82*(1+N('My Loans'!D7)/1200)) | P82: =IF(F82<0.5,0,F82*(1+N('My Loans'!D8)/1200)) | Q82: =IF(G82<0.5,0,G82*(1+N('My Loans'!D9)/1200)) | R82: =IF(H82<0.5,0,H82*(1+N('My Loans'!D10)/1200)) | S82: =IF(I82<0.5,0,I82*(1+N('My Loans'!D11)/1200)) | T82: =IF(J82<0.5,0,J82*(1+N('My Loans'!D12)/1200)) | U82: =IF(K82<0.5,0,K82*(1+N('My Loans'!D13)/1200)) | V82: =IF(L82<0.5,0,L82*(1+N('My Loans'!D14)/1200)) | W82: =IF(M82<0.5,0,M82*(1+N('My Loans'!D15)/1200)) | X82: =MIN(N82,N('My Loans'!E6)) | Y82: =MIN(O82,N('My Loans'!E7)) | Z82: =MIN(P82,N('My Loans'!E8)) | AA82: =MIN(Q82,N('My Loans'!E9)) | AB82: =MIN(R82,N('My Loans'!E10)) | AC82: =MIN(S82,N('My Loans'!E11)) | AD82: =MIN(T82,N('My Loans'!E12)) | AE82: =MIN(U82,N('My Loans'!E13)) | AF82: =MIN(V82,N('My Loans'!E14)) | AG82: =MIN(W82,N('My Loans'!E15)) | AH82: =MIN(N82-X82,MAX(0,$C82-SUMPRODUCT(($D$3:$M$3<D$3)*($N82:$W82-$X82:$AG82)))) | AI82: =MIN(O82-Y82,MAX(0,$C82-SUMPRODUCT(($D$3:$M$3<E$3)*($N82:$W82-$X82:$AG82)))) | AJ82: =MIN(P82-Z82,MAX(0,$C82-SUMPRODUCT(($D$3:$M$3<F$3)*($N82:$W82-$X82:$AG82)))) | AK82: =MIN(Q82-AA82,MAX(0,$C82-SUMPRODUCT(($D$3:$M$3<G$3)*($N82:$W82-$X82:$AG82)))) | AL82: =MIN(R82-AB82,MAX(0,$C82-SUMPRODUCT(($D$3:$M$3<H$3)*($N82:$W82-$X82:$AG82)))) | AM82: =MIN(S82-AC82,MAX(0,$C82-SUMPRODUCT(($D$3:$M$3<I$3)*($N82:$W82-$X82:$AG82)))) | AN82: =MIN(T82-AD82,MAX(0,$C82-SUMPRODUCT(($D$3:$M$3<J$3)*($N82:$W82-$X82:$AG82)))) | AO82: =MIN(U82-AE82,MAX(0,$C82-SUMPRODUCT(($D$3:$M$3<K$3)*($N82:$W82-$X82:$AG82)))) | ... AQ82: =MIN(W82-AG82,MAX(0,$C82-SUMPRODUCT(($D$3:$M$3<M$3)*($N82:$W82-$X82:$AG82)))) | AR82: =ROUND(N82-X82-AH82,2) | AS82: =ROUND(O82-Y82-AI82,2) | AT82: =ROUND(P82-Z82-AJ82,2) | AU82: =ROUND(Q82-AA82-AK82,2) | AV82: =ROUND(R82-AB82-AL82,2) | AW82: =ROUND(S82-AC82-AM82,2) | AX82: =ROUND(T82-AD82-AN82,2) | AY82: =ROUND(U82-AE82-AO82,2) | ... BA82: =ROUND(W82-AG82-AQ82,2) | BB82: =SUM(AR82:BA82)
A83: 79 | B83: =EOMONTH(TODAY(),78) | C83: =MAX(0,(SUM('My Loans'!$E$6:$E$15)+'My Loans'!$D$3)-SUM($X83:$AG83)) | D83: =MAX(0,AR82) | E83: =MAX(0,AS82) | F83: =MAX(0,AT82) | G83: =MAX(0,AU82) | H83: =MAX(0,AV82) | I83: =MAX(0,AW82) | J83: =MAX(0,AX82) | K83: =MAX(0,AY82) | ... M83: =MAX(0,BA82) | N83: =IF(D83<0.5,0,D83*(1+N('My Loans'!D6)/1200)) | O83: =IF(E83<0.5,0,E83*(1+N('My Loans'!D7)/1200)) | P83: =IF(F83<0.5,0,F83*(1+N('My Loans'!D8)/1200)) | Q83: =IF(G83<0.5,0,G83*(1+N('My Loans'!D9)/1200)) | R83: =IF(H83<0.5,0,H83*(1+N('My Loans'!D10)/1200)) | S83: =IF(I83<0.5,0,I83*(1+N('My Loans'!D11)/1200)) | T83: =IF(J83<0.5,0,J83*(1+N('My Loans'!D12)/1200)) | U83: =IF(K83<0.5,0,K83*(1+N('My Loans'!D13)/1200)) | V83: =IF(L83<0.5,0,L83*(1+N('My Loans'!D14)/1200)) | W83: =IF(M83<0.5,0,M83*(1+N('My Loans'!D15)/1200)) | X83: =MIN(N83,N('My Loans'!E6)) | Y83: =MIN(O83,N('My Loans'!E7)) | Z83: =MIN(P83,N('My Loans'!E8)) | AA83: =MIN(Q83,N('My Loans'!E9)) | AB83: =MIN(R83,N('My Loans'!E10)) | AC83: =MIN(S83,N('My Loans'!E11)) | AD83: =MIN(T83,N('My Loans'!E12)) | AE83: =MIN(U83,N('My Loans'!E13)) | AF83: =MIN(V83,N('My Loans'!E14)) | AG83: =MIN(W83,N('My Loans'!E15)) | AH83: =MIN(N83-X83,MAX(0,$C83-SUMPRODUCT(($D$3:$M$3<D$3)*($N83:$W83-$X83:$AG83)))) | AI83: =MIN(O83-Y83,MAX(0,$C83-SUMPRODUCT(($D$3:$M$3<E$3)*($N83:$W83-$X83:$AG83)))) | AJ83: =MIN(P83-Z83,MAX(0,$C83-SUMPRODUCT(($D$3:$M$3<F$3)*($N83:$W83-$X83:$AG83)))) | AK83: =MIN(Q83-AA83,MAX(0,$C83-SUMPRODUCT(($D$3:$M$3<G$3)*($N83:$W83-$X83:$AG83)))) | AL83: =MIN(R83-AB83,MAX(0,$C83-SUMPRODUCT(($D$3:$M$3<H$3)*($N83:$W83-$X83:$AG83)))) | AM83: =MIN(S83-AC83,MAX(0,$C83-SUMPRODUCT(($D$3:$M$3<I$3)*($N83:$W83-$X83:$AG83)))) | AN83: =MIN(T83-AD83,MAX(0,$C83-SUMPRODUCT(($D$3:$M$3<J$3)*($N83:$W83-$X83:$AG83)))) | AO83: =MIN(U83-AE83,MAX(0,$C83-SUMPRODUCT(($D$3:$M$3<K$3)*($N83:$W83-$X83:$AG83)))) | ... AQ83: =MIN(W83-AG83,MAX(0,$C83-SUMPRODUCT(($D$3:$M$3<M$3)*($N83:$W83-$X83:$AG83)))) | AR83: =ROUND(N83-X83-AH83,2) | AS83: =ROUND(O83-Y83-AI83,2) | AT83: =ROUND(P83-Z83-AJ83,2) | AU83: =ROUND(Q83-AA83-AK83,2) | AV83: =ROUND(R83-AB83-AL83,2) | AW83: =ROUND(S83-AC83-AM83,2) | AX83: =ROUND(T83-AD83-AN83,2) | AY83: =ROUND(U83-AE83-AO83,2) | ... BA83: =ROUND(W83-AG83-AQ83,2) | BB83: =SUM(AR83:BA83)
A84: 80 | B84: =EOMONTH(TODAY(),79) | C84: =MAX(0,(SUM('My Loans'!$E$6:$E$15)+'My Loans'!$D$3)-SUM($X84:$AG84)) | D84: =MAX(0,AR83) | E84: =MAX(0,AS83) | F84: =MAX(0,AT83) | G84: =MAX(0,AU83) | H84: =MAX(0,AV83) | I84: =MAX(0,AW83) | J84: =MAX(0,AX83) | K84: =MAX(0,AY83) | ... M84: =MAX(0,BA83) | N84: =IF(D84<0.5,0,D84*(1+N('My Loans'!D6)/1200)) | O84: =IF(E84<0.5,0,E84*(1+N('My Loans'!D7)/1200)) | P84: =IF(F84<0.5,0,F84*(1+N('My Loans'!D8)/1200)) | Q84: =IF(G84<0.5,0,G84*(1+N('My Loans'!D9)/1200)) | R84: =IF(H84<0.5,0,H84*(1+N('My Loans'!D10)/1200)) | S84: =IF(I84<0.5,0,I84*(1+N('My Loans'!D11)/1200)) | T84: =IF(J84<0.5,0,J84*(1+N('My Loans'!D12)/1200)) | U84: =IF(K84<0.5,0,K84*(1+N('My Loans'!D13)/1200)) | V84: =IF(L84<0.5,0,L84*(1+N('My Loans'!D14)/1200)) | W84: =IF(M84<0.5,0,M84*(1+N('My Loans'!D15)/1200)) | X84: =MIN(N84,N('My Loans'!E6)) | Y84: =MIN(O84,N('My Loans'!E7)) | Z84: =MIN(P84,N('My Loans'!E8)) | AA84: =MIN(Q84,N('My Loans'!E9)) | AB84: =MIN(R84,N('My Loans'!E10)) | AC84: =MIN(S84,N('My Loans'!E11)) | AD84: =MIN(T84,N('My Loans'!E12)) | AE84: =MIN(U84,N('My Loans'!E13)) | AF84: =MIN(V84,N('My Loans'!E14)) | AG84: =MIN(W84,N('My Loans'!E15)) | AH84: =MIN(N84-X84,MAX(0,$C84-SUMPRODUCT(($D$3:$M$3<D$3)*($N84:$W84-$X84:$AG84)))) | AI84: =MIN(O84-Y84,MAX(0,$C84-SUMPRODUCT(($D$3:$M$3<E$3)*($N84:$W84-$X84:$AG84)))) | AJ84: =MIN(P84-Z84,MAX(0,$C84-SUMPRODUCT(($D$3:$M$3<F$3)*($N84:$W84-$X84:$AG84)))) | AK84: =MIN(Q84-AA84,MAX(0,$C84-SUMPRODUCT(($D$3:$M$3<G$3)*($N84:$W84-$X84:$AG84)))) | AL84: =MIN(R84-AB84,MAX(0,$C84-SUMPRODUCT(($D$3:$M$3<H$3)*($N84:$W84-$X84:$AG84)))) | AM84: =MIN(S84-AC84,MAX(0,$C84-SUMPRODUCT(($D$3:$M$3<I$3)*($N84:$W84-$X84:$AG84)))) | AN84: =MIN(T84-AD84,MAX(0,$C84-SUMPRODUCT(($D$3:$M$3<J$3)*($N84:$W84-$X84:$AG84)))) | AO84: =MIN(U84-AE84,MAX(0,$C84-SUMPRODUCT(($D$3:$M$3<K$3)*($N84:$W84-$X84:$AG84)))) | ... AQ84: =MIN(W84-AG84,MAX(0,$C84-SUMPRODUCT(($D$3:$M$3<M$3)*($N84:$W84-$X84:$AG84)))) | AR84: =ROUND(N84-X84-AH84,2) | AS84: =ROUND(O84-Y84-AI84,2) | AT84: =ROUND(P84-Z84-AJ84,2) | AU84: =ROUND(Q84-AA84-AK84,2) | AV84: =ROUND(R84-AB84-AL84,2) | AW84: =ROUND(S84-AC84-AM84,2) | AX84: =ROUND(T84-AD84-AN84,2) | AY84: =ROUND(U84-AE84-AO84,2) | ... BA84: =ROUND(W84-AG84-AQ84,2) | BB84: =SUM(AR84:BA84)
A85: 81 | B85: =EOMONTH(TODAY(),80) | C85: =MAX(0,(SUM('My Loans'!$E$6:$E$15)+'My Loans'!$D$3)-SUM($X85:$AG85)) | D85: =MAX(0,AR84) | E85: =MAX(0,AS84) | F85: =MAX(0,AT84) | G85: =MAX(0,AU84) | H85: =MAX(0,AV84) | I85: =MAX(0,AW84) | J85: =MAX(0,AX84) | K85: =MAX(0,AY84) | ... M85: =MAX(0,BA84) | N85: =IF(D85<0.5,0,D85*(1+N('My Loans'!D6)/1200)) | O85: =IF(E85<0.5,0,E85*(1+N('My Loans'!D7)/1200)) | P85: =IF(F85<0.5,0,F85*(1+N('My Loans'!D8)/1200)) | Q85: =IF(G85<0.5,0,G85*(1+N('My Loans'!D9)/1200)) | R85: =IF(H85<0.5,0,H85*(1+N('My Loans'!D10)/1200)) | S85: =IF(I85<0.5,0,I85*(1+N('My Loans'!D11)/1200)) | T85: =IF(J85<0.5,0,J85*(1+N('My Loans'!D12)/1200)) | U85: =IF(K85<0.5,0,K85*(1+N('My Loans'!D13)/1200)) | V85: =IF(L85<0.5,0,L85*(1+N('My Loans'!D14)/1200)) | W85: =IF(M85<0.5,0,M85*(1+N('My Loans'!D15)/1200)) | X85: =MIN(N85,N('My Loans'!E6)) | Y85: =MIN(O85,N('My Loans'!E7)) | Z85: =MIN(P85,N('My Loans'!E8)) | AA85: =MIN(Q85,N('My Loans'!E9)) | AB85: =MIN(R85,N('My Loans'!E10)) | AC85: =MIN(S85,N('My Loans'!E11)) | AD85: =MIN(T85,N('My Loans'!E12)) | AE85: =MIN(U85,N('My Loans'!E13)) | AF85: =MIN(V85,N('My Loans'!E14)) | AG85: =MIN(W85,N('My Loans'!E15)) | AH85: =MIN(N85-X85,MAX(0,$C85-SUMPRODUCT(($D$3:$M$3<D$3)*($N85:$W85-$X85:$AG85)))) | AI85: =MIN(O85-Y85,MAX(0,$C85-SUMPRODUCT(($D$3:$M$3<E$3)*($N85:$W85-$X85:$AG85)))) | AJ85: =MIN(P85-Z85,MAX(0,$C85-SUMPRODUCT(($D$3:$M$3<F$3)*($N85:$W85-$X85:$AG85)))) | AK85: =MIN(Q85-AA85,MAX(0,$C85-SUMPRODUCT(($D$3:$M$3<G$3)*($N85:$W85-$X85:$AG85)))) | AL85: =MIN(R85-AB85,MAX(0,$C85-SUMPRODUCT(($D$3:$M$3<H$3)*($N85:$W85-$X85:$AG85)))) | AM85: =MIN(S85-AC85,MAX(0,$C85-SUMPRODUCT(($D$3:$M$3<I$3)*($N85:$W85-$X85:$AG85)))) | AN85: =MIN(T85-AD85,MAX(0,$C85-SUMPRODUCT(($D$3:$M$3<J$3)*($N85:$W85-$X85:$AG85)))) | AO85: =MIN(U85-AE85,MAX(0,$C85-SUMPRODUCT(($D$3:$M$3<K$3)*($N85:$W85-$X85:$AG85)))) | ... AQ85: =MIN(W85-AG85,MAX(0,$C85-SUMPRODUCT(($D$3:$M$3<M$3)*($N85:$W85-$X85:$AG85)))) | AR85: =ROUND(N85-X85-AH85,2) | AS85: =ROUND(O85-Y85-AI85,2) | AT85: =ROUND(P85-Z85-AJ85,2) | AU85: =ROUND(Q85-AA85-AK85,2) | AV85: =ROUND(R85-AB85-AL85,2) | AW85: =ROUND(S85-AC85-AM85,2) | AX85: =ROUND(T85-AD85-AN85,2) | AY85: =ROUND(U85-AE85-AO85,2) | ... BA85: =ROUND(W85-AG85-AQ85,2) | BB85: =SUM(AR85:BA85)
A86: 82 | B86: =EOMONTH(TODAY(),81) | C86: =MAX(0,(SUM('My Loans'!$E$6:$E$15)+'My Loans'!$D$3)-SUM($X86:$AG86)) | D86: =MAX(0,AR85) | E86: =MAX(0,AS85) | F86: =MAX(0,AT85) | G86: =MAX(0,AU85) | H86: =MAX(0,AV85) | I86: =MAX(0,AW85) | J86: =MAX(0,AX85) | K86: =MAX(0,AY85) | ... M86: =MAX(0,BA85) | N86: =IF(D86<0.5,0,D86*(1+N('My Loans'!D6)/1200)) | O86: =IF(E86<0.5,0,E86*(1+N('My Loans'!D7)/1200)) | P86: =IF(F86<0.5,0,F86*(1+N('My Loans'!D8)/1200)) | Q86: =IF(G86<0.5,0,G86*(1+N('My Loans'!D9)/1200)) | R86: =IF(H86<0.5,0,H86*(1+N('My Loans'!D10)/1200)) | S86: =IF(I86<0.5,0,I86*(1+N('My Loans'!D11)/1200)) | T86: =IF(J86<0.5,0,J86*(1+N('My Loans'!D12)/1200)) | U86: =IF(K86<0.5,0,K86*(1+N('My Loans'!D13)/1200)) | V86: =IF(L86<0.5,0,L86*(1+N('My Loans'!D14)/1200)) | W86: =IF(M86<0.5,0,M86*(1+N('My Loans'!D15)/1200)) | X86: =MIN(N86,N('My Loans'!E6)) | Y86: =MIN(O86,N('My Loans'!E7)) | Z86: =MIN(P86,N('My Loans'!E8)) | AA86: =MIN(Q86,N('My Loans'!E9)) | AB86: =MIN(R86,N('My Loans'!E10)) | AC86: =MIN(S86,N('My Loans'!E11)) | AD86: =MIN(T86,N('My Loans'!E12)) | AE86: =MIN(U86,N('My Loans'!E13)) | AF86: =MIN(V86,N('My Loans'!E14)) | AG86: =MIN(W86,N('My Loans'!E15)) | AH86: =MIN(N86-X86,MAX(0,$C86-SUMPRODUCT(($D$3:$M$3<D$3)*($N86:$W86-$X86:$AG86)))) | AI86: =MIN(O86-Y86,MAX(0,$C86-SUMPRODUCT(($D$3:$M$3<E$3)*($N86:$W86-$X86:$AG86)))) | AJ86: =MIN(P86-Z86,MAX(0,$C86-SUMPRODUCT(($D$3:$M$3<F$3)*($N86:$W86-$X86:$AG86)))) | AK86: =MIN(Q86-AA86,MAX(0,$C86-SUMPRODUCT(($D$3:$M$3<G$3)*($N86:$W86-$X86:$AG86)))) | AL86: =MIN(R86-AB86,MAX(0,$C86-SUMPRODUCT(($D$3:$M$3<H$3)*($N86:$W86-$X86:$AG86)))) | AM86: =MIN(S86-AC86,MAX(0,$C86-SUMPRODUCT(($D$3:$M$3<I$3)*($N86:$W86-$X86:$AG86)))) | AN86: =MIN(T86-AD86,MAX(0,$C86-SUMPRODUCT(($D$3:$M$3<J$3)*($N86:$W86-$X86:$AG86)))) | AO86: =MIN(U86-AE86,MAX(0,$C86-SUMPRODUCT(($D$3:$M$3<K$3)*($N86:$W86-$X86:$AG86)))) | ... AQ86: =MIN(W86-AG86,MAX(0,$C86-SUMPRODUCT(($D$3:$M$3<M$3)*($N86:$W86-$X86:$AG86)))) | AR86: =ROUND(N86-X86-AH86,2) | AS86: =ROUND(O86-Y86-AI86,2) | AT86: =ROUND(P86-Z86-AJ86,2) | AU86: =ROUND(Q86-AA86-AK86,2) | AV86: =ROUND(R86-AB86-AL86,2) | AW86: =ROUND(S86-AC86-AM86,2) | AX86: =ROUND(T86-AD86-AN86,2) | AY86: =ROUND(U86-AE86-AO86,2) | ... BA86: =ROUND(W86-AG86-AQ86,2) | BB86: =SUM(AR86:BA86)
A87: 83 | B87: =EOMONTH(TODAY(),82) | C87: =MAX(0,(SUM('My Loans'!$E$6:$E$15)+'My Loans'!$D$3)-SUM($X87:$AG87)) | D87: =MAX(0,AR86) | E87: =MAX(0,AS86) | F87: =MAX(0,AT86) | G87: =MAX(0,AU86) | H87: =MAX(0,AV86) | I87: =MAX(0,AW86) | J87: =MAX(0,AX86) | K87: =MAX(0,AY86) | ... M87: =MAX(0,BA86) | N87: =IF(D87<0.5,0,D87*(1+N('My Loans'!D6)/1200)) | O87: =IF(E87<0.5,0,E87*(1+N('My Loans'!D7)/1200)) | P87: =IF(F87<0.5,0,F87*(1+N('My Loans'!D8)/1200)) | Q87: =IF(G87<0.5,0,G87*(1+N('My Loans'!D9)/1200)) | R87: =IF(H87<0.5,0,H87*(1+N('My Loans'!D10)/1200)) | S87: =IF(I87<0.5,0,I87*(1+N('My Loans'!D11)/1200)) | T87: =IF(J87<0.5,0,J87*(1+N('My Loans'!D12)/1200)) | U87: =IF(K87<0.5,0,K87*(1+N('My Loans'!D13)/1200)) | V87: =IF(L87<0.5,0,L87*(1+N('My Loans'!D14)/1200)) | W87: =IF(M87<0.5,0,M87*(1+N('My Loans'!D15)/1200)) | X87: =MIN(N87,N('My Loans'!E6)) | Y87: =MIN(O87,N('My Loans'!E7)) | Z87: =MIN(P87,N('My Loans'!E8)) | AA87: =MIN(Q87,N('My Loans'!E9)) | AB87: =MIN(R87,N('My Loans'!E10)) | AC87: =MIN(S87,N('My Loans'!E11)) | AD87: =MIN(T87,N('My Loans'!E12)) | AE87: =MIN(U87,N('My Loans'!E13)) | AF87: =MIN(V87,N('My Loans'!E14)) | AG87: =MIN(W87,N('My Loans'!E15)) | AH87: =MIN(N87-X87,MAX(0,$C87-SUMPRODUCT(($D$3:$M$3<D$3)*($N87:$W87-$X87:$AG87)))) | AI87: =MIN(O87-Y87,MAX(0,$C87-SUMPRODUCT(($D$3:$M$3<E$3)*($N87:$W87-$X87:$AG87)))) | AJ87: =MIN(P87-Z87,MAX(0,$C87-SUMPRODUCT(($D$3:$M$3<F$3)*($N87:$W87-$X87:$AG87)))) | AK87: =MIN(Q87-AA87,MAX(0,$C87-SUMPRODUCT(($D$3:$M$3<G$3)*($N87:$W87-$X87:$AG87)))) | AL87: =MIN(R87-AB87,MAX(0,$C87-SUMPRODUCT(($D$3:$M$3<H$3)*($N87:$W87-$X87:$AG87)))) | AM87: =MIN(S87-AC87,MAX(0,$C87-SUMPRODUCT(($D$3:$M$3<I$3)*($N87:$W87-$X87:$AG87)))) | AN87: =MIN(T87-AD87,MAX(0,$C87-SUMPRODUCT(($D$3:$M$3<J$3)*($N87:$W87-$X87:$AG87)))) | AO87: =MIN(U87-AE87,MAX(0,$C87-SUMPRODUCT(($D$3:$M$3<K$3)*($N87:$W87-$X87:$AG87)))) | ... AQ87: =MIN(W87-AG87,MAX(0,$C87-SUMPRODUCT(($D$3:$M$3<M$3)*($N87:$W87-$X87:$AG87)))) | AR87: =ROUND(N87-X87-AH87,2) | AS87: =ROUND(O87-Y87-AI87,2) | AT87: =ROUND(P87-Z87-AJ87,2) | AU87: =ROUND(Q87-AA87-AK87,2) | AV87: =ROUND(R87-AB87-AL87,2) | AW87: =ROUND(S87-AC87-AM87,2) | AX87: =ROUND(T87-AD87-AN87,2) | AY87: =ROUND(U87-AE87-AO87,2) | ... BA87: =ROUND(W87-AG87-AQ87,2) | BB87: =SUM(AR87:BA87)
