Workbook

Sheet How to use
B1: Investment & Net Worth Tracker
B2: Rajput Lalit & Associates · www.rajputlalitassociates.in · WhatsApp +91 93549 53603
B4: Steps
A5: 1 | B5: In 'Assets' list everything you own: bank balances, FDs, PPF, EPF, NPS, mutual funds, shares, gold, property, crypto — with the amount invested and today's value.
A6: 2 | B6: In 'Loans' list what you owe: home loan, car loan, personal loan, card balance.
A7: 3 | B7: 'Net Worth' shows your total, the asset mix chart and the gain on your investments.
A8: 4 | B8: Once a month (or quarter) copy the net worth figure into 'History' — the chart shows how you are growing.
A9: 5 | B9: FDs and policies maturing in the next 90 days are highlighted in 'Assets'.
B11: Good to know
B12: • Update current values from your bank / broker / CAMS statement — the sheet does not fetch prices.
B13: • Write the nominee for every asset — it saves your family a lot of trouble.
B15: Cells shaded light yellow are for your entries. White cells contain formulas — please don't type over them.
B17: Licensed for use in your own business. Please do not resell or share publicly. This template is a working aid, not professional advice.

Sheet Net Worth
A1: Net Worth
A2: ="As on "&TEXT(TODAY(),"dd mmm yyyy")
A4: Total assets (current value) | B4: =SUM(Assets!E5:E64)
A5: Total loans | B5: =SUM(Loans!C5:C24)
A6: NET WORTH | B6: =B4-B5
A7: Gain on investments | B7: =SUM(Assets!F5:F64)
A9: Asset type | B9: Current value | C9: Share
A10: Bank | B10: =SUMIF(Assets!$B$5:$B$64,A10,Assets!$E$5:$E$64) | C10: =IF($B$4=0,0,B10/$B$4)
A11: FD / RD | B11: =SUMIF(Assets!$B$5:$B$64,A11,Assets!$E$5:$E$64) | C11: =IF($B$4=0,0,B11/$B$4)
A12: PPF | B12: =SUMIF(Assets!$B$5:$B$64,A12,Assets!$E$5:$E$64) | C12: =IF($B$4=0,0,B12/$B$4)
A13: EPF | B13: =SUMIF(Assets!$B$5:$B$64,A13,Assets!$E$5:$E$64) | C13: =IF($B$4=0,0,B13/$B$4)
A14: NPS | B14: =SUMIF(Assets!$B$5:$B$64,A14,Assets!$E$5:$E$64) | C14: =IF($B$4=0,0,B14/$B$4)
A15: Mutual funds | B15: =SUMIF(Assets!$B$5:$B$64,A15,Assets!$E$5:$E$64) | C15: =IF($B$4=0,0,B15/$B$4)
A16: Shares | B16: =SUMIF(Assets!$B$5:$B$64,A16,Assets!$E$5:$E$64) | C16: =IF($B$4=0,0,B16/$B$4)
A17: Gold | B17: =SUMIF(Assets!$B$5:$B$64,A17,Assets!$E$5:$E$64) | C17: =IF($B$4=0,0,B17/$B$4)
A18: Property | B18: =SUMIF(Assets!$B$5:$B$64,A18,Assets!$E$5:$E$64) | C18: =IF($B$4=0,0,B18/$B$4)
A19: Insurance (savings) | B19: =SUMIF(Assets!$B$5:$B$64,A19,Assets!$E$5:$E$64) | C19: =IF($B$4=0,0,B19/$B$4)
A20: Crypto | B20: =SUMIF(Assets!$B$5:$B$64,A20,Assets!$E$5:$E$64) | C20: =IF($B$4=0,0,B20/$B$4)
A21: Other | B21: =SUMIF(Assets!$B$5:$B$64,A21,Assets!$E$5:$E$64) | C21: =IF($B$4=0,0,B21/$B$4)
A24: Tax, GST or accounts question? Rajput Lalit & Associates — WhatsApp +91 93549 53603 · www.rajputlalitassociates.in

Sheet Assets
A1: Assets
A4: Asset | B4: Type | C4: Where held | D4: Amount invested (₹) | E4: Current value (₹) | F4: Gain (₹) | G4: Gain % | H4: Maturity date | I4: Nominee
A5: Savings account | B5: Bank | C5: SBI | D5: 50000 | E5: 50000 | F5: =IF(A5="","",N(E5)-N(D5)) | G5: =IF(OR(A5="",N(D5)=0),"",F5/D5)
A6: Equity SIP | B6: Mutual funds | C6: CAMS | D6: 200000 | E6: 236000 | F6: =IF(A6="","",N(E6)-N(D6)) | G6: =IF(OR(A6="",N(D6)=0),"",F6/D6)
A7: PPF | B7: PPF | C7: Post office | D7: 300000 | E7: 352000 | F7: =IF(A7="","",N(E7)-N(D7)) | G7: =IF(OR(A7="",N(D7)=0),"",F7/D7)
F8: =IF(A8="","",N(E8)-N(D8)) | G8: =IF(OR(A8="",N(D8)=0),"",F8/D8)
F9: =IF(A9="","",N(E9)-N(D9)) | G9: =IF(OR(A9="",N(D9)=0),"",F9/D9)
F10: =IF(A10="","",N(E10)-N(D10)) | G10: =IF(OR(A10="",N(D10)=0),"",F10/D10)
F11: =IF(A11="","",N(E11)-N(D11)) | G11: =IF(OR(A11="",N(D11)=0),"",F11/D11)
F12: =IF(A12="","",N(E12)-N(D12)) | G12: =IF(OR(A12="",N(D12)=0),"",F12/D12)
F13: =IF(A13="","",N(E13)-N(D13)) | G13: =IF(OR(A13="",N(D13)=0),"",F13/D13)
F14: =IF(A14="","",N(E14)-N(D14)) | G14: =IF(OR(A14="",N(D14)=0),"",F14/D14)
F15: =IF(A15="","",N(E15)-N(D15)) | G15: =IF(OR(A15="",N(D15)=0),"",F15/D15)
F16: =IF(A16="","",N(E16)-N(D16)) | G16: =IF(OR(A16="",N(D16)=0),"",F16/D16)
F17: =IF(A17="","",N(E17)-N(D17)) | G17: =IF(OR(A17="",N(D17)=0),"",F17/D17)
F18: =IF(A18="","",N(E18)-N(D18)) | G18: =IF(OR(A18="",N(D18)=0),"",F18/D18)
F19: =IF(A19="","",N(E19)-N(D19)) | G19: =IF(OR(A19="",N(D19)=0),"",F19/D19)
... F64: =IF(A64="","",N(E64)-N(D64)) | G64: =IF(OR(A64="",N(D64)=0),"",F64/D64)

Sheet History
A1: Net Worth History
A2: Copy the figures from 'Net Worth' once a month
A4: Date | B4: Total assets | C4: Total loans | D4: Net worth
D5: =IF(A5="","",N(B5)-N(C5))
D6: =IF(A6="","",N(B6)-N(C6))
D7: =IF(A7="","",N(B7)-N(C7))
D8: =IF(A8="","",N(B8)-N(C8))
D9: =IF(A9="","",N(B9)-N(C9))
D10: =IF(A10="","",N(B10)-N(C10))
D11: =IF(A11="","",N(B11)-N(C11))
D12: =IF(A12="","",N(B12)-N(C12))
D13: =IF(A13="","",N(B13)-N(C13))
D14: =IF(A14="","",N(B14)-N(C14))
D15: =IF(A15="","",N(B15)-N(C15))
D16: =IF(A16="","",N(B16)-N(C16))
... D124: =IF(A124="","",N(B124)-N(C124))

Sheet Loans
A1: Loans & Dues
A4: Loan | B4: Lender | C4: Outstanding today (₹) | D4: EMI (₹) | E4: Ends on
