Workbook

Sheet How to use
B1: Salary Sheet + Attendance + Salary Slip Kit
B2: Rajput Lalit & Associates · www.rajputlalitassociates.in · WhatsApp +91 93549 53603
B4: Steps
A5: 1 | B5: 'Setup': company name, address and the month you are processing (any date in that month).
A6: 2 | B6: 'Employees': one row per employee — monthly Basic, HRA and other allowances, and whether PF / ESI apply. Fill once; change only when salary changes.
A7: 3 | B7: 'Attendance': mark each day with P (present), A (absent), H (half day), L (paid leave), WO (weekly off) or HO (holiday). Paid days are counted automatically.
A8: 4 | B8: 'Salary Sheet' calculates earned salary for the paid days, PF, ESI, professional tax, TDS, advances and net pay for everyone.
A9: 5 | B9: 'Salary Slip': choose an employee code in C5 — a print-ready slip appears. Print or save as PDF, then pick the next code.
A10: 6 | B10: Next month: File → Save As with the new month's name, change the month in Setup and clear the attendance.
B12: Good to know
B13: • PF: 12% of Basic for the employee and 12% by the employer, on Basic up to ₹15,000 a month (the usual wage ceiling; you can pay on higher Basic if you choose).
B14: • ESI: 0.75% employee + 3.25% employer, for employees whose gross pay is up to ₹21,000 a month.
B15: • Under the new Labour Codes (in force from 21 November 2025), 'wages' (Basic + DA + retaining allowance) should be at least 50% of total pay — the Employees sheet flags anyone below 50%.
B16: • Professional tax and its slabs differ by state — enter the amount that applies to you. Haryana has no professional tax.
B17: • Rates as of FY 2026-27 — check with your consultant if a rate changes.
B19: Cells shaded light yellow are for your entries. White cells contain formulas — please don't type over them.
B21: Licensed for use in your own business. Please do not resell or share publicly. This template is a working aid, not professional advice.

Sheet Salary Slip
B2: =Setup!B3
B3: =Setup!B4
B4: ="SALARY SLIP — "&UPPER(TEXT(Setup!B5,"mmmm yyyy"))
B5: Employee code ▶ | C5: E001
B7: Name | C7: =IFERROR(INDEX(Employees!$B$5:$B$54,MATCH($C$5,Employees!$A$5:$A$54,0)),"") | E7: Designation | F7: =IFERROR(INDEX(Employees!$C$5:$C$54,MATCH($C$5,Employees!$A$5:$A$54,0)),"")
B8: Date of joining | C8: =IFERROR(INDEX(Employees!$D$5:$D$54,MATCH($C$5,Employees!$A$5:$A$54,0)),"") | E8: PAN | F8: =IFERROR(INDEX(Employees!$E$5:$E$54,MATCH($C$5,Employees!$A$5:$A$54,0)),"")
B9: UAN | C9: =IFERROR(INDEX(Employees!$F$5:$F$54,MATCH($C$5,Employees!$A$5:$A$54,0)),"") | E9: ESI no. | F9: =IFERROR(INDEX(Employees!$G$5:$G$54,MATCH($C$5,Employees!$A$5:$A$54,0)),"")
B10: Bank A/c | C10: =IFERROR(INDEX(Employees!$H$5:$H$54,MATCH($C$5,Employees!$A$5:$A$54,0)),"") | E10: Paid days | F10: =IFERROR(INDEX('Salary Sheet'!$C$5:$C$54,MATCH($C$5,'Salary Sheet'!$A$5:$A$54,0)),"")
B12: Earnings | C12: ₹ | E12: Deductions | F12: ₹
B13: Basic | C13: =IFERROR(INDEX('Salary Sheet'!$D$5:$D$54,MATCH($C$5,'Salary Sheet'!$A$5:$A$54,0)),0) | E13: Provident Fund | F13: =IFERROR(INDEX('Salary Sheet'!$H$5:$H$54,MATCH($C$5,'Salary Sheet'!$A$5:$A$54,0)),0)
B14: HRA | C14: =IFERROR(INDEX('Salary Sheet'!$E$5:$E$54,MATCH($C$5,'Salary Sheet'!$A$5:$A$54,0)),0) | E14: ESI | F14: =IFERROR(INDEX('Salary Sheet'!$I$5:$I$54,MATCH($C$5,'Salary Sheet'!$A$5:$A$54,0)),0)
B15: Other allowances | C15: =IFERROR(INDEX('Salary Sheet'!$F$5:$F$54,MATCH($C$5,'Salary Sheet'!$A$5:$A$54,0)),0) | E15: Professional tax | F15: =IFERROR(INDEX('Salary Sheet'!$J$5:$J$54,MATCH($C$5,'Salary Sheet'!$A$5:$A$54,0)),0)
E16: TDS | F16: =IFERROR(INDEX('Salary Sheet'!$K$5:$K$54,MATCH($C$5,'Salary Sheet'!$A$5:$A$54,0)),0)
E17: Advance / other | F17: =IFERROR(INDEX('Salary Sheet'!$L$5:$L$54,MATCH($C$5,'Salary Sheet'!$A$5:$A$54,0)),0)
B18: Gross earnings | C18: =IFERROR(INDEX('Salary Sheet'!$G$5:$G$54,MATCH($C$5,'Salary Sheet'!$A$5:$A$54,0)),0) | E18: Total deductions | F18: =IFERROR(INDEX('Salary Sheet'!$M$5:$M$54,MATCH($C$5,'Salary Sheet'!$A$5:$A$54,0)),0)
B20: NET PAY | F20: =IFERROR(INDEX('Salary Sheet'!$N$5:$N$54,MATCH($C$5,'Salary Sheet'!$A$5:$A$54,0)),0)
B23: This is a computer-generated salary slip.
E26: Authorised signatory

Sheet Setup
A1: Setup
A3: Company / shop name | B3: Your Company
A4: Address | B4: City, State
A5: Salary month (any date in it) | B5: =DATE(YEAR(TODAY()),MONTH(TODAY()),1)
A6: PF wage ceiling (₹ per month) | B6: 15000
A7: ESI limit (gross ₹ per month) | B7: 21000
A9: Days in this month | B9: =DAY(EOMONTH(B5,0))

Sheet Employees
A1: Employees
A2: Monthly (full-month) figures
A4: Emp. code | B4: Name | C4: Designation | D4: Date of joining | E4: PAN | F4: UAN (PF) | G4: ESI no. | H4: Bank A/c & IFSC | I4: Basic (₹) | J4: HRA (₹) | K4: Other allowances (₹) | L4: Gross (₹) | M4: PF? (Y/N) | N4: ESI? (Y/N) | O4: Professional tax (₹) | P4: Basic share
A5: E001 | B5: Ramesh Kumar | C5: Salesman | I5: 12000 | J5: 4800 | K5: 3200 | L5: =IF(A5="","",N(I5)+N(J5)+N(K5)) | M5: Y | N5: Y | O5: 0 | P5: =IF(OR(A5="",N(L5)=0),"",I5/L5)
A6: E002 | B6: Sunita Devi | C6: Accountant | I6: 16000 | J6: 6400 | K6: 2600 | L6: =IF(A6="","",N(I6)+N(J6)+N(K6)) | M6: Y | N6: N | O6: 0 | P6: =IF(OR(A6="",N(L6)=0),"",I6/L6)
L7: =IF(A7="","",N(I7)+N(J7)+N(K7)) | P7: =IF(OR(A7="",N(L7)=0),"",I7/L7)
L8: =IF(A8="","",N(I8)+N(J8)+N(K8)) | P8: =IF(OR(A8="",N(L8)=0),"",I8/L8)
L9: =IF(A9="","",N(I9)+N(J9)+N(K9)) | P9: =IF(OR(A9="",N(L9)=0),"",I9/L9)
L10: =IF(A10="","",N(I10)+N(J10)+N(K10)) | P10: =IF(OR(A10="",N(L10)=0),"",I10/L10)
L11: =IF(A11="","",N(I11)+N(J11)+N(K11)) | P11: =IF(OR(A11="",N(L11)=0),"",I11/L11)
L12: =IF(A12="","",N(I12)+N(J12)+N(K12)) | P12: =IF(OR(A12="",N(L12)=0),"",I12/L12)
L13: =IF(A13="","",N(I13)+N(J13)+N(K13)) | P13: =IF(OR(A13="",N(L13)=0),"",I13/L13)
L14: =IF(A14="","",N(I14)+N(J14)+N(K14)) | P14: =IF(OR(A14="",N(L14)=0),"",I14/L14)
L15: =IF(A15="","",N(I15)+N(J15)+N(K15)) | P15: =IF(OR(A15="",N(L15)=0),"",I15/L15)
L16: =IF(A16="","",N(I16)+N(J16)+N(K16)) | P16: =IF(OR(A16="",N(L16)=0),"",I16/L16)
L17: =IF(A17="","",N(I17)+N(J17)+N(K17)) | P17: =IF(OR(A17="",N(L17)=0),"",I17/L17)
L18: =IF(A18="","",N(I18)+N(J18)+N(K18)) | P18: =IF(OR(A18="",N(L18)=0),"",I18/L18)
... L54: =IF(A54="","",N(I54)+N(J54)+N(K54)) | P54: =IF(OR(A54="",N(L54)=0),"",I54/L54)

Sheet Attendance
A1: Attendance
A2: P present · A absent · H half day · L paid leave · WO weekly off · HO holiday
A4: Code | B4: Name | C4: =IF(1>Setup!$B$9,"",DATE(YEAR(Setup!$B$5),MONTH(Setup!$B$5),1)) | D4: =IF(2>Setup!$B$9,"",DATE(YEAR(Setup!$B$5),MONTH(Setup!$B$5),2)) | E4: =IF(3>Setup!$B$9,"",DATE(YEAR(Setup!$B$5),MONTH(Setup!$B$5),3)) | F4: =IF(4>Setup!$B$9,"",DATE(YEAR(Setup!$B$5),MONTH(Setup!$B$5),4)) | G4: =IF(5>Setup!$B$9,"",DATE(YEAR(Setup!$B$5),MONTH(Setup!$B$5),5)) | H4: =IF(6>Setup!$B$9,"",DATE(YEAR(Setup!$B$5),MONTH(Setup!$B$5),6)) | I4: =IF(7>Setup!$B$9,"",DATE(YEAR(Setup!$B$5),MONTH(Setup!$B$5),7)) | J4: =IF(8>Setup!$B$9,"",DATE(YEAR(Setup!$B$5),MONTH(Setup!$B$5),8)) | K4: =IF(9>Setup!$B$9,"",DATE(YEAR(Setup!$B$5),MONTH(Setup!$B$5),9)) | L4: =IF(10>Setup!$B$9,"",DATE(YEAR(Setup!$B$5),MONTH(Setup!$B$5),10)) | M4: =IF(11>Setup!$B$9,"",DATE(YEAR(Setup!$B$5),MONTH(Setup!$B$5),11)) | N4: =IF(12>Setup!$B$9,"",DATE(YEAR(Setup!$B$5),MONTH(Setup!$B$5),12)) | O4: =IF(13>Setup!$B$9,"",DATE(YEAR(Setup!$B$5),MONTH(Setup!$B$5),13)) | P4: =IF(14>Setup!$B$9,"",DATE(YEAR(Setup!$B$5),MONTH(Setup!$B$5),14)) | Q4: =IF(15>Setup!$B$9,"",DATE(YEAR(Setup!$B$5),MONTH(Setup!$B$5),15)) | R4: =IF(16>Setup!$B$9,"",DATE(YEAR(Setup!$B$5),MONTH(Setup!$B$5),16)) | S4: =IF(17>Setup!$B$9,"",DATE(YEAR(Setup!$B$5),MONTH(Setup!$B$5),17)) | T4: =IF(18>Setup!$B$9,"",DATE(YEAR(Setup!$B$5),MONTH(Setup!$B$5),18)) | U4: =IF(19>Setup!$B$9,"",DATE(YEAR(Setup!$B$5),MONTH(Setup!$B$5),19)) | V4: =IF(20>Setup!$B$9,"",DATE(YEAR(Setup!$B$5),MONTH(Setup!$B$5),20)) | W4: =IF(21>Setup!$B$9,"",DATE(YEAR(Setup!$B$5),MONTH(Setup!$B$5),21)) | X4: =IF(22>Setup!$B$9,"",DATE(YEAR(Setup!$B$5),MONTH(Setup!$B$5),22)) | Y4: =IF(23>Setup!$B$9,"",DATE(YEAR(Setup!$B$5),MONTH(Setup!$B$5),23)) | Z4: =IF(24>Setup!$B$9,"",DATE(YEAR(Setup!$B$5),MONTH(Setup!$B$5),24)) | AA4: =IF(25>Setup!$B$9,"",DATE(YEAR(Setup!$B$5),MONTH(Setup!$B$5),25)) | AB4: =IF(26>Setup!$B$9,"",DATE(YEAR(Setup!$B$5),MONTH(Setup!$B$5),26)) | AC4: =IF(27>Setup!$B$9,"",DATE(YEAR(Setup!$B$5),MONTH(Setup!$B$5),27)) | AD4: =IF(28>Setup!$B$9,"",DATE(YEAR(Setup!$B$5),MONTH(Setup!$B$5),28)) | AE4: =IF(29>Setup!$B$9,"",DATE(YEAR(Setup!$B$5),MONTH(Setup!$B$5),29)) | AF4: =IF(30>Setup!$B$9,"",DATE(YEAR(Setup!$B$5),MONTH(Setup!$B$5),30)) | AG4: =IF(31>Setup!$B$9,"",DATE(YEAR(Setup!$B$5),MONTH(Setup!$B$5),31)) | AH4: P | AI4: A | AJ4: H | AK4: L | AL4: WO+HO | AM4: Paid days
A5: =IF(Employees!A5="","",Employees!A5) | B5: =IF(Employees!B5="","",Employees!B5) | AH5: =COUNTIF(C5:AG5,"P") | AI5: =COUNTIF(C5:AG5,"A") | AJ5: =COUNTIF(C5:AG5,"H") | AK5: =COUNTIF(C5:AG5,"L") | AL5: =COUNTIF(C5:AG5,"WO")+COUNTIF(C5:AG5,"HO") | AM5: =IF(A5="","",MIN(Setup!$B$9,AH5+AK5+AL5+AJ5/2))
A6: =IF(Employees!A6="","",Employees!A6) | B6: =IF(Employees!B6="","",Employees!B6) | AH6: =COUNTIF(C6:AG6,"P") | AI6: =COUNTIF(C6:AG6,"A") | AJ6: =COUNTIF(C6:AG6,"H") | AK6: =COUNTIF(C6:AG6,"L") | AL6: =COUNTIF(C6:AG6,"WO")+COUNTIF(C6:AG6,"HO") | AM6: =IF(A6="","",MIN(Setup!$B$9,AH6+AK6+AL6+AJ6/2))
A7: =IF(Employees!A7="","",Employees!A7) | B7: =IF(Employees!B7="","",Employees!B7) | AH7: =COUNTIF(C7:AG7,"P") | AI7: =COUNTIF(C7:AG7,"A") | AJ7: =COUNTIF(C7:AG7,"H") | AK7: =COUNTIF(C7:AG7,"L") | AL7: =COUNTIF(C7:AG7,"WO")+COUNTIF(C7:AG7,"HO") | AM7: =IF(A7="","",MIN(Setup!$B$9,AH7+AK7+AL7+AJ7/2))
A8: =IF(Employees!A8="","",Employees!A8) | B8: =IF(Employees!B8="","",Employees!B8) | AH8: =COUNTIF(C8:AG8,"P") | AI8: =COUNTIF(C8:AG8,"A") | AJ8: =COUNTIF(C8:AG8,"H") | AK8: =COUNTIF(C8:AG8,"L") | AL8: =COUNTIF(C8:AG8,"WO")+COUNTIF(C8:AG8,"HO") | AM8: =IF(A8="","",MIN(Setup!$B$9,AH8+AK8+AL8+AJ8/2))
A9: =IF(Employees!A9="","",Employees!A9) | B9: =IF(Employees!B9="","",Employees!B9) | AH9: =COUNTIF(C9:AG9,"P") | AI9: =COUNTIF(C9:AG9,"A") | AJ9: =COUNTIF(C9:AG9,"H") | AK9: =COUNTIF(C9:AG9,"L") | AL9: =COUNTIF(C9:AG9,"WO")+COUNTIF(C9:AG9,"HO") | AM9: =IF(A9="","",MIN(Setup!$B$9,AH9+AK9+AL9+AJ9/2))
A10: =IF(Employees!A10="","",Employees!A10) | B10: =IF(Employees!B10="","",Employees!B10) | AH10: =COUNTIF(C10:AG10,"P") | AI10: =COUNTIF(C10:AG10,"A") | AJ10: =COUNTIF(C10:AG10,"H") | AK10: =COUNTIF(C10:AG10,"L") | AL10: =COUNTIF(C10:AG10,"WO")+COUNTIF(C10:AG10,"HO") | AM10: =IF(A10="","",MIN(Setup!$B$9,AH10+AK10+AL10+AJ10/2))
A11: =IF(Employees!A11="","",Employees!A11) | B11: =IF(Employees!B11="","",Employees!B11) | AH11: =COUNTIF(C11:AG11,"P") | AI11: =COUNTIF(C11:AG11,"A") | AJ11: =COUNTIF(C11:AG11,"H") | AK11: =COUNTIF(C11:AG11,"L") | AL11: =COUNTIF(C11:AG11,"WO")+COUNTIF(C11:AG11,"HO") | AM11: =IF(A11="","",MIN(Setup!$B$9,AH11+AK11+AL11+AJ11/2))
A12: =IF(Employees!A12="","",Employees!A12) | B12: =IF(Employees!B12="","",Employees!B12) | AH12: =COUNTIF(C12:AG12,"P") | AI12: =COUNTIF(C12:AG12,"A") | AJ12: =COUNTIF(C12:AG12,"H") | AK12: =COUNTIF(C12:AG12,"L") | AL12: =COUNTIF(C12:AG12,"WO")+COUNTIF(C12:AG12,"HO") | AM12: =IF(A12="","",MIN(Setup!$B$9,AH12+AK12+AL12+AJ12/2))
A13: =IF(Employees!A13="","",Employees!A13) | B13: =IF(Employees!B13="","",Employees!B13) | AH13: =COUNTIF(C13:AG13,"P") | AI13: =COUNTIF(C13:AG13,"A") | AJ13: =COUNTIF(C13:AG13,"H") | AK13: =COUNTIF(C13:AG13,"L") | AL13: =COUNTIF(C13:AG13,"WO")+COUNTIF(C13:AG13,"HO") | AM13: =IF(A13="","",MIN(Setup!$B$9,AH13+AK13+AL13+AJ13/2))
A14: =IF(Employees!A14="","",Employees!A14) | B14: =IF(Employees!B14="","",Employees!B14) | AH14: =COUNTIF(C14:AG14,"P") | AI14: =COUNTIF(C14:AG14,"A") | AJ14: =COUNTIF(C14:AG14,"H") | AK14: =COUNTIF(C14:AG14,"L") | AL14: =COUNTIF(C14:AG14,"WO")+COUNTIF(C14:AG14,"HO") | AM14: =IF(A14="","",MIN(Setup!$B$9,AH14+AK14+AL14+AJ14/2))
A15: =IF(Employees!A15="","",Employees!A15) | B15: =IF(Employees!B15="","",Employees!B15) | AH15: =COUNTIF(C15:AG15,"P") | AI15: =COUNTIF(C15:AG15,"A") | AJ15: =COUNTIF(C15:AG15,"H") | AK15: =COUNTIF(C15:AG15,"L") | AL15: =COUNTIF(C15:AG15,"WO")+COUNTIF(C15:AG15,"HO") | AM15: =IF(A15="","",MIN(Setup!$B$9,AH15+AK15+AL15+AJ15/2))
A16: =IF(Employees!A16="","",Employees!A16) | B16: =IF(Employees!B16="","",Employees!B16) | AH16: =COUNTIF(C16:AG16,"P") | AI16: =COUNTIF(C16:AG16,"A") | AJ16: =COUNTIF(C16:AG16,"H") | AK16: =COUNTIF(C16:AG16,"L") | AL16: =COUNTIF(C16:AG16,"WO")+COUNTIF(C16:AG16,"HO") | AM16: =IF(A16="","",MIN(Setup!$B$9,AH16+AK16+AL16+AJ16/2))
... A54: =IF(Employees!A54="","",Employees!A54) | B54: =IF(Employees!B54="","",Employees!B54) | AH54: =COUNTIF(C54:AG54,"P") | AI54: =COUNTIF(C54:AG54,"A") | AJ54: =COUNTIF(C54:AG54,"H") | AK54: =COUNTIF(C54:AG54,"L") | AL54: =COUNTIF(C54:AG54,"WO")+COUNTIF(C54:AG54,"HO") | AM54: =IF(A54="","",MIN(Setup!$B$9,AH54+AK54+AL54+AJ54/2))

Sheet Salary Sheet
A1: Salary Sheet
A2: ="For "&TEXT(Setup!B5,"mmmm yyyy")
A4: Code | B4: Name | C4: Paid days | D4: Basic earned | E4: HRA earned | F4: Other earned | G4: Gross earned | H4: PF (employee 12%) | I4: ESI (employee 0.75%) | J4: Professional tax | K4: TDS | L4: Advance / other deduction | M4: Total deductions | N4: NET PAY | O4: PF (employer 12%) | P4: ESI (employer 3.25%) | Q4: Cost to company
A5: =IF(Employees!A5="","",Employees!A5) | B5: =IF(A5="","",Employees!B5) | C5: =IF(A5="","",Attendance!AM5) | D5: =IF(A5="","",ROUND(N(Employees!I5)/Setup!$B$9*C5,0)) | E5: =IF(A5="","",ROUND(N(Employees!J5)/Setup!$B$9*C5,0)) | F5: =IF(A5="","",ROUND(N(Employees!K5)/Setup!$B$9*C5,0)) | G5: =IF(A5="","",D5+E5+F5) | H5: =IF(OR(A5="",Employees!M5<>"Y"),0,ROUND(MIN(D5,Setup!$B$6)*12%,0)) | I5: =IF(OR(A5="",Employees!N5<>"Y",N(Employees!L5)>Setup!$B$7),0,ROUNDUP(G5*0.75%,0)) | J5: =IF(A5="","",N(Employees!O5)) | M5: =IF(A5="","",H5+I5+J5+N(K5)+N(L5)) | N5: =IF(A5="","",G5-M5) | O5: =IF(OR(A5="",Employees!M5<>"Y"),0,ROUND(MIN(D5,Setup!$B$6)*12%,0)) | P5: =IF(OR(A5="",Employees!N5<>"Y",N(Employees!L5)>Setup!$B$7),0,ROUNDUP(G5*3.25%,0)) | Q5: =IF(A5="","",G5+O5+P5)
A6: =IF(Employees!A6="","",Employees!A6) | B6: =IF(A6="","",Employees!B6) | C6: =IF(A6="","",Attendance!AM6) | D6: =IF(A6="","",ROUND(N(Employees!I6)/Setup!$B$9*C6,0)) | E6: =IF(A6="","",ROUND(N(Employees!J6)/Setup!$B$9*C6,0)) | F6: =IF(A6="","",ROUND(N(Employees!K6)/Setup!$B$9*C6,0)) | G6: =IF(A6="","",D6+E6+F6) | H6: =IF(OR(A6="",Employees!M6<>"Y"),0,ROUND(MIN(D6,Setup!$B$6)*12%,0)) | I6: =IF(OR(A6="",Employees!N6<>"Y",N(Employees!L6)>Setup!$B$7),0,ROUNDUP(G6*0.75%,0)) | J6: =IF(A6="","",N(Employees!O6)) | M6: =IF(A6="","",H6+I6+J6+N(K6)+N(L6)) | N6: =IF(A6="","",G6-M6) | O6: =IF(OR(A6="",Employees!M6<>"Y"),0,ROUND(MIN(D6,Setup!$B$6)*12%,0)) | P6: =IF(OR(A6="",Employees!N6<>"Y",N(Employees!L6)>Setup!$B$7),0,ROUNDUP(G6*3.25%,0)) | Q6: =IF(A6="","",G6+O6+P6)
A7: =IF(Employees!A7="","",Employees!A7) | B7: =IF(A7="","",Employees!B7) | C7: =IF(A7="","",Attendance!AM7) | D7: =IF(A7="","",ROUND(N(Employees!I7)/Setup!$B$9*C7,0)) | E7: =IF(A7="","",ROUND(N(Employees!J7)/Setup!$B$9*C7,0)) | F7: =IF(A7="","",ROUND(N(Employees!K7)/Setup!$B$9*C7,0)) | G7: =IF(A7="","",D7+E7+F7) | H7: =IF(OR(A7="",Employees!M7<>"Y"),0,ROUND(MIN(D7,Setup!$B$6)*12%,0)) | I7: =IF(OR(A7="",Employees!N7<>"Y",N(Employees!L7)>Setup!$B$7),0,ROUNDUP(G7*0.75%,0)) | J7: =IF(A7="","",N(Employees!O7)) | M7: =IF(A7="","",H7+I7+J7+N(K7)+N(L7)) | N7: =IF(A7="","",G7-M7) | O7: =IF(OR(A7="",Employees!M7<>"Y"),0,ROUND(MIN(D7,Setup!$B$6)*12%,0)) | P7: =IF(OR(A7="",Employees!N7<>"Y",N(Employees!L7)>Setup!$B$7),0,ROUNDUP(G7*3.25%,0)) | Q7: =IF(A7="","",G7+O7+P7)
A8: =IF(Employees!A8="","",Employees!A8) | B8: =IF(A8="","",Employees!B8) | C8: =IF(A8="","",Attendance!AM8) | D8: =IF(A8="","",ROUND(N(Employees!I8)/Setup!$B$9*C8,0)) | E8: =IF(A8="","",ROUND(N(Employees!J8)/Setup!$B$9*C8,0)) | F8: =IF(A8="","",ROUND(N(Employees!K8)/Setup!$B$9*C8,0)) | G8: =IF(A8="","",D8+E8+F8) | H8: =IF(OR(A8="",Employees!M8<>"Y"),0,ROUND(MIN(D8,Setup!$B$6)*12%,0)) | I8: =IF(OR(A8="",Employees!N8<>"Y",N(Employees!L8)>Setup!$B$7),0,ROUNDUP(G8*0.75%,0)) | J8: =IF(A8="","",N(Employees!O8)) | M8: =IF(A8="","",H8+I8+J8+N(K8)+N(L8)) | N8: =IF(A8="","",G8-M8) | O8: =IF(OR(A8="",Employees!M8<>"Y"),0,ROUND(MIN(D8,Setup!$B$6)*12%,0)) | P8: =IF(OR(A8="",Employees!N8<>"Y",N(Employees!L8)>Setup!$B$7),0,ROUNDUP(G8*3.25%,0)) | Q8: =IF(A8="","",G8+O8+P8)
A9: =IF(Employees!A9="","",Employees!A9) | B9: =IF(A9="","",Employees!B9) | C9: =IF(A9="","",Attendance!AM9) | D9: =IF(A9="","",ROUND(N(Employees!I9)/Setup!$B$9*C9,0)) | E9: =IF(A9="","",ROUND(N(Employees!J9)/Setup!$B$9*C9,0)) | F9: =IF(A9="","",ROUND(N(Employees!K9)/Setup!$B$9*C9,0)) | G9: =IF(A9="","",D9+E9+F9) | H9: =IF(OR(A9="",Employees!M9<>"Y"),0,ROUND(MIN(D9,Setup!$B$6)*12%,0)) | I9: =IF(OR(A9="",Employees!N9<>"Y",N(Employees!L9)>Setup!$B$7),0,ROUNDUP(G9*0.75%,0)) | J9: =IF(A9="","",N(Employees!O9)) | M9: =IF(A9="","",H9+I9+J9+N(K9)+N(L9)) | N9: =IF(A9="","",G9-M9) | O9: =IF(OR(A9="",Employees!M9<>"Y"),0,ROUND(MIN(D9,Setup!$B$6)*12%,0)) | P9: =IF(OR(A9="",Employees!N9<>"Y",N(Employees!L9)>Setup!$B$7),0,ROUNDUP(G9*3.25%,0)) | Q9: =IF(A9="","",G9+O9+P9)
A10: =IF(Employees!A10="","",Employees!A10) | B10: =IF(A10="","",Employees!B10) | C10: =IF(A10="","",Attendance!AM10) | D10: =IF(A10="","",ROUND(N(Employees!I10)/Setup!$B$9*C10,0)) | E10: =IF(A10="","",ROUND(N(Employees!J10)/Setup!$B$9*C10,0)) | F10: =IF(A10="","",ROUND(N(Employees!K10)/Setup!$B$9*C10,0)) | G10: =IF(A10="","",D10+E10+F10) | H10: =IF(OR(A10="",Employees!M10<>"Y"),0,ROUND(MIN(D10,Setup!$B$6)*12%,0)) | I10: =IF(OR(A10="",Employees!N10<>"Y",N(Employees!L10)>Setup!$B$7),0,ROUNDUP(G10*0.75%,0)) | J10: =IF(A10="","",N(Employees!O10)) | M10: =IF(A10="","",H10+I10+J10+N(K10)+N(L10)) | N10: =IF(A10="","",G10-M10) | O10: =IF(OR(A10="",Employees!M10<>"Y"),0,ROUND(MIN(D10,Setup!$B$6)*12%,0)) | P10: =IF(OR(A10="",Employees!N10<>"Y",N(Employees!L10)>Setup!$B$7),0,ROUNDUP(G10*3.25%,0)) | Q10: =IF(A10="","",G10+O10+P10)
A11: =IF(Employees!A11="","",Employees!A11) | B11: =IF(A11="","",Employees!B11) | C11: =IF(A11="","",Attendance!AM11) | D11: =IF(A11="","",ROUND(N(Employees!I11)/Setup!$B$9*C11,0)) | E11: =IF(A11="","",ROUND(N(Employees!J11)/Setup!$B$9*C11,0)) | F11: =IF(A11="","",ROUND(N(Employees!K11)/Setup!$B$9*C11,0)) | G11: =IF(A11="","",D11+E11+F11) | H11: =IF(OR(A11="",Employees!M11<>"Y"),0,ROUND(MIN(D11,Setup!$B$6)*12%,0)) | I11: =IF(OR(A11="",Employees!N11<>"Y",N(Employees!L11)>Setup!$B$7),0,ROUNDUP(G11*0.75%,0)) | J11: =IF(A11="","",N(Employees!O11)) | M11: =IF(A11="","",H11+I11+J11+N(K11)+N(L11)) | N11: =IF(A11="","",G11-M11) | O11: =IF(OR(A11="",Employees!M11<>"Y"),0,ROUND(MIN(D11,Setup!$B$6)*12%,0)) | P11: =IF(OR(A11="",Employees!N11<>"Y",N(Employees!L11)>Setup!$B$7),0,ROUNDUP(G11*3.25%,0)) | Q11: =IF(A11="","",G11+O11+P11)
A12: =IF(Employees!A12="","",Employees!A12) | B12: =IF(A12="","",Employees!B12) | C12: =IF(A12="","",Attendance!AM12) | D12: =IF(A12="","",ROUND(N(Employees!I12)/Setup!$B$9*C12,0)) | E12: =IF(A12="","",ROUND(N(Employees!J12)/Setup!$B$9*C12,0)) | F12: =IF(A12="","",ROUND(N(Employees!K12)/Setup!$B$9*C12,0)) | G12: =IF(A12="","",D12+E12+F12) | H12: =IF(OR(A12="",Employees!M12<>"Y"),0,ROUND(MIN(D12,Setup!$B$6)*12%,0)) | I12: =IF(OR(A12="",Employees!N12<>"Y",N(Employees!L12)>Setup!$B$7),0,ROUNDUP(G12*0.75%,0)) | J12: =IF(A12="","",N(Employees!O12)) | M12: =IF(A12="","",H12+I12+J12+N(K12)+N(L12)) | N12: =IF(A12="","",G12-M12) | O12: =IF(OR(A12="",Employees!M12<>"Y"),0,ROUND(MIN(D12,Setup!$B$6)*12%,0)) | P12: =IF(OR(A12="",Employees!N12<>"Y",N(Employees!L12)>Setup!$B$7),0,ROUNDUP(G12*3.25%,0)) | Q12: =IF(A12="","",G12+O12+P12)
A13: =IF(Employees!A13="","",Employees!A13) | B13: =IF(A13="","",Employees!B13) | C13: =IF(A13="","",Attendance!AM13) | D13: =IF(A13="","",ROUND(N(Employees!I13)/Setup!$B$9*C13,0)) | E13: =IF(A13="","",ROUND(N(Employees!J13)/Setup!$B$9*C13,0)) | F13: =IF(A13="","",ROUND(N(Employees!K13)/Setup!$B$9*C13,0)) | G13: =IF(A13="","",D13+E13+F13) | H13: =IF(OR(A13="",Employees!M13<>"Y"),0,ROUND(MIN(D13,Setup!$B$6)*12%,0)) | I13: =IF(OR(A13="",Employees!N13<>"Y",N(Employees!L13)>Setup!$B$7),0,ROUNDUP(G13*0.75%,0)) | J13: =IF(A13="","",N(Employees!O13)) | M13: =IF(A13="","",H13+I13+J13+N(K13)+N(L13)) | N13: =IF(A13="","",G13-M13) | O13: =IF(OR(A13="",Employees!M13<>"Y"),0,ROUND(MIN(D13,Setup!$B$6)*12%,0)) | P13: =IF(OR(A13="",Employees!N13<>"Y",N(Employees!L13)>Setup!$B$7),0,ROUNDUP(G13*3.25%,0)) | Q13: =IF(A13="","",G13+O13+P13)
A14: =IF(Employees!A14="","",Employees!A14) | B14: =IF(A14="","",Employees!B14) | C14: =IF(A14="","",Attendance!AM14) | D14: =IF(A14="","",ROUND(N(Employees!I14)/Setup!$B$9*C14,0)) | E14: =IF(A14="","",ROUND(N(Employees!J14)/Setup!$B$9*C14,0)) | F14: =IF(A14="","",ROUND(N(Employees!K14)/Setup!$B$9*C14,0)) | G14: =IF(A14="","",D14+E14+F14) | H14: =IF(OR(A14="",Employees!M14<>"Y"),0,ROUND(MIN(D14,Setup!$B$6)*12%,0)) | I14: =IF(OR(A14="",Employees!N14<>"Y",N(Employees!L14)>Setup!$B$7),0,ROUNDUP(G14*0.75%,0)) | J14: =IF(A14="","",N(Employees!O14)) | M14: =IF(A14="","",H14+I14+J14+N(K14)+N(L14)) | N14: =IF(A14="","",G14-M14) | O14: =IF(OR(A14="",Employees!M14<>"Y"),0,ROUND(MIN(D14,Setup!$B$6)*12%,0)) | P14: =IF(OR(A14="",Employees!N14<>"Y",N(Employees!L14)>Setup!$B$7),0,ROUNDUP(G14*3.25%,0)) | Q14: =IF(A14="","",G14+O14+P14)
A15: =IF(Employees!A15="","",Employees!A15) | B15: =IF(A15="","",Employees!B15) | C15: =IF(A15="","",Attendance!AM15) | D15: =IF(A15="","",ROUND(N(Employees!I15)/Setup!$B$9*C15,0)) | E15: =IF(A15="","",ROUND(N(Employees!J15)/Setup!$B$9*C15,0)) | F15: =IF(A15="","",ROUND(N(Employees!K15)/Setup!$B$9*C15,0)) | G15: =IF(A15="","",D15+E15+F15) | H15: =IF(OR(A15="",Employees!M15<>"Y"),0,ROUND(MIN(D15,Setup!$B$6)*12%,0)) | I15: =IF(OR(A15="",Employees!N15<>"Y",N(Employees!L15)>Setup!$B$7),0,ROUNDUP(G15*0.75%,0)) | J15: =IF(A15="","",N(Employees!O15)) | M15: =IF(A15="","",H15+I15+J15+N(K15)+N(L15)) | N15: =IF(A15="","",G15-M15) | O15: =IF(OR(A15="",Employees!M15<>"Y"),0,ROUND(MIN(D15,Setup!$B$6)*12%,0)) | P15: =IF(OR(A15="",Employees!N15<>"Y",N(Employees!L15)>Setup!$B$7),0,ROUNDUP(G15*3.25%,0)) | Q15: =IF(A15="","",G15+O15+P15)
A16: =IF(Employees!A16="","",Employees!A16) | B16: =IF(A16="","",Employees!B16) | C16: =IF(A16="","",Attendance!AM16) | D16: =IF(A16="","",ROUND(N(Employees!I16)/Setup!$B$9*C16,0)) | E16: =IF(A16="","",ROUND(N(Employees!J16)/Setup!$B$9*C16,0)) | F16: =IF(A16="","",ROUND(N(Employees!K16)/Setup!$B$9*C16,0)) | G16: =IF(A16="","",D16+E16+F16) | H16: =IF(OR(A16="",Employees!M16<>"Y"),0,ROUND(MIN(D16,Setup!$B$6)*12%,0)) | I16: =IF(OR(A16="",Employees!N16<>"Y",N(Employees!L16)>Setup!$B$7),0,ROUNDUP(G16*0.75%,0)) | J16: =IF(A16="","",N(Employees!O16)) | M16: =IF(A16="","",H16+I16+J16+N(K16)+N(L16)) | N16: =IF(A16="","",G16-M16) | O16: =IF(OR(A16="",Employees!M16<>"Y"),0,ROUND(MIN(D16,Setup!$B$6)*12%,0)) | P16: =IF(OR(A16="",Employees!N16<>"Y",N(Employees!L16)>Setup!$B$7),0,ROUNDUP(G16*3.25%,0)) | Q16: =IF(A16="","",G16+O16+P16)
... A54: =IF(Employees!A54="","",Employees!A54) | B54: =IF(A54="","",Employees!B54) | C54: =IF(A54="","",Attendance!AM54) | D54: =IF(A54="","",ROUND(N(Employees!I54)/Setup!$B$9*C54,0)) | E54: =IF(A54="","",ROUND(N(Employees!J54)/Setup!$B$9*C54,0)) | F54: =IF(A54="","",ROUND(N(Employees!K54)/Setup!$B$9*C54,0)) | G54: =IF(A54="","",D54+E54+F54) | H54: =IF(OR(A54="",Employees!M54<>"Y"),0,ROUND(MIN(D54,Setup!$B$6)*12%,0)) | I54: =IF(OR(A54="",Employees!N54<>"Y",N(Employees!L54)>Setup!$B$7),0,ROUNDUP(G54*0.75%,0)) | J54: =IF(A54="","",N(Employees!O54)) | M54: =IF(A54="","",H54+I54+J54+N(K54)+N(L54)) | N54: =IF(A54="","",G54-M54) | O54: =IF(OR(A54="",Employees!M54<>"Y"),0,ROUND(MIN(D54,Setup!$B$6)*12%,0)) | P54: =IF(OR(A54="",Employees!N54<>"Y",N(Employees!L54)>Setup!$B$7),0,ROUNDUP(G54*3.25%,0)) | Q54: =IF(A54="","",G54+O54+P54)
B55: TOTAL | D55: =SUM(D5:D54) | E55: =SUM(E5:E54) | F55: =SUM(F5:F54) | G55: =SUM(G5:G54) | H55: =SUM(H5:H54) | I55: =SUM(I5:I54) | J55: =SUM(J5:J54) | K55: =SUM(K5:K54) | ... Q55: =SUM(Q5:Q54)
