Workbook

Sheet How to use
B1: Small Business Bookkeeping Kit
B2: Rajput Lalit & Associates · www.rajputlalitassociates.in · WhatsApp +91 93549 53603
B4: Steps
A5: 1 | B5: In 'Settings' enter your business name and the opening cash and bank balance on 1 April 2026.
A6: 2 | B6: Record every cash receipt/payment in 'Cash Book' and every bank entry in 'Bank Book' — the balance runs automatically.
A7: 3 | B7: Record each sale bill in 'Sales Register' and each purchase bill in 'Purchase Register'.
A8: 4 | B8: Record expenses (rent, salary, electricity...) in 'Expenses' and choose the head from the drop-down.
A9: 5 | B9: In the Purchase Register mark whether the bill appears in your GSTR-2B — 'ITC Tracker' then shows the month-wise gap.
A10: 6 | B10: Open 'P&L Summary' any time to see month-wise sales, purchases, expenses and profit.
A11: 7 | B11: Share this file with your CA at year end — everything is already classified.
B13: Good to know
B14: • If a sale/purchase is paid in cash or bank, also enter it in the Cash/Bank Book so balances stay correct.
B15: • Profit shown is an estimate (no stock valuation or depreciation) — your CA will finalise it.
B16: • Cash expenses above ₹10,000 paid to one person in a day are not allowed as a deduction (Income Tax rule) — pay by bank.
B18: Cells shaded light yellow are for your entries. White cells contain formulas — please don't type over them.
B20: Licensed for use in your own business. Please do not resell or share publicly. This template is a working aid, not professional advice.

Sheet Settings
A1: Settings
A3: Business name | B3: Your Business Name
A4: Financial year | B4: FY 2026-27
A5: Opening cash balance (1 Apr 2026) | B5: 0
A6: Opening bank balance (1 Apr 2026) | B6: 0

Sheet Heads
A1: Expense heads (edit if you like)
A2: Rent
A3: Salary & Wages
A4: Electricity
A5: Telephone & Internet
A6: Travel & Conveyance
A7: Office Expenses
A8: Printing & Stationery
A9: Repairs & Maintenance
A10: Professional Fees
A11: Bank Charges
A12: Advertising
... A16: Miscellaneous

Sheet Cash Book
A1: Cash Book
A2: Balance is calculated automatically
A4: Date | B4: Particulars | C4: Voucher / Ref | D4: Receipt (In) | E4: Payment (Out) | F4: Balance
B5: Opening balance | F5: =Settings!B5
F6: =IF(AND(D6="",E6=""),"",Settings!B5+SUM(D$6:D6)-SUM(E$6:E6))
F7: =IF(AND(D7="",E7=""),"",Settings!B5+SUM(D$6:D7)-SUM(E$6:E7))
F8: =IF(AND(D8="",E8=""),"",Settings!B5+SUM(D$6:D8)-SUM(E$6:E8))
F9: =IF(AND(D9="",E9=""),"",Settings!B5+SUM(D$6:D9)-SUM(E$6:E9))
F10: =IF(AND(D10="",E10=""),"",Settings!B5+SUM(D$6:D10)-SUM(E$6:E10))
F11: =IF(AND(D11="",E11=""),"",Settings!B5+SUM(D$6:D11)-SUM(E$6:E11))
F12: =IF(AND(D12="",E12=""),"",Settings!B5+SUM(D$6:D12)-SUM(E$6:E12))
F13: =IF(AND(D13="",E13=""),"",Settings!B5+SUM(D$6:D13)-SUM(E$6:E13))
F14: =IF(AND(D14="",E14=""),"",Settings!B5+SUM(D$6:D14)-SUM(E$6:E14))
F15: =IF(AND(D15="",E15=""),"",Settings!B5+SUM(D$6:D15)-SUM(E$6:E15))
F16: =IF(AND(D16="",E16=""),"",Settings!B5+SUM(D$6:D16)-SUM(E$6:E16))
F17: =IF(AND(D17="",E17=""),"",Settings!B5+SUM(D$6:D17)-SUM(E$6:E17))
F18: =IF(AND(D18="",E18=""),"",Settings!B5+SUM(D$6:D18)-SUM(E$6:E18))
F19: =IF(AND(D19="",E19=""),"",Settings!B5+SUM(D$6:D19)-SUM(E$6:E19))
F20: =IF(AND(D20="",E20=""),"",Settings!B5+SUM(D$6:D20)-SUM(E$6:E20))
F21: =IF(AND(D21="",E21=""),"",Settings!B5+SUM(D$6:D21)-SUM(E$6:E21))
F22: =IF(AND(D22="",E22=""),"",Settings!B5+SUM(D$6:D22)-SUM(E$6:E22))
F23: =IF(AND(D23="",E23=""),"",Settings!B5+SUM(D$6:D23)-SUM(E$6:E23))
F24: =IF(AND(D24="",E24=""),"",Settings!B5+SUM(D$6:D24)-SUM(E$6:E24))
F25: =IF(AND(D25="",E25=""),"",Settings!B5+SUM(D$6:D25)-SUM(E$6:E25))
F26: =IF(AND(D26="",E26=""),"",Settings!B5+SUM(D$6:D26)-SUM(E$6:E26))
F27: =IF(AND(D27="",E27=""),"",Settings!B5+SUM(D$6:D27)-SUM(E$6:E27))
F28: =IF(AND(D28="",E28=""),"",Settings!B5+SUM(D$6:D28)-SUM(E$6:E28))
F29: =IF(AND(D29="",E29=""),"",Settings!B5+SUM(D$6:D29)-SUM(E$6:E29))
F30: =IF(AND(D30="",E30=""),"",Settings!B5+SUM(D$6:D30)-SUM(E$6:E30))
F31: =IF(AND(D31="",E31=""),"",Settings!B5+SUM(D$6:D31)-SUM(E$6:E31))
F32: =IF(AND(D32="",E32=""),"",Settings!B5+SUM(D$6:D32)-SUM(E$6:E32))
F33: =IF(AND(D33="",E33=""),"",Settings!B5+SUM(D$6:D33)-SUM(E$6:E33))
F34: =IF(AND(D34="",E34=""),"",Settings!B5+SUM(D$6:D34)-SUM(E$6:E34))
F35: =IF(AND(D35="",E35=""),"",Settings!B5+SUM(D$6:D35)-SUM(E$6:E35))
F36: =IF(AND(D36="",E36=""),"",Settings!B5+SUM(D$6:D36)-SUM(E$6:E36))
F37: =IF(AND(D37="",E37=""),"",Settings!B5+SUM(D$6:D37)-SUM(E$6:E37))
F38: =IF(AND(D38="",E38=""),"",Settings!B5+SUM(D$6:D38)-SUM(E$6:E38))
F39: =IF(AND(D39="",E39=""),"",Settings!B5+SUM(D$6:D39)-SUM(E$6:E39))
F40: =IF(AND(D40="",E40=""),"",Settings!B5+SUM(D$6:D40)-SUM(E$6:E40))
F41: =IF(AND(D41="",E41=""),"",Settings!B5+SUM(D$6:D41)-SUM(E$6:E41))
F42: =IF(AND(D42="",E42=""),"",Settings!B5+SUM(D$6:D42)-SUM(E$6:E42))
F43: =IF(AND(D43="",E43=""),"",Settings!B5+SUM(D$6:D43)-SUM(E$6:E43))
F44: =IF(AND(D44="",E44=""),"",Settings!B5+SUM(D$6:D44)-SUM(E$6:E44))
F45: =IF(AND(D45="",E45=""),"",Settings!B5+SUM(D$6:D45)-SUM(E$6:E45))
F46: =IF(AND(D46="",E46=""),"",Settings!B5+SUM(D$6:D46)-SUM(E$6:E46))
F47: =IF(AND(D47="",E47=""),"",Settings!B5+SUM(D$6:D47)-SUM(E$6:E47))
F48: =IF(AND(D48="",E48=""),"",Settings!B5+SUM(D$6:D48)-SUM(E$6:E48))
F49: =IF(AND(D49="",E49=""),"",Settings!B5+SUM(D$6:D49)-SUM(E$6:E49))
F50: =IF(AND(D50="",E50=""),"",Settings!B5+SUM(D$6:D50)-SUM(E$6:E50))
F51: =IF(AND(D51="",E51=""),"",Settings!B5+SUM(D$6:D51)-SUM(E$6:E51))
F52: =IF(AND(D52="",E52=""),"",Settings!B5+SUM(D$6:D52)-SUM(E$6:E52))
F53: =IF(AND(D53="",E53=""),"",Settings!B5+SUM(D$6:D53)-SUM(E$6:E53))
F54: =IF(AND(D54="",E54=""),"",Settings!B5+SUM(D$6:D54)-SUM(E$6:E54))
F55: =IF(AND(D55="",E55=""),"",Settings!B5+SUM(D$6:D55)-SUM(E$6:E55))
F56: =IF(AND(D56="",E56=""),"",Settings!B5+SUM(D$6:D56)-SUM(E$6:E56))
F57: =IF(AND(D57="",E57=""),"",Settings!B5+SUM(D$6:D57)-SUM(E$6:E57))
F58: =IF(AND(D58="",E58=""),"",Settings!B5+SUM(D$6:D58)-SUM(E$6:E58))
F59: =IF(AND(D59="",E59=""),"",Settings!B5+SUM(D$6:D59)-SUM(E$6:E59))
F60: =IF(AND(D60="",E60=""),"",Settings!B5+SUM(D$6:D60)-SUM(E$6:E60))
F61: =IF(AND(D61="",E61=""),"",Settings!B5+SUM(D$6:D61)-SUM(E$6:E61))
F62: =IF(AND(D62="",E62=""),"",Settings!B5+SUM(D$6:D62)-SUM(E$6:E62))
F63: =IF(AND(D63="",E63=""),"",Settings!B5+SUM(D$6:D63)-SUM(E$6:E63))
F64: =IF(AND(D64="",E64=""),"",Settings!B5+SUM(D$6:D64)-SUM(E$6:E64))
F65: =IF(AND(D65="",E65=""),"",Settings!B5+SUM(D$6:D65)-SUM(E$6:E65))
F66: =IF(AND(D66="",E66=""),"",Settings!B5+SUM(D$6:D66)-SUM(E$6:E66))
F67: =IF(AND(D67="",E67=""),"",Settings!B5+SUM(D$6:D67)-SUM(E$6:E67))
F68: =IF(AND(D68="",E68=""),"",Settings!B5+SUM(D$6:D68)-SUM(E$6:E68))
F69: =IF(AND(D69="",E69=""),"",Settings!B5+SUM(D$6:D69)-SUM(E$6:E69))
F70: =IF(AND(D70="",E70=""),"",Settings!B5+SUM(D$6:D70)-SUM(E$6:E70))
F71: =IF(AND(D71="",E71=""),"",Settings!B5+SUM(D$6:D71)-SUM(E$6:E71))
F72: =IF(AND(D72="",E72=""),"",Settings!B5+SUM(D$6:D72)-SUM(E$6:E72))
F73: =IF(AND(D73="",E73=""),"",Settings!B5+SUM(D$6:D73)-SUM(E$6:E73))
F74: =IF(AND(D74="",E74=""),"",Settings!B5+SUM(D$6:D74)-SUM(E$6:E74))
F75: =IF(AND(D75="",E75=""),"",Settings!B5+SUM(D$6:D75)-SUM(E$6:E75))
F76: =IF(AND(D76="",E76=""),"",Settings!B5+SUM(D$6:D76)-SUM(E$6:E76))
F77: =IF(AND(D77="",E77=""),"",Settings!B5+SUM(D$6:D77)-SUM(E$6:E77))
F78: =IF(AND(D78="",E78=""),"",Settings!B5+SUM(D$6:D78)-SUM(E$6:E78))
F79: =IF(AND(D79="",E79=""),"",Settings!B5+SUM(D$6:D79)-SUM(E$6:E79))
F80: =IF(AND(D80="",E80=""),"",Settings!B5+SUM(D$6:D80)-SUM(E$6:E80))
F81: =IF(AND(D81="",E81=""),"",Settings!B5+SUM(D$6:D81)-SUM(E$6:E81))
F82: =IF(AND(D82="",E82=""),"",Settings!B5+SUM(D$6:D82)-SUM(E$6:E82))
F83: =IF(AND(D83="",E83=""),"",Settings!B5+SUM(D$6:D83)-SUM(E$6:E83))
F84: =IF(AND(D84="",E84=""),"",Settings!B5+SUM(D$6:D84)-SUM(E$6:E84))
F85: =IF(AND(D85="",E85=""),"",Settings!B5+SUM(D$6:D85)-SUM(E$6:E85))
F86: =IF(AND(D86="",E86=""),"",Settings!B5+SUM(D$6:D86)-SUM(E$6:E86))
F87: =IF(AND(D87="",E87=""),"",Settings!B5+SUM(D$6:D87)-SUM(E$6:E87))
F88: =IF(AND(D88="",E88=""),"",Settings!B5+SUM(D$6:D88)-SUM(E$6:E88))
F89: =IF(AND(D89="",E89=""),"",Settings!B5+SUM(D$6:D89)-SUM(E$6:E89))
F90: =IF(AND(D90="",E90=""),"",Settings!B5+SUM(D$6:D90)-SUM(E$6:E90))
F91: =IF(AND(D91="",E91=""),"",Settings!B5+SUM(D$6:D91)-SUM(E$6:E91))
F92: =IF(AND(D92="",E92=""),"",Settings!B5+SUM(D$6:D92)-SUM(E$6:E92))
F93: =IF(AND(D93="",E93=""),"",Settings!B5+SUM(D$6:D93)-SUM(E$6:E93))
F94: =IF(AND(D94="",E94=""),"",Settings!B5+SUM(D$6:D94)-SUM(E$6:E94))
F95: =IF(AND(D95="",E95=""),"",Settings!B5+SUM(D$6:D95)-SUM(E$6:E95))
F96: =IF(AND(D96="",E96=""),"",Settings!B5+SUM(D$6:D96)-SUM(E$6:E96))
F97: =IF(AND(D97="",E97=""),"",Settings!B5+SUM(D$6:D97)-SUM(E$6:E97))
F98: =IF(AND(D98="",E98=""),"",Settings!B5+SUM(D$6:D98)-SUM(E$6:E98))
F99: =IF(AND(D99="",E99=""),"",Settings!B5+SUM(D$6:D99)-SUM(E$6:E99))
F100: =IF(AND(D100="",E100=""),"",Settings!B5+SUM(D$6:D100)-SUM(E$6:E100))
F101: =IF(AND(D101="",E101=""),"",Settings!B5+SUM(D$6:D101)-SUM(E$6:E101))
...

Sheet Bank Book
A1: Bank Book
A2: Balance is calculated automatically
A4: Date | B4: Particulars | C4: Voucher / Ref | D4: Cheque / UTR | E4: Receipt (In) | F4: Payment (Out) | G4: Balance
B5: Opening balance | G5: =Settings!B6
G6: =IF(AND(E6="",F6=""),"",Settings!B6+SUM(E$6:E6)-SUM(F$6:F6))
G7: =IF(AND(E7="",F7=""),"",Settings!B6+SUM(E$6:E7)-SUM(F$6:F7))
G8: =IF(AND(E8="",F8=""),"",Settings!B6+SUM(E$6:E8)-SUM(F$6:F8))
G9: =IF(AND(E9="",F9=""),"",Settings!B6+SUM(E$6:E9)-SUM(F$6:F9))
G10: =IF(AND(E10="",F10=""),"",Settings!B6+SUM(E$6:E10)-SUM(F$6:F10))
G11: =IF(AND(E11="",F11=""),"",Settings!B6+SUM(E$6:E11)-SUM(F$6:F11))
G12: =IF(AND(E12="",F12=""),"",Settings!B6+SUM(E$6:E12)-SUM(F$6:F12))
G13: =IF(AND(E13="",F13=""),"",Settings!B6+SUM(E$6:E13)-SUM(F$6:F13))
G14: =IF(AND(E14="",F14=""),"",Settings!B6+SUM(E$6:E14)-SUM(F$6:F14))
G15: =IF(AND(E15="",F15=""),"",Settings!B6+SUM(E$6:E15)-SUM(F$6:F15))
G16: =IF(AND(E16="",F16=""),"",Settings!B6+SUM(E$6:E16)-SUM(F$6:F16))
G17: =IF(AND(E17="",F17=""),"",Settings!B6+SUM(E$6:E17)-SUM(F$6:F17))
G18: =IF(AND(E18="",F18=""),"",Settings!B6+SUM(E$6:E18)-SUM(F$6:F18))
G19: =IF(AND(E19="",F19=""),"",Settings!B6+SUM(E$6:E19)-SUM(F$6:F19))
G20: =IF(AND(E20="",F20=""),"",Settings!B6+SUM(E$6:E20)-SUM(F$6:F20))
G21: =IF(AND(E21="",F21=""),"",Settings!B6+SUM(E$6:E21)-SUM(F$6:F21))
G22: =IF(AND(E22="",F22=""),"",Settings!B6+SUM(E$6:E22)-SUM(F$6:F22))
G23: =IF(AND(E23="",F23=""),"",Settings!B6+SUM(E$6:E23)-SUM(F$6:F23))
G24: =IF(AND(E24="",F24=""),"",Settings!B6+SUM(E$6:E24)-SUM(F$6:F24))
G25: =IF(AND(E25="",F25=""),"",Settings!B6+SUM(E$6:E25)-SUM(F$6:F25))
G26: =IF(AND(E26="",F26=""),"",Settings!B6+SUM(E$6:E26)-SUM(F$6:F26))
G27: =IF(AND(E27="",F27=""),"",Settings!B6+SUM(E$6:E27)-SUM(F$6:F27))
G28: =IF(AND(E28="",F28=""),"",Settings!B6+SUM(E$6:E28)-SUM(F$6:F28))
G29: =IF(AND(E29="",F29=""),"",Settings!B6+SUM(E$6:E29)-SUM(F$6:F29))
G30: =IF(AND(E30="",F30=""),"",Settings!B6+SUM(E$6:E30)-SUM(F$6:F30))
G31: =IF(AND(E31="",F31=""),"",Settings!B6+SUM(E$6:E31)-SUM(F$6:F31))
G32: =IF(AND(E32="",F32=""),"",Settings!B6+SUM(E$6:E32)-SUM(F$6:F32))
G33: =IF(AND(E33="",F33=""),"",Settings!B6+SUM(E$6:E33)-SUM(F$6:F33))
G34: =IF(AND(E34="",F34=""),"",Settings!B6+SUM(E$6:E34)-SUM(F$6:F34))
G35: =IF(AND(E35="",F35=""),"",Settings!B6+SUM(E$6:E35)-SUM(F$6:F35))
G36: =IF(AND(E36="",F36=""),"",Settings!B6+SUM(E$6:E36)-SUM(F$6:F36))
G37: =IF(AND(E37="",F37=""),"",Settings!B6+SUM(E$6:E37)-SUM(F$6:F37))
G38: =IF(AND(E38="",F38=""),"",Settings!B6+SUM(E$6:E38)-SUM(F$6:F38))
G39: =IF(AND(E39="",F39=""),"",Settings!B6+SUM(E$6:E39)-SUM(F$6:F39))
G40: =IF(AND(E40="",F40=""),"",Settings!B6+SUM(E$6:E40)-SUM(F$6:F40))
G41: =IF(AND(E41="",F41=""),"",Settings!B6+SUM(E$6:E41)-SUM(F$6:F41))
G42: =IF(AND(E42="",F42=""),"",Settings!B6+SUM(E$6:E42)-SUM(F$6:F42))
G43: =IF(AND(E43="",F43=""),"",Settings!B6+SUM(E$6:E43)-SUM(F$6:F43))
G44: =IF(AND(E44="",F44=""),"",Settings!B6+SUM(E$6:E44)-SUM(F$6:F44))
G45: =IF(AND(E45="",F45=""),"",Settings!B6+SUM(E$6:E45)-SUM(F$6:F45))
G46: =IF(AND(E46="",F46=""),"",Settings!B6+SUM(E$6:E46)-SUM(F$6:F46))
G47: =IF(AND(E47="",F47=""),"",Settings!B6+SUM(E$6:E47)-SUM(F$6:F47))
G48: =IF(AND(E48="",F48=""),"",Settings!B6+SUM(E$6:E48)-SUM(F$6:F48))
G49: =IF(AND(E49="",F49=""),"",Settings!B6+SUM(E$6:E49)-SUM(F$6:F49))
G50: =IF(AND(E50="",F50=""),"",Settings!B6+SUM(E$6:E50)-SUM(F$6:F50))
G51: =IF(AND(E51="",F51=""),"",Settings!B6+SUM(E$6:E51)-SUM(F$6:F51))
G52: =IF(AND(E52="",F52=""),"",Settings!B6+SUM(E$6:E52)-SUM(F$6:F52))
G53: =IF(AND(E53="",F53=""),"",Settings!B6+SUM(E$6:E53)-SUM(F$6:F53))
G54: =IF(AND(E54="",F54=""),"",Settings!B6+SUM(E$6:E54)-SUM(F$6:F54))
G55: =IF(AND(E55="",F55=""),"",Settings!B6+SUM(E$6:E55)-SUM(F$6:F55))
G56: =IF(AND(E56="",F56=""),"",Settings!B6+SUM(E$6:E56)-SUM(F$6:F56))
G57: =IF(AND(E57="",F57=""),"",Settings!B6+SUM(E$6:E57)-SUM(F$6:F57))
G58: =IF(AND(E58="",F58=""),"",Settings!B6+SUM(E$6:E58)-SUM(F$6:F58))
G59: =IF(AND(E59="",F59=""),"",Settings!B6+SUM(E$6:E59)-SUM(F$6:F59))
G60: =IF(AND(E60="",F60=""),"",Settings!B6+SUM(E$6:E60)-SUM(F$6:F60))
G61: =IF(AND(E61="",F61=""),"",Settings!B6+SUM(E$6:E61)-SUM(F$6:F61))
G62: =IF(AND(E62="",F62=""),"",Settings!B6+SUM(E$6:E62)-SUM(F$6:F62))
G63: =IF(AND(E63="",F63=""),"",Settings!B6+SUM(E$6:E63)-SUM(F$6:F63))
G64: =IF(AND(E64="",F64=""),"",Settings!B6+SUM(E$6:E64)-SUM(F$6:F64))
G65: =IF(AND(E65="",F65=""),"",Settings!B6+SUM(E$6:E65)-SUM(F$6:F65))
G66: =IF(AND(E66="",F66=""),"",Settings!B6+SUM(E$6:E66)-SUM(F$6:F66))
G67: =IF(AND(E67="",F67=""),"",Settings!B6+SUM(E$6:E67)-SUM(F$6:F67))
G68: =IF(AND(E68="",F68=""),"",Settings!B6+SUM(E$6:E68)-SUM(F$6:F68))
G69: =IF(AND(E69="",F69=""),"",Settings!B6+SUM(E$6:E69)-SUM(F$6:F69))
G70: =IF(AND(E70="",F70=""),"",Settings!B6+SUM(E$6:E70)-SUM(F$6:F70))
G71: =IF(AND(E71="",F71=""),"",Settings!B6+SUM(E$6:E71)-SUM(F$6:F71))
G72: =IF(AND(E72="",F72=""),"",Settings!B6+SUM(E$6:E72)-SUM(F$6:F72))
G73: =IF(AND(E73="",F73=""),"",Settings!B6+SUM(E$6:E73)-SUM(F$6:F73))
G74: =IF(AND(E74="",F74=""),"",Settings!B6+SUM(E$6:E74)-SUM(F$6:F74))
G75: =IF(AND(E75="",F75=""),"",Settings!B6+SUM(E$6:E75)-SUM(F$6:F75))
G76: =IF(AND(E76="",F76=""),"",Settings!B6+SUM(E$6:E76)-SUM(F$6:F76))
G77: =IF(AND(E77="",F77=""),"",Settings!B6+SUM(E$6:E77)-SUM(F$6:F77))
G78: =IF(AND(E78="",F78=""),"",Settings!B6+SUM(E$6:E78)-SUM(F$6:F78))
G79: =IF(AND(E79="",F79=""),"",Settings!B6+SUM(E$6:E79)-SUM(F$6:F79))
G80: =IF(AND(E80="",F80=""),"",Settings!B6+SUM(E$6:E80)-SUM(F$6:F80))
G81: =IF(AND(E81="",F81=""),"",Settings!B6+SUM(E$6:E81)-SUM(F$6:F81))
G82: =IF(AND(E82="",F82=""),"",Settings!B6+SUM(E$6:E82)-SUM(F$6:F82))
G83: =IF(AND(E83="",F83=""),"",Settings!B6+SUM(E$6:E83)-SUM(F$6:F83))
G84: =IF(AND(E84="",F84=""),"",Settings!B6+SUM(E$6:E84)-SUM(F$6:F84))
G85: =IF(AND(E85="",F85=""),"",Settings!B6+SUM(E$6:E85)-SUM(F$6:F85))
G86: =IF(AND(E86="",F86=""),"",Settings!B6+SUM(E$6:E86)-SUM(F$6:F86))
G87: =IF(AND(E87="",F87=""),"",Settings!B6+SUM(E$6:E87)-SUM(F$6:F87))
G88: =IF(AND(E88="",F88=""),"",Settings!B6+SUM(E$6:E88)-SUM(F$6:F88))
G89: =IF(AND(E89="",F89=""),"",Settings!B6+SUM(E$6:E89)-SUM(F$6:F89))
G90: =IF(AND(E90="",F90=""),"",Settings!B6+SUM(E$6:E90)-SUM(F$6:F90))
G91: =IF(AND(E91="",F91=""),"",Settings!B6+SUM(E$6:E91)-SUM(F$6:F91))
G92: =IF(AND(E92="",F92=""),"",Settings!B6+SUM(E$6:E92)-SUM(F$6:F92))
G93: =IF(AND(E93="",F93=""),"",Settings!B6+SUM(E$6:E93)-SUM(F$6:F93))
G94: =IF(AND(E94="",F94=""),"",Settings!B6+SUM(E$6:E94)-SUM(F$6:F94))
G95: =IF(AND(E95="",F95=""),"",Settings!B6+SUM(E$6:E95)-SUM(F$6:F95))
G96: =IF(AND(E96="",F96=""),"",Settings!B6+SUM(E$6:E96)-SUM(F$6:F96))
G97: =IF(AND(E97="",F97=""),"",Settings!B6+SUM(E$6:E97)-SUM(F$6:F97))
G98: =IF(AND(E98="",F98=""),"",Settings!B6+SUM(E$6:E98)-SUM(F$6:F98))
G99: =IF(AND(E99="",F99=""),"",Settings!B6+SUM(E$6:E99)-SUM(F$6:F99))
G100: =IF(AND(E100="",F100=""),"",Settings!B6+SUM(E$6:E100)-SUM(F$6:F100))
G101: =IF(AND(E101="",F101=""),"",Settings!B6+SUM(E$6:E101)-SUM(F$6:F101))
...

Sheet Sales Register
A1: Sales Register
A4: Date | B4: Invoice No. | C4: Customer | D4: GSTIN | E4: Taxable value | F4: CGST | G4: SGST | H4: IGST | I4: Total
I5: =IF(E5="","",E5+F5+G5+H5)
I6: =IF(E6="","",E6+F6+G6+H6)
I7: =IF(E7="","",E7+F7+G7+H7)
I8: =IF(E8="","",E8+F8+G8+H8)
I9: =IF(E9="","",E9+F9+G9+H9)
I10: =IF(E10="","",E10+F10+G10+H10)
I11: =IF(E11="","",E11+F11+G11+H11)
I12: =IF(E12="","",E12+F12+G12+H12)
I13: =IF(E13="","",E13+F13+G13+H13)
I14: =IF(E14="","",E14+F14+G14+H14)
I15: =IF(E15="","",E15+F15+G15+H15)
I16: =IF(E16="","",E16+F16+G16+H16)
... I1004: =IF(E1004="","",E1004+F1004+G1004+H1004)

Sheet Purchase Register
A1: Purchase Register
A2: Mark ITC eligibility and whether the bill shows in your GSTR-2B
A4: Date | B4: Bill No. | C4: Supplier | D4: Supplier GSTIN | E4: Taxable value | F4: CGST | G4: SGST | H4: IGST | I4: Total | J4: ITC eligible? (Y/N) | K4: In GSTR-2B? (Y/N)
I5: =IF(E5="","",E5+F5+G5+H5)
I6: =IF(E6="","",E6+F6+G6+H6)
I7: =IF(E7="","",E7+F7+G7+H7)
I8: =IF(E8="","",E8+F8+G8+H8)
I9: =IF(E9="","",E9+F9+G9+H9)
I10: =IF(E10="","",E10+F10+G10+H10)
I11: =IF(E11="","",E11+F11+G11+H11)
I12: =IF(E12="","",E12+F12+G12+H12)
I13: =IF(E13="","",E13+F13+G13+H13)
I14: =IF(E14="","",E14+F14+G14+H14)
I15: =IF(E15="","",E15+F15+G15+H15)
I16: =IF(E16="","",E16+F16+G16+H16)
... I1004: =IF(E1004="","",E1004+F1004+G1004+H1004)

Sheet Expenses
A1: Expenses
A2: Pick the head from the drop-down
A4: Date | B4: Expense head | C4: Paid to | D4: Amount | E4: Mode (Cash/Bank/UPI) | F4: Remarks

Sheet ITC Tracker
A1: ITC Tracker — books vs GSTR-2B
A2: Difference = ITC you booked that is not yet in GSTR-2B (follow up with the supplier)
A4: Month | B4: Eligible ITC in books | C4: ITC reflected in GSTR-2B | D4: Difference | E4: Status
A5: =DATE(2026,4,1) | B5: =SUMPRODUCT(('Purchase Register'!$A$5:$A$1004>=A5)*('Purchase Register'!$A$5:$A$1004<=EOMONTH(A5,0))*('Purchase Register'!$J$5:$J$1004="Y")*('Purchase Register'!$F$5:$F$1004+'Purchase Register'!$G$5:$G$1004+'Purchase Register'!$H$5:$H$1004)) | C5: =SUMPRODUCT(('Purchase Register'!$A$5:$A$1004>=A5)*('Purchase Register'!$A$5:$A$1004<=EOMONTH(A5,0))*('Purchase Register'!$J$5:$J$1004="Y")*('Purchase Register'!$K$5:$K$1004="Y")*('Purchase Register'!$F$5:$F$1004+'Purchase Register'!$G$5:$G$1004+'Purchase Register'!$H$5:$H$1004)) | D5: =B5-C5 | E5: =IF(B5=0,"",IF(D5=0,"All matched","Follow up with suppliers"))
A6: =DATE(2026,5,1) | B6: =SUMPRODUCT(('Purchase Register'!$A$5:$A$1004>=A6)*('Purchase Register'!$A$5:$A$1004<=EOMONTH(A6,0))*('Purchase Register'!$J$5:$J$1004="Y")*('Purchase Register'!$F$5:$F$1004+'Purchase Register'!$G$5:$G$1004+'Purchase Register'!$H$5:$H$1004)) | C6: =SUMPRODUCT(('Purchase Register'!$A$5:$A$1004>=A6)*('Purchase Register'!$A$5:$A$1004<=EOMONTH(A6,0))*('Purchase Register'!$J$5:$J$1004="Y")*('Purchase Register'!$K$5:$K$1004="Y")*('Purchase Register'!$F$5:$F$1004+'Purchase Register'!$G$5:$G$1004+'Purchase Register'!$H$5:$H$1004)) | D6: =B6-C6 | E6: =IF(B6=0,"",IF(D6=0,"All matched","Follow up with suppliers"))
A7: =DATE(2026,6,1) | B7: =SUMPRODUCT(('Purchase Register'!$A$5:$A$1004>=A7)*('Purchase Register'!$A$5:$A$1004<=EOMONTH(A7,0))*('Purchase Register'!$J$5:$J$1004="Y")*('Purchase Register'!$F$5:$F$1004+'Purchase Register'!$G$5:$G$1004+'Purchase Register'!$H$5:$H$1004)) | C7: =SUMPRODUCT(('Purchase Register'!$A$5:$A$1004>=A7)*('Purchase Register'!$A$5:$A$1004<=EOMONTH(A7,0))*('Purchase Register'!$J$5:$J$1004="Y")*('Purchase Register'!$K$5:$K$1004="Y")*('Purchase Register'!$F$5:$F$1004+'Purchase Register'!$G$5:$G$1004+'Purchase Register'!$H$5:$H$1004)) | D7: =B7-C7 | E7: =IF(B7=0,"",IF(D7=0,"All matched","Follow up with suppliers"))
A8: =DATE(2026,7,1) | B8: =SUMPRODUCT(('Purchase Register'!$A$5:$A$1004>=A8)*('Purchase Register'!$A$5:$A$1004<=EOMONTH(A8,0))*('Purchase Register'!$J$5:$J$1004="Y")*('Purchase Register'!$F$5:$F$1004+'Purchase Register'!$G$5:$G$1004+'Purchase Register'!$H$5:$H$1004)) | C8: =SUMPRODUCT(('Purchase Register'!$A$5:$A$1004>=A8)*('Purchase Register'!$A$5:$A$1004<=EOMONTH(A8,0))*('Purchase Register'!$J$5:$J$1004="Y")*('Purchase Register'!$K$5:$K$1004="Y")*('Purchase Register'!$F$5:$F$1004+'Purchase Register'!$G$5:$G$1004+'Purchase Register'!$H$5:$H$1004)) | D8: =B8-C8 | E8: =IF(B8=0,"",IF(D8=0,"All matched","Follow up with suppliers"))
A9: =DATE(2026,8,1) | B9: =SUMPRODUCT(('Purchase Register'!$A$5:$A$1004>=A9)*('Purchase Register'!$A$5:$A$1004<=EOMONTH(A9,0))*('Purchase Register'!$J$5:$J$1004="Y")*('Purchase Register'!$F$5:$F$1004+'Purchase Register'!$G$5:$G$1004+'Purchase Register'!$H$5:$H$1004)) | C9: =SUMPRODUCT(('Purchase Register'!$A$5:$A$1004>=A9)*('Purchase Register'!$A$5:$A$1004<=EOMONTH(A9,0))*('Purchase Register'!$J$5:$J$1004="Y")*('Purchase Register'!$K$5:$K$1004="Y")*('Purchase Register'!$F$5:$F$1004+'Purchase Register'!$G$5:$G$1004+'Purchase Register'!$H$5:$H$1004)) | D9: =B9-C9 | E9: =IF(B9=0,"",IF(D9=0,"All matched","Follow up with suppliers"))
A10: =DATE(2026,9,1) | B10: =SUMPRODUCT(('Purchase Register'!$A$5:$A$1004>=A10)*('Purchase Register'!$A$5:$A$1004<=EOMONTH(A10,0))*('Purchase Register'!$J$5:$J$1004="Y")*('Purchase Register'!$F$5:$F$1004+'Purchase Register'!$G$5:$G$1004+'Purchase Register'!$H$5:$H$1004)) | C10: =SUMPRODUCT(('Purchase Register'!$A$5:$A$1004>=A10)*('Purchase Register'!$A$5:$A$1004<=EOMONTH(A10,0))*('Purchase Register'!$J$5:$J$1004="Y")*('Purchase Register'!$K$5:$K$1004="Y")*('Purchase Register'!$F$5:$F$1004+'Purchase Register'!$G$5:$G$1004+'Purchase Register'!$H$5:$H$1004)) | D10: =B10-C10 | E10: =IF(B10=0,"",IF(D10=0,"All matched","Follow up with suppliers"))
A11: =DATE(2026,10,1) | B11: =SUMPRODUCT(('Purchase Register'!$A$5:$A$1004>=A11)*('Purchase Register'!$A$5:$A$1004<=EOMONTH(A11,0))*('Purchase Register'!$J$5:$J$1004="Y")*('Purchase Register'!$F$5:$F$1004+'Purchase Register'!$G$5:$G$1004+'Purchase Register'!$H$5:$H$1004)) | C11: =SUMPRODUCT(('Purchase Register'!$A$5:$A$1004>=A11)*('Purchase Register'!$A$5:$A$1004<=EOMONTH(A11,0))*('Purchase Register'!$J$5:$J$1004="Y")*('Purchase Register'!$K$5:$K$1004="Y")*('Purchase Register'!$F$5:$F$1004+'Purchase Register'!$G$5:$G$1004+'Purchase Register'!$H$5:$H$1004)) | D11: =B11-C11 | E11: =IF(B11=0,"",IF(D11=0,"All matched","Follow up with suppliers"))
A12: =DATE(2026,11,1) | B12: =SUMPRODUCT(('Purchase Register'!$A$5:$A$1004>=A12)*('Purchase Register'!$A$5:$A$1004<=EOMONTH(A12,0))*('Purchase Register'!$J$5:$J$1004="Y")*('Purchase Register'!$F$5:$F$1004+'Purchase Register'!$G$5:$G$1004+'Purchase Register'!$H$5:$H$1004)) | C12: =SUMPRODUCT(('Purchase Register'!$A$5:$A$1004>=A12)*('Purchase Register'!$A$5:$A$1004<=EOMONTH(A12,0))*('Purchase Register'!$J$5:$J$1004="Y")*('Purchase Register'!$K$5:$K$1004="Y")*('Purchase Register'!$F$5:$F$1004+'Purchase Register'!$G$5:$G$1004+'Purchase Register'!$H$5:$H$1004)) | D12: =B12-C12 | E12: =IF(B12=0,"",IF(D12=0,"All matched","Follow up with suppliers"))
A13: =DATE(2026,12,1) | B13: =SUMPRODUCT(('Purchase Register'!$A$5:$A$1004>=A13)*('Purchase Register'!$A$5:$A$1004<=EOMONTH(A13,0))*('Purchase Register'!$J$5:$J$1004="Y")*('Purchase Register'!$F$5:$F$1004+'Purchase Register'!$G$5:$G$1004+'Purchase Register'!$H$5:$H$1004)) | C13: =SUMPRODUCT(('Purchase Register'!$A$5:$A$1004>=A13)*('Purchase Register'!$A$5:$A$1004<=EOMONTH(A13,0))*('Purchase Register'!$J$5:$J$1004="Y")*('Purchase Register'!$K$5:$K$1004="Y")*('Purchase Register'!$F$5:$F$1004+'Purchase Register'!$G$5:$G$1004+'Purchase Register'!$H$5:$H$1004)) | D13: =B13-C13 | E13: =IF(B13=0,"",IF(D13=0,"All matched","Follow up with suppliers"))
A14: =DATE(2027,1,1) | B14: =SUMPRODUCT(('Purchase Register'!$A$5:$A$1004>=A14)*('Purchase Register'!$A$5:$A$1004<=EOMONTH(A14,0))*('Purchase Register'!$J$5:$J$1004="Y")*('Purchase Register'!$F$5:$F$1004+'Purchase Register'!$G$5:$G$1004+'Purchase Register'!$H$5:$H$1004)) | C14: =SUMPRODUCT(('Purchase Register'!$A$5:$A$1004>=A14)*('Purchase Register'!$A$5:$A$1004<=EOMONTH(A14,0))*('Purchase Register'!$J$5:$J$1004="Y")*('Purchase Register'!$K$5:$K$1004="Y")*('Purchase Register'!$F$5:$F$1004+'Purchase Register'!$G$5:$G$1004+'Purchase Register'!$H$5:$H$1004)) | D14: =B14-C14 | E14: =IF(B14=0,"",IF(D14=0,"All matched","Follow up with suppliers"))
A15: =DATE(2027,2,1) | B15: =SUMPRODUCT(('Purchase Register'!$A$5:$A$1004>=A15)*('Purchase Register'!$A$5:$A$1004<=EOMONTH(A15,0))*('Purchase Register'!$J$5:$J$1004="Y")*('Purchase Register'!$F$5:$F$1004+'Purchase Register'!$G$5:$G$1004+'Purchase Register'!$H$5:$H$1004)) | C15: =SUMPRODUCT(('Purchase Register'!$A$5:$A$1004>=A15)*('Purchase Register'!$A$5:$A$1004<=EOMONTH(A15,0))*('Purchase Register'!$J$5:$J$1004="Y")*('Purchase Register'!$K$5:$K$1004="Y")*('Purchase Register'!$F$5:$F$1004+'Purchase Register'!$G$5:$G$1004+'Purchase Register'!$H$5:$H$1004)) | D15: =B15-C15 | E15: =IF(B15=0,"",IF(D15=0,"All matched","Follow up with suppliers"))
A16: =DATE(2027,3,1) | B16: =SUMPRODUCT(('Purchase Register'!$A$5:$A$1004>=A16)*('Purchase Register'!$A$5:$A$1004<=EOMONTH(A16,0))*('Purchase Register'!$J$5:$J$1004="Y")*('Purchase Register'!$F$5:$F$1004+'Purchase Register'!$G$5:$G$1004+'Purchase Register'!$H$5:$H$1004)) | C16: =SUMPRODUCT(('Purchase Register'!$A$5:$A$1004>=A16)*('Purchase Register'!$A$5:$A$1004<=EOMONTH(A16,0))*('Purchase Register'!$J$5:$J$1004="Y")*('Purchase Register'!$K$5:$K$1004="Y")*('Purchase Register'!$F$5:$F$1004+'Purchase Register'!$G$5:$G$1004+'Purchase Register'!$H$5:$H$1004)) | D16: =B16-C16 | E16: =IF(B16=0,"",IF(D16=0,"All matched","Follow up with suppliers"))

Sheet P&L Summary
A1: Profit & Loss Summary — FY 2026-27
A2: Estimated, from your registers (taxable values, excluding GST)
A4: Particulars | B4: =DATE(2026,4,1) | C4: =DATE(2026,5,1) | D4: =DATE(2026,6,1) | E4: =DATE(2026,7,1) | F4: =DATE(2026,8,1) | G4: =DATE(2026,9,1) | H4: =DATE(2026,10,1) | I4: =DATE(2026,11,1) | J4: =DATE(2026,12,1) | K4: =DATE(2027,1,1) | L4: =DATE(2027,2,1) | M4: =DATE(2027,3,1) | N4: Total
A5: Sales | B5: =SUMIFS('Sales Register'!$E$5:$E$1004,'Sales Register'!$A$5:$A$1004,">="&B$4,'Sales Register'!$A$5:$A$1004,"<="&EOMONTH(B$4,0)) | C5: =SUMIFS('Sales Register'!$E$5:$E$1004,'Sales Register'!$A$5:$A$1004,">="&C$4,'Sales Register'!$A$5:$A$1004,"<="&EOMONTH(C$4,0)) | D5: =SUMIFS('Sales Register'!$E$5:$E$1004,'Sales Register'!$A$5:$A$1004,">="&D$4,'Sales Register'!$A$5:$A$1004,"<="&EOMONTH(D$4,0)) | E5: =SUMIFS('Sales Register'!$E$5:$E$1004,'Sales Register'!$A$5:$A$1004,">="&E$4,'Sales Register'!$A$5:$A$1004,"<="&EOMONTH(E$4,0)) | F5: =SUMIFS('Sales Register'!$E$5:$E$1004,'Sales Register'!$A$5:$A$1004,">="&F$4,'Sales Register'!$A$5:$A$1004,"<="&EOMONTH(F$4,0)) | G5: =SUMIFS('Sales Register'!$E$5:$E$1004,'Sales Register'!$A$5:$A$1004,">="&G$4,'Sales Register'!$A$5:$A$1004,"<="&EOMONTH(G$4,0)) | H5: =SUMIFS('Sales Register'!$E$5:$E$1004,'Sales Register'!$A$5:$A$1004,">="&H$4,'Sales Register'!$A$5:$A$1004,"<="&EOMONTH(H$4,0)) | I5: =SUMIFS('Sales Register'!$E$5:$E$1004,'Sales Register'!$A$5:$A$1004,">="&I$4,'Sales Register'!$A$5:$A$1004,"<="&EOMONTH(I$4,0)) | ... M5: =SUMIFS('Sales Register'!$E$5:$E$1004,'Sales Register'!$A$5:$A$1004,">="&M$4,'Sales Register'!$A$5:$A$1004,"<="&EOMONTH(M$4,0)) | N5: =SUM(B5:M5)
A6: Purchases | B6: =SUMIFS('Purchase Register'!$E$5:$E$1004,'Purchase Register'!$A$5:$A$1004,">="&B$4,'Purchase Register'!$A$5:$A$1004,"<="&EOMONTH(B$4,0)) | C6: =SUMIFS('Purchase Register'!$E$5:$E$1004,'Purchase Register'!$A$5:$A$1004,">="&C$4,'Purchase Register'!$A$5:$A$1004,"<="&EOMONTH(C$4,0)) | D6: =SUMIFS('Purchase Register'!$E$5:$E$1004,'Purchase Register'!$A$5:$A$1004,">="&D$4,'Purchase Register'!$A$5:$A$1004,"<="&EOMONTH(D$4,0)) | E6: =SUMIFS('Purchase Register'!$E$5:$E$1004,'Purchase Register'!$A$5:$A$1004,">="&E$4,'Purchase Register'!$A$5:$A$1004,"<="&EOMONTH(E$4,0)) | F6: =SUMIFS('Purchase Register'!$E$5:$E$1004,'Purchase Register'!$A$5:$A$1004,">="&F$4,'Purchase Register'!$A$5:$A$1004,"<="&EOMONTH(F$4,0)) | G6: =SUMIFS('Purchase Register'!$E$5:$E$1004,'Purchase Register'!$A$5:$A$1004,">="&G$4,'Purchase Register'!$A$5:$A$1004,"<="&EOMONTH(G$4,0)) | H6: =SUMIFS('Purchase Register'!$E$5:$E$1004,'Purchase Register'!$A$5:$A$1004,">="&H$4,'Purchase Register'!$A$5:$A$1004,"<="&EOMONTH(H$4,0)) | I6: =SUMIFS('Purchase Register'!$E$5:$E$1004,'Purchase Register'!$A$5:$A$1004,">="&I$4,'Purchase Register'!$A$5:$A$1004,"<="&EOMONTH(I$4,0)) | ... M6: =SUMIFS('Purchase Register'!$E$5:$E$1004,'Purchase Register'!$A$5:$A$1004,">="&M$4,'Purchase Register'!$A$5:$A$1004,"<="&EOMONTH(M$4,0)) | N6: =SUM(B6:M6)
A7: Gross profit | B7: =B5-B6 | C7: =C5-C6 | D7: =D5-D6 | E7: =E5-E6 | F7: =F5-F6 | G7: =G5-G6 | H7: =H5-H6 | I7: =I5-I6 | ... M7: =M5-M6 | N7: =SUM(B7:M7)
A9: =Heads!A2 | B9: =SUMIFS('Expenses'!$D$5:$D$1004,'Expenses'!$A$5:$A$1004,">="&B$4,'Expenses'!$A$5:$A$1004,"<="&EOMONTH(B$4,0),'Expenses'!$B$5:$B$1004,$A9) | C9: =SUMIFS('Expenses'!$D$5:$D$1004,'Expenses'!$A$5:$A$1004,">="&C$4,'Expenses'!$A$5:$A$1004,"<="&EOMONTH(C$4,0),'Expenses'!$B$5:$B$1004,$A9) | D9: =SUMIFS('Expenses'!$D$5:$D$1004,'Expenses'!$A$5:$A$1004,">="&D$4,'Expenses'!$A$5:$A$1004,"<="&EOMONTH(D$4,0),'Expenses'!$B$5:$B$1004,$A9) | E9: =SUMIFS('Expenses'!$D$5:$D$1004,'Expenses'!$A$5:$A$1004,">="&E$4,'Expenses'!$A$5:$A$1004,"<="&EOMONTH(E$4,0),'Expenses'!$B$5:$B$1004,$A9) | F9: =SUMIFS('Expenses'!$D$5:$D$1004,'Expenses'!$A$5:$A$1004,">="&F$4,'Expenses'!$A$5:$A$1004,"<="&EOMONTH(F$4,0),'Expenses'!$B$5:$B$1004,$A9) | G9: =SUMIFS('Expenses'!$D$5:$D$1004,'Expenses'!$A$5:$A$1004,">="&G$4,'Expenses'!$A$5:$A$1004,"<="&EOMONTH(G$4,0),'Expenses'!$B$5:$B$1004,$A9) | H9: =SUMIFS('Expenses'!$D$5:$D$1004,'Expenses'!$A$5:$A$1004,">="&H$4,'Expenses'!$A$5:$A$1004,"<="&EOMONTH(H$4,0),'Expenses'!$B$5:$B$1004,$A9) | I9: =SUMIFS('Expenses'!$D$5:$D$1004,'Expenses'!$A$5:$A$1004,">="&I$4,'Expenses'!$A$5:$A$1004,"<="&EOMONTH(I$4,0),'Expenses'!$B$5:$B$1004,$A9) | ... M9: =SUMIFS('Expenses'!$D$5:$D$1004,'Expenses'!$A$5:$A$1004,">="&M$4,'Expenses'!$A$5:$A$1004,"<="&EOMONTH(M$4,0),'Expenses'!$B$5:$B$1004,$A9) | N9: =SUM(B9:M9)
A10: =Heads!A3 | B10: =SUMIFS('Expenses'!$D$5:$D$1004,'Expenses'!$A$5:$A$1004,">="&B$4,'Expenses'!$A$5:$A$1004,"<="&EOMONTH(B$4,0),'Expenses'!$B$5:$B$1004,$A10) | C10: =SUMIFS('Expenses'!$D$5:$D$1004,'Expenses'!$A$5:$A$1004,">="&C$4,'Expenses'!$A$5:$A$1004,"<="&EOMONTH(C$4,0),'Expenses'!$B$5:$B$1004,$A10) | D10: =SUMIFS('Expenses'!$D$5:$D$1004,'Expenses'!$A$5:$A$1004,">="&D$4,'Expenses'!$A$5:$A$1004,"<="&EOMONTH(D$4,0),'Expenses'!$B$5:$B$1004,$A10) | E10: =SUMIFS('Expenses'!$D$5:$D$1004,'Expenses'!$A$5:$A$1004,">="&E$4,'Expenses'!$A$5:$A$1004,"<="&EOMONTH(E$4,0),'Expenses'!$B$5:$B$1004,$A10) | F10: =SUMIFS('Expenses'!$D$5:$D$1004,'Expenses'!$A$5:$A$1004,">="&F$4,'Expenses'!$A$5:$A$1004,"<="&EOMONTH(F$4,0),'Expenses'!$B$5:$B$1004,$A10) | G10: =SUMIFS('Expenses'!$D$5:$D$1004,'Expenses'!$A$5:$A$1004,">="&G$4,'Expenses'!$A$5:$A$1004,"<="&EOMONTH(G$4,0),'Expenses'!$B$5:$B$1004,$A10) | H10: =SUMIFS('Expenses'!$D$5:$D$1004,'Expenses'!$A$5:$A$1004,">="&H$4,'Expenses'!$A$5:$A$1004,"<="&EOMONTH(H$4,0),'Expenses'!$B$5:$B$1004,$A10) | I10: =SUMIFS('Expenses'!$D$5:$D$1004,'Expenses'!$A$5:$A$1004,">="&I$4,'Expenses'!$A$5:$A$1004,"<="&EOMONTH(I$4,0),'Expenses'!$B$5:$B$1004,$A10) | ... M10: =SUMIFS('Expenses'!$D$5:$D$1004,'Expenses'!$A$5:$A$1004,">="&M$4,'Expenses'!$A$5:$A$1004,"<="&EOMONTH(M$4,0),'Expenses'!$B$5:$B$1004,$A10) | N10: =SUM(B10:M10)
A11: =Heads!A4 | B11: =SUMIFS('Expenses'!$D$5:$D$1004,'Expenses'!$A$5:$A$1004,">="&B$4,'Expenses'!$A$5:$A$1004,"<="&EOMONTH(B$4,0),'Expenses'!$B$5:$B$1004,$A11) | C11: =SUMIFS('Expenses'!$D$5:$D$1004,'Expenses'!$A$5:$A$1004,">="&C$4,'Expenses'!$A$5:$A$1004,"<="&EOMONTH(C$4,0),'Expenses'!$B$5:$B$1004,$A11) | D11: =SUMIFS('Expenses'!$D$5:$D$1004,'Expenses'!$A$5:$A$1004,">="&D$4,'Expenses'!$A$5:$A$1004,"<="&EOMONTH(D$4,0),'Expenses'!$B$5:$B$1004,$A11) | E11: =SUMIFS('Expenses'!$D$5:$D$1004,'Expenses'!$A$5:$A$1004,">="&E$4,'Expenses'!$A$5:$A$1004,"<="&EOMONTH(E$4,0),'Expenses'!$B$5:$B$1004,$A11) | F11: =SUMIFS('Expenses'!$D$5:$D$1004,'Expenses'!$A$5:$A$1004,">="&F$4,'Expenses'!$A$5:$A$1004,"<="&EOMONTH(F$4,0),'Expenses'!$B$5:$B$1004,$A11) | G11: =SUMIFS('Expenses'!$D$5:$D$1004,'Expenses'!$A$5:$A$1004,">="&G$4,'Expenses'!$A$5:$A$1004,"<="&EOMONTH(G$4,0),'Expenses'!$B$5:$B$1004,$A11) | H11: =SUMIFS('Expenses'!$D$5:$D$1004,'Expenses'!$A$5:$A$1004,">="&H$4,'Expenses'!$A$5:$A$1004,"<="&EOMONTH(H$4,0),'Expenses'!$B$5:$B$1004,$A11) | I11: =SUMIFS('Expenses'!$D$5:$D$1004,'Expenses'!$A$5:$A$1004,">="&I$4,'Expenses'!$A$5:$A$1004,"<="&EOMONTH(I$4,0),'Expenses'!$B$5:$B$1004,$A11) | ... M11: =SUMIFS('Expenses'!$D$5:$D$1004,'Expenses'!$A$5:$A$1004,">="&M$4,'Expenses'!$A$5:$A$1004,"<="&EOMONTH(M$4,0),'Expenses'!$B$5:$B$1004,$A11) | N11: =SUM(B11:M11)
A12: =Heads!A5 | B12: =SUMIFS('Expenses'!$D$5:$D$1004,'Expenses'!$A$5:$A$1004,">="&B$4,'Expenses'!$A$5:$A$1004,"<="&EOMONTH(B$4,0),'Expenses'!$B$5:$B$1004,$A12) | C12: =SUMIFS('Expenses'!$D$5:$D$1004,'Expenses'!$A$5:$A$1004,">="&C$4,'Expenses'!$A$5:$A$1004,"<="&EOMONTH(C$4,0),'Expenses'!$B$5:$B$1004,$A12) | D12: =SUMIFS('Expenses'!$D$5:$D$1004,'Expenses'!$A$5:$A$1004,">="&D$4,'Expenses'!$A$5:$A$1004,"<="&EOMONTH(D$4,0),'Expenses'!$B$5:$B$1004,$A12) | E12: =SUMIFS('Expenses'!$D$5:$D$1004,'Expenses'!$A$5:$A$1004,">="&E$4,'Expenses'!$A$5:$A$1004,"<="&EOMONTH(E$4,0),'Expenses'!$B$5:$B$1004,$A12) | F12: =SUMIFS('Expenses'!$D$5:$D$1004,'Expenses'!$A$5:$A$1004,">="&F$4,'Expenses'!$A$5:$A$1004,"<="&EOMONTH(F$4,0),'Expenses'!$B$5:$B$1004,$A12) | G12: =SUMIFS('Expenses'!$D$5:$D$1004,'Expenses'!$A$5:$A$1004,">="&G$4,'Expenses'!$A$5:$A$1004,"<="&EOMONTH(G$4,0),'Expenses'!$B$5:$B$1004,$A12) | H12: =SUMIFS('Expenses'!$D$5:$D$1004,'Expenses'!$A$5:$A$1004,">="&H$4,'Expenses'!$A$5:$A$1004,"<="&EOMONTH(H$4,0),'Expenses'!$B$5:$B$1004,$A12) | I12: =SUMIFS('Expenses'!$D$5:$D$1004,'Expenses'!$A$5:$A$1004,">="&I$4,'Expenses'!$A$5:$A$1004,"<="&EOMONTH(I$4,0),'Expenses'!$B$5:$B$1004,$A12) | ... M12: =SUMIFS('Expenses'!$D$5:$D$1004,'Expenses'!$A$5:$A$1004,">="&M$4,'Expenses'!$A$5:$A$1004,"<="&EOMONTH(M$4,0),'Expenses'!$B$5:$B$1004,$A12) | N12: =SUM(B12:M12)
A13: =Heads!A6 | B13: =SUMIFS('Expenses'!$D$5:$D$1004,'Expenses'!$A$5:$A$1004,">="&B$4,'Expenses'!$A$5:$A$1004,"<="&EOMONTH(B$4,0),'Expenses'!$B$5:$B$1004,$A13) | C13: =SUMIFS('Expenses'!$D$5:$D$1004,'Expenses'!$A$5:$A$1004,">="&C$4,'Expenses'!$A$5:$A$1004,"<="&EOMONTH(C$4,0),'Expenses'!$B$5:$B$1004,$A13) | D13: =SUMIFS('Expenses'!$D$5:$D$1004,'Expenses'!$A$5:$A$1004,">="&D$4,'Expenses'!$A$5:$A$1004,"<="&EOMONTH(D$4,0),'Expenses'!$B$5:$B$1004,$A13) | E13: =SUMIFS('Expenses'!$D$5:$D$1004,'Expenses'!$A$5:$A$1004,">="&E$4,'Expenses'!$A$5:$A$1004,"<="&EOMONTH(E$4,0),'Expenses'!$B$5:$B$1004,$A13) | F13: =SUMIFS('Expenses'!$D$5:$D$1004,'Expenses'!$A$5:$A$1004,">="&F$4,'Expenses'!$A$5:$A$1004,"<="&EOMONTH(F$4,0),'Expenses'!$B$5:$B$1004,$A13) | G13: =SUMIFS('Expenses'!$D$5:$D$1004,'Expenses'!$A$5:$A$1004,">="&G$4,'Expenses'!$A$5:$A$1004,"<="&EOMONTH(G$4,0),'Expenses'!$B$5:$B$1004,$A13) | H13: =SUMIFS('Expenses'!$D$5:$D$1004,'Expenses'!$A$5:$A$1004,">="&H$4,'Expenses'!$A$5:$A$1004,"<="&EOMONTH(H$4,0),'Expenses'!$B$5:$B$1004,$A13) | I13: =SUMIFS('Expenses'!$D$5:$D$1004,'Expenses'!$A$5:$A$1004,">="&I$4,'Expenses'!$A$5:$A$1004,"<="&EOMONTH(I$4,0),'Expenses'!$B$5:$B$1004,$A13) | ... M13: =SUMIFS('Expenses'!$D$5:$D$1004,'Expenses'!$A$5:$A$1004,">="&M$4,'Expenses'!$A$5:$A$1004,"<="&EOMONTH(M$4,0),'Expenses'!$B$5:$B$1004,$A13) | N13: =SUM(B13:M13)
A14: =Heads!A7 | B14: =SUMIFS('Expenses'!$D$5:$D$1004,'Expenses'!$A$5:$A$1004,">="&B$4,'Expenses'!$A$5:$A$1004,"<="&EOMONTH(B$4,0),'Expenses'!$B$5:$B$1004,$A14) | C14: =SUMIFS('Expenses'!$D$5:$D$1004,'Expenses'!$A$5:$A$1004,">="&C$4,'Expenses'!$A$5:$A$1004,"<="&EOMONTH(C$4,0),'Expenses'!$B$5:$B$1004,$A14) | D14: =SUMIFS('Expenses'!$D$5:$D$1004,'Expenses'!$A$5:$A$1004,">="&D$4,'Expenses'!$A$5:$A$1004,"<="&EOMONTH(D$4,0),'Expenses'!$B$5:$B$1004,$A14) | E14: =SUMIFS('Expenses'!$D$5:$D$1004,'Expenses'!$A$5:$A$1004,">="&E$4,'Expenses'!$A$5:$A$1004,"<="&EOMONTH(E$4,0),'Expenses'!$B$5:$B$1004,$A14) | F14: =SUMIFS('Expenses'!$D$5:$D$1004,'Expenses'!$A$5:$A$1004,">="&F$4,'Expenses'!$A$5:$A$1004,"<="&EOMONTH(F$4,0),'Expenses'!$B$5:$B$1004,$A14) | G14: =SUMIFS('Expenses'!$D$5:$D$1004,'Expenses'!$A$5:$A$1004,">="&G$4,'Expenses'!$A$5:$A$1004,"<="&EOMONTH(G$4,0),'Expenses'!$B$5:$B$1004,$A14) | H14: =SUMIFS('Expenses'!$D$5:$D$1004,'Expenses'!$A$5:$A$1004,">="&H$4,'Expenses'!$A$5:$A$1004,"<="&EOMONTH(H$4,0),'Expenses'!$B$5:$B$1004,$A14) | I14: =SUMIFS('Expenses'!$D$5:$D$1004,'Expenses'!$A$5:$A$1004,">="&I$4,'Expenses'!$A$5:$A$1004,"<="&EOMONTH(I$4,0),'Expenses'!$B$5:$B$1004,$A14) | ... M14: =SUMIFS('Expenses'!$D$5:$D$1004,'Expenses'!$A$5:$A$1004,">="&M$4,'Expenses'!$A$5:$A$1004,"<="&EOMONTH(M$4,0),'Expenses'!$B$5:$B$1004,$A14) | N14: =SUM(B14:M14)
A15: =Heads!A8 | B15: =SUMIFS('Expenses'!$D$5:$D$1004,'Expenses'!$A$5:$A$1004,">="&B$4,'Expenses'!$A$5:$A$1004,"<="&EOMONTH(B$4,0),'Expenses'!$B$5:$B$1004,$A15) | C15: =SUMIFS('Expenses'!$D$5:$D$1004,'Expenses'!$A$5:$A$1004,">="&C$4,'Expenses'!$A$5:$A$1004,"<="&EOMONTH(C$4,0),'Expenses'!$B$5:$B$1004,$A15) | D15: =SUMIFS('Expenses'!$D$5:$D$1004,'Expenses'!$A$5:$A$1004,">="&D$4,'Expenses'!$A$5:$A$1004,"<="&EOMONTH(D$4,0),'Expenses'!$B$5:$B$1004,$A15) | E15: =SUMIFS('Expenses'!$D$5:$D$1004,'Expenses'!$A$5:$A$1004,">="&E$4,'Expenses'!$A$5:$A$1004,"<="&EOMONTH(E$4,0),'Expenses'!$B$5:$B$1004,$A15) | F15: =SUMIFS('Expenses'!$D$5:$D$1004,'Expenses'!$A$5:$A$1004,">="&F$4,'Expenses'!$A$5:$A$1004,"<="&EOMONTH(F$4,0),'Expenses'!$B$5:$B$1004,$A15) | G15: =SUMIFS('Expenses'!$D$5:$D$1004,'Expenses'!$A$5:$A$1004,">="&G$4,'Expenses'!$A$5:$A$1004,"<="&EOMONTH(G$4,0),'Expenses'!$B$5:$B$1004,$A15) | H15: =SUMIFS('Expenses'!$D$5:$D$1004,'Expenses'!$A$5:$A$1004,">="&H$4,'Expenses'!$A$5:$A$1004,"<="&EOMONTH(H$4,0),'Expenses'!$B$5:$B$1004,$A15) | I15: =SUMIFS('Expenses'!$D$5:$D$1004,'Expenses'!$A$5:$A$1004,">="&I$4,'Expenses'!$A$5:$A$1004,"<="&EOMONTH(I$4,0),'Expenses'!$B$5:$B$1004,$A15) | ... M15: =SUMIFS('Expenses'!$D$5:$D$1004,'Expenses'!$A$5:$A$1004,">="&M$4,'Expenses'!$A$5:$A$1004,"<="&EOMONTH(M$4,0),'Expenses'!$B$5:$B$1004,$A15) | N15: =SUM(B15:M15)
A16: =Heads!A9 | B16: =SUMIFS('Expenses'!$D$5:$D$1004,'Expenses'!$A$5:$A$1004,">="&B$4,'Expenses'!$A$5:$A$1004,"<="&EOMONTH(B$4,0),'Expenses'!$B$5:$B$1004,$A16) | C16: =SUMIFS('Expenses'!$D$5:$D$1004,'Expenses'!$A$5:$A$1004,">="&C$4,'Expenses'!$A$5:$A$1004,"<="&EOMONTH(C$4,0),'Expenses'!$B$5:$B$1004,$A16) | D16: =SUMIFS('Expenses'!$D$5:$D$1004,'Expenses'!$A$5:$A$1004,">="&D$4,'Expenses'!$A$5:$A$1004,"<="&EOMONTH(D$4,0),'Expenses'!$B$5:$B$1004,$A16) | E16: =SUMIFS('Expenses'!$D$5:$D$1004,'Expenses'!$A$5:$A$1004,">="&E$4,'Expenses'!$A$5:$A$1004,"<="&EOMONTH(E$4,0),'Expenses'!$B$5:$B$1004,$A16) | F16: =SUMIFS('Expenses'!$D$5:$D$1004,'Expenses'!$A$5:$A$1004,">="&F$4,'Expenses'!$A$5:$A$1004,"<="&EOMONTH(F$4,0),'Expenses'!$B$5:$B$1004,$A16) | G16: =SUMIFS('Expenses'!$D$5:$D$1004,'Expenses'!$A$5:$A$1004,">="&G$4,'Expenses'!$A$5:$A$1004,"<="&EOMONTH(G$4,0),'Expenses'!$B$5:$B$1004,$A16) | H16: =SUMIFS('Expenses'!$D$5:$D$1004,'Expenses'!$A$5:$A$1004,">="&H$4,'Expenses'!$A$5:$A$1004,"<="&EOMONTH(H$4,0),'Expenses'!$B$5:$B$1004,$A16) | I16: =SUMIFS('Expenses'!$D$5:$D$1004,'Expenses'!$A$5:$A$1004,">="&I$4,'Expenses'!$A$5:$A$1004,"<="&EOMONTH(I$4,0),'Expenses'!$B$5:$B$1004,$A16) | ... M16: =SUMIFS('Expenses'!$D$5:$D$1004,'Expenses'!$A$5:$A$1004,">="&M$4,'Expenses'!$A$5:$A$1004,"<="&EOMONTH(M$4,0),'Expenses'!$B$5:$B$1004,$A16) | N16: =SUM(B16:M16)
A17: =Heads!A10 | B17: =SUMIFS('Expenses'!$D$5:$D$1004,'Expenses'!$A$5:$A$1004,">="&B$4,'Expenses'!$A$5:$A$1004,"<="&EOMONTH(B$4,0),'Expenses'!$B$5:$B$1004,$A17) | C17: =SUMIFS('Expenses'!$D$5:$D$1004,'Expenses'!$A$5:$A$1004,">="&C$4,'Expenses'!$A$5:$A$1004,"<="&EOMONTH(C$4,0),'Expenses'!$B$5:$B$1004,$A17) | D17: =SUMIFS('Expenses'!$D$5:$D$1004,'Expenses'!$A$5:$A$1004,">="&D$4,'Expenses'!$A$5:$A$1004,"<="&EOMONTH(D$4,0),'Expenses'!$B$5:$B$1004,$A17) | E17: =SUMIFS('Expenses'!$D$5:$D$1004,'Expenses'!$A$5:$A$1004,">="&E$4,'Expenses'!$A$5:$A$1004,"<="&EOMONTH(E$4,0),'Expenses'!$B$5:$B$1004,$A17) | F17: =SUMIFS('Expenses'!$D$5:$D$1004,'Expenses'!$A$5:$A$1004,">="&F$4,'Expenses'!$A$5:$A$1004,"<="&EOMONTH(F$4,0),'Expenses'!$B$5:$B$1004,$A17) | G17: =SUMIFS('Expenses'!$D$5:$D$1004,'Expenses'!$A$5:$A$1004,">="&G$4,'Expenses'!$A$5:$A$1004,"<="&EOMONTH(G$4,0),'Expenses'!$B$5:$B$1004,$A17) | H17: =SUMIFS('Expenses'!$D$5:$D$1004,'Expenses'!$A$5:$A$1004,">="&H$4,'Expenses'!$A$5:$A$1004,"<="&EOMONTH(H$4,0),'Expenses'!$B$5:$B$1004,$A17) | I17: =SUMIFS('Expenses'!$D$5:$D$1004,'Expenses'!$A$5:$A$1004,">="&I$4,'Expenses'!$A$5:$A$1004,"<="&EOMONTH(I$4,0),'Expenses'!$B$5:$B$1004,$A17) | ... M17: =SUMIFS('Expenses'!$D$5:$D$1004,'Expenses'!$A$5:$A$1004,">="&M$4,'Expenses'!$A$5:$A$1004,"<="&EOMONTH(M$4,0),'Expenses'!$B$5:$B$1004,$A17) | N17: =SUM(B17:M17)
A18: =Heads!A11 | B18: =SUMIFS('Expenses'!$D$5:$D$1004,'Expenses'!$A$5:$A$1004,">="&B$4,'Expenses'!$A$5:$A$1004,"<="&EOMONTH(B$4,0),'Expenses'!$B$5:$B$1004,$A18) | C18: =SUMIFS('Expenses'!$D$5:$D$1004,'Expenses'!$A$5:$A$1004,">="&C$4,'Expenses'!$A$5:$A$1004,"<="&EOMONTH(C$4,0),'Expenses'!$B$5:$B$1004,$A18) | D18: =SUMIFS('Expenses'!$D$5:$D$1004,'Expenses'!$A$5:$A$1004,">="&D$4,'Expenses'!$A$5:$A$1004,"<="&EOMONTH(D$4,0),'Expenses'!$B$5:$B$1004,$A18) | E18: =SUMIFS('Expenses'!$D$5:$D$1004,'Expenses'!$A$5:$A$1004,">="&E$4,'Expenses'!$A$5:$A$1004,"<="&EOMONTH(E$4,0),'Expenses'!$B$5:$B$1004,$A18) | F18: =SUMIFS('Expenses'!$D$5:$D$1004,'Expenses'!$A$5:$A$1004,">="&F$4,'Expenses'!$A$5:$A$1004,"<="&EOMONTH(F$4,0),'Expenses'!$B$5:$B$1004,$A18) | G18: =SUMIFS('Expenses'!$D$5:$D$1004,'Expenses'!$A$5:$A$1004,">="&G$4,'Expenses'!$A$5:$A$1004,"<="&EOMONTH(G$4,0),'Expenses'!$B$5:$B$1004,$A18) | H18: =SUMIFS('Expenses'!$D$5:$D$1004,'Expenses'!$A$5:$A$1004,">="&H$4,'Expenses'!$A$5:$A$1004,"<="&EOMONTH(H$4,0),'Expenses'!$B$5:$B$1004,$A18) | I18: =SUMIFS('Expenses'!$D$5:$D$1004,'Expenses'!$A$5:$A$1004,">="&I$4,'Expenses'!$A$5:$A$1004,"<="&EOMONTH(I$4,0),'Expenses'!$B$5:$B$1004,$A18) | ... M18: =SUMIFS('Expenses'!$D$5:$D$1004,'Expenses'!$A$5:$A$1004,">="&M$4,'Expenses'!$A$5:$A$1004,"<="&EOMONTH(M$4,0),'Expenses'!$B$5:$B$1004,$A18) | N18: =SUM(B18:M18)
A19: =Heads!A12 | B19: =SUMIFS('Expenses'!$D$5:$D$1004,'Expenses'!$A$5:$A$1004,">="&B$4,'Expenses'!$A$5:$A$1004,"<="&EOMONTH(B$4,0),'Expenses'!$B$5:$B$1004,$A19) | C19: =SUMIFS('Expenses'!$D$5:$D$1004,'Expenses'!$A$5:$A$1004,">="&C$4,'Expenses'!$A$5:$A$1004,"<="&EOMONTH(C$4,0),'Expenses'!$B$5:$B$1004,$A19) | D19: =SUMIFS('Expenses'!$D$5:$D$1004,'Expenses'!$A$5:$A$1004,">="&D$4,'Expenses'!$A$5:$A$1004,"<="&EOMONTH(D$4,0),'Expenses'!$B$5:$B$1004,$A19) | E19: =SUMIFS('Expenses'!$D$5:$D$1004,'Expenses'!$A$5:$A$1004,">="&E$4,'Expenses'!$A$5:$A$1004,"<="&EOMONTH(E$4,0),'Expenses'!$B$5:$B$1004,$A19) | F19: =SUMIFS('Expenses'!$D$5:$D$1004,'Expenses'!$A$5:$A$1004,">="&F$4,'Expenses'!$A$5:$A$1004,"<="&EOMONTH(F$4,0),'Expenses'!$B$5:$B$1004,$A19) | G19: =SUMIFS('Expenses'!$D$5:$D$1004,'Expenses'!$A$5:$A$1004,">="&G$4,'Expenses'!$A$5:$A$1004,"<="&EOMONTH(G$4,0),'Expenses'!$B$5:$B$1004,$A19) | H19: =SUMIFS('Expenses'!$D$5:$D$1004,'Expenses'!$A$5:$A$1004,">="&H$4,'Expenses'!$A$5:$A$1004,"<="&EOMONTH(H$4,0),'Expenses'!$B$5:$B$1004,$A19) | I19: =SUMIFS('Expenses'!$D$5:$D$1004,'Expenses'!$A$5:$A$1004,">="&I$4,'Expenses'!$A$5:$A$1004,"<="&EOMONTH(I$4,0),'Expenses'!$B$5:$B$1004,$A19) | ... M19: =SUMIFS('Expenses'!$D$5:$D$1004,'Expenses'!$A$5:$A$1004,">="&M$4,'Expenses'!$A$5:$A$1004,"<="&EOMONTH(M$4,0),'Expenses'!$B$5:$B$1004,$A19) | N19: =SUM(B19:M19)
A20: =Heads!A13 | B20: =SUMIFS('Expenses'!$D$5:$D$1004,'Expenses'!$A$5:$A$1004,">="&B$4,'Expenses'!$A$5:$A$1004,"<="&EOMONTH(B$4,0),'Expenses'!$B$5:$B$1004,$A20) | C20: =SUMIFS('Expenses'!$D$5:$D$1004,'Expenses'!$A$5:$A$1004,">="&C$4,'Expenses'!$A$5:$A$1004,"<="&EOMONTH(C$4,0),'Expenses'!$B$5:$B$1004,$A20) | D20: =SUMIFS('Expenses'!$D$5:$D$1004,'Expenses'!$A$5:$A$1004,">="&D$4,'Expenses'!$A$5:$A$1004,"<="&EOMONTH(D$4,0),'Expenses'!$B$5:$B$1004,$A20) | E20: =SUMIFS('Expenses'!$D$5:$D$1004,'Expenses'!$A$5:$A$1004,">="&E$4,'Expenses'!$A$5:$A$1004,"<="&EOMONTH(E$4,0),'Expenses'!$B$5:$B$1004,$A20) | F20: =SUMIFS('Expenses'!$D$5:$D$1004,'Expenses'!$A$5:$A$1004,">="&F$4,'Expenses'!$A$5:$A$1004,"<="&EOMONTH(F$4,0),'Expenses'!$B$5:$B$1004,$A20) | G20: =SUMIFS('Expenses'!$D$5:$D$1004,'Expenses'!$A$5:$A$1004,">="&G$4,'Expenses'!$A$5:$A$1004,"<="&EOMONTH(G$4,0),'Expenses'!$B$5:$B$1004,$A20) | H20: =SUMIFS('Expenses'!$D$5:$D$1004,'Expenses'!$A$5:$A$1004,">="&H$4,'Expenses'!$A$5:$A$1004,"<="&EOMONTH(H$4,0),'Expenses'!$B$5:$B$1004,$A20) | I20: =SUMIFS('Expenses'!$D$5:$D$1004,'Expenses'!$A$5:$A$1004,">="&I$4,'Expenses'!$A$5:$A$1004,"<="&EOMONTH(I$4,0),'Expenses'!$B$5:$B$1004,$A20) | ... M20: =SUMIFS('Expenses'!$D$5:$D$1004,'Expenses'!$A$5:$A$1004,">="&M$4,'Expenses'!$A$5:$A$1004,"<="&EOMONTH(M$4,0),'Expenses'!$B$5:$B$1004,$A20) | N20: =SUM(B20:M20)
... A23: =Heads!A16 | B23: =SUMIFS('Expenses'!$D$5:$D$1004,'Expenses'!$A$5:$A$1004,">="&B$4,'Expenses'!$A$5:$A$1004,"<="&EOMONTH(B$4,0),'Expenses'!$B$5:$B$1004,$A23) | C23: =SUMIFS('Expenses'!$D$5:$D$1004,'Expenses'!$A$5:$A$1004,">="&C$4,'Expenses'!$A$5:$A$1004,"<="&EOMONTH(C$4,0),'Expenses'!$B$5:$B$1004,$A23) | D23: =SUMIFS('Expenses'!$D$5:$D$1004,'Expenses'!$A$5:$A$1004,">="&D$4,'Expenses'!$A$5:$A$1004,"<="&EOMONTH(D$4,0),'Expenses'!$B$5:$B$1004,$A23) | E23: =SUMIFS('Expenses'!$D$5:$D$1004,'Expenses'!$A$5:$A$1004,">="&E$4,'Expenses'!$A$5:$A$1004,"<="&EOMONTH(E$4,0),'Expenses'!$B$5:$B$1004,$A23) | F23: =SUMIFS('Expenses'!$D$5:$D$1004,'Expenses'!$A$5:$A$1004,">="&F$4,'Expenses'!$A$5:$A$1004,"<="&EOMONTH(F$4,0),'Expenses'!$B$5:$B$1004,$A23) | G23: =SUMIFS('Expenses'!$D$5:$D$1004,'Expenses'!$A$5:$A$1004,">="&G$4,'Expenses'!$A$5:$A$1004,"<="&EOMONTH(G$4,0),'Expenses'!$B$5:$B$1004,$A23) | H23: =SUMIFS('Expenses'!$D$5:$D$1004,'Expenses'!$A$5:$A$1004,">="&H$4,'Expenses'!$A$5:$A$1004,"<="&EOMONTH(H$4,0),'Expenses'!$B$5:$B$1004,$A23) | I23: =SUMIFS('Expenses'!$D$5:$D$1004,'Expenses'!$A$5:$A$1004,">="&I$4,'Expenses'!$A$5:$A$1004,"<="&EOMONTH(I$4,0),'Expenses'!$B$5:$B$1004,$A23) | ... M23: =SUMIFS('Expenses'!$D$5:$D$1004,'Expenses'!$A$5:$A$1004,">="&M$4,'Expenses'!$A$5:$A$1004,"<="&EOMONTH(M$4,0),'Expenses'!$B$5:$B$1004,$A23) | N23: =SUM(B23:M23)
A24: Total expenses | B24: =SUM(B9:B23) | C24: =SUM(C9:C23) | D24: =SUM(D9:D23) | E24: =SUM(E9:E23) | F24: =SUM(F9:F23) | G24: =SUM(G9:G23) | H24: =SUM(H9:H23) | I24: =SUM(I9:I23) | ... M24: =SUM(M9:M23) | N24: =SUM(B24:M24)
A26: NET PROFIT | B26: =B7-B24 | C26: =C7-C24 | D26: =D7-D24 | E26: =E7-E24 | F26: =F7-F24 | G26: =G7-G24 | H26: =H7-H24 | I26: =I7-I24 | ... M26: =M7-M24 | N26: =SUM(B26:M26)
